Workbook
Name AREA: #REF!
Name CLIENTE: #REF!
Name CODIFICAÇÃO: #REF!
Name DOCUMENTO: #REF!
Name os: #REF!
Name PROJETO: #REF!
Name REVISAO: #REF!
Name TITULO: #REF!

Sheet LISTA
B1: Código | C1: Descricao NF | D1: Unidade | E1: ESTOQUE | F1: Tipo
A2: =VALUE(B2) -> 1 | B2: 000001 | C2: DESPESAS C/ PASSAGENS AEREAS | D2: UN | F2: MC
A3: =VALUE(B3) -> 2 | B3: 000002 | C3: PLATAFORMA AREA DE TRABALHO | D3: UN | F3: AI
A4: =VALUE(B4) -> 3 | B4: 000003 | C4: ISOLADOR DE SINAIS ANALOGICOS IS-5000 SERVICES | D4: PC | F4: EE
A5: =VALUE(B5) -> 4 | B5: 000004 | C5: SENSOR PT-100, 03 FIOS, BAINHA 6MM A304, CABECOTE TEMPO, CONEXAO ELETR. E PROC.1/2NPT, U=150, T=100, N=100MM CONSISTEC | D5: PC | E5: 0 | F5: IS
A6: =VALUE(B6) -> 5 | B6: 000005 | C6: CHAVE SECCIONADORA, BASE FUSIVEL, TAM. 00, 160A ERGONFUSE 160 SIEMENS | D6: PC | F6: MI
A7: =VALUE(B7) -> 6 | B7: 000006 | C7: RETALHOS DE CHAPAS DE ACO | D7: KG | F7: MC
A8: =VALUE(B8) -> 7 | B8: 000007 | C8: RETALHOS DE FERRO | D8: KG | F8: MC
A9: =VALUE(B9) -> 8 | B9: 000008 | C9: MODULO CONTAINER HABITAVEL, VAO LIVRE, REVESTIDO, MED. 6 X 2,30 MT | D9: UN | F9: MF
A10: =VALUE(B10) -> 9 | B10: 000009 | C10: CURVA VERTICAL EXTERNA P/ LEITO, MEDIO, VIROLA EXTERNA 19MM, GF, CHAPA #16/18, R320, 90 G, 300 X 100MM | D10: PC | F10: MI
A11: =VALUE(B11) -> 10 | B11: 000010 | C11: PLACA DE MONTAGEM P/ ESTRUTURA, LJ. 2,5YR6/14, CHAPA #12, MED. 1820 X 1140 MM | D11: PC | F11: OI
A12: =VALUE(B12) -> 11 | B12: 000011 | C12: CONECTOR RETO UNIAO ASTM A276 INOX 316 TP C CL 6500 PSI 1/2OD X 1/2OD F. MASTER | D12: PC | F12: MI
A13: =VALUE(B13) -> 12 | B13: 000012 | C13: MINI-VALVULA AGULHA, INT. ASTM A276 INOX 316, EXT. INOX 316 MICROF. CF8M, 6500 PSI, VED.TEFLON,3/8OD 206-T-316 TRIUNION | D13: PC | F13: IS
A14: =VALUE(B14) -> 13 | B14: 000013 | C14: IMPRESSORA, MULTIFUNCIONAL, MONOCROMATICA, LASER, DCP-1512, BROTHER | D14: PC | F14: AI
A15: =VALUE(B15) -> 14 | B15: 000014 | C15: CARTUCHO DE TONER PRETO, 1000 IMPRESSOES, TN-1060, BROTHER | D15: PC | F15: TI
A16: =VALUE(B16) -> 15 | B16: 000015 | C16: PLACA DE POLICARBONATO, MED. 1,00 MT X 1,50 MT X 2,00 MM | D16: PC | F16: OI
A17: =VALUE(B17) -> 16 | B17: 000016 | C17: CARRETINHA C/ ENGATE, ABERTA, LATERAL MADEIRA, CAP. 750 KG, PRETO, MED. 2 X 1,20 MT, C/ 02 PNEUS ARO 13, POLI | D17: UN | F17: AI
... A11844: =VALUE(B11844) -> 11843 | B11844: 011843 | C11844: DESPESAS C/ AGUA E ESGOTO | D11844: M3 | F11844: MC
A11845: =VALUE(B11845) -> 11844 | B11845: 011844 | C11845: DESPESAS C/ ENERGIA ELETRICA | D11845: W
A11846: =VALUE(B11846) -> 11845 | B11846: 011845 | C11846: SACO P/ LIXO 40 LT, PLASZOM | D11846: UN | F11846: MC
A11847: =VALUE(B11847) -> 11846 | B11847: 011846 | C11847: PA P/ LIXO | D11847: UN | F11847: MC
A11848: =VALUE(B11848) -> 11847 | B11848: 011847 | C11848: RETENTOR P/ VEICULOS | D11848: PC | F11848: MC
A11849: =VALUE(B11849) -> 11848 | B11849: 011848 | C11849: PROTETOR DA CORREIA DO ALTERNADOR | D11849: PC | F11849: MC
A11850: =VALUE(B11850) -> 11849 | B11850: 011849 | C11850: FILTRO DE COMBUSTIVEL P/ VEICULO | D11850: PC | F11850: MC
A11851: =VALUE(B11851) -> 11850 | B11851: 011850 | C11851: SILENCIOSO P/ VEICULO | D11851: PC | F11851: MC
A11852: =VALUE(B11852) -> 11851 | B11852: 011851 | C11852: VELA DE IGNICAO, P/ VEICULO | D11852: PC | F11852: MC
A11853: =VALUE(B11853) -> 11852 | B11853: 011852 | C11853: FILTRO DE AR P/ VEICULO | D11853: PC | F11853: MC
A11854: =VALUE(B11854) -> 11853 | B11854: 011853 | C11854: FILTRO DE OLEO P/ VEICULO | D11854: PC | F11854: MC
A11855: =VALUE(B11855) -> 11854 | B11855: 011854 | C11855: LIMPADOR PARABRISA P/ VEICULO | D11855: PC | F11855: MC
A11856: =VALUE(B11856) -> 11855 | B11856: 011855 | C11856: SENSOR KIT ESTACIONAMENTO, RE P/ VEICULO | D11856: PC | F11856: MC
A11857: =VALUE(B11857) -> 11856 | B11857: 011856 | C11857: RODA DE FERRO ARO14 | D11857: PC | F11857: MC
... A13406: =VALUE(B13406) -> 23922 | B13406: 023922 | C13406: PARAFUSO CABECA SEXTAVADA, ROSCA PARCIAL, ACO G5, EN, 7/8 X 6 POL. | D13406: PC | F13406: MI
A13407: =VALUE(B13407) -> 0
A13408: =VALUE(B13408) -> 0
A13409: =VALUE(B13409) -> 0
A13410: =VALUE(B13410) -> 0
A13411: =VALUE(B13411) -> 0
A13412: =VALUE(B13412) -> 0
A13413: =VALUE(B13413) -> 0
A13414: =VALUE(B13414) -> 0
A13415: =VALUE(B13415) -> 0
A13416: =VALUE(B13416) -> 0
A13417: =VALUE(B13417) -> 0
A13418: =VALUE(B13418) -> 0
... A19998: =VALUE(B19998) -> 0

Sheet Encaminhamento
A1: Código | B1: Descricao NF | C1: Unidade | D1: Quant | E1: Categoria | F1: Est. Mínimo | G1: Fabricante | H1: NCM | I1: CEST | J1: Ind. Origem | K1: Tipo Custódia | L1: Preço Custo | M1: Lote | N1: Classif. Fiscal | O1: Cód. Barras
A2: =IFERROR(_xlfn.XLOOKUP(B2,LISTA!C:C,LISTA!B:B,""),"") -> 000009 | B2: CURVA VERTICAL EXTERNA P/ LEITO, MEDIO, VIROLA EXTERNA 19MM, GF, CHAPA #16/18, R320, 90 G, 300 X 100MM | C2: PC | D2: 6 | E2: =IFERROR(_xlfn.XLOOKUP(B2,LISTA!C:C,LISTA!F:F,""),"") -> MI | F2: 66 | G2: DISPAN | H2: 73089010 | I2: 1004100 | J2: 0 - Nacional | K2: Próprio | L2: 207.97 | M2: L20251218 | N2: II - 73089010 | O2: 7897813895198
A3: =IFERROR(_xlfn.XLOOKUP(B3,LISTA!C:C,LISTA!B:B,""),"") -> 000062 | B3: ABRACADEIRA TIPO OMEGA GF 1.1/2 DP 632-5 DISPAN | C3: PC | D3: 469 | E3: =IFERROR(_xlfn.XLOOKUP(B3,LISTA!C:C,LISTA!F:F,""),"") -> MI | F3: 60 | G3: DISPAN | H3: 73269090 | I3: 1005000 | J3: 0 - Nacional | K3: Próprio | L3: 4.7 | M3: L20250815 | N3: II - 73269090 | O3: 7896690099645
A4: =IFERROR(_xlfn.XLOOKUP(B4,LISTA!C:C,LISTA!B:B,""),"") -> 000069 | B4: CONDULETE, ROSCAVEL, ALUMINIO, C/ TAMPA, JUNTA VEDACAO, 2 BSP, TIPO C | C4: PC | D4: 250 | E4: =IFERROR(_xlfn.XLOOKUP(B4,LISTA!C:C,LISTA!F:F,""),"") -> MI | F4: 12 | H4: 76090000 | I4: 1004100 | J4: 0 - Nacional | K4: Próprio | L4: 42.1 | M4: L20250511 | N4: II - 76090000 | O4: 7899863300688
A5: =IFERROR(_xlfn.XLOOKUP(B5,LISTA!C:C,LISTA!B:B,""),"") -> 000071 | B5: UNIDUT CONICO, ROSCA LONGA, ALUMINIO, C/ PARAFUSO, 1 POL. | C5: PC | D5: 304 | E5: =IFERROR(_xlfn.XLOOKUP(B5,LISTA!C:C,LISTA!F:F,""),"") -> MI | F5: 66 | H5: 76090000 | I5: 1004800 | J5: 0 - Nacional | K5: Próprio | L5: 8.93 | M5: L20250416 | N5: II - 76090000 | O5: 7897464892369
A6: =IFERROR(_xlfn.XLOOKUP(B6,LISTA!C:C,LISTA!B:B,""),"") -> 000074 | B6: BUCHA REDUCAO, EX-D, FERRO NODULAR, GF, GR. IIA/IIB OU IIC ZN. 1 OU 2, 1 X 1/2 NPT | C6: PC | D6: 97 | E6: =IFERROR(_xlfn.XLOOKUP(B6,LISTA!C:C,LISTA!F:F,""),"") -> MI | F6: 5 | H6: 73071920 | I6: 1004800 | J6: 0 - Nacional | K6: Controlado | L6: 60.43 | M6: L20250911 | N6: II - 73071920 | O6: 7897487071858
A7: =IFERROR(_xlfn.XLOOKUP(B7,LISTA!C:C,LISTA!B:B,""),"") -> 000075 | B7: ELETRODUTO SEMIPESADO, C/ COSTURA, ACO CARBONO, G.F, NBR 5624, C/ LUVA, 1 X 3000MM BSP | C7: PC | D7: 476 | E7: =IFERROR(_xlfn.XLOOKUP(B7,LISTA!C:C,LISTA!F:F,""),"") -> MI | F7: 26 | H7: 73063000 | I7: 1004100 | J7: 0 - Nacional | K7: Próprio | L7: 121.68 | M7: L20250821 | N7: II - 73063000 | O7: 7894278691813
A8: =IFERROR(_xlfn.XLOOKUP(B8,LISTA!C:C,LISTA!B:B,""),"") -> 000076 | B8: BUCHA TERMINAL S/ ROSCA ZC P/ ELETRODUTO DIN 3/4 BT 034-D DAISA | C8: PC | D8: 92 | E8: =IFERROR(_xlfn.XLOOKUP(B8,LISTA!C:C,LISTA!F:F,""),"") -> MI | F8: 33 | G8: DAISA | H8: 73269090 | I8: 1004100 | J8: 0 - Nacional | K8: Próprio | L8: 3.38 | M8: L20251028 | N8: II - 73269090 | O8: 7899640294620
A9: =IFERROR(_xlfn.XLOOKUP(B9,LISTA!C:C,LISTA!B:B,""),"") -> 000078 | B9: CONECTOR FIXO, REUSAVEL, ALUMINIO, MACHO, P/ ELETRODUTO FLEXIVEL DE ACO REVEST. PVC, ROSCA 3 BSP | C9: PC | D9: 304 | E9: =IFERROR(_xlfn.XLOOKUP(B9,LISTA!C:C,LISTA!F:F,""),"") -> MI | F9: 15 | H9: 39173900 | I9: 1004100 | J9: 0 - Nacional | K9: Próprio | L9: 6.32 | M9: L20250303 | N9: II - 39173900 | O9: 7893727069371
A10: =IFERROR(_xlfn.XLOOKUP(B10,LISTA!C:C,LISTA!B:B,""),"") -> 000084 | B10: CONDULETE ROSCAVEL EM ALUMINIO C/ TAMPA 1BSP TIPO E DIIRT 100-BSP-E DAISA | C10: PC | D10: 411 | E10: =IFERROR(_xlfn.XLOOKUP(B10,LISTA!C:C,LISTA!F:F,""),"") -> MI | F10: 16 | G10: DAISA | H10: 76090000 | I10: 1004100 | J10: 0 - Nacional | K10: Próprio | L10: 55.04 | M10: L20250821 | N10: II - 76090000 | O10: 7892996147553
A11: =IFERROR(_xlfn.XLOOKUP(B11,LISTA!C:C,LISTA!B:B,""),"") -> 000085 | B11: CONDULETE ROSCAVEL EM ALUMINIO FUNDIDO EX-D C/ TAMPA 2NPT TIPO LB TCLX/6-LB TELBRA | C11: PC | D11: 195 | E11: =IFERROR(_xlfn.XLOOKUP(B11,LISTA!C:C,LISTA!F:F,""),"") -> MI | F11: 55 | G11: TELBRA | H11: 76090000 | I11: 1004100 | J11: 0 - Nacional | K11: Controlado | L11: 166.74 | M11: L20251110 | N11: II - 76090000 | O11: 7898859844908
A12: =IFERROR(_xlfn.XLOOKUP(B12,LISTA!C:C,LISTA!B:B,""),"") -> 000088 | B12: BUCHA REDUCAO, GF, CL 150, 1 X 1/2BSP | C12: PC | D12: 251 | E12: =IFERROR(_xlfn.XLOOKUP(B12,LISTA!C:C,LISTA!F:F,""),"") -> MI | F12: 46 | H12: 73071100 | I12: 1004800 | J12: 0 - Nacional | K12: Próprio | L12: 10.92 | M12: L20251016 | N12: II - 73071100 | O12: 7899698210949
A13: =IFERROR(_xlfn.XLOOKUP(B13,LISTA!C:C,LISTA!B:B,""),"") -> 000089 | B13: BUCHA REDUCAO, GF CL 150, 2 X 1BSP | C13: PC | D13: 86 | E13: =IFERROR(_xlfn.XLOOKUP(B13,LISTA!C:C,LISTA!F:F,""),"") -> MI | F13: 30 | H13: 73071100 | I13: 1004800 | J13: 0 - Nacional | K13: Próprio | L13: 5.05 | M13: L20250907 | N13: II - 73071100 | O13: 7891228082962
A14: =IFERROR(_xlfn.XLOOKUP(B14,LISTA!C:C,LISTA!B:B,""),"") -> 000091 | B14: CONDULETE ROSCAVEL EM ALUMINIO C/ TAMPA 2.1/2BSP TIPO LB DIIRT 212-BSP-LB DAISA | C14: PC | D14: 347 | E14: =IFERROR(_xlfn.XLOOKUP(B14,LISTA!C:C,LISTA!F:F,""),"") -> MI | F14: 8 | G14: DAISA | H14: 76090000 | I14: 1004100 | J14: 0 - Nacional | K14: Próprio | L14: 77.43 | M14: L20250410 | N14: II - 76090000 | O14: 7899663496369
A15: =IFERROR(_xlfn.XLOOKUP(B15,LISTA!C:C,LISTA!B:B,""),"") -> 000093 | B15: CAIXA DE INSPECAO SUSPENSA, POLIAMIDA, 123 X 158 MM, 1 BSP, TEL-541, TERMOTECNICA | C15: PC | D15: 91 | E15: =IFERROR(_xlfn.XLOOKUP(B15,LISTA!C:C,LISTA!F:F,""),"") -> MI | F15: 78 | G15: TERMOTECNICA | H15: 39259090 | I15: 1004100 | J15: 0 - Nacional | K15: Próprio | L15: 32.47 | M15: L20250414 | N15: II - 39259090 | O15: 7891894778612
A16: =IFERROR(_xlfn.XLOOKUP(B16,LISTA!C:C,LISTA!B:B,""),"") -> 000094 | B16: BUCHA ACABAMENTO, FERRO NODULAR, GE, 2 NPT | C16: PC | D16: 96 | E16: =IFERROR(_xlfn.XLOOKUP(B16,LISTA!C:C,LISTA!F:F,""),"") -> MI | F16: 61 | H16: 73089010 | I16: 1004800 | J16: 0 - Nacional | K16: Próprio | L16: 14.84 | M16: L20251103 | N16: II - 73089010 | O16: 7893668589711
A17: =IFERROR(_xlfn.XLOOKUP(B17,LISTA!C:C,LISTA!B:B,""),"") -> 000096 | B17: BUCHA ACABAMENTO EX-D FERRO NODULAR GF 1 NPT CX / BF-3 FG CONEX | C17: PC | D17: 465 | E17: =IFERROR(_xlfn.XLOOKUP(B17,LISTA!C:C,LISTA!F:F,""),"") -> MI | F17: 79 | G17: CONEX | H17: 73071920 | I17: 1004800 | J17: 0 - Nacional | K17: Controlado | L17: 38.27 | M17: L20250507 | N17: II - 73071920 | O17: 7897698136660
A18: =IFERROR(_xlfn.XLOOKUP(B18,LISTA!C:C,LISTA!B:B,""),"") -> 000098 | B18: BUCHA ACABAMENTO EX-D FERRO NODULAR GF 2.1/4 NPT CX / BF-7 FG CONEX | C18: PC | D18: 140 | E18: =IFERROR(_xlfn.XLOOKUP(B18,LISTA!C:C,LISTA!F:F,""),"") -> MI | F18: 8 | G18: CONEX | H18: 73071920 | I18: 1004800 | J18: 0 - Nacional | K18: Controlado | L18: 73.56 | M18: L20250619 | N18: II - 73071920 | O18: 7896327459724
A19: =IFERROR(_xlfn.XLOOKUP(B19,LISTA!C:C,LISTA!B:B,""),"") -> 000100 | B19: ARRUELA ACABAMENTO, ALUMINIO, 3 BSP | C19: PC | D19: 94 | E19: =IFERROR(_xlfn.XLOOKUP(B19,LISTA!C:C,LISTA!F:F,""),"") -> MI | F19: 54 | H19: 76090000 | I19: 1004800 | J19: 0 - Nacional | K19: Próprio | L19: 4.33 | M19: L20250521 | N19: II - 76090000 | O19: 7893098240635
A20: =IFERROR(_xlfn.XLOOKUP(B20,LISTA!C:C,LISTA!B:B,""),"") -> 000101 | B20: PORCA ACABAMENTO ALUMINIO 2.1/2BSP PU-212-BSP DAISA | C20: PC | D20: 59 | E20: =IFERROR(_xlfn.XLOOKUP(B20,LISTA!C:C,LISTA!F:F,""),"") -> MI | F20: 34 | G20: DAISA | H20: 76090000 | I20: 1004800 | J20: 0 - Nacional | K20: Próprio | L20: 8.86 | M20: L20250410 | N20: II - 76090000 | O20: 7896743921166
A21: =IFERROR(_xlfn.XLOOKUP(B21,LISTA!C:C,LISTA!B:B,""),"") -> 000102 | B21: ARRUELA ACABAMENTO EX-D FERRO NODULAR GF 2 NPT CX / AR-6 FG CONEX | C21: PC | D21: 438 | E21: =IFERROR(_xlfn.XLOOKUP(B21,LISTA!C:C,LISTA!F:F,""),"") -> MI | F21: 48 | G21: CONEX | H21: 73071920 | I21: 1004800 | J21: 0 - Nacional | K21: Controlado | L21: 8.78 | M21: L20251127 | N21: II - 73071920 | O21: 7891560673864
A22: =IFERROR(_xlfn.XLOOKUP(B22,LISTA!C:C,LISTA!B:B,""),"") -> 000107 | B22: ELETROCALHA FUNDO PERFURADO C/ VIROLA LATERAL 18AWG GF, TAMPA PRESSAO 2 AGUAS 300X100X3000MM DP 703 DISPAN | C22: BR | D22: 54 | E22: =IFERROR(_xlfn.XLOOKUP(B22,LISTA!C:C,LISTA!F:F,""),"") -> MI | F22: 42 | G22: DISPAN | H22: 73089010 | I22: 1004100 | J22: 0 - Nacional | K22: Próprio | L22: 154.85 | M22: L20250803 | N22: II - 73089010 | O22: 7896927469183
A23: =IFERROR(_xlfn.XLOOKUP(B23,LISTA!C:C,LISTA!B:B,""),"") -> 000111 | B23: ABRACADEIRA VERGALHAO, GRAMPO U, GE, C/ PORCAS E ARRUELAS, 3 X 5/16 POL. | C23: PC | D23: 494 | E23: =IFERROR(_xlfn.XLOOKUP(B23,LISTA!C:C,LISTA!F:F,""),"") -> MI | F23: 68 | H23: 73269090 | I23: 1005000 | J23: 0 - Nacional | K23: Próprio | L23: 6.69 | M23: L20250902 | N23: II - 73269090 | O23: 7899185943741
A24: =IFERROR(_xlfn.XLOOKUP(B24,LISTA!C:C,LISTA!B:B,""),"") -> 000112 | B24: ABRACADEIRA VERGALHAO GRAMPO U GF 2 X 3/8 DP 634-6 DISPAN | C24: PC | D24: 305 | E24: =IFERROR(_xlfn.XLOOKUP(B24,LISTA!C:C,LISTA!F:F,""),"") -> MI | F24: 15 | G24: DISPAN | H24: 73269090 | I24: 1005000 | J24: 0 - Nacional | K24: Próprio | L24: 5.23 | M24: L20250222 | N24: II - 73269090 | O24: 7899838670566
A25: =IFERROR(_xlfn.XLOOKUP(B25,LISTA!C:C,LISTA!B:B,""),"") -> 000113 | B25: ABRACADEIRA VERGALHAO GRAMPO U GF 1.1/2 X 5/16 DP 634-5 DISPAN | C25: PC | D25: 181 | E25: =IFERROR(_xlfn.XLOOKUP(B25,LISTA!C:C,LISTA!F:F,""),"") -> MI | F25: 80 | G25: DISPAN | H25: 73269090 | I25: 1005000 | J25: 0 - Nacional | K25: Próprio | L25: 13.83 | M25: L20250925 | N25: II - 73269090 | O25: 7898158672226
A26: =IFERROR(_xlfn.XLOOKUP(B26,LISTA!C:C,LISTA!B:B,""),"") -> 000114 | B26: ABRACADEIRA VERGALHAO GRAMPO U GF 2 X 5/16 DP 634-6 DISPAN | C26: PC | D26: 31 | E26: =IFERROR(_xlfn.XLOOKUP(B26,LISTA!C:C,LISTA!F:F,""),"") -> MI | F26: 38 | G26: DISPAN | H26: 73269090 | I26: 1005000 | J26: 0 - Nacional | K26: Próprio | L26: 4.99 | M26: L20250706 | N26: II - 73269090 | O26: 7896583833463
A27: =IFERROR(_xlfn.XLOOKUP(B27,LISTA!C:C,LISTA!B:B,""),"") -> 000115 | B27: ABRACADEIRA VERGALHAO, GRAMPO U, GE, C/ PORCAS E ARRUELAS, 4 X 5/16 POL. | C27: PC | D27: 53 | E27: =IFERROR(_xlfn.XLOOKUP(B27,LISTA!C:C,LISTA!F:F,""),"") -> MI | F27: 17 | H27: 73269090 | I27: 1005000 | J27: 0 - Nacional | K27: Próprio | L27: 10.71 | M27: L20251106 | N27: II - 73269090 | O27: 7895846516606
A28: =IFERROR(_xlfn.XLOOKUP(B28,LISTA!C:C,LISTA!B:B,""),"") -> 000116 | B28: ABRACADEIRA VERGALHAO GRAMPO U GF 1 X 5/16 DP 634-3 DISPAN | C28: PC | D28: 188 | E28: =IFERROR(_xlfn.XLOOKUP(B28,LISTA!C:C,LISTA!F:F,""),"") -> MI | F28: 80 | G28: DISPAN | H28: 73269090 | I28: 1005000 | J28: 0 - Nacional | K28: Próprio | L28: 5.27 | M28: L20250409 | N28: II - 73269090 | O28: 7899609888725
A29: =IFERROR(_xlfn.XLOOKUP(B29,LISTA!C:C,LISTA!B:B,""),"") -> 000117 | B29: ABRACADEIRA VERGALHAO, GRAMPO U, GE, C/ PORCAS E ARRUELAS, 1/2 X 1/4 POL. | C29: PC | D29: 438 | E29: =IFERROR(_xlfn.XLOOKUP(B29,LISTA!C:C,LISTA!F:F,""),"") -> MI | F29: 26 | H29: 73269090 | I29: 1005000 | J29: 0 - Nacional | K29: Próprio | L29: 8.19 | M29: L20251010 | N29: II - 73269090 | O29: 7895172959432
A30: =IFERROR(_xlfn.XLOOKUP(B30,LISTA!C:C,LISTA!B:B,""),"") -> 000118 | B30: ABRACADEIRA VERGALHAO, GRAMPO U, GE, C/ PORCAS E ARRUELAS, 1 X 1/4 POL. | C30: PC | D30: 137 | E30: =IFERROR(_xlfn.XLOOKUP(B30,LISTA!C:C,LISTA!F:F,""),"") -> MI | F30: 69 | H30: 73269090 | I30: 1005000 | J30: 0 - Nacional | K30: Próprio | L30: 12.19 | M30: L20250709 | N30: II - 73269090 | O30: 7896932226577
A31: =IFERROR(_xlfn.XLOOKUP(B31,LISTA!C:C,LISTA!B:B,""),"") -> 000120 | B31: BUCHA REDUCAO, ALUMINIO, 2 X 3/4BSP | C31: PC | D31: 479 | E31: =IFERROR(_xlfn.XLOOKUP(B31,LISTA!C:C,LISTA!F:F,""),"") -> MI | F31: 79 | H31: 76090000 | I31: 1004800 | J31: 0 - Nacional | K31: Próprio | L31: 13.28 | M31: L20250410 | N31: II - 76090000 | O31: 7899834922535
A32: =IFERROR(_xlfn.XLOOKUP(B32,LISTA!C:C,LISTA!B:B,""),"") -> 000124 | B32: CONDULETE, ROSCAVEL, ALUMINIO FUNDIDO, EX-D, C/ TAMPA, IIA/IIB/IEC 60079-0/60079-1/60529, 1NPT, LB | C32: PC | D32: 19 | E32: =IFERROR(_xlfn.XLOOKUP(B32,LISTA!C:C,LISTA!F:F,""),"") -> MI | F32: 7 | H32: 76090000 | I32: 1004100 | J32: 0 - Nacional | K32: Controlado | L32: 168.51 | M32: L20250827 | N32: II - 76090000 | O32: 7891376155411
A33: =IFERROR(_xlfn.XLOOKUP(B33,LISTA!C:C,LISTA!B:B,""),"") -> 000125 | B33: CONDULETE, ROSCAVEL, ALUMINIO FUNDIDO, EX-D, C/ TAMPA, IIA/IIB/IEC 60079-0/60079-1/60529, 1NPT, LL | C33: PC | D33: 65 | E33: =IFERROR(_xlfn.XLOOKUP(B33,LISTA!C:C,LISTA!F:F,""),"") -> MI | F33: 13 | H33: 76090000 | I33: 1004100 | J33: 0 - Nacional | K33: Controlado | L33: 197.54 | M33: L20250725 | N33: II - 76090000 | O33: 7899255933332
A34: =IFERROR(_xlfn.XLOOKUP(B34,LISTA!C:C,LISTA!B:B,""),"") -> 000126 | B34: CONDULETE, ROSCAVEL, ALUMINIO FUNDIDO, EX-D, C/ TAMPA, IIA/IIB/IEC 60079-0/60079-1/60529, 1NPT, LR | C34: PC | D34: 416 | E34: =IFERROR(_xlfn.XLOOKUP(B34,LISTA!C:C,LISTA!F:F,""),"") -> MI | F34: 70 | H34: 76090000 | I34: 1004100 | J34: 0 - Nacional | K34: Controlado | L34: 236.95 | M34: L20250222 | N34: II - 76090000 | O34: 7896212254814
A35: =IFERROR(_xlfn.XLOOKUP(B35,LISTA!C:C,LISTA!B:B,""),"") -> 000128 | B35: CONDULETE, ROSCAVEL, ALUMINIO FUNDIDO, EX-D, C/ TAMPA, IIA/IIB/IEC 60079-0/60079-1/60529, 1NPT, T | C35: PC | D35: 298 | E35: =IFERROR(_xlfn.XLOOKUP(B35,LISTA!C:C,LISTA!F:F,""),"") -> MI | F35: 80 | H35: 76090000 | I35: 1004100 | J35: 0 - Nacional | K35: Controlado | L35: 230.8 | M35: L20250206 | N35: II - 76090000 | O35: 7891924484508
A36: =IFERROR(_xlfn.XLOOKUP(B36,LISTA!C:C,LISTA!B:B,""),"") -> 000130 | B36: CONDULETE, ROSCAVEL, ALUMINIO FUNDIDO, EX-D, C/ TAMPA, IIA/IIB/IEC 60079-0/60079-1/60529, 1NPT, X | C36: PC | D36: 407 | E36: =IFERROR(_xlfn.XLOOKUP(B36,LISTA!C:C,LISTA!F:F,""),"") -> MI | F36: 80 | H36: 76090000 | I36: 1004100 | J36: 0 - Nacional | K36: Controlado | L36: 206.23 | M36: L20250126 | N36: II - 76090000 | O36: 7896059639049
A37: =IFERROR(_xlfn.XLOOKUP(B37,LISTA!C:C,LISTA!B:B,""),"") -> 000131 | B37: CONDULETE, ROSCAVEL, ALUMINIO FUNDIDO, EX-D, C/ TAMPA, IIA/IIB/IEC 60079-0/60079-1/60529, 1.1/2NPT, C | C37: PC | D37: 475 | E37: =IFERROR(_xlfn.XLOOKUP(B37,LISTA!C:C,LISTA!F:F,""),"") -> MI | F37: 77 | H37: 76090000 | I37: 1004100 | J37: 0 - Nacional | K37: Controlado | L37: 223.18 | M37: L20250513 | N37: II - 76090000 | O37: 7898582479680
A38: =IFERROR(_xlfn.XLOOKUP(B38,LISTA!C:C,LISTA!B:B,""),"") -> 000134 | B38: CONDULETE, ROSCAVEL, ALUMINIO FUNDIDO, EX-D, C/ TAMPA, IIA/IIB/IEC 60079-0/60079-1/60529, 1.1/2NPT, LB | C38: PC | D38: 56 | E38: =IFERROR(_xlfn.XLOOKUP(B38,LISTA!C:C,LISTA!F:F,""),"") -> MI | F38: 75 | H38: 76090000 | I38: 1004100 | J38: 0 - Nacional | K38: Controlado | L38: 160.09 | M38: L20250416 | N38: II - 76090000 | O38: 7891162007628
A39: =IFERROR(_xlfn.XLOOKUP(B39,LISTA!C:C,LISTA!B:B,""),"") -> 000135 | B39: TAMPAO FENDA PVC 1/2 MT 012 DAISA | C39: PC | D39: 290 | E39: =IFERROR(_xlfn.XLOOKUP(B39,LISTA!C:C,LISTA!F:F,""),"") -> MI | F39: 71 | G39: DAISA | H39: 39174090 | I39: 1004100 | J39: 0 - Nacional | K39: Próprio | L39: 4.79 | M39: L20250704 | N39: II - 39174090 | O39: 7896645114419
A40: =IFERROR(_xlfn.XLOOKUP(B40,LISTA!C:C,LISTA!B:B,""),"") -> 000146 | B40: CONDULETE, ROSCAVEL, ALUMINIO FUNDIDO, EX-D, C/ TAMPA, IIA/IIB/IEC 60079-0/60079-1/60529, 1.1/2NPT, LL | C40: PC | D40: 463 | E40: =IFERROR(_xlfn.XLOOKUP(B40,LISTA!C:C,LISTA!F:F,""),"") -> MI | F40: 62 | H40: 76090000 | I40: 1004100 | J40: 0 - Nacional | K40: Controlado | L40: 111.76 | M40: L20250603 | N40: II - 76090000 | O40: 7893805020045
A41: =IFERROR(_xlfn.XLOOKUP(B41,LISTA!C:C,LISTA!B:B,""),"") -> 000147 | B41: CONDULETE, ROSCAVEL, ALUMINIO FUNDIDO, EX-D, C/ TAMPA, IIA/IIB/IEC 60079-0/60079-1/60529, 1.1/2NPT, LR | C41: PC | D41: 493 | E41: =IFERROR(_xlfn.XLOOKUP(B41,LISTA!C:C,LISTA!F:F,""),"") -> MI | F41: 23 | H41: 76090000 | I41: 1004100 | J41: 0 - Nacional | K41: Controlado | L41: 252.22 | M41: L20250417 | N41: II - 76090000 | O41: 7898629521428
A42: =IFERROR(_xlfn.XLOOKUP(B42,LISTA!C:C,LISTA!B:B,""),"") -> 000150 | B42: CONDULETE, ROSCAVEL, ALUMINIO FUNDIDO, EX-D, C/ TAMPA, IIA/IIB/IEC 60079-0/60079-1/60529, 1.1/2NPT, T | C42: PC | D42: 83 | E42: =IFERROR(_xlfn.XLOOKUP(B42,LISTA!C:C,LISTA!F:F,""),"") -> MI | F42: 57 | H42: 76090000 | I42: 1004100 | J42: 0 - Nacional | K42: Controlado | L42: 238.72 | M42: L20250104 | N42: II - 76090000 | O42: 7896701874863
A43: =IFERROR(_xlfn.XLOOKUP(B43,LISTA!C:C,LISTA!B:B,""),"") -> 000153 | B43: CONDULETE ROSCAVEL EM ALUMINIO FUNDIDO EX-D C/ TAMPA 2NPT TIPO C TCLX/6-C TELBRA | C43: PC | D43: 494 | E43: =IFERROR(_xlfn.XLOOKUP(B43,LISTA!C:C,LISTA!F:F,""),"") -> MI | F43: 57 | G43: TELBRA | H43: 76090000 | I43: 1004100 | J43: 0 - Nacional | K43: Controlado | L43: 161.17 | M43: L20251127 | N43: II - 76090000 | O43: 7893519667883
A44: =IFERROR(_xlfn.XLOOKUP(B44,LISTA!C:C,LISTA!B:B,""),"") -> 000158 | B44: CONECTOR MACHO ZC DE LATAO GIRATORIO 3/4NPT CMZGL-34 S.P.T.F | C44: PC | D44: 347 | E44: =IFERROR(_xlfn.XLOOKUP(B44,LISTA!C:C,LISTA!F:F,""),"") -> MI | F44: 26 | G44: S.P.T.F | H44: 74122000 | I44: 1004800 | J44: 0 - Nacional | K44: Próprio | L44: 21.07 | M44: L20251028 | N44: II - 74122000 | O44: 7899167069771
A45: =IFERROR(_xlfn.XLOOKUP(B45,LISTA!C:C,LISTA!B:B,""),"") -> 000171 | B45: CONDULETE, ROSCAVEL, ALUMINIO, C/ TAMPA, JUNTA VEDACAO, 1.1/2 BSP, TIPO X | C45: PC | D45: 161 | E45: =IFERROR(_xlfn.XLOOKUP(B45,LISTA!C:C,LISTA!F:F,""),"") -> MI | F45: 32 | H45: 76090000 | I45: 1004100 | J45: 0 - Nacional | K45: Próprio | L45: 63.06 | M45: L20250801 | N45: II - 76090000 | O45: 7897539214465
A46: =IFERROR(_xlfn.XLOOKUP(B46,LISTA!C:C,LISTA!B:B,""),"") -> 000186 | B46: UNIAO DUTO PEAD CINZA, SECAO CIRCULAR C/ CORRUGACAO HELICOIDAL C/ ELETRODUTO ROSQUEAVEL, 4 CONEXAO II CP KANAFLEX | C46: PC | D46: 138 | E46: =IFERROR(_xlfn.XLOOKUP(B46,LISTA!C:C,LISTA!F:F,""),"") -> MI | F46: 79 | G46: KANAFLEX | H46: 73089010 | I46: 1004100 | J46: 0 - Nacional | K46: Próprio | L46: 33.37 | M46: L20250707 | N46: II - 73089010 | O46: 7892291142012
A47: =IFERROR(_xlfn.XLOOKUP(B47,LISTA!C:C,LISTA!B:B,""),"") -> 000188 | B47: CONDULETE ROSCAVEL EM ALUMINIO C/ TAMPA 2.1/2BSP TIPO C DIIRT 212-BSP-C DAISA | C47: PC | D47: 7 | E47: =IFERROR(_xlfn.XLOOKUP(B47,LISTA!C:C,LISTA!F:F,""),"") -> MI | F47: 74 | G47: DAISA | H47: 76090000 | I47: 1004100 | J47: 0 - Nacional | K47: Próprio | L47: 30.44 | M47: L20250207 | N47: II - 76090000 | O47: 7891696119119
A48: =IFERROR(_xlfn.XLOOKUP(B48,LISTA!C:C,LISTA!B:B,""),"") -> 000191 | B48: PARAFUSO CABECA REDONDA FENDA, ROSCA SOBERBA ZC 5/16 X 2 DP 616 DISPAN | C48: PC | D48: 215 | E48: =IFERROR(_xlfn.XLOOKUP(B48,LISTA!C:C,LISTA!F:F,""),"") -> MI | F48: 23 | G48: DISPAN | H48: 73181200 | I48: 1005000 | J48: 0 - Nacional | K48: Próprio | L48: 3.42 | M48: L20250321 | N48: II - 73181200 | O48: 7894587519013
A49: =IFERROR(_xlfn.XLOOKUP(B49,LISTA!C:C,LISTA!B:B,""),"") -> 000194 | B49: ELETROCALHA, FUNDO E LATERAL PERFURADO, S/ VIROLA, CHAPA #20, PZ, 100 X 100 X 3000MM | C49: PC | D49: 322 | E49: =IFERROR(_xlfn.XLOOKUP(B49,LISTA!C:C,LISTA!F:F,""),"") -> MI | F49: 60 | H49: 73089010 | I49: 1004100 | J49: 0 - Nacional | K49: Próprio | L49: 157.02 | M49: L20250412 | N49: II - 73089010 | O49: 7895856344781
A50: =IFERROR(_xlfn.XLOOKUP(B50,LISTA!C:C,LISTA!B:B,""),"") -> 000199 | B50: ELETROCALHA, FUNDO E LATERAL PERFURADO, C/ VIROLA, CHAPA #16, GF, 400 X 100 X 3000 MM | C50: PC | D50: 177 | E50: =IFERROR(_xlfn.XLOOKUP(B50,LISTA!C:C,LISTA!F:F,""),"") -> MI | F50: 9 | H50: 73089010 | I50: 1004100 | J50: 0 - Nacional | K50: Próprio | L50: 33.16 | M50: L20250128 | N50: II - 73089010 | O50: 7894065649669
A51: =IFERROR(_xlfn.XLOOKUP(B51,LISTA!C:C,LISTA!B:B,""),"") -> 000200 | B51: TEE HORIZONTAL P/ ELETROCALHA, GF, CHAPA #20, R150, 100 X 50MM, 90 G | C51: PC | D51: 396 | E51: =IFERROR(_xlfn.XLOOKUP(B51,LISTA!C:C,LISTA!F:F,""),"") -> MI | F51: 64 | H51: 73089010 | I51: 1004100 | J51: 0 - Nacional | K51: Próprio | L51: 53.54 | M51: L20250512 | N51: II - 73089010 | O51: 7897021674620
A52: =IFERROR(_xlfn.XLOOKUP(B52,LISTA!C:C,LISTA!B:B,""),"") -> 000202 | B52: CONDULETE, ROSCAVEL, ALUMINIO, C/ TAMPA, JUNTA VEDACAO, 1.1/2 BSP, TIPO LL | C52: PC | D52: 99 | E52: =IFERROR(_xlfn.XLOOKUP(B52,LISTA!C:C,LISTA!F:F,""),"") -> MI | F52: 24 | H52: 76090000 | I52: 1004100 | J52: 0 - Nacional | K52: Próprio | L52: 80.28 | M52: L20250527 | N52: II - 76090000 | O52: 7893963594550
A53: =IFERROR(_xlfn.XLOOKUP(B53,LISTA!C:C,LISTA!B:B,""),"") -> 000203 | B53: CONDULETE, ROSCAVEL, ALUMINIO, C/ TAMPA, JUNTA VEDACAO, 1 BSP, TIPO LL | C53: PC | D53: 223 | E53: =IFERROR(_xlfn.XLOOKUP(B53,LISTA!C:C,LISTA!F:F,""),"") -> MI | F53: 39 | H53: 76090000 | I53: 1004100 | J53: 0 - Nacional | K53: Próprio | L53: 38.95 | M53: L20250907 | N53: II - 76090000 | O53: 7898566243163
A54: =IFERROR(_xlfn.XLOOKUP(B54,LISTA!C:C,LISTA!B:B,""),"") -> 000218 | B54: BUJAO C/ REBAIXO SEXTAVADO, ALUMINIO, 3/4BSP | C54: PC | D54: 98 | E54: =IFERROR(_xlfn.XLOOKUP(B54,LISTA!C:C,LISTA!F:F,""),"") -> MI | F54: 62 | H54: 76090000 | I54: 1004800 | J54: 0 - Nacional | K54: Próprio | L54: 28.1 | M54: L20251112 | N54: II - 76090000 | O54: 7897180465285
A55: =IFERROR(_xlfn.XLOOKUP(B55,LISTA!C:C,LISTA!B:B,""),"") -> 000230 | B55: BUCHA REDUCAO ALUMINIO, 1 X 3/4 BSP | C55: PC | D55: 247 | E55: =IFERROR(_xlfn.XLOOKUP(B55,LISTA!C:C,LISTA!F:F,""),"") -> MI | F55: 26 | H55: 76090000 | I55: 1004800 | J55: 0 - Nacional | K55: Próprio | L55: 5.82 | M55: L20250417 | N55: II - 76090000 | O55: 7894196196239
A56: =IFERROR(_xlfn.XLOOKUP(B56,LISTA!C:C,LISTA!B:B,""),"") -> 000235 | B56: CONDULETE ROSCAVEL EM ALUMINIO C/ TAMPA 2BSP TIPO A DIIRT 200-BSP-A DAISA | C56: PC | D56: 328 | E56: =IFERROR(_xlfn.XLOOKUP(B56,LISTA!C:C,LISTA!F:F,""),"") -> MI | F56: 57 | G56: DAISA | H56: 76090000 | I56: 1004100 | J56: 0 - Nacional | K56: Próprio | L56: 66.38 | M56: L20251106 | N56: II - 76090000 | O56: 7893189538836
A57: =IFERROR(_xlfn.XLOOKUP(B57,LISTA!C:C,LISTA!B:B,""),"") -> 000292 | B57: BUCHA REDUCAO EX-D FERRO NODULAR GF 2 X 3/4 NPT CX / BRD-62 FG CONEX | C57: PC | D57: 157 | E57: =IFERROR(_xlfn.XLOOKUP(B57,LISTA!C:C,LISTA!F:F,""),"") -> MI | F57: 18 | G57: CONEX | H57: 73071920 | I57: 1004800 | J57: 0 - Nacional | K57: Controlado | L57: 24.2 | M57: L20251001 | N57: II - 73071920 | O57: 7891889395957
A58: =IFERROR(_xlfn.XLOOKUP(B58,LISTA!C:C,LISTA!B:B,""),"") -> 000293 | B58: BUCHA ACABAMENTO EX-D FERRO NODULAR GF 2.1/2 NPT CX / BF-5 FG CONEX | C58: PC | D58: 302 | E58: =IFERROR(_xlfn.XLOOKUP(B58,LISTA!C:C,LISTA!F:F,""),"") -> MI | F58: 43 | G58: CONEX | H58: 73071920 | I58: 1004800 | J58: 0 - Nacional | K58: Controlado | L58: 49.79 | M58: L20250709 | N58: II - 73071920 | O58: 7891325213844
A59: =IFERROR(_xlfn.XLOOKUP(B59,LISTA!C:C,LISTA!B:B,""),"") -> 000296 | B59: PORCA ACABAMENTO ALUMINIO 1.1/4BSP PU-114-BSP DAISA | C59: PC | D59: 206 | E59: =IFERROR(_xlfn.XLOOKUP(B59,LISTA!C:C,LISTA!F:F,""),"") -> MI | F59: 26 | G59: DAISA | H59: 76090000 | I59: 1004800 | J59: 0 - Nacional | K59: Próprio | L59: 6.21 | M59: L20250913 | N59: II - 76090000 | O59: 7899561530441
A60: =IFERROR(_xlfn.XLOOKUP(B60,LISTA!C:C,LISTA!B:B,""),"") -> 000299 | B60: BUCHA ACABAMENTO, ALUMINIO, 3 BSP | C60: PC | D60: 88 | E60: =IFERROR(_xlfn.XLOOKUP(B60,LISTA!C:C,LISTA!F:F,""),"") -> MI | F60: 19 | H60: 76090000 | I60: 1004800 | J60: 0 - Nacional | K60: Próprio | L60: 10.45 | M60: L20251219 | N60: II - 76090000 | O60: 7891388210438
A61: =IFERROR(_xlfn.XLOOKUP(B61,LISTA!C:C,LISTA!B:B,""),"") -> 000300 | B61: BUCHA ACABAMENTO, ALUMINIO, 1 BSP | C61: PC | D61: 20 | E61: =IFERROR(_xlfn.XLOOKUP(B61,LISTA!C:C,LISTA!F:F,""),"") -> MI | F61: 39 | H61: 73089010 | I61: 1004800 | J61: 0 - Nacional | K61: Próprio | L61: 9.71 | M61: L20250818 | N61: II - 73089010 | O61: 7899840422526
A62: =IFERROR(_xlfn.XLOOKUP(B62,LISTA!C:C,LISTA!B:B,""),"") -> 000302 | B62: BUCHA ACABAMENTO ALUMINIO 1/2BSP BU-012-B DAISA | C62: PC | D62: 465 | E62: =IFERROR(_xlfn.XLOOKUP(B62,LISTA!C:C,LISTA!F:F,""),"") -> MI | F62: 61 | G62: DAISA | H62: 76090000 | I62: 1004800 | J62: 0 - Nacional | K62: Próprio | L62: 9.97 | M62: L20250122 | N62: II - 76090000 | O62: 7892719319013
A63: =IFERROR(_xlfn.XLOOKUP(B63,LISTA!C:C,LISTA!B:B,""),"") -> 000303 | B63: BUCHA ACABAMENTO ALUMINIO 2.1/2BSP BU-212-B DAISA | C63: PC | D63: 353 | E63: =IFERROR(_xlfn.XLOOKUP(B63,LISTA!C:C,LISTA!F:F,""),"") -> MI | F63: 12 | G63: DAISA | H63: 76090000 | I63: 1004800 | J63: 0 - Nacional | K63: Próprio | L63: 11.79 | M63: L20250217 | N63: II - 76090000 | O63: 7895884952611
A64: =IFERROR(_xlfn.XLOOKUP(B64,LISTA!C:C,LISTA!B:B,""),"") -> 000310 | B64: PORCA ACABAMENTO ALUMINIO 1/2BSP PU-012-BSP DAISA | C64: PC | D64: 379 | E64: =IFERROR(_xlfn.XLOOKUP(B64,LISTA!C:C,LISTA!F:F,""),"") -> MI | F64: 54 | G64: DAISA | H64: 76090000 | I64: 1004800 | J64: 0 - Nacional | K64: Próprio | L64: 14.88 | M64: L20250209 | N64: II - 76090000 | O64: 7898694131802
A65: =IFERROR(_xlfn.XLOOKUP(B65,LISTA!C:C,LISTA!B:B,""),"") -> 000311 | B65: BUCHA REDUCAO, EX-D, FERRO NODULAR, GF, GR. IIA/IIB OU IIC ZN. 1 OU 2, 3/4 X 1/2 NPT | C65: PC | D65: 449 | E65: =IFERROR(_xlfn.XLOOKUP(B65,LISTA!C:C,LISTA!F:F,""),"") -> MI | F65: 42 | H65: 73071920 | I65: 1004800 | J65: 0 - Nacional | K65: Controlado | L65: 40.29 | M65: L20250611 | N65: II - 73071920 | O65: 7898803068311
A66: =IFERROR(_xlfn.XLOOKUP(B66,LISTA!C:C,LISTA!B:B,""),"") -> 000312 | B66: BUCHA REDUCAO ALUMINIO 2 X 1/2BSP BRR 200 X 012 DAISA | C66: PC | D66: 166 | E66: =IFERROR(_xlfn.XLOOKUP(B66,LISTA!C:C,LISTA!F:F,""),"") -> MI | F66: 42 | G66: DAISA | H66: 76090000 | I66: 1004800 | J66: 0 - Nacional | K66: Próprio | L66: 5.31 | M66: L20250424 | N66: II - 76090000 | O66: 7891402034202
A67: =IFERROR(_xlfn.XLOOKUP(B67,LISTA!C:C,LISTA!B:B,""),"") -> 000318 | B67: ARRUELA ACABAMENTO ALUMINIO 4BSP AU 400 - BSP DAISA | C67: PC | D67: 439 | E67: =IFERROR(_xlfn.XLOOKUP(B67,LISTA!C:C,LISTA!F:F,""),"") -> MI | F67: 26 | G67: DAISA | H67: 76090000 | I67: 1004800 | J67: 0 - Nacional | K67: Próprio | L67: 7.63 | M67: L20250603 | N67: II - 76090000 | O67: 7894979531049
A68: =IFERROR(_xlfn.XLOOKUP(B68,LISTA!C:C,LISTA!B:B,""),"") -> 000320 | B68: BUCHA REDUCAO, EX-D, FERRO NODULAR, GF, GR. IIA/IIB OU IIC ZN. 1 OU 2, 1 X 3/4 NPT | C68: PC | D68: 302 | E68: =IFERROR(_xlfn.XLOOKUP(B68,LISTA!C:C,LISTA!F:F,""),"") -> MI | F68: 25 | H68: 73071920 | I68: 1004800 | J68: 0 - Nacional | K68: Controlado | L68: 29.1 | M68: L20250514 | N68: II - 73071920 | O68: 7893449479968
A69: =IFERROR(_xlfn.XLOOKUP(B69,LISTA!C:C,LISTA!B:B,""),"") -> 000397 | B69: CONECTOR MACHO ZC DE LATAO FIXO 1NPT CMZL-1 S.P.T.F | C69: PC | D69: 50 | E69: =IFERROR(_xlfn.XLOOKUP(B69,LISTA!C:C,LISTA!F:F,""),"") -> MI | F69: 41 | G69: S.P.T.F | H69: 74122000 | I69: 1004800 | J69: 0 - Nacional | K69: Próprio | L69: 30.68 | M69: L20250326 | N69: II - 74122000 | O69: 7891943852917
A70: =IFERROR(_xlfn.XLOOKUP(B70,LISTA!C:C,LISTA!B:B,""),"") -> 000399 | B70: CONECTOR MACHO GIRATORIO, ALUMINIO, P/ SEALTUBO 1.1/2, ROSCA 1.1/2BSP CMGA-112 S.P.T.F | C70: PC | D70: 284 | E70: =IFERROR(_xlfn.XLOOKUP(B70,LISTA!C:C,LISTA!F:F,""),"") -> MI | F70: 19 | G70: S.P.T.F | H70: 83071010 | I70: 1004800 | J70: 0 - Nacional | K70: Próprio | L70: 18.94 | M70: L20251118 | N70: II - 83071010 | O70: 7899134394113
A71: =IFERROR(_xlfn.XLOOKUP(B71,LISTA!C:C,LISTA!B:B,""),"") -> 000403 | B71: CONECTOR MACHO ZC DE LATAO GIRATORIO 1/2NPT CMZGL-12 S.P.T.F | C71: PC | D71: 375 | E71: =IFERROR(_xlfn.XLOOKUP(B71,LISTA!C:C,LISTA!F:F,""),"") -> MI | F71: 30 | G71: S.P.T.F | H71: 74122000 | I71: 1004800 | J71: 0 - Nacional | K71: Próprio | L71: 8.82 | M71: L20250627 | N71: II - 74122000 | O71: 7894600527596
A72: =IFERROR(_xlfn.XLOOKUP(B72,LISTA!C:C,LISTA!B:B,""),"") -> 000406 | B72: CONECTOR FIXO, REUSAVEL, ALUMINIO, MACHO, P/ ELETRODUTO FLEXIVEL DE ACO REVEST. PVC, ROSCA 2 BSP | C72: PC | D72: 235 | E72: =IFERROR(_xlfn.XLOOKUP(B72,LISTA!C:C,LISTA!F:F,""),"") -> MI | F72: 17 | H72: 39173900 | I72: 1004100 | J72: 0 - Nacional | K72: Próprio | L72: 7.39 | M72: L20251022 | N72: II - 39173900 | O72: 7896391253950
A73: =IFERROR(_xlfn.XLOOKUP(B73,LISTA!C:C,LISTA!B:B,""),"") -> 000440 | B73: PORCA LOSANGULAR S/ MOLA ZC 3/8 DP 621 DISPAN | C73: PC | D73: 232 | E73: =IFERROR(_xlfn.XLOOKUP(B73,LISTA!C:C,LISTA!F:F,""),"") -> MI | F73: 79 | G73: DISPAN | H73: 73181600 | I73: 1005000 | J73: 0 - Nacional | K73: Próprio | L73: 0.98 | M73: L20251012 | N73: II - 73181600 | O73: 7891348628590
A74: =IFERROR(_xlfn.XLOOKUP(B74,LISTA!C:C,LISTA!B:B,""),"") -> 000441 | B74: CONDULETE ROSCAVEL EM ALUMINIO FUNDIDO EX-D C/ TAMPA 1.1/2NPT TIPO X TCLX/5-X TELBRA | C74: PC | D74: 272 | E74: =IFERROR(_xlfn.XLOOKUP(B74,LISTA!C:C,LISTA!F:F,""),"") -> MI | F74: 75 | G74: TELBRA | H74: 76090000 | I74: 1004100 | J74: 0 - Nacional | K74: Controlado | L74: 116.68 | M74: L20250503 | N74: II - 76090000 | O74: 7891778352838
A75: =IFERROR(_xlfn.XLOOKUP(B75,LISTA!C:C,LISTA!B:B,""),"") -> 000444 | B75: CONDULETE, ROSCAVEL, ALUMINIO, C/ TAMPA, JUNTA VEDACAO, 1.1/2 BSP, TIPO T | C75: PC | D75: 215 | E75: =IFERROR(_xlfn.XLOOKUP(B75,LISTA!C:C,LISTA!F:F,""),"") -> MI | F75: 59 | H75: 76090000 | I75: 1004100 | J75: 0 - Nacional | K75: Próprio | L75: 55.6 | M75: L20250628 | N75: II - 76090000 | O75: 7898174894866
A76: =IFERROR(_xlfn.XLOOKUP(B76,LISTA!C:C,LISTA!B:B,""),"") -> 000454 | B76: SUPORTE TIPO C | C76: PC | D76: 150 | E76: =IFERROR(_xlfn.XLOOKUP(B76,LISTA!C:C,LISTA!F:F,""),"") -> MI | F76: 16 | H76: 73089010 | I76: 1005000 | J76: 0 - Nacional | K76: Próprio | L76: 20.47 | M76: L20251012 | N76: II - 73089010 | O76: 7894380577018
A77: =IFERROR(_xlfn.XLOOKUP(B77,LISTA!C:C,LISTA!B:B,""),"") -> 000478 | B77: SUPORTE EM L | C77: PC | D77: 280 | E77: =IFERROR(_xlfn.XLOOKUP(B77,LISTA!C:C,LISTA!F:F,""),"") -> MI | F77: 69 | H77: 73089010 | I77: 1005000 | J77: 0 - Nacional | K77: Próprio | L77: 32.04 | M77: L20250506 | N77: II - 73089010 | O77: 7898236298447
A78: =IFERROR(_xlfn.XLOOKUP(B78,LISTA!C:C,LISTA!B:B,""),"") -> 000502 | B78: CONDULETE, ROSCAVEL, ALUMINIO FUNDIDO, EX-D, C/ TAMPA, IIA/IIB/IEC 60079-0/60079-1/60529, 3/4NPT, C | C78: PC | D78: 320 | E78: =IFERROR(_xlfn.XLOOKUP(B78,LISTA!C:C,LISTA!F:F,""),"") -> MI | F78: 38 | H78: 76090000 | I78: 1004100 | J78: 0 - Nacional | K78: Controlado | L78: 240.77 | M78: L20250911 | N78: II - 76090000 | O78: 7899586107496
A79: =IFERROR(_xlfn.XLOOKUP(B79,LISTA!C:C,LISTA!B:B,""),"") -> 000528 | B79: CONDULETE ROSCAVEL EM ALUMINIO C/ TAMPA 1BSP TIPO B DIIRT 100-BSP-B DAISA | C79: PC | D79: 344 | E79: =IFERROR(_xlfn.XLOOKUP(B79,LISTA!C:C,LISTA!F:F,""),"") -> MI | F79: 6 | G79: DAISA | H79: 76090000 | I79: 1004100 | J79: 0 - Nacional | K79: Próprio | L79: 35.16 | M79: L20250703 | N79: II - 76090000 | O79: 7895565313698
A80: =IFERROR(_xlfn.XLOOKUP(B80,LISTA!C:C,LISTA!B:B,""),"") -> 000575 | B80: SUPORTE HORIZONTAL P/ ELETROCALHA, CHAPA #16, PZ, 100 MM | C80: PC | D80: 58 | E80: =IFERROR(_xlfn.XLOOKUP(B80,LISTA!C:C,LISTA!F:F,""),"") -> MI | F80: 22 | H80: 73089010 | I80: 1004100 | J80: 0 - Nacional | K80: Próprio | L80: 55.66 | M80: L20250501 | N80: II - 73089010 | O80: 7896037540556
A81: =IFERROR(_xlfn.XLOOKUP(B81,LISTA!C:C,LISTA!B:B,""),"") -> 000579 | B81: CABECOTE DE ALUMINIO, TIPO L, 2 POL. | C81: PC | D81: 194 | E81: =IFERROR(_xlfn.XLOOKUP(B81,LISTA!C:C,LISTA!F:F,""),"") -> MI | F81: 26 | H81: 76090000 | I81: 1004800 | J81: 0 - Nacional | K81: Próprio | L81: 29.97 | M81: L20250910 | N81: II - 76090000 | O81: 7894549278976
A82: =IFERROR(_xlfn.XLOOKUP(B82,LISTA!C:C,LISTA!B:B,""),"") -> 000581 | B82: PRENSA CABO, CZ RAL 7035, POLIAMIDA 6.6, IP67, C/ CONTRA PORCA, ROSCA CURTA, 3/8BSP | C82: PC | D82: 162 | E82: =IFERROR(_xlfn.XLOOKUP(B82,LISTA!C:C,LISTA!F:F,""),"") -> MI | F82: 18 | H82: 39174090 | I82: 1004800 | J82: 0 - Nacional | K82: Próprio | L82: 15.13 | M82: L20250621 | N82: II - 39174090 | O82: 7896133465997
A83: =IFERROR(_xlfn.XLOOKUP(B83,LISTA!C:C,LISTA!B:B,""),"") -> 000582 | B83: TAMPAO EM PVC P/ CONDULETE MULTIPLO, 1 POL. | C83: PC | D83: 272 | E83: =IFERROR(_xlfn.XLOOKUP(B83,LISTA!C:C,LISTA!F:F,""),"") -> MI | F83: 78 | H83: 39174090 | I83: 1004100 | J83: 0 - Nacional | K83: Próprio | L83: 50.58 | M83: L20251024 | N83: II - 39174090 | O83: 7893192339289
A84: =IFERROR(_xlfn.XLOOKUP(B84,LISTA!C:C,LISTA!B:B,""),"") -> 000614 | B84: CONDULETE ROSCAVEL EM ALUMINIO C/ TAMPA 2.1/2BSP TIPO LR DIIRT 212-BSP-LR DAISA | C84: PC | D84: 196 | E84: =IFERROR(_xlfn.XLOOKUP(B84,LISTA!C:C,LISTA!F:F,""),"") -> MI | F84: 25 | G84: DAISA | H84: 76090000 | I84: 1004100 | J84: 0 - Nacional | K84: Próprio | L84: 76.75 | M84: L20251019 | N84: II - 76090000 | O84: 7891996533513
A85: =IFERROR(_xlfn.XLOOKUP(B85,LISTA!C:C,LISTA!B:B,""),"") -> 000621 | B85: CABECOTE DE ALUMINIO, TIPO L, 1 POL. | C85: PC | D85: 437 | E85: =IFERROR(_xlfn.XLOOKUP(B85,LISTA!C:C,LISTA!F:F,""),"") -> MI | F85: 40 | H85: 76090000 | I85: 1004800 | J85: 0 - Nacional | K85: Próprio | L85: 18.97 | M85: L20250310 | N85: II - 76090000 | O85: 7898844844207
A86: =IFERROR(_xlfn.XLOOKUP(B86,LISTA!C:C,LISTA!B:B,""),"") -> 000622 | B86: CONDULETE, MULTIPLO, ALUMINIO, C/ TAMPA, 2 BSP, TIPO X | C86: PC | D86: 41 | E86: =IFERROR(_xlfn.XLOOKUP(B86,LISTA!C:C,LISTA!F:F,""),"") -> MI | F86: 58 | H86: 76090000 | I86: 1004100 | J86: 0 - Nacional | K86: Próprio | L86: 47.62 | M86: L20250107 | N86: II - 76090000 | O86: 7892752081191
A87: =IFERROR(_xlfn.XLOOKUP(B87,LISTA!C:C,LISTA!B:B,""),"") -> 000814 | B87: CONDULETE, ROSCAVEL, ALUMINIO FUNDIDO, EX-D, C/ TAMPA, IIA/IIB/IEC 60079-0/60079-1/60529, 1BSP, TIPO C | C87: PC | D87: 291 | E87: =IFERROR(_xlfn.XLOOKUP(B87,LISTA!C:C,LISTA!F:F,""),"") -> MI | F87: 23 | H87: 76090000 | I87: 1004100 | J87: 0 - Nacional | K87: Controlado | L87: 122.5 | M87: L20251219 | N87: II - 76090000 | O87: 7899632946974
A88: =IFERROR(_xlfn.XLOOKUP(B88,LISTA!C:C,LISTA!B:B,""),"") -> 000818 | B88: CONDULETE, ROSCAVEL, ALUMINIO FUNDIDO, EX-D, C/ TAMPA, IIA/IIB/IEC 60079-0/60079-1/60529, 1BSP, TIPO LL | C88: PC | D88: 255 | E88: =IFERROR(_xlfn.XLOOKUP(B88,LISTA!C:C,LISTA!F:F,""),"") -> MI | F88: 61 | H88: 76090000 | I88: 1004100 | J88: 0 - Nacional | K88: Controlado | L88: 234.34 | M88: L20251226 | N88: II - 76090000 | O88: 7891735057052
A89: =IFERROR(_xlfn.XLOOKUP(B89,LISTA!C:C,LISTA!B:B,""),"") -> 000820 | B89: CONDULETE, ROSCAVEL, ALUMINIO FUNDIDO, EX-D, C/ TAMPA, IIA/IIB/IEC 60079-0/60079-1/60529, 1BSP, TIPO LR | C89: PC | D89: 180 | E89: =IFERROR(_xlfn.XLOOKUP(B89,LISTA!C:C,LISTA!F:F,""),"") -> MI | F89: 61 | H89: 76090000 | I89: 1004100 | J89: 0 - Nacional | K89: Controlado | L89: 97.69 | M89: L20250602 | N89: II - 76090000 | O89: 7895452371291
A90: =IFERROR(_xlfn.XLOOKUP(B90,LISTA!C:C,LISTA!B:B,""),"") -> 000821 | B90: CONDULETE, ROSCAVEL, ALUMINIO FUNDIDO, EX-D, C/ TAMPA, IIA/IIB/IEC 60079-0/60079-1/60529, 3/4BSP, TIPO C | C90: PC | D90: 106 | E90: =IFERROR(_xlfn.XLOOKUP(B90,LISTA!C:C,LISTA!F:F,""),"") -> MI | F90: 55 | H90: 76090000 | I90: 1004100 | J90: 0 - Nacional | K90: Controlado | L90: 129.94 | M90: L20250614 | N90: II - 76090000 | O90: 7897057587106
A91: =IFERROR(_xlfn.XLOOKUP(B91,LISTA!C:C,LISTA!B:B,""),"") -> 000823 | B91: CONDULETE, ROSCAVEL, ALUMINIO FUNDIDO, EX-D, C/ TAMPA, IIA/IIB/IEC 60079-0/60079-1/60529, 3/4BSP, TIPO LL | C91: PC | D91: 146 | E91: =IFERROR(_xlfn.XLOOKUP(B91,LISTA!C:C,LISTA!F:F,""),"") -> MI | F91: 6 | H91: 76090000 | I91: 1004100 | J91: 0 - Nacional | K91: Controlado | L91: 86.39 | M91: L20251205 | N91: II - 76090000 | O91: 7897553506201
A92: =IFERROR(_xlfn.XLOOKUP(B92,LISTA!C:C,LISTA!B:B,""),"") -> 000824 | B92: CONDULETE, ROSCAVEL, ALUMINIO FUNDIDO, EX-D, C/ TAMPA, IIA/IIB/IEC 60079-0/60079-1/60529, 3/4BSP, TIPO LR | C92: PC | D92: 223 | E92: =IFERROR(_xlfn.XLOOKUP(B92,LISTA!C:C,LISTA!F:F,""),"") -> MI | F92: 55 | H92: 76090000 | I92: 1004100 | J92: 0 - Nacional | K92: Controlado | L92: 253.69 | M92: L20250719 | N92: II - 76090000 | O92: 7895086467093
A93: =IFERROR(_xlfn.XLOOKUP(B93,LISTA!C:C,LISTA!B:B,""),"") -> 000825 | B93: CONDULETE, ROSCAVEL, ALUMINIO FUNDIDO, EX-D, C/ TAMPA, IIA/IIB/IEC 60079-0/60079-1/60529, 3/4BSP, TIPO T | C93: PC | D93: 298 | E93: =IFERROR(_xlfn.XLOOKUP(B93,LISTA!C:C,LISTA!F:F,""),"") -> MI | F93: 72 | H93: 76090000 | I93: 1004100 | J93: 0 - Nacional | K93: Controlado | L93: 200.72 | M93: L20250714 | N93: II - 76090000 | O93: 7894861376189
A94: =IFERROR(_xlfn.XLOOKUP(B94,LISTA!C:C,LISTA!B:B,""),"") -> 000826 | B94: CONDULETE, ROSCAVEL, ALUMINIO FUNDIDO, EX-D, C/ TAMPA, IIA/IIB/IEC 60079-0/60079-1/60529, 2BSP, TIPO C | C94: PC | D94: 104 | E94: =IFERROR(_xlfn.XLOOKUP(B94,LISTA!C:C,LISTA!F:F,""),"") -> MI | F94: 23 | H94: 76090000 | I94: 1004100 | J94: 0 - Nacional | K94: Controlado | L94: 230.12 | M94: L20250315 | N94: II - 76090000 | O94: 7892999683453
A95: =IFERROR(_xlfn.XLOOKUP(B95,LISTA!C:C,LISTA!B:B,""),"") -> 000827 | B95: CONDULETE, ROSCAVEL, ALUMINIO FUNDIDO, EX-D, C/ TAMPA, IIA/IIB/IEC 60079-0/60079-1/60529, 2BSP, TIPO LL | C95: PC | D95: 474 | E95: =IFERROR(_xlfn.XLOOKUP(B95,LISTA!C:C,LISTA!F:F,""),"") -> MI | F95: 51 | H95: 76090000 | I95: 1004100 | J95: 0 - Nacional | K95: Controlado | L95: 116.82 | M95: L20250122 | N95: II - 76090000 | O95: 7891583885966
A96: =IFERROR(_xlfn.XLOOKUP(B96,LISTA!C:C,LISTA!B:B,""),"") -> 000829 | B96: CONDULETE, ROSCAVEL, ALUMINIO FUNDIDO, EX-D, C/ TAMPA, IIA/IIB/IEC 60079-0/60079-1/60529, 2BSP, TIPO LR | C96: PC | D96: 123 | E96: =IFERROR(_xlfn.XLOOKUP(B96,LISTA!C:C,LISTA!F:F,""),"") -> MI | F96: 25 | H96: 76090000 | I96: 1004100 | J96: 0 - Nacional | K96: Controlado | L96: 125.42 | M96: L20251201 | N96: II - 76090000 | O96: 7899725450057
... A100: =IFERROR(_xlfn.XLOOKUP(B100,LISTA!C:C,LISTA!B:B,""),"") -> 000834 | B100: UNIAO MACHO / FEMEA, P/ ELETRODUTO, ALUMINIO, TGVP, 3/4 BSP | C100: PC | D100: 186 | E100: =IFERROR(_xlfn.XLOOKUP(B100,LISTA!C:C,LISTA!F:F,""),"") -> MI | F100: 69 | H100: 73089010 | I100: 1004100 | J100: 0 - Nacional | K100: Próprio | L100: 23.32 | M100: L20251227 | N100: II - 73089010 | O100: 7891874866627
A101: =IFERROR(_xlfn.XLOOKUP(B101,LISTA!C:C,LISTA!B:B,""),"") -> 000918 | B101: CONDULETE DAILET EM ALUMINIO C/ TAMPA, 4 TIPO C DAISA | C101: PC | D101: 400 | E101: =IFERROR(_xlfn.XLOOKUP(B101,LISTA!C:C,LISTA!F:F,""),"") -> MI | F101: 16 | G101: DAISA | H101: 76090000 | I101: 1004100 | J101: 0 - Nacional | K101: Próprio | L101: 117.92 | M101: L20250726 | N101: II - 76090000 | O101: 7895879650290
A102: =IFERROR(_xlfn.XLOOKUP(B102,LISTA!C:C,LISTA!B:B,""),"") -> 000922 | B102: CONDULETE DAILET EM ALUMINIO C/ TAMPA, 2 TIPO LL DAISA | C102: PC | D102: 393 | E102: =IFERROR(_xlfn.XLOOKUP(B102,LISTA!C:C,LISTA!F:F,""),"") -> MI | F102: 39 | G102: DAISA | H102: 76090000 | I102: 1004100 | J102: 0 - Nacional | K102: Próprio | L102: 88.12 | M102: L20250122 | N102: II - 76090000 | O102: 7896062703688
A103: =IFERROR(_xlfn.XLOOKUP(B103,LISTA!C:C,LISTA!B:B,""),"") -> 000923 | B103: CONDULETE DAILET EM ALUMINIO C/ TAMPA, 2 TIPO T DAISA | C103: PC | D103: 304 | E103: =IFERROR(_xlfn.XLOOKUP(B103,LISTA!C:C,LISTA!F:F,""),"") -> MI | F103: 60 | G103: DAISA | H103: 76090000 | I103: 1004100 | J103: 0 - Nacional | K103: Próprio | L103: 139.08 | M103: L20250506 | N103: II - 76090000 | O103: 7898952775574
...

Sheet Instrucoes
B4: Preenchimento da lista para solicitação de materiais
B6: Importante: O documento deve ser preenchido conforme instrução abaixo. Não serão aceitos documentos não preenchidos ou parcialmente preenchidos.
B8: 1. Atualização dos dados da Planilha F-T-001 - Solicitação de Compra de Matéria-Prima:
B9: A planilha será atualizada mensalmente e disponibilizada pelo controle de documentos.
B11: 2. Cabeçalho (conf. imagem 2):
B12: a. Cliente: Informar o nome do cliente e a unidade de atendimento em caso de duas ou mais;
B13: b. Projeto: Nome do projeto. Ex.: Caldeira II;
B14: c. OS: Preencher com o número da ordem de serviços: OCS_xxx_xx ou ATK_xxx_xx;
B15: d. Data: Data da solicitação;
B16: e. Elaborado por: Nome do solicitante;
B17: f. N° Contrato: Quando houve, citar o contrato;
B18: g. Doc. Ref.: Se houve uma lista do cliente como base, cite o número;
... B21: j. ID: Preencher a identificação da solicitação (conf. imagem 1);
B23: #VALUE!
B24: Imagem 1
B25: #VALUE!
B26: Imagem 2
B28: 3. Seleção de produtos
B29: a. Utilize o campo de busca para localizar o produto desejado; digite parte do Texto e Tecle "Enter"
B30: b. A busca sera realizada pelo código e/ou produto.
B31: c. O símbolo * é utilizado como um facilitador na busca, exemplo: se estiver buscando por CONDULETE, ROSCAVEL, ALUMINIO FUNDIDO, EX-D, C/ TAMPA, IIA/IIB/IEC 60079-0/60079-1/60529, 1NPT, LR, posso procurar por “CONDULETE*EX”, mas, ainda aparecerão conduletes de diversas formas e bitolas (imagem 3), porém, se pesquisarmos por “CONDULETE*EX*1.1/2” a pesquisa fica mais restrita e rápida (imagem 4);
B32: d. Após localizar o produto desejado clique 2 vezes no código numérico ou no produto, assim o produto será gravado na lista de materiais
B33: e. Em seguida, para Limpar o filtro e localizar outro produto tecle "ESC" ou clique em “Limpa Filtro” e refaça a busca (imagem 5);
B35: #VALUE!
B36: Imagem 3
B37: #VALUE!
B38: Imagem 4
B39: #VALUE!
B40: Imagem 5
B41: f. Na coluna D denominada Estoque, pode-se conferir o estoque mensal para ajudar a tomar a melhor decisão conforme a necessidade.
B42: Conforme abaixo, se a necessidade for para CONDULETE, ROSCAVEL, ALUMINIO FUNDIDO, EX-D, C/ TAMPA, IIA/IIB/IEC 60079-0/60079-1/60529, 1.1/2NPT, LR o solicitante pode alterar a solicitação e adequar o projeto para LL e considerar as 20 peças de estoque (imagem 6).
B43: #VALUE!
B44: Imagem 6
B45: g. Após a inclusão do produto, ele automaticamente será enviado a aba “LM” e será agrupado conforme ordem de inclusão.
B46: Se acaso selecionar um produto incorretamente, basta clicar em cima do código e em seguida DELETE, a planilha entenderá que ele foi excluído e o próximo produto assumirá seu lugar.
B47: 4. Preenchimento da lista de materiais (LM) (imagem 7)
B48: a. Rev: Inicia-se na revisão 0 e deve ser preenchido individualmente. Quando algum item sofrer alteração, deve-se considerar como revisão 1 e assim sucessivamente;
B49: b. Na sequência informe a quantidade de produtos;
B50: c. Adicione alguma observação que considerar relevante;
B51: #VALUE!
B52: Imagem 7
B54: 5. Produtos que não possuam cadastro (imagem 8)
B55: a. O preenchimento dos produtos que não tiverem cadastro deve ser diretamente no campo DESCRIÇÃO localizado na coluna H, mantendo o campo CÓDIGO na coluna D como XXXXXX. Em seguida, preencha a quantidade e observação quando cabível.
B56: #VALUE!
B57: Imagem 8
B58: 6. Envio da lista de materiais
B59: a. Salve o arquivo em seu computador como o nome ID, exemplo: S-T-TLM-CBN-031-001-00 que pelo título indica uma lista de materiais para uso em campo do cliente Combio de Balsa Nova, ATK_031_23, lista 01 e revisão 00.
B60: Envie por e-mail aos compradores Rafael e William em caso de materiais de instalação: rsouza@authomathika.com.br; wpessini@authomathika.com.br
B61: Ou para Rafael e Alan em caso de materiais para painéis e consumíveis: rsouza@authomathika.com.br; astegani@authomathika.com.br.
B62: 7. É de responsabilidade do Suprimentos salvar esta LM na pasta do cliente e atualiza-la conforme as revisões – ENGENHARIA / CLIENTES / EM ANDAMENTO / CLIENTE X / UNIDADE X / OS X / EM ANDAMENTO / ADMINISTRATIVO / DOC COMPRA / LM.
B63: 8. É de responsabilidade do Suprimentos a atualização da lista de materiais e o envio aos usuários, mensalmente.
B64: 9. É de responsabilidade do solicitante acompanhar a entrega dos produtos solicitados.

Sheet Cabeamento
A1: Código | B1: Descricao NF | C1: Unidade | D1: Quant | E1: Categoria | F1: Est. Mínimo | G1: Fabricante | H1: NCM | I1: CEST | J1: Ind. Origem | K1: Tipo Custódia | L1: Preço Custo | M1: Lote | N1: Classif. Fiscal | O1: Cód. Barras
A2: =IFERROR(_xlfn.XLOOKUP(B2,LISTA!C:C,LISTA!B:B,""),"") -> 000136 | B2: CABO INSTRUMENTACAO BC, ISOL PVC 70ØC, NBR 10300, C/ BLIND. ELETROST. COLETIVA E FIO DRENO 2X4,00MMY TELEFIO | C2: =IFERROR(_xlfn.XLOOKUP(B2,LISTA!C:C,LISTA!D:D,""),"") -> MT | D2: =IFERROR(_xlfn.XLOOKUP(B2,LISTA!C:C,LISTA!E:E,""),"") -> 0 | E2: =IFERROR(_xlfn.XLOOKUP(B2,LISTA!C:C,LISTA!F:F,""),"") -> MI | F2: 49 | G2: TELEFIO | H2: 85444900 | I2: 1004800 | J2: 0 - Nacional | K2: Próprio | L2: 86.93 | M2: L20250922 | N2: II - 85444900 | O2: 7897204901102
A3: =IFERROR(_xlfn.XLOOKUP(B3,LISTA!C:C,LISTA!B:B,""),"") -> 000151 | B3: CABO TERMOPAR EXTENSAO K, ISOL. SILICONE AMARELO EXTERNO E INTERNO, SEM BLINDAGEM, 2 X 1,00MM CK100SS-A CONSISTEC | C3: =IFERROR(_xlfn.XLOOKUP(B3,LISTA!C:C,LISTA!D:D,""),"") -> MT | D3: =IFERROR(_xlfn.XLOOKUP(B3,LISTA!C:C,LISTA!E:E,""),"") -> 0 | E3: =IFERROR(_xlfn.XLOOKUP(B3,LISTA!C:C,LISTA!F:F,""),"") -> MI | F3: 44 | G3: CONSISTEC | H3: 85444900 | I3: 1004100 | J3: 0 - Nacional | K3: Próprio | L3: 4.8 | M3: L20250309 | N3: II - 85444900 | O3: 7899973295931
A4: =IFERROR(_xlfn.XLOOKUP(B4,LISTA!C:C,LISTA!B:B,""),"") -> 000156 | B4: CABO INSTRUMENTACAO BF, MA, PVC/E 70ØC, NBR 10300, C/ BLIND. ELETROST. COLETIVA E FIO DRENO 2X1,0MMY 900475 INNOV | C4: =IFERROR(_xlfn.XLOOKUP(B4,LISTA!C:C,LISTA!D:D,""),"") -> MT | D4: =IFERROR(_xlfn.XLOOKUP(B4,LISTA!C:C,LISTA!E:E,""),"") -> 0 | E4: =IFERROR(_xlfn.XLOOKUP(B4,LISTA!C:C,LISTA!F:F,""),"") -> MI | F4: 58 | G4: INNOV | H4: 85444900 | I4: 1005000 | J4: 0 - Nacional | K4: Próprio | L4: 34.47 | M4: L20250403 | N4: II - 85444900 | O4: 7899095128092
A5: =IFERROR(_xlfn.XLOOKUP(B5,LISTA!C:C,LISTA!B:B,""),"") -> 000173 | B5: CABO INSTRUMENTACAO BC, ISOL PVC 70ØC, NBR 10300, C/ BLIND. ELETROST. COLETIVA E FIO DRENO 2X0,75MMY TELEFIO | C5: =IFERROR(_xlfn.XLOOKUP(B5,LISTA!C:C,LISTA!D:D,""),"") -> MT | D5: =IFERROR(_xlfn.XLOOKUP(B5,LISTA!C:C,LISTA!E:E,""),"") -> 0 | E5: =IFERROR(_xlfn.XLOOKUP(B5,LISTA!C:C,LISTA!F:F,""),"") -> MI | F5: 69 | G5: TELEFIO | H5: 85444900 | I5: 1005000 | J5: 0 - Nacional | K5: Próprio | L5: 42.95 | M5: L20250424 | N5: II - 85444900 | O5: 7891409400582
A6: =IFERROR(_xlfn.XLOOKUP(B6,LISTA!C:C,LISTA!B:B,""),"") -> 000241 | B6: CABO INSTRUMENTACAO BC, ISOL PVC 70ØC, NBR 10300, C/ BLIND. ELETROST. COLETIVA E FIO DRENO 2X2,50MMY TELEFIO | C6: =IFERROR(_xlfn.XLOOKUP(B6,LISTA!C:C,LISTA!D:D,""),"") -> MT | D6: =IFERROR(_xlfn.XLOOKUP(B6,LISTA!C:C,LISTA!E:E,""),"") -> 0 | E6: =IFERROR(_xlfn.XLOOKUP(B6,LISTA!C:C,LISTA!F:F,""),"") -> MI | F6: 63 | G6: TELEFIO | H6: 85444900 | I6: 1005000 | J6: 0 - Nacional | K6: Próprio | L6: 76.51 | M6: L20250210 | N6: II - 85444900 | O6: 7896846017244
A7: =IFERROR(_xlfn.XLOOKUP(B7,LISTA!C:C,LISTA!B:B,""),"") -> 000249 | B7: TERMINAL OLHAL, PRE-ISOLADO, VERMELHO, P/ CABOS 0,50·1,50MM, FURO 5MM | C7: =IFERROR(_xlfn.XLOOKUP(B7,LISTA!C:C,LISTA!D:D,""),"") -> PC | D7: =IFERROR(_xlfn.XLOOKUP(B7,LISTA!C:C,LISTA!E:E,""),"") -> 0 | E7: =IFERROR(_xlfn.XLOOKUP(B7,LISTA!C:C,LISTA!F:F,""),"") -> MC | F7: 9 | H7: 85369090 | I7: 1004100 | J7: 0 - Nacional | K7: Próprio | L7: 48.05 | M7: L20251008 | N7: II - 85369090 | O7: 7895649570705
A8: =IFERROR(_xlfn.XLOOKUP(B8,LISTA!C:C,LISTA!B:B,""),"") -> 000252 | B8: TERMINAL OLHAL, PRE-ISOLADO, VERMELHO, P/ CABOS 0,50·1,50MM, FURO 6,00MM | C8: =IFERROR(_xlfn.XLOOKUP(B8,LISTA!C:C,LISTA!D:D,""),"") -> PC | D8: =IFERROR(_xlfn.XLOOKUP(B8,LISTA!C:C,LISTA!E:E,""),"") -> 0 | E8: =IFERROR(_xlfn.XLOOKUP(B8,LISTA!C:C,LISTA!F:F,""),"") -> MC | F8: 5 | H8: 85369090 | I8: 1004800 | J8: 0 - Nacional | K8: Próprio | L8: 52.81 | M8: L20250820 | N8: II - 85369090 | O8: 7898682550433
A9: =IFERROR(_xlfn.XLOOKUP(B9,LISTA!C:C,LISTA!B:B,""),"") -> 000253 | B9: TERMINAL OLHAL, PRE-ISOLADO, AZUL, P/ CABOS 1,50·2,50MM, FURO 8,00MM | C9: =IFERROR(_xlfn.XLOOKUP(B9,LISTA!C:C,LISTA!D:D,""),"") -> PC | D9: =IFERROR(_xlfn.XLOOKUP(B9,LISTA!C:C,LISTA!E:E,""),"") -> 0 | E9: =IFERROR(_xlfn.XLOOKUP(B9,LISTA!C:C,LISTA!F:F,""),"") -> MC | F9: 66 | H9: 85369090 | I9: 1004100 | J9: 0 - Nacional | K9: Próprio | L9: 79.44 | M9: L20250626 | N9: II - 85369090 | O9: 7892255259872
A10: =IFERROR(_xlfn.XLOOKUP(B10,LISTA!C:C,LISTA!B:B,""),"") -> 000255 | B10: TERMINAL GARFO, PRE-ISOLADO, P/ CABOS 0,50 A 1,50MM, FURO 5,00 MM | C10: =IFERROR(_xlfn.XLOOKUP(B10,LISTA!C:C,LISTA!D:D,""),"") -> PC | D10: =IFERROR(_xlfn.XLOOKUP(B10,LISTA!C:C,LISTA!E:E,""),"") -> 0 | E10: =IFERROR(_xlfn.XLOOKUP(B10,LISTA!C:C,LISTA!F:F,""),"") -> MC | F10: 69 | H10: 85369090 | I10: 1004100 | J10: 0 - Nacional | K10: Próprio | L10: 1.82 | M10: L20250601 | N10: II - 85369090 | O10: 7892386850353
A11: =IFERROR(_xlfn.XLOOKUP(B11,LISTA!C:C,LISTA!B:B,""),"") -> 000258 | B11: TERMINAL OLHAL, PRE-ISOLADO, AZUL, P/ CABOS 1,50 A 2,50MM, FURO 3,00 MM | C11: =IFERROR(_xlfn.XLOOKUP(B11,LISTA!C:C,LISTA!D:D,""),"") -> PC | D11: =IFERROR(_xlfn.XLOOKUP(B11,LISTA!C:C,LISTA!E:E,""),"") -> 0 | E11: =IFERROR(_xlfn.XLOOKUP(B11,LISTA!C:C,LISTA!F:F,""),"") -> MI | F11: 76 | H11: 85369090 | I11: 1004100 | J11: 0 - Nacional | K11: Próprio | L11: 31.02 | M11: L20250821 | N11: II - 85369090 | O11: 7896262014510
A12: =IFERROR(_xlfn.XLOOKUP(B12,LISTA!C:C,LISTA!B:B,""),"") -> 000263 | B12: TERMINAL GARFO, PRE-ISOLADO VERMELHO, P/ CABOS 0,50 A 1,50MM, FURO 4,00 MM | C12: =IFERROR(_xlfn.XLOOKUP(B12,LISTA!C:C,LISTA!D:D,""),"") -> PC | D12: =IFERROR(_xlfn.XLOOKUP(B12,LISTA!C:C,LISTA!E:E,""),"") -> 0 | E12: =IFERROR(_xlfn.XLOOKUP(B12,LISTA!C:C,LISTA!F:F,""),"") -> MI | F12: 66 | H12: 85369090 | I12: 1004800 | J12: 0 - Nacional | K12: Próprio | L12: 58.96 | M12: L20250208 | N12: II - 85369090 | O12: 7891718398571
A13: =IFERROR(_xlfn.XLOOKUP(B13,LISTA!C:C,LISTA!B:B,""),"") -> 000269 | B13: TERMINAL OLHAL, PRE-ISOLADO AMARELO, P/ CABOS 4,00 A 6,00MM, FURO 8MM | C13: =IFERROR(_xlfn.XLOOKUP(B13,LISTA!C:C,LISTA!D:D,""),"") -> PC | D13: =IFERROR(_xlfn.XLOOKUP(B13,LISTA!C:C,LISTA!E:E,""),"") -> 0 | E13: =IFERROR(_xlfn.XLOOKUP(B13,LISTA!C:C,LISTA!F:F,""),"") -> MI | F13: 73 | H13: 85369090 | I13: 1005000 | J13: 0 - Nacional | K13: Próprio | L13: 22.83 | M13: L20251007 | N13: II - 85369090 | O13: 7894798414857
A14: =IFERROR(_xlfn.XLOOKUP(B14,LISTA!C:C,LISTA!B:B,""),"") -> 000270 | B14: TERMINAL GARFO, PRE-ISOLADO, AMARELO, P/ CABOS 4,00 A 6,00MM, FURO 5,00 MM | C14: =IFERROR(_xlfn.XLOOKUP(B14,LISTA!C:C,LISTA!D:D,""),"") -> PC | D14: =IFERROR(_xlfn.XLOOKUP(B14,LISTA!C:C,LISTA!E:E,""),"") -> 0 | E14: =IFERROR(_xlfn.XLOOKUP(B14,LISTA!C:C,LISTA!F:F,""),"") -> MC | F14: 10 | H14: 85369090 | I14: 1004100 | J14: 0 - Nacional | K14: Próprio | L14: 14.09 | M14: L20250516 | N14: II - 85369090 | O14: 7899948127154
A15: =IFERROR(_xlfn.XLOOKUP(B15,LISTA!C:C,LISTA!B:B,""),"") -> 000271 | B15: TERMINAL OLHAL, PRE-ISOLADO, P/ CABOS 1,50 A 2,50MM, FURO 6,00 MM | C15: =IFERROR(_xlfn.XLOOKUP(B15,LISTA!C:C,LISTA!D:D,""),"") -> PC | D15: =IFERROR(_xlfn.XLOOKUP(B15,LISTA!C:C,LISTA!E:E,""),"") -> 0 | E15: =IFERROR(_xlfn.XLOOKUP(B15,LISTA!C:C,LISTA!F:F,""),"") -> MI | F15: 37 | H15: 85369090 | I15: 1004800 | J15: 0 - Nacional | K15: Próprio | L15: 33.82 | M15: L20250812 | N15: II - 85369090 | O15: 7891203015327
A16: =IFERROR(_xlfn.XLOOKUP(B16,LISTA!C:C,LISTA!B:B,""),"") -> 000275 | B16: TERMINAL OLHAL, PRE-ISOLADO VERMELHO, P/ CABOS 1,50 · 2,50MM, FURO 8MM TP-2,5-8 INTELLI | C16: =IFERROR(_xlfn.XLOOKUP(B16,LISTA!C:C,LISTA!D:D,""),"") -> PC | D16: =IFERROR(_xlfn.XLOOKUP(B16,LISTA!C:C,LISTA!E:E,""),"") -> 0 | E16: =IFERROR(_xlfn.XLOOKUP(B16,LISTA!C:C,LISTA!F:F,""),"") -> MI | F16: 62 | G16: INTELLI | H16: 85369090 | I16: 1004800 | J16: 0 - Nacional | K16: Próprio | L16: 78.84 | M16: L20250320 | N16: II - 85369090 | O16: 7895768627526
A17: =IFERROR(_xlfn.XLOOKUP(B17,LISTA!C:C,LISTA!B:B,""),"") -> 000286 | B17: TERMINAL GARFO, PRE-ISOLADO AZUL, P/ CABOS 1,50 · 2,5MM, FURO 4MM TPF-2,5-4 INTELLI | C17: =IFERROR(_xlfn.XLOOKUP(B17,LISTA!C:C,LISTA!D:D,""),"") -> PC | D17: =IFERROR(_xlfn.XLOOKUP(B17,LISTA!C:C,LISTA!E:E,""),"") -> 0 | E17: =IFERROR(_xlfn.XLOOKUP(B17,LISTA!C:C,LISTA!F:F,""),"") -> MI | F17: 63 | G17: INTELLI | H17: 85369090 | I17: 1004800 | J17: 0 - Nacional | K17: Próprio | L17: 46.27 | M17: L20250607 | N17: II - 85369090 | O17: 7891101781517
A18: =IFERROR(_xlfn.XLOOKUP(B18,LISTA!C:C,LISTA!B:B,""),"") -> 000352 | B18: CABO FLEXIVEL FOREPLAST, ISOL. PVC BWF, 450 / 750V BRANCO 0,50MM 25404001371 PHELPS DODGE | C18: =IFERROR(_xlfn.XLOOKUP(B18,LISTA!C:C,LISTA!D:D,""),"") -> MT | D18: =IFERROR(_xlfn.XLOOKUP(B18,LISTA!C:C,LISTA!E:E,""),"") -> 0 | E18: =IFERROR(_xlfn.XLOOKUP(B18,LISTA!C:C,LISTA!F:F,""),"") -> MI | F18: 30 | G18: PHELPS DODGE | H18: 85444900 | I18: 1004800 | J18: 0 - Nacional | K18: Próprio | L18: 27.59 | M18: L20251224 | N18: II - 85444900 | O18: 7896361963274
A19: =IFERROR(_xlfn.XLOOKUP(B19,LISTA!C:C,LISTA!B:B,""),"") -> 000378 | B19: TERMINAL OLHAL, PRE-ISOLADO, P/ CABOS 4,00 A 6,00MM, FURO 6,00 MM | C19: =IFERROR(_xlfn.XLOOKUP(B19,LISTA!C:C,LISTA!D:D,""),"") -> PC | D19: =IFERROR(_xlfn.XLOOKUP(B19,LISTA!C:C,LISTA!E:E,""),"") -> 0 | E19: =IFERROR(_xlfn.XLOOKUP(B19,LISTA!C:C,LISTA!F:F,""),"") -> MI | F19: 12 | H19: 85369090 | I19: 1005000 | J19: 0 - Nacional | K19: Próprio | L19: 55.63 | M19: L20250804 | N19: II - 85369090 | O19: 7891863876492
A20: =IFERROR(_xlfn.XLOOKUP(B20,LISTA!C:C,LISTA!B:B,""),"") -> 000456 | B20: CABO INSTRUMENTACAO BIC, ISOL PVC 70ØC, NBR 10300, C/ BLIND. ELETROST. COLETIVA E IND. FIO DRENO 4X2X0,75MMY TELEFIO | C20: =IFERROR(_xlfn.XLOOKUP(B20,LISTA!C:C,LISTA!D:D,""),"") -> MT | D20: =IFERROR(_xlfn.XLOOKUP(B20,LISTA!C:C,LISTA!E:E,""),"") -> 0 | E20: =IFERROR(_xlfn.XLOOKUP(B20,LISTA!C:C,LISTA!F:F,""),"") -> MI | F20: 68 | G20: TELEFIO | H20: 85444900 | I20: 1005000 | J20: 0 - Nacional | K20: Próprio | L20: 44.27 | M20: L20251019 | N20: II - 85444900 | O20: 7898802614692
A21: =IFERROR(_xlfn.XLOOKUP(B21,LISTA!C:C,LISTA!B:B,""),"") -> 000503 | B21: CABO FLEXIVEL , ISOL. PVC/F, CAPA PVC/ST1, TEMP. 70C, 500/750V PRETO 2 X 1,00MM | C21: =IFERROR(_xlfn.XLOOKUP(B21,LISTA!C:C,LISTA!D:D,""),"") -> MT | D21: -150 | E21: =IFERROR(_xlfn.XLOOKUP(B21,LISTA!C:C,LISTA!F:F,""),"") -> MI | F21: 30 | H21: 85444900 | I21: 1004100 | J21: 0 - Nacional | K21: Próprio | L21: 43.51 | M21: L20250126 | N21: II - 85444900 | O21: 7894083280803
A22: =IFERROR(_xlfn.XLOOKUP(B22,LISTA!C:C,LISTA!B:B,""),"") -> 000507 | B22: CABO COAXIAL P/ REDE CONTROLNET RG6/U, 18AWG, CAPA EM PVC PRETA 3092A# BELDEN | C22: =IFERROR(_xlfn.XLOOKUP(B22,LISTA!C:C,LISTA!D:D,""),"") -> MT | D22: =IFERROR(_xlfn.XLOOKUP(B22,LISTA!C:C,LISTA!E:E,""),"") -> 0 | E22: =IFERROR(_xlfn.XLOOKUP(B22,LISTA!C:C,LISTA!F:F,""),"") -> MI | F22: 58 | G22: BELDEN | H22: 85441900 | I22: 1004800 | J22: 0 - Nacional | K22: Próprio | L22: 6.58 | M22: L20250216 | N22: II - 85441900 | O22: 7895033604623
A23: =IFERROR(_xlfn.XLOOKUP(B23,LISTA!C:C,LISTA!B:B,""),"") -> 000645 | B23: TERMINAL DE COMPRESSAO, COBRE ESTANHADO, SERIE METRICA, P/ CABOS 4 A 6MM C/ FURO 5,00 MM | C23: =IFERROR(_xlfn.XLOOKUP(B23,LISTA!C:C,LISTA!D:D,""),"") -> PC | D23: =IFERROR(_xlfn.XLOOKUP(B23,LISTA!C:C,LISTA!E:E,""),"") -> 0 | E23: =IFERROR(_xlfn.XLOOKUP(B23,LISTA!C:C,LISTA!F:F,""),"") -> MI | F23: 77 | H23: 85369090 | I23: 1004100 | J23: 0 - Nacional | K23: Próprio | L23: 90.13 | M23: L20251218 | N23: II - 85369090 | O23: 7896590101244
A24: =IFERROR(_xlfn.XLOOKUP(B24,LISTA!C:C,LISTA!B:B,""),"") -> 000647 | B24: TERMINAL DE COMPRESSAO, COBRE ESTANHADO, P/ CABOS 240,00MM, C/ FURO 13,00MM | C24: =IFERROR(_xlfn.XLOOKUP(B24,LISTA!C:C,LISTA!D:D,""),"") -> PC | D24: =IFERROR(_xlfn.XLOOKUP(B24,LISTA!C:C,LISTA!E:E,""),"") -> 0 | E24: =IFERROR(_xlfn.XLOOKUP(B24,LISTA!C:C,LISTA!F:F,""),"") -> MI | F24: 44 | H24: 85369090 | I24: 1004800 | J24: 0 - Nacional | K24: Próprio | L24: 49.11 | M24: L20250307 | N24: II - 85369090 | O24: 7891840981424
A25: =IFERROR(_xlfn.XLOOKUP(B25,LISTA!C:C,LISTA!B:B,""),"") -> 000648 | B25: TERMINAL DE COMPRESSAO, COBRE ESTANHADO, SERIE METRICA, P/ CABOS 185MM C/ FURO 13,8MM TM-185 INTELLI | C25: =IFERROR(_xlfn.XLOOKUP(B25,LISTA!C:C,LISTA!D:D,""),"") -> PC | D25: =IFERROR(_xlfn.XLOOKUP(B25,LISTA!C:C,LISTA!E:E,""),"") -> 0 | E25: =IFERROR(_xlfn.XLOOKUP(B25,LISTA!C:C,LISTA!F:F,""),"") -> MI | F25: 30 | G25: INTELLI | H25: 85369090 | I25: 1005000 | J25: 0 - Nacional | K25: Próprio | L25: 60.32 | M25: L20250320 | N25: II - 85369090 | O25: 7893594304443
A26: =IFERROR(_xlfn.XLOOKUP(B26,LISTA!C:C,LISTA!B:B,""),"") -> 000649 | B26: TERMINAL DE COMPRESSAO, COBRE ESTANHADO, SERIE METRICA, P/ CABOS 150MM C/ FURO 13,8MM TM-150 INTELLI | C26: =IFERROR(_xlfn.XLOOKUP(B26,LISTA!C:C,LISTA!D:D,""),"") -> PC | D26: =IFERROR(_xlfn.XLOOKUP(B26,LISTA!C:C,LISTA!E:E,""),"") -> 0 | E26: =IFERROR(_xlfn.XLOOKUP(B26,LISTA!C:C,LISTA!F:F,""),"") -> MI | F26: 58 | G26: INTELLI | H26: 85369090 | I26: 1005000 | J26: 0 - Nacional | K26: Próprio | L26: 24.55 | M26: L20250116 | N26: II - 85369090 | O26: 7897907505753
A27: =IFERROR(_xlfn.XLOOKUP(B27,LISTA!C:C,LISTA!B:B,""),"") -> 000650 | B27: TERMINAL DE COMPRESSAO, COBRE ESTANHADO, P/ CABOS 120,00 MM C/ FURO 10,00 MM | C27: =IFERROR(_xlfn.XLOOKUP(B27,LISTA!C:C,LISTA!D:D,""),"") -> PC | D27: =IFERROR(_xlfn.XLOOKUP(B27,LISTA!C:C,LISTA!E:E,""),"") -> 0 | E27: =IFERROR(_xlfn.XLOOKUP(B27,LISTA!C:C,LISTA!F:F,""),"") -> MI | F27: 53 | H27: 85369090 | I27: 1004100 | J27: 0 - Nacional | K27: Próprio | L27: 72.6 | M27: L20251205 | N27: II - 85369090 | O27: 7891286529928
A28: =IFERROR(_xlfn.XLOOKUP(B28,LISTA!C:C,LISTA!B:B,""),"") -> 000651 | B28: TERMINAL DE COMPRESSAO, COBRE ESTANHADO, P/ CABOS 95,00 MM C/ FURO 10,00 MM | C28: =IFERROR(_xlfn.XLOOKUP(B28,LISTA!C:C,LISTA!D:D,""),"") -> PC | D28: =IFERROR(_xlfn.XLOOKUP(B28,LISTA!C:C,LISTA!E:E,""),"") -> 0 | E28: =IFERROR(_xlfn.XLOOKUP(B28,LISTA!C:C,LISTA!F:F,""),"") -> MI | F28: 23 | H28: 85369090 | I28: 1004100 | J28: 0 - Nacional | K28: Próprio | L28: 42.96 | M28: L20250322 | N28: II - 85369090 | O28: 7893356819511
A29: =IFERROR(_xlfn.XLOOKUP(B29,LISTA!C:C,LISTA!B:B,""),"") -> 000652 | B29: TERMINAL DE COMPRESSAO, COBRE ESTANHADO, SERIE METRICA, P/ CABOS 70MM C/ FURO 10,5MM TM-70 INTELLI | C29: =IFERROR(_xlfn.XLOOKUP(B29,LISTA!C:C,LISTA!D:D,""),"") -> PC | D29: =IFERROR(_xlfn.XLOOKUP(B29,LISTA!C:C,LISTA!E:E,""),"") -> 0 | E29: =IFERROR(_xlfn.XLOOKUP(B29,LISTA!C:C,LISTA!F:F,""),"") -> MI | F29: 9 | G29: INTELLI | H29: 85369090 | I29: 1004100 | J29: 0 - Nacional | K29: Próprio | L29: 32.6 | M29: L20250123 | N29: II - 85369090 | O29: 7891083770751
A30: =IFERROR(_xlfn.XLOOKUP(B30,LISTA!C:C,LISTA!B:B,""),"") -> 000680 | B30: TERMINAL GARFO, PRE-ISOLADO, AMARELO, P/ CABOS 4,00 A 6,00 MM, FURO 6,00 MM | C30: =IFERROR(_xlfn.XLOOKUP(B30,LISTA!C:C,LISTA!D:D,""),"") -> PC | D30: =IFERROR(_xlfn.XLOOKUP(B30,LISTA!C:C,LISTA!E:E,""),"") -> 0 | E30: =IFERROR(_xlfn.XLOOKUP(B30,LISTA!C:C,LISTA!F:F,""),"") -> MC | F30: 71 | H30: 85369090 | I30: 1004100 | J30: 0 - Nacional | K30: Próprio | L30: 66.74 | M30: L20250322 | N30: II - 85369090 | O30: 7893863507033
A31: =IFERROR(_xlfn.XLOOKUP(B31,LISTA!C:C,LISTA!B:B,""),"") -> 000681 | B31: TERMINAL OLHAL, TUBULAR, PRE-ISOLADO, VERMELHO, P/ CABOS 10,00 MM, FURO 8,00 MM | C31: =IFERROR(_xlfn.XLOOKUP(B31,LISTA!C:C,LISTA!D:D,""),"") -> PC | D31: =IFERROR(_xlfn.XLOOKUP(B31,LISTA!C:C,LISTA!E:E,""),"") -> 0 | E31: =IFERROR(_xlfn.XLOOKUP(B31,LISTA!C:C,LISTA!F:F,""),"") -> MC | F31: 33 | H31: 85369090 | I31: 1004800 | J31: 0 - Nacional | K31: Próprio | L31: 40.62 | M31: L20250921 | N31: II - 85369090 | O31: 7897039431336
A32: =IFERROR(_xlfn.XLOOKUP(B32,LISTA!C:C,LISTA!B:B,""),"") -> 000690 | B32: TERMINAL OLHAL, PRE-ISOLADO, P/ CABOS 4,00 A 6,00MM, FURO 4,00 MM | C32: =IFERROR(_xlfn.XLOOKUP(B32,LISTA!C:C,LISTA!D:D,""),"") -> PC | D32: =IFERROR(_xlfn.XLOOKUP(B32,LISTA!C:C,LISTA!E:E,""),"") -> 0 | E32: =IFERROR(_xlfn.XLOOKUP(B32,LISTA!C:C,LISTA!F:F,""),"") -> MI | F32: 36 | H32: 85369090 | I32: 1004100 | J32: 0 - Nacional | K32: Próprio | L32: 57.51 | M32: L20251026 | N32: II - 85369090 | O32: 7894530617477
A33: =IFERROR(_xlfn.XLOOKUP(B33,LISTA!C:C,LISTA!B:B,""),"") -> 000716 | B33: CABO FLEXIVEL, ISOL. PVC/A, TEMP. 70 C, 750V, PRETO, 1 X 6,00 MM | C33: =IFERROR(_xlfn.XLOOKUP(B33,LISTA!C:C,LISTA!D:D,""),"") -> MT | D33: =IFERROR(_xlfn.XLOOKUP(B33,LISTA!C:C,LISTA!E:E,""),"") -> 0 | E33: =IFERROR(_xlfn.XLOOKUP(B33,LISTA!C:C,LISTA!F:F,""),"") -> MI | F33: 9 | H33: 85444900 | I33: 1004100 | J33: 0 - Nacional | K33: Próprio | L33: 84.61 | M33: L20250717 | N33: II - 85444900 | O33: 7899074655059
A34: =IFERROR(_xlfn.XLOOKUP(B34,LISTA!C:C,LISTA!B:B,""),"") -> 000720 | B34: CABO FLEXIVEL, ISOL. PVC/A, TEMP. 70 C, 750V, PRETO, 1 X 4,00 MM | C34: =IFERROR(_xlfn.XLOOKUP(B34,LISTA!C:C,LISTA!D:D,""),"") -> MT | D34: =IFERROR(_xlfn.XLOOKUP(B34,LISTA!C:C,LISTA!E:E,""),"") -> 0 | E34: =IFERROR(_xlfn.XLOOKUP(B34,LISTA!C:C,LISTA!F:F,""),"") -> MI | F34: 67 | H34: 85444900 | I34: 1005000 | J34: 0 - Nacional | K34: Próprio | L34: 82.35 | M34: L20250112 | N34: II - 85444900 | O34: 7894602424504
A35: =IFERROR(_xlfn.XLOOKUP(B35,LISTA!C:C,LISTA!B:B,""),"") -> 000760 | B35: CABO FLEXIVEL, ISOL. PVC/A, TEMP. 70 C, 750V, PRETO, 1 X 1,50 MM | C35: =IFERROR(_xlfn.XLOOKUP(B35,LISTA!C:C,LISTA!D:D,""),"") -> RL | D35: =IFERROR(_xlfn.XLOOKUP(B35,LISTA!C:C,LISTA!E:E,""),"") -> 0 | E35: =IFERROR(_xlfn.XLOOKUP(B35,LISTA!C:C,LISTA!F:F,""),"") -> MI | F35: 7 | H35: 85444900 | I35: 1004800 | J35: 0 - Nacional | K35: Próprio | L35: 64.48 | M35: L20250824 | N35: II - 85444900 | O35: 7897072493317
A36: =IFERROR(_xlfn.XLOOKUP(B36,LISTA!C:C,LISTA!B:B,""),"") -> 000766 | B36: CABO FLEXIVEL, ISOL. PVC/A, TEMP. 70 C, 750V, BRANCO, 1 X 1,50 MM | C36: =IFERROR(_xlfn.XLOOKUP(B36,LISTA!C:C,LISTA!D:D,""),"") -> MT | D36: =IFERROR(_xlfn.XLOOKUP(B36,LISTA!C:C,LISTA!E:E,""),"") -> 0 | E36: =IFERROR(_xlfn.XLOOKUP(B36,LISTA!C:C,LISTA!F:F,""),"") -> MI | F36: 55 | H36: 85444900 | I36: 1004100 | J36: 0 - Nacional | K36: Próprio | L36: 77.96 | M36: L20250709 | N36: II - 85444900 | O36: 7892464853049
A37: =IFERROR(_xlfn.XLOOKUP(B37,LISTA!C:C,LISTA!B:B,""),"") -> 000771 | B37: CABO FLEXIVEL, ISOL. PVC/F, CAPA PVC/ST1, TEMP. 70C, 750V, CL. 4, PRETO, 3 X 1,50 MM | C37: =IFERROR(_xlfn.XLOOKUP(B37,LISTA!C:C,LISTA!D:D,""),"") -> MT | D37: =IFERROR(_xlfn.XLOOKUP(B37,LISTA!C:C,LISTA!E:E,""),"") -> 0 | E37: =IFERROR(_xlfn.XLOOKUP(B37,LISTA!C:C,LISTA!F:F,""),"") -> MI | F37: 17 | H37: 85444900 | I37: 1004100 | J37: 0 - Nacional | K37: Próprio | L37: 17.77 | M37: L20250903 | N37: II - 85444900 | O37: 7892469352991
A38: =IFERROR(_xlfn.XLOOKUP(B38,LISTA!C:C,LISTA!B:B,""),"") -> 000808 | B38: CABO INSTRUMENTACAO, 300V, ISOL. PVC, 70 C, BLINDAGEM, MALHA, 4 X 18 AWG | C38: =IFERROR(_xlfn.XLOOKUP(B38,LISTA!C:C,LISTA!D:D,""),"") -> MT | D38: =IFERROR(_xlfn.XLOOKUP(B38,LISTA!C:C,LISTA!E:E,""),"") -> 0 | E38: =IFERROR(_xlfn.XLOOKUP(B38,LISTA!C:C,LISTA!F:F,""),"") -> MI | F38: 57 | H38: 85444900 | I38: 1004100 | J38: 0 - Nacional | K38: Próprio | L38: 16.7 | M38: L20250105 | N38: II - 85444900 | O38: 7898595247749
A39: =IFERROR(_xlfn.XLOOKUP(B39,LISTA!C:C,LISTA!B:B,""),"") -> 000809 | B39: CABO INSTRUMENTACAO, 300V, ISOL. PVC, 70 C, BLINDAGEM, MALHA, 2 X 18 AWG | C39: =IFERROR(_xlfn.XLOOKUP(B39,LISTA!C:C,LISTA!D:D,""),"") -> MT | D39: =IFERROR(_xlfn.XLOOKUP(B39,LISTA!C:C,LISTA!E:E,""),"") -> 0 | E39: =IFERROR(_xlfn.XLOOKUP(B39,LISTA!C:C,LISTA!F:F,""),"") -> MI | F39: 61 | H39: 85444900 | I39: 1004800 | J39: 0 - Nacional | K39: Próprio | L39: 36.24 | M39: L20250911 | N39: II - 85444900 | O39: 7896634531500
A40: =IFERROR(_xlfn.XLOOKUP(B40,LISTA!C:C,LISTA!B:B,""),"") -> 000822 | B40: CABO FLEXIVEL, ISOL. PVC/A, TEMP. 70 C, 750V, VERDE, 1 X 2,50 MM | C40: =IFERROR(_xlfn.XLOOKUP(B40,LISTA!C:C,LISTA!D:D,""),"") -> MT | D40: =IFERROR(_xlfn.XLOOKUP(B40,LISTA!C:C,LISTA!E:E,""),"") -> 0 | E40: =IFERROR(_xlfn.XLOOKUP(B40,LISTA!C:C,LISTA!F:F,""),"") -> MI | F40: 67 | H40: 85444900 | I40: 1004800 | J40: 0 - Nacional | K40: Próprio | L40: 38.97 | M40: L20250102 | N40: II - 85444900 | O40: 7891331542626
A41: =IFERROR(_xlfn.XLOOKUP(B41,LISTA!C:C,LISTA!B:B,""),"") -> 000828 | B41: CABO FLEXIVEL, ISOL. PVC/A, TEMP. 70 C, 750V, PRETO, 1 X 2,50 MM | C41: =IFERROR(_xlfn.XLOOKUP(B41,LISTA!C:C,LISTA!D:D,""),"") -> MT | D41: =IFERROR(_xlfn.XLOOKUP(B41,LISTA!C:C,LISTA!E:E,""),"") -> 0 | E41: =IFERROR(_xlfn.XLOOKUP(B41,LISTA!C:C,LISTA!F:F,""),"") -> MI | F41: 31 | H41: 85444900 | I41: 1004800 | J41: 0 - Nacional | K41: Próprio | L41: 17.07 | M41: L20250920 | N41: II - 85444900 | O41: 7894509223105
... A45: =IFERROR(_xlfn.XLOOKUP(B45,LISTA!C:C,LISTA!B:B,""),"") -> 000937 | B45: CABO FLEXIVEL, ISOL. PVC/A, TEMP. 70 C, 750V, AZUL, 1 X 1,00 MM | C45: =IFERROR(_xlfn.XLOOKUP(B45,LISTA!C:C,LISTA!D:D,""),"") -> MT | D45: =IFERROR(_xlfn.XLOOKUP(B45,LISTA!C:C,LISTA!E:E,""),"") -> 0 | E45: =IFERROR(_xlfn.XLOOKUP(B45,LISTA!C:C,LISTA!F:F,""),"") -> MI | F45: 77 | H45: 85444900 | I45: 1004100 | J45: 0 - Nacional | K45: Próprio | L45: 6.43 | M45: L20250709 | N45: II - 85444900 | O45: 7894125385047
A46: =IFERROR(_xlfn.XLOOKUP(B46,LISTA!C:C,LISTA!B:B,""),"") -> 000941 | B46: CABO INSTRUMENTACAO COPPERCON BFA, ISOL. PVC/A 70§C, NBR 7289, C/ BLINDAGEM E FITA ALUM. 500V, CL.04, 2X1MM BRASCOPPER | C46: =IFERROR(_xlfn.XLOOKUP(B46,LISTA!C:C,LISTA!D:D,""),"") -> MT | D46: -87 | E46: =IFERROR(_xlfn.XLOOKUP(B46,LISTA!C:C,LISTA!F:F,""),"") -> MI | F46: 19 | G46: BRASCOPPER | H46: 85444900 | I46: 1004800 | J46: 0 - Nacional | K46: Próprio | L46: 16.79 | M46: L20250417 | N46: II - 85444900 | O46: 7894820551397
A47: =IFERROR(_xlfn.XLOOKUP(B47,LISTA!C:C,LISTA!B:B,""),"") -> 000943 | B47: CABO FLEXIVEL, ISOL. PVC/A, TEMP. 70 C, 750V, CINZA, 1 X 1,50 MM | C47: =IFERROR(_xlfn.XLOOKUP(B47,LISTA!C:C,LISTA!D:D,""),"") -> MT | D47: =IFERROR(_xlfn.XLOOKUP(B47,LISTA!C:C,LISTA!E:E,""),"") -> 0 | E47: =IFERROR(_xlfn.XLOOKUP(B47,LISTA!C:C,LISTA!F:F,""),"") -> MI | F47: 23 | H47: 85444900 | I47: 1004800 | J47: 0 - Nacional | K47: Próprio | L47: 43.4 | M47: L20250219 | N47: II - 85444900 | O47: 7897587855103
A48: =IFERROR(_xlfn.XLOOKUP(B48,LISTA!C:C,LISTA!B:B,""),"") -> 000947 | B48: CABO FLEXIVEL, ISOL. PVC/A, TEMP. 70 C, 750V, PRETO, 1 X 10,00 MM | C48: =IFERROR(_xlfn.XLOOKUP(B48,LISTA!C:C,LISTA!D:D,""),"") -> MT | D48: =IFERROR(_xlfn.XLOOKUP(B48,LISTA!C:C,LISTA!E:E,""),"") -> 0 | E48: =IFERROR(_xlfn.XLOOKUP(B48,LISTA!C:C,LISTA!F:F,""),"") -> MI | F48: 67 | H48: 85444900 | I48: 1004100 | J48: 0 - Nacional | K48: Próprio | L48: 81.79 | M48: L20251121 | N48: II - 85444900 | O48: 7896934240463
A49: =IFERROR(_xlfn.XLOOKUP(B49,LISTA!C:C,LISTA!B:B,""),"") -> 000984 | B49: TERMINAL DE COMPRESSAO, COBRE ESTANHADO, P/ CABOS 35,00 MM C/ FURO M8 | C49: =IFERROR(_xlfn.XLOOKUP(B49,LISTA!C:C,LISTA!D:D,""),"") -> PC | D49: =IFERROR(_xlfn.XLOOKUP(B49,LISTA!C:C,LISTA!E:E,""),"") -> 0 | E49: =IFERROR(_xlfn.XLOOKUP(B49,LISTA!C:C,LISTA!F:F,""),"") -> MI | F49: 34 | H49: 85369090 | I49: 1004100 | J49: 0 - Nacional | K49: Próprio | L49: 85.97 | M49: L20250828 | N49: II - 85369090 | O49: 7893285177708
A50: =IFERROR(_xlfn.XLOOKUP(B50,LISTA!C:C,LISTA!B:B,""),"") -> 000987 | B50: TERMINAL DE COMPRESSAO, COBRE ESTANHADO, P/ CABOS 10,00 MM C/ FURO M5 | C50: =IFERROR(_xlfn.XLOOKUP(B50,LISTA!C:C,LISTA!D:D,""),"") -> PC | D50: =IFERROR(_xlfn.XLOOKUP(B50,LISTA!C:C,LISTA!E:E,""),"") -> 0 | E50: =IFERROR(_xlfn.XLOOKUP(B50,LISTA!C:C,LISTA!F:F,""),"") -> MI | F50: 55 | H50: 85369090 | I50: 1004800 | J50: 0 - Nacional | K50: Próprio | L50: 89.74 | M50: L20251018 | N50: II - 85369090 | O50: 7891547209263
A51: =IFERROR(_xlfn.XLOOKUP(B51,LISTA!C:C,LISTA!B:B,""),"") -> 000990 | B51: TERMINAL DE COMPRESSAO, COBRE ESTANHADO, P/ CABOS 240,00MM, C/ FURO 17,00MM | C51: =IFERROR(_xlfn.XLOOKUP(B51,LISTA!C:C,LISTA!D:D,""),"") -> PC | D51: =IFERROR(_xlfn.XLOOKUP(B51,LISTA!C:C,LISTA!E:E,""),"") -> 0 | E51: =IFERROR(_xlfn.XLOOKUP(B51,LISTA!C:C,LISTA!F:F,""),"") -> MI | F51: 53 | H51: 85369090 | I51: 1005000 | J51: 0 - Nacional | K51: Próprio | L51: 3.9 | M51: L20250218 | N51: II - 85369090 | O51: 7891824820042
A52: =IFERROR(_xlfn.XLOOKUP(B52,LISTA!C:C,LISTA!B:B,""),"") -> 000994 | B52: CABO FLEXIVEL, ISOL. HEPR, CAPA PVC ST2, TEMP. 90C, 0,6 / 1KV, NBR 7286, PRETO, 4 X 2,50 MM | C52: =IFERROR(_xlfn.XLOOKUP(B52,LISTA!C:C,LISTA!D:D,""),"") -> MT | D52: =IFERROR(_xlfn.XLOOKUP(B52,LISTA!C:C,LISTA!E:E,""),"") -> 0 | E52: =IFERROR(_xlfn.XLOOKUP(B52,LISTA!C:C,LISTA!F:F,""),"") -> MI | F52: 75 | H52: 85444900 | I52: 1004100 | J52: 0 - Nacional | K52: Próprio | L52: 62.91 | M52: L20250719 | N52: II - 85444900 | O52: 7896053057553
A53: =IFERROR(_xlfn.XLOOKUP(B53,LISTA!C:C,LISTA!B:B,""),"") -> 001051 | B53: TERMINAL DE COMPRESSAO, COBRE ESTANHADO, P/ CABOS 120,00 MM C/ FURO 13,00 MM | C53: =IFERROR(_xlfn.XLOOKUP(B53,LISTA!C:C,LISTA!D:D,""),"") -> PC | D53: =IFERROR(_xlfn.XLOOKUP(B53,LISTA!C:C,LISTA!E:E,""),"") -> 0 | E53: =IFERROR(_xlfn.XLOOKUP(B53,LISTA!C:C,LISTA!F:F,""),"") -> MI | F53: 20 | H53: 85369090 | I53: 1004100 | J53: 0 - Nacional | K53: Próprio | L53: 59.94 | M53: L20250818 | N53: II - 85369090 | O53: 7897733318808
A54: =IFERROR(_xlfn.XLOOKUP(B54,LISTA!C:C,LISTA!B:B,""),"") -> 001069 | B54: TERMINAL DE COMPRESSAO, COBRE ESTANHADO, P/ CABOS 185,00MM, C/ FURO 17,00 MM | C54: =IFERROR(_xlfn.XLOOKUP(B54,LISTA!C:C,LISTA!D:D,""),"") -> PC | D54: =IFERROR(_xlfn.XLOOKUP(B54,LISTA!C:C,LISTA!E:E,""),"") -> 0 | E54: =IFERROR(_xlfn.XLOOKUP(B54,LISTA!C:C,LISTA!F:F,""),"") -> MI | F54: 60 | H54: 85369090 | I54: 1005000 | J54: 0 - Nacional | K54: Próprio | L54: 91.04 | M54: L20250227 | N54: II - 85369090 | O54: 7892618731380
A55: =IFERROR(_xlfn.XLOOKUP(B55,LISTA!C:C,LISTA!B:B,""),"") -> 001091 | B55: TERMINAL DE COMPRESSAO, COBRE ESTANHADO, SERIE METRICA, P/ CABOS 240,00 MM C/ FURO 16,00 MM TM-240-L-17 INTELLI | C55: =IFERROR(_xlfn.XLOOKUP(B55,LISTA!C:C,LISTA!D:D,""),"") -> PC | D55: =IFERROR(_xlfn.XLOOKUP(B55,LISTA!C:C,LISTA!E:E,""),"") -> 0 | E55: =IFERROR(_xlfn.XLOOKUP(B55,LISTA!C:C,LISTA!F:F,""),"") -> MI | F55: 79 | G55: INTELLI | H55: 85369090 | I55: 1004100 | J55: 0 - Nacional | K55: Próprio | L55: 81.27 | M55: L20250508 | N55: II - 85369090 | O55: 7891238511681
A56: =IFERROR(_xlfn.XLOOKUP(B56,LISTA!C:C,LISTA!B:B,""),"") -> 001121 | B56: TERMINAL DE COMPRESSAO, COBRE ESTANHADO, P/ CABOS 50,00 MM C/ FURO M10 | C56: =IFERROR(_xlfn.XLOOKUP(B56,LISTA!C:C,LISTA!D:D,""),"") -> PC | D56: =IFERROR(_xlfn.XLOOKUP(B56,LISTA!C:C,LISTA!E:E,""),"") -> 0 | E56: =IFERROR(_xlfn.XLOOKUP(B56,LISTA!C:C,LISTA!F:F,""),"") -> MI | F56: 27 | H56: 85369090 | I56: 1004800 | J56: 0 - Nacional | K56: Próprio | L56: 88.6 | M56: L20250410 | N56: II - 85369090 | O56: 7893789914728
A57: =IFERROR(_xlfn.XLOOKUP(B57,LISTA!C:C,LISTA!B:B,""),"") -> 001138 | B57: CABO FLEXIVEL, ISOL. HEPR, CAPA PVC ST2, TEMP. 90C, 0,6 / 1KV, NBR 7286, PRETO, 1 X 150,00 MM | C57: =IFERROR(_xlfn.XLOOKUP(B57,LISTA!C:C,LISTA!D:D,""),"") -> MT | D57: =IFERROR(_xlfn.XLOOKUP(B57,LISTA!C:C,LISTA!E:E,""),"") -> 0 | E57: =IFERROR(_xlfn.XLOOKUP(B57,LISTA!C:C,LISTA!F:F,""),"") -> MI | F57: 36 | H57: 85444900 | I57: 1004100 | J57: 0 - Nacional | K57: Próprio | L57: 5.48 | M57: L20250508 | N57: II - 85444900 | O57: 7897570781233
A58: =IFERROR(_xlfn.XLOOKUP(B58,LISTA!C:C,LISTA!B:B,""),"") -> 001140 | B58: TERMINAL DE COMPRESSAO, COBRE ESTANHADO, SERIE METRICA, P/ CABOS 70,00 MM C/ FURO 12,00 MM TM-70-L-13 INTELLI | C58: =IFERROR(_xlfn.XLOOKUP(B58,LISTA!C:C,LISTA!D:D,""),"") -> PC | D58: =IFERROR(_xlfn.XLOOKUP(B58,LISTA!C:C,LISTA!E:E,""),"") -> 0 | E58: =IFERROR(_xlfn.XLOOKUP(B58,LISTA!C:C,LISTA!F:F,""),"") -> MI | F58: 63 | G58: INTELLI | H58: 85369090 | I58: 1005000 | J58: 0 - Nacional | K58: Próprio | L58: 18.95 | M58: L20250408 | N58: II - 85369090 | O58: 7893246561409
A59: =IFERROR(_xlfn.XLOOKUP(B59,LISTA!C:C,LISTA!B:B,""),"") -> 001142 | B59: CABO FLEXIVEL, ISOL. PVC/A, TEMP. 70 C, 750V, VERMELHO, 1 X 1,50 MM | C59: =IFERROR(_xlfn.XLOOKUP(B59,LISTA!C:C,LISTA!D:D,""),"") -> MT | D59: =IFERROR(_xlfn.XLOOKUP(B59,LISTA!C:C,LISTA!E:E,""),"") -> 0 | E59: =IFERROR(_xlfn.XLOOKUP(B59,LISTA!C:C,LISTA!F:F,""),"") -> MI | F59: 69 | H59: 85444900 | I59: 1004100 | J59: 0 - Nacional | K59: Próprio | L59: 23.96 | M59: L20251208 | N59: II - 85444900 | O59: 7894502739669
A60: =IFERROR(_xlfn.XLOOKUP(B60,LISTA!C:C,LISTA!B:B,""),"") -> 001143 | B60: CABO FLEXIVEL, ISOL. PVC/A, TEMP. 70 C, 750V, AZUL, 1 X 1,50 MM | C60: =IFERROR(_xlfn.XLOOKUP(B60,LISTA!C:C,LISTA!D:D,""),"") -> RL | D60: =IFERROR(_xlfn.XLOOKUP(B60,LISTA!C:C,LISTA!E:E,""),"") -> 0 | E60: =IFERROR(_xlfn.XLOOKUP(B60,LISTA!C:C,LISTA!F:F,""),"") -> MI | F60: 70 | H60: 85444900 | I60: 1004800 | J60: 0 - Nacional | K60: Próprio | L60: 34.71 | M60: L20250827 | N60: II - 85444900 | O60: 7893197615386
A61: =IFERROR(_xlfn.XLOOKUP(B61,LISTA!C:C,LISTA!B:B,""),"") -> 001150 | B61: CABO FLEXIVEL, ISOL. PVC/A, TEMP. 70 C, 750V, CINZA, 1 X 1,00 MM | C61: =IFERROR(_xlfn.XLOOKUP(B61,LISTA!C:C,LISTA!D:D,""),"") -> MT | D61: =IFERROR(_xlfn.XLOOKUP(B61,LISTA!C:C,LISTA!E:E,""),"") -> 0 | E61: =IFERROR(_xlfn.XLOOKUP(B61,LISTA!C:C,LISTA!F:F,""),"") -> MI | F61: 56 | H61: 85444900 | I61: 1004100 | J61: 0 - Nacional | K61: Próprio | L61: 72.93 | M61: L20250701 | N61: II - 85444900 | O61: 7898345606207
A62: =IFERROR(_xlfn.XLOOKUP(B62,LISTA!C:C,LISTA!B:B,""),"") -> 001152 | B62: CABO FLEXIVEL, ISOL. PVC/A, TEMP. 70C, 750V, AMARELO, 1 X 2,50 MM | C62: =IFERROR(_xlfn.XLOOKUP(B62,LISTA!C:C,LISTA!D:D,""),"") -> MT | D62: =IFERROR(_xlfn.XLOOKUP(B62,LISTA!C:C,LISTA!E:E,""),"") -> 0 | E62: =IFERROR(_xlfn.XLOOKUP(B62,LISTA!C:C,LISTA!F:F,""),"") -> MI | F62: 13 | H62: 85444900 | I62: 1004100 | J62: 0 - Nacional | K62: Próprio | L62: 77.94 | M62: L20251103 | N62: II - 85444900 | O62: 7899814715419
A63: =IFERROR(_xlfn.XLOOKUP(B63,LISTA!C:C,LISTA!B:B,""),"") -> 001283 | B63: CABO FLEXIVEL WIREX POWER H90VF, ISOL. HEPR, CAPA PVC-ST2, NBR 7286, TEMP. 90§C 0,6 / 1KV PRETO 2 X 2,50MM WIREX | C63: =IFERROR(_xlfn.XLOOKUP(B63,LISTA!C:C,LISTA!D:D,""),"") -> MT | D63: -245 | E63: =IFERROR(_xlfn.XLOOKUP(B63,LISTA!C:C,LISTA!F:F,""),"") -> MI | F63: 30 | G63: WIREX | H63: 85444900 | I63: 1004800 | J63: 0 - Nacional | K63: Próprio | L63: 57.2 | M63: L20250511 | N63: II - 85444900 | O63: 7895075723888
A64: =IFERROR(_xlfn.XLOOKUP(B64,LISTA!C:C,LISTA!B:B,""),"") -> 001319 | B64: CABO DE FIBRA OPTICA, 62,5/125, 4 VIAS, MULTI MODO, CFOT-MM-UTR 04F COG, FURUKAWA | C64: =IFERROR(_xlfn.XLOOKUP(B64,LISTA!C:C,LISTA!D:D,""),"") -> MT | D64: =IFERROR(_xlfn.XLOOKUP(B64,LISTA!C:C,LISTA!E:E,""),"") -> 0 | E64: =IFERROR(_xlfn.XLOOKUP(B64,LISTA!C:C,LISTA!F:F,""),"") -> TV | F64: 14 | G64: FURUKAWA | H64: 85447000 | I64: 1005000 | J64: 0 - Nacional | K64: Próprio | L64: 76.86 | M64: L20250117 | N64: II - 85447000 | O64: 7893890026570
A65: =IFERROR(_xlfn.XLOOKUP(B65,LISTA!C:C,LISTA!B:B,""),"") -> 001338 | B65: CABO INSTRUMENTACAO, ISOL. PVC/E, CAPA PVC/ST1, NBR 10300, FITA POLIESTER, BLIND. ELETROST. COL. E FIO DRENO, 2 X 1,50MM | C65: =IFERROR(_xlfn.XLOOKUP(B65,LISTA!C:C,LISTA!D:D,""),"") -> MT | D65: =IFERROR(_xlfn.XLOOKUP(B65,LISTA!C:C,LISTA!E:E,""),"") -> 0 | E65: =IFERROR(_xlfn.XLOOKUP(B65,LISTA!C:C,LISTA!F:F,""),"") -> MI | F65: 19 | H65: 85444900 | I65: 1005000 | J65: 0 - Nacional | K65: Próprio | L65: 31.82 | M65: L20250822 | N65: II - 85444900 | O65: 7898752394083
A66: =IFERROR(_xlfn.XLOOKUP(B66,LISTA!C:C,LISTA!B:B,""),"") -> 001340 | B66: CABO INSTRUMENTACAO BF, ISOL PVC/E 105ØC, NBR 10300, C/ BLIND. ELETROST.COLETIVA FIO DRENO 3X2X1,50MMY 900502 ENERGIFLEX | C66: =IFERROR(_xlfn.XLOOKUP(B66,LISTA!C:C,LISTA!D:D,""),"") -> MT | D66: =IFERROR(_xlfn.XLOOKUP(B66,LISTA!C:C,LISTA!E:E,""),"") -> 0 | E66: =IFERROR(_xlfn.XLOOKUP(B66,LISTA!C:C,LISTA!F:F,""),"") -> MI | F66: 53 | G66: ENERGIFLEX | H66: 85444900 | I66: 1005000 | J66: 0 - Nacional | K66: Próprio | L66: 92.68 | M66: L20250625 | N66: II - 85444900 | O66: 7892441419125
A67: =IFERROR(_xlfn.XLOOKUP(B67,LISTA!C:C,LISTA!B:B,""),"") -> 001346 | B67: CABO INSTRUMENTACAO BF, ISOL PVC/E 105ØC, NBR 10300, C/ BLIND.ELETROST. COLETIVA FIO DRENO 1X3X1,50MMY 901000 ENERGIFLEX | C67: =IFERROR(_xlfn.XLOOKUP(B67,LISTA!C:C,LISTA!D:D,""),"") -> MT | D67: =IFERROR(_xlfn.XLOOKUP(B67,LISTA!C:C,LISTA!E:E,""),"") -> 0 | E67: =IFERROR(_xlfn.XLOOKUP(B67,LISTA!C:C,LISTA!F:F,""),"") -> MI | F67: 8 | G67: ENERGIFLEX | H67: 85444900 | I67: 1004100 | J67: 0 - Nacional | K67: Próprio | L67: 30.7 | M67: L20250503 | N67: II - 85444900 | O67: 7897959392282
A68: =IFERROR(_xlfn.XLOOKUP(B68,LISTA!C:C,LISTA!B:B,""),"") -> 001385 | B68: CABO FLEXIVEL, ISOL. PVC/A, TEMP. 70 C, 750V, BRANCO, 1 X 1,00 MM | C68: =IFERROR(_xlfn.XLOOKUP(B68,LISTA!C:C,LISTA!D:D,""),"") -> MT | D68: =IFERROR(_xlfn.XLOOKUP(B68,LISTA!C:C,LISTA!E:E,""),"") -> 0 | E68: =IFERROR(_xlfn.XLOOKUP(B68,LISTA!C:C,LISTA!F:F,""),"") -> MI | F68: 40 | H68: 85444900 | I68: 1005000 | J68: 0 - Nacional | K68: Próprio | L68: 81.96 | M68: L20251025 | N68: II - 85444900 | O68: 7891126429677
A69: =IFERROR(_xlfn.XLOOKUP(B69,LISTA!C:C,LISTA!B:B,""),"") -> 001386 | B69: CABO FLEXIVEL, ISOL. PVC/A, TEMP. 70 C, 750V, VERMELHO, 1 X 1,00 MM | C69: =IFERROR(_xlfn.XLOOKUP(B69,LISTA!C:C,LISTA!D:D,""),"") -> MT | D69: =IFERROR(_xlfn.XLOOKUP(B69,LISTA!C:C,LISTA!E:E,""),"") -> 0 | E69: =IFERROR(_xlfn.XLOOKUP(B69,LISTA!C:C,LISTA!F:F,""),"") -> MI | F69: 30 | H69: 85444900 | I69: 1005000 | J69: 0 - Nacional | K69: Próprio | L69: 74.37 | M69: L20250425 | N69: II - 85444900 | O69: 7895216090323
A70: =IFERROR(_xlfn.XLOOKUP(B70,LISTA!C:C,LISTA!B:B,""),"") -> 001394 | B70: CABO FLEXIVEL, ISOL. PVC/A, TEMP. 70 C, 750V, CINZA, 1 X 0,75 MM | C70: =IFERROR(_xlfn.XLOOKUP(B70,LISTA!C:C,LISTA!D:D,""),"") -> MT | D70: =IFERROR(_xlfn.XLOOKUP(B70,LISTA!C:C,LISTA!E:E,""),"") -> 0 | E70: =IFERROR(_xlfn.XLOOKUP(B70,LISTA!C:C,LISTA!F:F,""),"") -> MI | F70: 39 | H70: 85444900 | I70: 1004800 | J70: 0 - Nacional | K70: Próprio | L70: 1.11 | M70: L20250821 | N70: II - 85444900 | O70: 7894591071249
A71: =IFERROR(_xlfn.XLOOKUP(B71,LISTA!C:C,LISTA!B:B,""),"") -> 001395 | B71: CABO FLEXIVEL, ISOL. PVC/A, TEMP. 70 C, 750V, VERMELHO, 1 X 0,75 MM | C71: =IFERROR(_xlfn.XLOOKUP(B71,LISTA!C:C,LISTA!D:D,""),"") -> MT | D71: =IFERROR(_xlfn.XLOOKUP(B71,LISTA!C:C,LISTA!E:E,""),"") -> 0 | E71: =IFERROR(_xlfn.XLOOKUP(B71,LISTA!C:C,LISTA!F:F,""),"") -> MI | F71: 56 | H71: 85444900 | I71: 1005000 | J71: 0 - Nacional | K71: Próprio | L71: 82.3 | M71: L20250212 | N71: II - 85444900 | O71: 7896155235769
A72: =IFERROR(_xlfn.XLOOKUP(B72,LISTA!C:C,LISTA!B:B,""),"") -> 001397 | B72: CABO FLEXIVEL, ISOL. PVC/A, TEMP. 70 C, 750V, AMARELO, 1 X 0,50 MM | C72: =IFERROR(_xlfn.XLOOKUP(B72,LISTA!C:C,LISTA!D:D,""),"") -> MT | D72: =IFERROR(_xlfn.XLOOKUP(B72,LISTA!C:C,LISTA!E:E,""),"") -> 0 | E72: =IFERROR(_xlfn.XLOOKUP(B72,LISTA!C:C,LISTA!F:F,""),"") -> MI | F72: 71 | H72: 85444900 | I72: 1004100 | J72: 0 - Nacional | K72: Próprio | L72: 8.17 | M72: L20251227 | N72: II - 85444900 | O72: 7898497176531
A73: =IFERROR(_xlfn.XLOOKUP(B73,LISTA!C:C,LISTA!B:B,""),"") -> 001399 | B73: CABO FLEXIVEL, ISOL. PVC/A, TEMP. 70 C, 750V, PRETO, 1 X 0,50 MM | C73: =IFERROR(_xlfn.XLOOKUP(B73,LISTA!C:C,LISTA!D:D,""),"") -> MT | D73: =IFERROR(_xlfn.XLOOKUP(B73,LISTA!C:C,LISTA!E:E,""),"") -> 0 | E73: =IFERROR(_xlfn.XLOOKUP(B73,LISTA!C:C,LISTA!F:F,""),"") -> MI | F73: 56 | H73: 85444900 | I73: 1004100 | J73: 0 - Nacional | K73: Próprio | L73: 34.8 | M73: L20250426 | N73: II - 85444900 | O73: 7899355855707
A74: =IFERROR(_xlfn.XLOOKUP(B74,LISTA!C:C,LISTA!B:B,""),"") -> 001410 | B74: CABO FLEXIVEL, ISOL. PVC/A, TEMP. 70 C, 750V, BRANCO, 1 X 0,50 MM | C74: =IFERROR(_xlfn.XLOOKUP(B74,LISTA!C:C,LISTA!D:D,""),"") -> MT | D74: =IFERROR(_xlfn.XLOOKUP(B74,LISTA!C:C,LISTA!E:E,""),"") -> 0 | E74: =IFERROR(_xlfn.XLOOKUP(B74,LISTA!C:C,LISTA!F:F,""),"") -> MI | F74: 78 | H74: 85444900 | I74: 1005000 | J74: 0 - Nacional | K74: Próprio | L74: 32.03 | M74: L20250310 | N74: II - 85444900 | O74: 7891973850012
A75: =IFERROR(_xlfn.XLOOKUP(B75,LISTA!C:C,LISTA!B:B,""),"") -> 001482 | B75: CABO INSTRUMENTACAO BC, ISOL PVC 70ØC, NBR 10300, C/ BLIND. ELETROST. COLETIVA E FIO DRENO 3X2,50MMY POLIRON | C75: =IFERROR(_xlfn.XLOOKUP(B75,LISTA!C:C,LISTA!D:D,""),"") -> MT | D75: =IFERROR(_xlfn.XLOOKUP(B75,LISTA!C:C,LISTA!E:E,""),"") -> 0 | E75: =IFERROR(_xlfn.XLOOKUP(B75,LISTA!C:C,LISTA!F:F,""),"") -> MI | F75: 50 | G75: POLIRON | H75: 85444900 | I75: 1005000 | J75: 0 - Nacional | K75: Próprio | L75: 94.57 | M75: L20250502 | N75: II - 85444900 | O75: 7899111480984
A76: =IFERROR(_xlfn.XLOOKUP(B76,LISTA!C:C,LISTA!B:B,""),"") -> 001499 | B76: CABO INSTRUMENTACAO BF, ISOL PVC/E 105ØC, NBR 10300, C/ BLIND. ELETROST.COLETIVA FIO DRENO 2X2X0,75MMY 900401 ENERGIFLEX | C76: =IFERROR(_xlfn.XLOOKUP(B76,LISTA!C:C,LISTA!D:D,""),"") -> MT | D76: =IFERROR(_xlfn.XLOOKUP(B76,LISTA!C:C,LISTA!E:E,""),"") -> 0 | E76: =IFERROR(_xlfn.XLOOKUP(B76,LISTA!C:C,LISTA!F:F,""),"") -> MI | F76: 65 | G76: ENERGIFLEX | H76: 85444900 | I76: 1004100 | J76: 0 - Nacional | K76: Próprio | L76: 94.4 | M76: L20251116 | N76: II - 85444900 | O76: 7894813414575
A77: =IFERROR(_xlfn.XLOOKUP(B77,LISTA!C:C,LISTA!B:B,""),"") -> 001583 | B77: CABO FLEXIVEL, ISOL. HEPR, CAPA PVC ST2, TEMP. 90C, 0,6 / 1KV, NBR 7286, PRETO, 4 X 4,00 MM | C77: =IFERROR(_xlfn.XLOOKUP(B77,LISTA!C:C,LISTA!D:D,""),"") -> MT | D77: =IFERROR(_xlfn.XLOOKUP(B77,LISTA!C:C,LISTA!E:E,""),"") -> 0 | E77: =IFERROR(_xlfn.XLOOKUP(B77,LISTA!C:C,LISTA!F:F,""),"") -> MI | F77: 43 | H77: 85444900 | I77: 1004100 | J77: 0 - Nacional | K77: Próprio | L77: 15.98 | M77: L20251209 | N77: II - 85444900 | O77: 7894884857894
A78: =IFERROR(_xlfn.XLOOKUP(B78,LISTA!C:C,LISTA!B:B,""),"") -> 001584 | B78: CABO PAULIPP, ISOL. PVC/F, CAPA PVC, TEMP. 70§C 750V PRETO 4 X 1,50MM IPCE | C78: =IFERROR(_xlfn.XLOOKUP(B78,LISTA!C:C,LISTA!D:D,""),"") -> MT | D78: =IFERROR(_xlfn.XLOOKUP(B78,LISTA!C:C,LISTA!E:E,""),"") -> 0 | E78: =IFERROR(_xlfn.XLOOKUP(B78,LISTA!C:C,LISTA!F:F,""),"") -> MI | F78: 26 | G78: IPCE | H78: 85444900 | I78: 1005000 | J78: 0 - Nacional | K78: Próprio | L78: 90.04 | M78: L20250918 | N78: II - 85444900 | O78: 7894882162811
A79: =IFERROR(_xlfn.XLOOKUP(B79,LISTA!C:C,LISTA!B:B,""),"") -> 001585 | B79: CABO FLEXIVEL, ISOL. HEPR, CAPA PVC ST2, TEMP. 90C, 0,6 / 1KV, NBR 7286, PRETO, 1 X 95,00 MM | C79: =IFERROR(_xlfn.XLOOKUP(B79,LISTA!C:C,LISTA!D:D,""),"") -> MT | D79: -320 | E79: =IFERROR(_xlfn.XLOOKUP(B79,LISTA!C:C,LISTA!F:F,""),"") -> MI | F79: 44 | H79: 85444900 | I79: 1005000 | J79: 0 - Nacional | K79: Próprio | L79: 33.95 | M79: L20250313 | N79: II - 85444900 | O79: 7891672038197
A80: =IFERROR(_xlfn.XLOOKUP(B80,LISTA!C:C,LISTA!B:B,""),"") -> 001592 | B80: CABO INSTRUMENTACAO 300V, ISOL. PVC PRETO, FITA ALUM. FIO DRENO TEMP 70§C, 275 MA FR 2 X 0,75MM 01022BA20100001 POLIRON | C80: =IFERROR(_xlfn.XLOOKUP(B80,LISTA!C:C,LISTA!D:D,""),"") -> MT | D80: =IFERROR(_xlfn.XLOOKUP(B80,LISTA!C:C,LISTA!E:E,""),"") -> 0 | E80: =IFERROR(_xlfn.XLOOKUP(B80,LISTA!C:C,LISTA!F:F,""),"") -> MI | F80: 40 | G80: POLIRON | H80: 85444900 | I80: 1004800 | J80: 0 - Nacional | K80: Próprio | L80: 14.37 | M80: L20250310 | N80: II - 85444900 | O80: 7893691008271
A81: =IFERROR(_xlfn.XLOOKUP(B81,LISTA!C:C,LISTA!B:B,""),"") -> 001629 | B81: CABO DE REDE GIGALAN, SEM BLINDAGEM, U/UTP, CM, ENH. 23 X 4P, CAT. 6, VERMELHO, 23400044, FURUKAWA | C81: =IFERROR(_xlfn.XLOOKUP(B81,LISTA!C:C,LISTA!D:D,""),"") -> MT | D81: =IFERROR(_xlfn.XLOOKUP(B81,LISTA!C:C,LISTA!E:E,""),"") -> 0 | E81: =IFERROR(_xlfn.XLOOKUP(B81,LISTA!C:C,LISTA!F:F,""),"") -> MI | F81: 22 | G81: FURUKAWA | H81: 85444200 | I81: 1004100 | J81: 0 - Nacional | K81: Próprio | L81: 18.28 | M81: L20251101 | N81: II - 85444200 | O81: 7893032245637
A82: =IFERROR(_xlfn.XLOOKUP(B82,LISTA!C:C,LISTA!B:B,""),"") -> 001631 | B82: TERMINAL OLHAL, PRE-ISOLADO, P/ CABOS 2,50 A 4,00MM, FURO 6,00 MM | C82: =IFERROR(_xlfn.XLOOKUP(B82,LISTA!C:C,LISTA!D:D,""),"") -> PC | D82: =IFERROR(_xlfn.XLOOKUP(B82,LISTA!C:C,LISTA!E:E,""),"") -> 0 | E82: =IFERROR(_xlfn.XLOOKUP(B82,LISTA!C:C,LISTA!F:F,""),"") -> MI | F82: 76 | H82: 85369090 | I82: 1004800 | J82: 0 - Nacional | K82: Próprio | L82: 79.59 | M82: L20250622 | N82: II - 85369090 | O82: 7897812160733
A83: =IFERROR(_xlfn.XLOOKUP(B83,LISTA!C:C,LISTA!B:B,""),"") -> 001648 | B83: CABO FLEXIVEL PAULIFLEX BWF, ISOL. PVC/A, TEMP. 70§C, 750V, PRETO, 1 X 4,00 MM IPCE | C83: =IFERROR(_xlfn.XLOOKUP(B83,LISTA!C:C,LISTA!D:D,""),"") -> MT | D83: =IFERROR(_xlfn.XLOOKUP(B83,LISTA!C:C,LISTA!E:E,""),"") -> 0 | E83: =IFERROR(_xlfn.XLOOKUP(B83,LISTA!C:C,LISTA!F:F,""),"") -> MI | F83: 24 | G83: IPCE | H83: 85444900 | I83: 1005000 | J83: 0 - Nacional | K83: Próprio | L83: 78.62 | M83: L20251016 | N83: II - 85444900 | O83: 7896794363262
A84: =IFERROR(_xlfn.XLOOKUP(B84,LISTA!C:C,LISTA!B:B,""),"") -> 001649 | B84: CABO FLEXIVEL, ISOL. PVC/A, TEMP. 70 C, 750V, BRANCO, 1 X 2,50 MM | C84: =IFERROR(_xlfn.XLOOKUP(B84,LISTA!C:C,LISTA!D:D,""),"") -> MT | D84: =IFERROR(_xlfn.XLOOKUP(B84,LISTA!C:C,LISTA!E:E,""),"") -> 0 | E84: =IFERROR(_xlfn.XLOOKUP(B84,LISTA!C:C,LISTA!F:F,""),"") -> MI | F84: 45 | H84: 85444900 | I84: 1005000 | J84: 0 - Nacional | K84: Próprio | L84: 71.74 | M84: L20251124 | N84: II - 85444900 | O84: 7893477539302
A85: =IFERROR(_xlfn.XLOOKUP(B85,LISTA!C:C,LISTA!B:B,""),"") -> 001671 | B85: TERMINAL OLHAL, PRE-ISOLADO AMARELO, P/ CABOS 4,00 A 6,00MM, FURO 10MM | C85: =IFERROR(_xlfn.XLOOKUP(B85,LISTA!C:C,LISTA!D:D,""),"") -> PC | D85: =IFERROR(_xlfn.XLOOKUP(B85,LISTA!C:C,LISTA!E:E,""),"") -> 0 | E85: =IFERROR(_xlfn.XLOOKUP(B85,LISTA!C:C,LISTA!F:F,""),"") -> MI | F85: 18 | H85: 85369090 | I85: 1004100 | J85: 0 - Nacional | K85: Próprio | L85: 15.48 | M85: L20251226 | N85: II - 85369090 | O85: 7892561526299
A86: =IFERROR(_xlfn.XLOOKUP(B86,LISTA!C:C,LISTA!B:B,""),"") -> 001676 | B86: TERMINAL GARFO, PRE-ISOLADO VERMELHO, P/ CABOS 0,50 A 1,5MM, FURO 3MM | C86: =IFERROR(_xlfn.XLOOKUP(B86,LISTA!C:C,LISTA!D:D,""),"") -> PC | D86: =IFERROR(_xlfn.XLOOKUP(B86,LISTA!C:C,LISTA!E:E,""),"") -> 0 | E86: =IFERROR(_xlfn.XLOOKUP(B86,LISTA!C:C,LISTA!F:F,""),"") -> MI | F86: 46 | H86: 85369090 | I86: 1004100 | J86: 0 - Nacional | K86: Próprio | L86: 43.92 | M86: L20250320 | N86: II - 85369090 | O86: 7898620878938
A87: =IFERROR(_xlfn.XLOOKUP(B87,LISTA!C:C,LISTA!B:B,""),"") -> 001700 | B87: CABO FLEXIVEL, ISOL. HEPR, CAPA PVC ST2, TEMP. 90C, 0,6 / 1KV, NBR 7286, PRETO, 1 X 50,00 MM | C87: =IFERROR(_xlfn.XLOOKUP(B87,LISTA!C:C,LISTA!D:D,""),"") -> MT | D87: =IFERROR(_xlfn.XLOOKUP(B87,LISTA!C:C,LISTA!E:E,""),"") -> 0 | E87: =IFERROR(_xlfn.XLOOKUP(B87,LISTA!C:C,LISTA!F:F,""),"") -> MI | F87: 63 | H87: 85444900 | I87: 1005000 | J87: 0 - Nacional | K87: Próprio | L87: 3.78 | M87: L20250303 | N87: II - 85444900 | O87: 7899156159613
A88: =IFERROR(_xlfn.XLOOKUP(B88,LISTA!C:C,LISTA!B:B,""),"") -> 001701 | B88: CABO ALARME INCENDIO, PVC/E 105C, 600V, BLIND. POLIESTER, DRENO, CAPA VM PVC ST2, NBR9441, CL.4, 2 X 1,50MM | C88: =IFERROR(_xlfn.XLOOKUP(B88,LISTA!C:C,LISTA!D:D,""),"") -> MT | D88: =IFERROR(_xlfn.XLOOKUP(B88,LISTA!C:C,LISTA!E:E,""),"") -> 0 | E88: =IFERROR(_xlfn.XLOOKUP(B88,LISTA!C:C,LISTA!F:F,""),"") -> MI | F88: 62 | H88: 85444900 | I88: 1004800 | J88: 0 - Nacional | K88: Próprio | L88: 88.3 | M88: L20251116 | N88: II - 85444900 | O88: 7894148472429
A89: =IFERROR(_xlfn.XLOOKUP(B89,LISTA!C:C,LISTA!B:B,""),"") -> 001748 | B89: CABO FLEXIVEL, ISOL. PVC/A, TEMP. 70 C, 750V, VERDE, 1 X 4,00 MM | C89: =IFERROR(_xlfn.XLOOKUP(B89,LISTA!C:C,LISTA!D:D,""),"") -> MT | D89: =IFERROR(_xlfn.XLOOKUP(B89,LISTA!C:C,LISTA!E:E,""),"") -> 0 | E89: =IFERROR(_xlfn.XLOOKUP(B89,LISTA!C:C,LISTA!F:F,""),"") -> MI | F89: 73 | H89: 85444900 | I89: 1004100 | J89: 0 - Nacional | K89: Próprio | L89: 81.9 | M89: L20251022 | N89: II - 85444900 | O89: 7898371719959
A90: =IFERROR(_xlfn.XLOOKUP(B90,LISTA!C:C,LISTA!B:B,""),"") -> 001814 | B90: CABO FLEXIVEL, ISOL. HEPR, CAPA PVC ST2, TEMP. 90C, 0,6 / 1KV, NBR 7286, PRETO, 1 X 240,00 MM | C90: =IFERROR(_xlfn.XLOOKUP(B90,LISTA!C:C,LISTA!D:D,""),"") -> MT | D90: =IFERROR(_xlfn.XLOOKUP(B90,LISTA!C:C,LISTA!E:E,""),"") -> 0 | E90: =IFERROR(_xlfn.XLOOKUP(B90,LISTA!C:C,LISTA!F:F,""),"") -> MI | F90: 45 | H90: 85444900 | I90: 1004800 | J90: 0 - Nacional | K90: Próprio | L90: 56.76 | M90: L20250919 | N90: II - 85444900 | O90: 7897783942821
A91: =IFERROR(_xlfn.XLOOKUP(B91,LISTA!C:C,LISTA!B:B,""),"") -> 001847 | B91: CABO INSTRUMENTACAO 300V, ISOL. PVC PRETO, BLIND. ELETROST. FIO DRENO, TEMP 70C, NBR 10300, CL 2 1X2 X 0,75MM SPAR-FLEX | C91: =IFERROR(_xlfn.XLOOKUP(B91,LISTA!C:C,LISTA!D:D,""),"") -> MT | D91: =IFERROR(_xlfn.XLOOKUP(B91,LISTA!C:C,LISTA!E:E,""),"") -> 0 | E91: =IFERROR(_xlfn.XLOOKUP(B91,LISTA!C:C,LISTA!F:F,""),"") -> MI | F91: 77 | G91: SPAR-FLEX | H91: 85444900 | I91: 1005000 | J91: 0 - Nacional | K91: Próprio | L91: 75.33 | M91: L20251124 | N91: II - 85444900 | O91: 7892705023408
A92: =IFERROR(_xlfn.XLOOKUP(B92,LISTA!C:C,LISTA!B:B,""),"") -> 001876 | B92: CABO DE REDE, U/UTP, CMX, CAT. 5E, 24 AWG X 4P, AZUL | C92: =IFERROR(_xlfn.XLOOKUP(B92,LISTA!C:C,LISTA!D:D,""),"") -> MT | D92: =IFERROR(_xlfn.XLOOKUP(B92,LISTA!C:C,LISTA!E:E,""),"") -> 0 | E92: =IFERROR(_xlfn.XLOOKUP(B92,LISTA!C:C,LISTA!F:F,""),"") -> MI | F92: 53 | H92: 85444200 | I92: 1004800 | J92: 0 - Nacional | K92: Próprio | L92: 91.58 | M92: L20250728 | N92: II - 85444200 | O92: 7891831819534
A93: =IFERROR(_xlfn.XLOOKUP(B93,LISTA!C:C,LISTA!B:B,""),"") -> 001930 | B93: CABO CONTROLE, CL. 4, PVC/A 70C, NBR 7289, 500V, SEM BLINDAGEM, 2 X 1,00MM | C93: =IFERROR(_xlfn.XLOOKUP(B93,LISTA!C:C,LISTA!D:D,""),"") -> MT | D93: =IFERROR(_xlfn.XLOOKUP(B93,LISTA!C:C,LISTA!E:E,""),"") -> 0 | E93: =IFERROR(_xlfn.XLOOKUP(B93,LISTA!C:C,LISTA!F:F,""),"") -> MI | F93: 31 | H93: 85444200 | I93: 1005000 | J93: 0 - Nacional | K93: Próprio | L93: 31.1 | M93: L20250801 | N93: II - 85444200 | O93: 7892813631650
A94: =IFERROR(_xlfn.XLOOKUP(B94,LISTA!C:C,LISTA!B:B,""),"") -> 001971 | B94: CABO DE INSTRUMENTACAO, DEVICENET FINO, 18AWG, 300V, CL. 02, CAPA PVC CINZA 3084A# ALLEN BRADLEY | C94: =IFERROR(_xlfn.XLOOKUP(B94,LISTA!C:C,LISTA!D:D,""),"") -> MT | D94: =IFERROR(_xlfn.XLOOKUP(B94,LISTA!C:C,LISTA!E:E,""),"") -> 0 | E94: =IFERROR(_xlfn.XLOOKUP(B94,LISTA!C:C,LISTA!F:F,""),"") -> MI | F94: 69 | G94: ALLEN BRADLEY | H94: 85444200 | I94: 1004800 | J94: 0 - Nacional | K94: Próprio | L94: 91.73 | M94: L20250807 | N94: II - 85444200 | O94: 7895045384081
A95: =IFERROR(_xlfn.XLOOKUP(B95,LISTA!C:C,LISTA!B:B,""),"") -> 001999 | B95: CABO FLEXIVEL, ISOL. PVC/A, TEMP. 70 C, 750V, PRETO, 1 X 95,00 MM | C95: =IFERROR(_xlfn.XLOOKUP(B95,LISTA!C:C,LISTA!D:D,""),"") -> MT | D95: =IFERROR(_xlfn.XLOOKUP(B95,LISTA!C:C,LISTA!E:E,""),"") -> 0 | E95: =IFERROR(_xlfn.XLOOKUP(B95,LISTA!C:C,LISTA!F:F,""),"") -> MI | F95: 24 | H95: 85444900 | I95: 1004800 | J95: 0 - Nacional | K95: Próprio | L95: 74.43 | M95: L20250213 | N95: II - 85444900 | O95: 7892954155565
A96: =IFERROR(_xlfn.XLOOKUP(B96,LISTA!C:C,LISTA!B:B,""),"") -> 002023 | B96: CABO PROFIBUS DP, 300V, 105 C, CAPA PVC VIOLETA, BELDFOIL, FIO DRENO EM COBRE ESTANHADO 2 X 22AWG, 3079A, BELDEN | C96: =IFERROR(_xlfn.XLOOKUP(B96,LISTA!C:C,LISTA!D:D,""),"") -> MT | D96: -63 | E96: =IFERROR(_xlfn.XLOOKUP(B96,LISTA!C:C,LISTA!F:F,""),"") -> MI | F96: 16 | G96: BELDEN | H96: 85444200 | I96: 1005000 | J96: 0 - Nacional | K96: Próprio | L96: 59.14 | M96: L20250825 | N96: II - 85444200 | O96: 7895845054390
A97: =IFERROR(_xlfn.XLOOKUP(B97,LISTA!C:C,LISTA!B:B,""),"") -> 002034 | B97: CABO FLEXIVEL EPROTEMAX GSETTE, ISOL. EPR/B, CAPA PVC, TEMP. 90§C 0,6 / 1KV PRETO 4 X 2,5MM PRYSMIAN | C97: =IFERROR(_xlfn.XLOOKUP(B97,LISTA!C:C,LISTA!D:D,""),"") -> MT | D97: =IFERROR(_xlfn.XLOOKUP(B97,LISTA!C:C,LISTA!E:E,""),"") -> 0 | E97: =IFERROR(_xlfn.XLOOKUP(B97,LISTA!C:C,LISTA!F:F,""),"") -> MI | F97: 73 | G97: PRYSMIAN | H97: 85444900 | I97: 1004100 | J97: 0 - Nacional | K97: Próprio | L97: 14.37 | M97: L20250922 | N97: II - 85444900 | O97: 7897757617476
A98: =IFERROR(_xlfn.XLOOKUP(B98,LISTA!C:C,LISTA!B:B,""),"") -> 002092 | B98: CABO COBRE NU, MEIO DURO, 19X2,10 FIOS, CL 3A, NBR 6524, SECAO 70,00 MM | C98: =IFERROR(_xlfn.XLOOKUP(B98,LISTA!C:C,LISTA!D:D,""),"") -> MT | D98: =IFERROR(_xlfn.XLOOKUP(B98,LISTA!C:C,LISTA!E:E,""),"") -> 0 | E98: =IFERROR(_xlfn.XLOOKUP(B98,LISTA!C:C,LISTA!F:F,""),"") -> MI | F98: 47 | H98: 74081100 | I98: 1004800 | J98: 0 - Nacional | K98: Próprio | L98: 54.49 | M98: L20250823 | N98: II - 74081100 | O98: 7894113177777
A99: =IFERROR(_xlfn.XLOOKUP(B99,LISTA!C:C,LISTA!B:B,""),"") -> 002132 | B99: CABO FLEXIVEL, ISOL. HEPR, CAPA PVC ST2, TEMP. 90C, 0,6 / 1KV, NBR 7286, PRETO, 3 X 16,00 MM | C99: =IFERROR(_xlfn.XLOOKUP(B99,LISTA!C:C,LISTA!D:D,""),"") -> MT | D99: =IFERROR(_xlfn.XLOOKUP(B99,LISTA!C:C,LISTA!E:E,""),"") -> 0 | E99: =IFERROR(_xlfn.XLOOKUP(B99,LISTA!C:C,LISTA!F:F,""),"") -> MI | F99: 52 | H99: 85444900 | I99: 1005000 | J99: 0 - Nacional | K99: Próprio | L99: 41.45 | M99: L20250509 | N99: II - 85444900 | O99: 7897686755660
A100: =IFERROR(_xlfn.XLOOKUP(B100,LISTA!C:C,LISTA!B:B,""),"") -> 002160 | B100: CABO COBRE NU 07 FIOS CL 2A 10 MM CROSSRFOX | C100: =IFERROR(_xlfn.XLOOKUP(B100,LISTA!C:C,LISTA!D:D,""),"") -> PC | D100: =IFERROR(_xlfn.XLOOKUP(B100,LISTA!C:C,LISTA!E:E,""),"") -> 0 | E100: =IFERROR(_xlfn.XLOOKUP(B100,LISTA!C:C,LISTA!F:F,""),"") -> MI | F100: 41 | G100: CROSSRFOX | H100: 74081100 | I100: 1004100 | J100: 0 - Nacional | K100: Próprio | L100: 20.09 | M100: L20250603 | N100: II - 74081100 | O100: 7895106615694
A101: =IFERROR(_xlfn.XLOOKUP(B101,LISTA!C:C,LISTA!B:B,""),"") -> 002181 | B101: CABO FLEXIVEL, ISOL. PVC/A, TEMP. 70 C, 500V, PRETO, 4 X 1,00 MM | C101: =IFERROR(_xlfn.XLOOKUP(B101,LISTA!C:C,LISTA!D:D,""),"") -> MT | D101: =IFERROR(_xlfn.XLOOKUP(B101,LISTA!C:C,LISTA!E:E,""),"") -> 0 | E101: =IFERROR(_xlfn.XLOOKUP(B101,LISTA!C:C,LISTA!F:F,""),"") -> MI | F101: 12 | H101: 85444900 | I101: 1004100 | J101: 0 - Nacional | K101: Próprio | L101: 68.09 | M101: L20251113 | N101: II - 85444900 | O101: 7899506396297
