Workbook
Name Administrativo_Custo_Fx: '[1]Cockpit Retorno'!$D$41
Name Atendentes_Instr_Campo_QT: '[1]Calc Eng'!$B$53
Name Atendentes_Senior_QT: '[1]Calc Eng'!$B$51
Name Atendentes_Sistema_Processo_QT: '[1]Calc Eng'!$B$52
Name Atendentes_Total: '[1]Calc Eng'!$B$28
Name ATK_INTEG: SUM('[1]Resumo_HIA_HIC_HOC '!$Q$6:$Q$8)
Name ATK_LOG: '[1]Resumo_HIA_HIC_HOC '!$E$13
Name ATK_LOG_INT: '[1]Resumo_HIA_HIC_HOC '!$F$13
Name ATK_LOG_MOB: '[1]Resumo_HIA_HIC_HOC '!$G$13
Name ATK_MOA: '[1]Resumo_HIA_HIC_HOC '!$E$6
Name ATK_MOA_INT: '[1]Resumo_HIA_HIC_HOC '!$F$6
Name ATK_MOA_MOB: '[1]Resumo_HIA_HIC_HOC '!$G$6
Name ATK_MOB: '[1]Resumo_HIA_HIC_HOC '!$L$12
Name ATK_MOD: '[1]Resumo_HIA_HIC_HOC '!$E$8
Name ATK_MOD_INT: '[1]Resumo_HIA_HIC_HOC '!$F$8
Name ATK_MOD_MOB: '[1]Resumo_HIA_HIC_HOC '!$G$8
Name ATK_MOI: '[1]Resumo_HIA_HIC_HOC '!$E$7
Name ATK_MOI_INT: '[1]Resumo_HIA_HIC_HOC '!$F$7
Name ATK_MOI_MOB: '[1]Resumo_HIA_HIC_HOC '!$G$7
Name ATK_periculosidade: '[1]Resumo_HIA_HIC_HOC '!$E$10
Name ATK_Serviços: '[1]Cockpit Retorno'!$L$2
Name ATK_SSMA: '[1]Resumo_HIA_HIC_HOC '!$L$11
Name ATK_Turnover: '[1]Resumo_HIA_HIC_HOC '!$E$9
Name Base_REAJUSTE_MOD_E_MOI: '[1]Custo MO Impostos Obras'!$F$6
Name BDI: [1]BDI!$G$24
Name C_ADM_Geral: 0.1
Name Capital_Giro_ATM: '[1]Cockpit Retorno'!$C$42
Name Capital_Giro_Passivo_BNC_Passivo_Tributario_Tarifas_Advogados: '[1]Cockpit Retorno'!$AFR$174
Name Capital_Giro_Passivo_Custo_Fx: '[1]Cockpit Retorno'!$D$42
Name Casa_Total_Ocupantes: [1]TESTE_LOG_OBRA!$J$38
Name Cesta_Básica_Total: '[1]Resumo_HIA_HIC_HOC '!$G$23
Name Cofins__ATK: [1]Impostos_Taxas_ICMs!$I$31
Name Cofins__Sistema: [1]Impostos_Taxas_ICMs!$H$31
Name COFINS_lOG_MOB: [1]Impostos_Taxas_ICMs!$K$25
Name COFINS_M_S: [1]Impostos_Taxas_ICMs!$H$6
Name Comercial_Custo_Fx: '[1]Cockpit Retorno'!$AFB$174
Name Conteiner_Aluguel_Mes: '[1]Calc Eng'!$B$44
Name Contratação_LOG_Integração_Cliente: [1]HIC_Histograma_Integra_Cliente!$I$51
Name Contratação_Total__Logística: [1]HIA_Histograma_Integração_ATM!$J$51
Name CSLL: [1]Impostos_Taxas_ICMs!$H$28
Name Custo_Comercial__Plus: '[1]Cockpit Retorno'!$C$38
Name Custo_comercial_1: '[1]Cockpit Retorno'!$C$37
Name Custo_Contingência: '[1]Cockpit Retorno'!$C$45
Name Custo_Financeiro_Exclusivo_do_Contrato: '[1]Cockpit Retorno'!$C$43
Name Custo_fixo___Administrativo__Cartões__Carros__Manutenção__Custo_Consumo_interno__SSMA_interno__Alugueis__Luz__Água__Internet_Telefone__Material_escritório__Aquisições_Extra_OS__Totvs__Softwares: '[1]Cockpit Retorno'!$AFK$174
Name Custo_fixo_Adminstrativo: '[1]Cockpit Retorno'!$C$41
Name Custo_Impostos_Credito__Débito: '[1]Cockpit Retorno'!$K$32
Name Custo_Total: '[1]Cockpit Retorno'!$C$47
Name Custos_Viagens__Feiras__Marketing__Filiais: '[1]Cockpit Retorno'!$AFB$171
Name Debito_Impostos: '[1]Cockpit Retorno'!$K$32
Name Diária_Casa_Custo_Atendente: '[1]Calc Eng'!$B$3
Name Diária_Casa_Geral: '[1]Calc Eng'!$B$4
Name Diária_Completa_Sem_Transporte: '[1]Calc Eng'!$B$42
Name Diárias_Hotel_Avulsas_Custo: '[1]Calc Eng'!$B$5
Name Diárias_Hotel_Negociada_Custo: '[1]Calc Eng'!$B$6
Name Dias_Campo: '[1]Calc Eng'!$B$33
Name Dificuldade_Projeto: '[1]Calc Eng'!$K$68
Name Distância_Base_PLANTA: '[1]Calc Eng'!$B$38
Name Distância_STZ_BASE: '[1]Calc Eng'!$B$37
Name Dolar_Referencia: '[1]Cockpit Retorno'!$C$48

Sheet Mestre
D1: eparação Valores
H38: Real
H39: CFTV | U39: =Mestre!AG1312 -> 0
H40: INST
H41: LOG COM
H42: LOG MON
H43: LOG INT
H44: MI
H45: MI - Abraçadeiras
H46: MI - Aço
H47: MI - Aterramento e SPDA | K47: Retorno | L47: ATK | N47: Pis Cofins
H48: MI - Cabos | J48: 48 | K48: CFTV | L48: ATM | M48: 1 | N48: 1 | Z48: 1 ED 1 SD | AA48: 0 | AC48: ⁰C | AE48: Analisadores | AF48: 2 Fios | AI48: 0.15 | AJ48: 0.05 | AK48: 0
H49: MI - Conduletes | J49: 49 | K49: INST | L49: TERCEIROS | M49: 2 | N49: 1 | Z49: 2 ED 1 SD | AA49: 4 | AC49: % | AE49: Analisadores CO2 O2 | AF49: 4 fios | AI49: 0.03 | AJ49: 0.07 | AK49: 0.01
H50: MI - Diversos | J50: 50 | K50: LOG | L50: CLIENTE | M50: 3 | N50: 1 | Z50: ASi | AA50: 8 | AC50: brix | AE50: Bornes geral | AF50: Wireless | AI50: 0.05 | AJ50: 0.12 | AK50: 0.02
H51: MI - Eletrodutos | J51: 51 | K51: LOG_M | M51: 4 | N51: 1 | Z51: CN | AA51: 12 | AC51: g | AE51: Botoeiras | AF51: 3 fios | AI51: 0.1 | AJ51: 0.18 | AK51: 0.03
H52: MI - Iluminação | J52: 52 | K52: MI | M52: 5 | N52: 1 | Z52: DN | AA52: 16 | AC52: Kg | AE52: Chave Nível | AF52: NA | AI52: 0.2 | AJ52: 0.088 | AK52: 0.04
H53: MI - Incêndio | J53: 53 | K53: MOA | M53: 6 | N53: 1 | Z53: DP | AA53: 20 | AC53: kgf/cm² | AE53: Condutivimetro | AI53: 0 | AJ53: 0 | AK53: 0.05
H54: MI - Kanaflex | J54: 54 | K54: MOB | M54: 7 | N54: 1 | Z54: EA | AA54: 24 | AC54: l/h | AE54: Coriolise | AI54: 0.0075 | AK54: 0.06
H55: MI - Leitos | J55: 55 | K55: MOC | M55: 8 | N55: 1 | Z55: ED | AA55: 32 | AC55: m³ | AE55: Diferencial | AK55: 0.07
H56: MI - Manifold | J56: 56 | K56: MOE | M56: 9 | N56: 1 | Z56: IF | AA56: 36 | AC56: m³/h | AE56: Disjuntores Miscelâneas | AK56: 0.08
H57: MI - Manômetros | J57: 57 | K57: MOI | M57: 10 | N57: 1 | Z57: IT | AA57: 40 | AC57: mca | AE57: DT Densidade | AK57: 0.09
H58: MI - Parafusos | J58: 58 | K58: MOD | M58: 11 | N58: 1 | Z58: NA | AA58: 46 | AC58: mm | AE58: Fluxostato | AK58: 0.1
H59: MI - Potes | J59: 59 | K59: MOV | M59: 12 | N59: 1 | Z59: PA | AA59: 50 | AC59: mmH2O | AE59: Fontes | AK59: 0.11
H60: MI - Sealtube | J60: 60 | K60: PLC_DCS | M60: 13 | N60: 1 | Z60: SA | AA60: 62 | AC60: pH | AE60: Magnético | AK60: 0.12
H61: MI - Steck | J61: 61 | K61: PNL | M61: 14 | N61: 1 | Z61: SD | AA61: 14 | AC61: t | AE61: Manométrico | AK61: 0.13
H62: MI - Termômetros | J62: 62 | K62: PROD | M62: 15 | N62: 1 | Z62: 2 ED 2 SD | AC62: t/h | AE62: Manômetros | AK62: 0.14
H63: MI - Ar Comprimido | J63: 63 | K63: PROD REDE | M63: 16 | N63: 1 | Z63: 3 ED 2 SD | AC63: m | AE63: Nível Flangeado | AK63: 0.15
H64: MI - Tubbing | J64: 64 | K64: PROD TI | M64: 17 | N64: 1 | Z64: 1 ED 2 SD | AC64: g/cm³ | AE64: pH TRM | AK64: 0.16
H65: MOA | J65: 65 | K65: SERV | M65: 18 | N65: 1 | Z65: 2 ED 1 SD 1 EA 1 SA | AC65: mmHg | AE65: Pressostados | AK65: 0.17 | AU65: Nacional
H66: MOB | J66: 66 | K66: SOFT | M66: 19 | N66: 1 | AC66: G | AE66: Radar | AK66: 0.18 | AU66: Imp. Diretamente
H67: MOC | J67: 67 | K67: SSMA | M67: 20 | N67: 1 | AC67: mmca | AE67: Reles | AK67: 0.19 | AU67: Imp. Terceiros
H68: MOE | J68: 68 | K68: TRS | M68: 21 | N68: 1 | AC68: inH2O | AE68: Sensor Capacitivo | AK68: 0.2 | AU68: Fab. Própria
H69: MOI | J69: 69 | K69: MOT | AC69: mg/l | AE69: Sensor Indutivo | AK69: 0.21
H70: MOD | J70: 70 | K70: TXATM | AC70: uS | AE70: Sensores | AK70: 0.22
H71: MOV | K71: xxxx | AC71: NA | AE71: Solenóides | AK71: 0.23
H72: PLC | AC72: bar | AE72: Temperatura | AK72: 0.25
H73: PNL | AE73: Termo elemento | AK73: 0.27
H74: PROD | N74: CFTV | O74: Mercadorias | AE74: Termômetros | AK74: 0.29
H75: PROD REDE | N75: INST | O75: Mercadorias | AE75: Ultrassom | AK75: 0.31
H76: PROD TI | N76: LOG | O76: Despesas | AE76: Válvulas Controle | AK76: 0.33
H77: SDCD | N77: LOG_M | O77: Despesas | AE77: Válvulas ON OFF | AK77: 0.35
H78: SERV | N78: MI | O78: Mercadorias | Z78: 2 ED 2 SD | AE78: Vortex | AK78: 0.37
H79: SOFT | N79: MOA | O79: Serviços | Z79: 3 ED 2 SD | AE79: Sistema | AK79: 0.39
H80: SSMA | N80: MOB | O80: Despesas | Z80: 1 ED 2 SD | AE80: Posição | AK80: 0.41
H81: TRS | N81: MOC | O81: Serviços | T81: =VLOOKUP(T85,N74:O95,2) -> Serviços | Z81: 2 ED 1 SD 1 EA 1 SA | AE81: Absoluto | AK81: 0.43
H82: MOT | N82: MOD | O82: Serviços | Z82: EA | AE82: Chave de Vibração | AK82: 0.45
H83: INT - ATM | N83: MOE | O83: Serviços | Z83: SA | AE83: Rotâmetro | AK83: 0.47
H84: INT - Cliente | N84: MOI | O84: Serviços | Z84: ED | AE84: Chave de Desalinhamento | AK84: 0.49
I85: Mercadorias | N85: MOT | O85: Mercadorias | T85: moi | Z85: SD | AE85: Chave de Emergência | AK85: 0.51
I86: Despesas | N86: MOV | O86: Mercadorias | Z86: ASi | AE86: Sinalizador | AK86: 0.53
I87: Serviços | N87: PLC_DCS | O87: Mercadorias | Z87: PA | AE87: Visor de Nível | AK87: 0.55
N88: PNL | O88: Mercadorias | Z88: DP | AE88: Bocal | AK88: 0.57
N89: PROD | O89: Mercadorias | Z89: DN | AE89: Material Instalação | AK89: 0.59
N90: PROD REDE | O90: Mercadorias | Z90: CN | AE90: Posicionadores | AK90: 0.61
N91: PROD TI | O91: Mercadorias | Z91: IT | AE91: Placa de Orificio
N92: SERV | O92: Serviços | Z92: IF | AE92: Móvel
J93: ATM | M93: Itens Acrescentados | N93: SOFT | O93: Mercadorias | Z93: 2 ED 1 SD | AE93: CFTV | AW93: Serviço
J94: ATK | M94: Itens Alterados (Quantidades) | N94: SSMA | O94: Despesas | AE94: Acionamento de Motor | AX94: =IF('[1]Cockpit Retorno'!$C$66=Sim,0,1) -> 0 | BE94: Serviços
N95: TRS | O95: Despesas | AX95: d | BC95: =#REF! -> #REF! | BE95: Despesas
AX96: =Lucro -> 1 | AZ96: Finame | BE96: Mercadorias
M97: Authomathika | X97: =IF(M103=M98,0,IF(M103=$M$97,0,1)) -> 1 | AZ97: =1-BA97 -> 1 | BA97: =IF('[1]Cockpit Retorno'!C67=Sim,1,0) -> 0 | BE97: =IF('[1]Cockpit Retorno'!C66=Sim,1,0) -> 1 | BF97: =1-BE97 -> 0 | CD97: Mercadorias
M98: ATM | BE98: =IF(K100=$K$48,0,IF(K100=$K$49,0,IF(K100=$K$52,0,IF(K100=$K$59,0,IF(K100=$K$60,0,IF(K100=$K$61,0,IF(K100=$K$62,0,IF(K100=$K$63,0,IF(K100=$K$64,0,IF(K100=$K$66,0,IF(K100=$K$68,0,IF(K100=$K$68,0,IF(K100=$K$69,0,IF(K100=$K$70,0,1))))))))))))))*(($BE$102*AQ100)+((IF(I100=$BE$96,1,0)))) -> 0
E99: C | BA99: Impostos | BB99: ICM Débito | BC99: PIS Débito | BD99: COFINS Débito | BE99: ISSQN Débito | BF99: Total Impostos
Z100: 1 ED 1 SD | BA100: Valores | BB100: =SUM(BB103:BB454) -> 0 | BC100: =SUM(BC103:BC454) -> 55665.035 | BD100: =SUM(BD103:BD454) -> 256915.55 | BE100: =SUM(BE103:BE454) -> 0 | BF100: =SUM(BF103:BF454) -> 312932.26 | CD100: Despesas
H101: Preencher - Metas | K101: Dados Comerciais Base da Proposta | L101: ATM | AH101: Valores Authomathika | AS101: =IF('[1]Cockpit Retorno'!C65=Sim,0,1) -> 1 | AW101: =SUBTOTAL(9,AW103:AW454) -> 31.62 | AX101: =SUBTOTAL(9,AX103:AX454) -> 0 | AY101: =SUBTOTAL(9,AY103:AY454) -> 9808.5748 | AZ101: =SUBTOTAL(9,AZ103:AZ454) -> 45178.89 | BA101: =SUBTOTAL(9,BA103:BA454) -> 54987.465 | BB101: =SUBTOTAL(9,BB103:BB454) -> 0 | BC101: =SUBTOTAL(9,BC103:BC454) -> 55665.035 | BD101: =SUBTOTAL(9,BD103:BD454) -> 256915.55 | ... BF101: =SUBTOTAL(9,BF103:BF454) -> 312932.26 | CD101: Serviços
A102: Check1 | B102: Controle | C102: Check | D102: Grupo | E102: Criticidade | F102: Origem | G102: Indice | H102: Classificação Real | I102: Classificação | J102: Pedido aberto para a empresa: ATM/ATK | K102: Tipo Classsificação | L102: Fornecedor | M102: Fabricante | N102: Área de Aplicação | O102: Sub área de Aplicação | P102: TAG Identificação | Q102: TAG | R102: Tag GF | S102: Malha Setor Equipamento | T102: Função Tipo Serviço Classe | U102: TAG Painel Remota ou GTW | V102: Local Paineis & Remotas | W102: Diâmetro Tubulações | X102: Descrição Equipamento Informação | Y102: Modelo Código Equipamento | Z102: Tipo IO | AA102: Disponibilidade Cartão_Modulo IO | AB102: Range, faixa, Alcance | AC102: Unidade | AD102: Dados | AE102: Caracteristica Medição | AF102: Tipo Alimentação | AG102: QTDE | AH102: Custo Unitário ICM PIS COFINS | AI102: IPI Excluso % | AJ102: ICM Incluso % | AK102: Desconto % | AL102: Buyout | AM102: Custo_ S_ IPI | AN102: Custo_ C_IPI | AO102: Multiplicador | AP102: Valor Margem I _P_C | AQ102: Valor de Venda com o Fator | AR102: Valor Com Margem ICM+PIS+COFINS + IPI | AS102: Fee Venda sobre Custo Já com Credito e débito (Fora IPI) | AT102: Tipo Classsificação_R | AU102: Classificação_R | AV102: NCM Codigo para Finame | AW102: Pago de IPI | AX102: Crédito ICM | AY102: 0.0165 | AZ102: 0.076 | BA102: Crédito I _P_C | BB102: =ICMs_Mercadoria*$AX$94*'[1]Cockpit Retorno'!$D$1 -> 0 | BC102: =IF('[1]Cockpit Retorno'!E67=Sim,Pis__ATK,Pis__Sistema)*'[1]Cockpit Retorno'!D1 -> 0.0065 | BD102: =IF('[1]Cockpit Retorno'!E67=Sim,Cofins__ATK,Cofins__Sistema)*'[1]Cockpit Retorno'!D1 -> 0.03 | BE102: =ISSQN*'[1]Cockpit Retorno'!$D$2 -> 0 | BF102: Dédito Impostos I_P_C | BG102: Necessidades EA | BH102: Necessidades SA | BI102: Necessidades ED | BJ102: Necessidades SD | BK102: Necessidades IF | BL102: Necessidades IT | BM102: Necessidades ASi | BN102: Necessidades PA | BO102: Necessidades DP | BP102: Necessidades DN | BQ102: Necessidades CN | BR102: Disponibilidade EA | BS102: Disponibilidade SA | BT102: Disponibilidade ED | BU102: Disponibilidade SD | BV102: Disponibilidade IF | BW102: Disponibilidade IT | BX102: Disponibilidade ASi | BY102: Disponibilidade PA | BZ102: Disponibilidade DP | CA102: Disponibilidade DN | CB102: Disponibilidade CN | CC102: Faturamento Direto | CE102: Minimo | CF102: Medio 1 | CG102: Medio | CH102: Medio 2 | CI102: Max | CJ102: 0.98 | CK102: 0.93 | CL102: 0.98 | CM102: 0.97 | CN102: 0.96 | CO102: 0.96 | CP102: Credito Dédito | CQ102: Valor Venda depois Impostos | CR102: Débito Pis Cofins
A103: =IF(AND('[1]Cockpit Retorno'!$E$67=Sim,Mestre!M103=Mestre!$M$98),0,1) -> 1 | B103: =IF(AND('[1]Cockpit Retorno'!$E$67=Sim,Mestre!L103=Mestre!$L$48),0,1) -> 0 | C103: =IF(AND('[1]Cockpit Retorno'!$E$67=Sim,Mestre!M103=Mestre!$M$97),0,1) -> 1 | D103: LOG_LOGM_TRS | F103: Nacional | H103: LOG COM | I103: =VLOOKUP(K103,$N$74:$O$95,2) -> Despesas | J103: ATM | K103: LOG | L103: ATM | N103: NA | O103: NA | P103: NA | Q103: NA | R103: NA | S103: NA | T103: NA | U103: NA | V103: NA | W103: NA | Y103: NA | Z103: NA | AA103: 0 | AB103: NA | AC103: NA | AD103: NA | AF103: NA | AH103: 0 | AI103: 0 | AJ103: 0 | AM103: =(((IF(L103=$L$101,1,IF(L103=$L$47,1,0))*(AH103*(1-AK103)))*AG103)*(1-AL103)) -> 0 | AN103: =IF(K103=$K$50,AM103,IF(K103=$K$53,AM103,IF(K103=$K$54,AM103,IF(K103=$K$55,AM103,IF(K103=$K$56,AM103,IF(K103=$K$57,AM103,IF(K103=$K$58,AM103,IF(K103=$K$65,AM103,IF(K103=$K$66,AM103,IF(K103=$K$67,AM103,IF(K103=$K$68,AM103,IF(K103=$K$69,AM103,IF(K103=$K$51,AM103,(AM103*(1+AI103))))))))))))))) -> 0 | AO103: 1.6 | AP103: =AM103*AO103 -> 0 | AQ103: =AP103*Fator_Venda -> 0 | AR103: =AO103*AN103 -> 0 | AS103: =IFERROR(IF($AX$94=0,(CQ103/AN103),CQ103/AM103),0) -> 0 | AT103: =K103 -> LOG | AU103: =I103 -> Despesas | AW103: =IF(K103=$K$50,0,IF(K103=$K$53,0,IF(K103=$K$54,0,IF(K103=$K$55,0,IF(K103=$K$56,0,IF(K103=$K$57,0,IF(K103=$K$58,0,IF(K103=$K$65,0,IF(K103=$K$66,0,IF(K103=$K$67,0,IF(K103=$K$68,0,IF(K103=$K$69,0,IF(K103=$K$51,0,1))))))))))))*AM103*AI103) -> 0 | AX103: =IF(K103=$K$50,0,IF(K103=$K$53,0,IF(K103=$K$54,0,IF(K103=$K$55,0,IF(K103=$K$56,0,IF(K103=$K$57,0,IF(K103=$K$58,0,IF(K103=$K$65,0,IF(K103=$K$66,0,IF(K103=$K$67,0,IF(K103=$K$68,0,IF(K103=$K$69,0,IF(K103=$K$51,0,1))))))))))))*AM103*AJ103*$AX$94) -> 0 | AY103: =IF(K103=$K$53,0,IF(K103=$K$54,0,IF(K103=$K$55,0,IF(K103=$K$56,0,IF(K103=$K$58,0,IF(K103=$K$50,0,IF(K103=$K$65,0,IF(K103=$K$57,0,IF(K103=$K$51,0,AM103*$AY$102))))))))) -> 0 | AZ103: =IF(K103=$K$53,0,IF(K103=$K$54,0,IF(K103=$K$55,0,IF(K103=$K$56,0,IF(K103=$K$58,0,IF(K103=$K$50,0,IF(K103=$K$65,0,IF(K103=$K$57,0,IF(K103=$K$51,0,AM103*$AZ$102))))))))) -> 0 | BA103: =AZ103+AY103+AX103 -> 0 | BB103: =IF($BA$97=1,AQ103*$BB$102,IF(K103=$K$50,0,IF(K103=$K$53,0,IF(K103=$K$54,0,IF(K103=$K$55,0,IF(K103=$K$56,0,IF(K103=$K$57,0,IF(K103=$K$58,0,IF(K103=$K$65,0,IF(K103=$K$66,0,IF(K103=$K$67,0,IF(K103=$K$68,0,IF(K103=$K$69,0,IF(K103=$K$51,0,1)))))))))))*AQ103*$BB$102))) -> 0 | BC103: =AQ103*$BC$102 -> 0 | BD103: =$BD$102*AQ103 -> 0 | BE103: =IF($BE$95=I103,$BE$97,IF(I103=$BE$96,$BE$97,1))*($BE$102*AQ103)*$AZ$97 -> 0 | BF103: =IF('[1]Cockpit Retorno'!$C$65=Sim,Mestre!BA103,SUM(BB103:BE103)+(IF(K103=$K$56,AQ103*MOE_IRRF_LR,0))) -> 0 | BG103: =IF(AA103>0,0,IF(Z103=$Z$82,AG103*1,(IF(Z103=$Z$81,AG103*1,0)))) -> 0 | BH103: =IF(AA103>0,0,IF(Z103=$Z$83,AG103*1,IF(Z103=$Z$81,AG103*1,0))) -> 0 | BI103: =IF(AA103>0,0,IF(Z103=$Z$84,AG103*1,IF(Z103=$Z$93,AG103*2,IF(Z103=$Z$100,AG103,IF(Z103=$Z$81,AG103*2,IF(Z103=$Z$80,AG103*1,IF(Z103=$Z$79,AG103*3,IF(Z103=$Z$78,AG103*2,0)))))))) -> 0 | BJ103: =IF(AA103>0,0,IF(Z103=$Z$85,AG103,IF(Z103=$Z$93,AG103,IF(Z103=$Z$100,AG103,IF(Z103=$Z$81,AG103*1,IF(Z103=$Z$80,AG103*2,IF(Z103=$Z$79,AG103*2,IF(Z103=$Z$78,AG103*2,0)))))))) -> 0 | BK103: =IF(AA103>0,0,IF(Z103=$Z$92,AG103,0)) -> 0 | BL103: =IF(AA103>0,0,IF(Z103=$Z$91,AG103,0)) -> 0 | BM103: =IF(AA103>0,0,IF(Z103=$Z$86,AG103,0)) -> 0 | BN103: =IF(AA103>0,0,IF(Z103=$Z$87,AG103,0)) -> 0 | BO103: =IF(AA103>0,0,IF(Z103=$Z$88,AG103,0)) -> 0 | BP103: =IF(AA103>0,0,IF(Z103=$Z$89,AG103,0)) -> 0 | BQ103: =IF(AA103>0,0,IF(Z103=$Z$90,AG103,0)) -> 0 | BR103: =IF(Z103=$Z$82,AA103*AG103,0) -> 0 | BS103: =IF(Z103=$Z$83,AA103*AG103,0) -> 0 | BT103: =IF(AA103<1,0,IF(Z103=$Z$84,AA103*AG103,IF(Z103=$Z$93,"ERRO",IF(Z103=$Z$100,"ERRO",0)))) -> 0 | BU103: =IF(AA103<1,0,IF(Z103=$Z$85,AA103*AG103,IF(Z103=$Z$93,"ERRO",IF(Z103=$Z$100,"ERRO",0)))) -> 0 | BV103: =IF(Z103=$Z$92,AA103*AG103,0) -> 0 | BW103: =IF(Z103=$Z$91,AA103*AG103,0) -> 0 | BX103: =IF(Z103=$Z$86,AA103*AG103,0) -> 0 | BY103: =IF(Z103=$Z$87,AA103*AG103,0) -> 0 | BZ103: =IF(Z103=$Z$88,AA103*AG103,0) -> 0 | CA103: =IF(Z103=$Z$89,AA103*AG103,0) -> 0 | CB103: =IF(Z103=$Z$90,AA103*AG103,0) -> 0 | CC103: =IFERROR(IF(L103=$L$49,AG103*AH103*(1+AI103)*(1-AK103)*(1-AL103),0),0) -> 0 | CD103: =IF(I103=$CD$97,1,IF(I103=$CD$100,2,IF(K103=$K$66,1,IF(K103=$K$69,1,3)))) -> 2 | CE103: =IF($CD103=1,1.07,IF($CD103=2,1.07,1.3)) -> 1.07 | CF103: =CG103*0.87 -> 1.2789 | CG103: =IF($CD103=1,1.42,IF($CD103=2,1.47,2)) -> 1.47 | CH103: =CG103*1.09 -> 1.6023 | CI103: =IF($CD103=1,1.7,IF($CD103=2,1.7,2.4)) -> 1.7 | CJ103: =CE103*$CJ$102 -> 1.0486 | CK103: =CF103*$CK$102 -> 1.189377 | CL103: =CG103*$CL$102 -> 1.4406 | CM103: =CH103*$CM$102 -> 1.554231 | CN103: =CI103*$CN$102 -> 1.632 | CO103: 1.3 | CP103: =BF103-BA103 -> 0 | CQ103: =AQ103-CP103 -> 0 | CR103: =BC103+BD103 -> 0
A104: =IF(AND('[1]Cockpit Retorno'!$E$67=Sim,Mestre!M104=Mestre!$M$98),0,1) -> 1 | B104: =IF(AND('[1]Cockpit Retorno'!$E$67=Sim,Mestre!L104=Mestre!$L$48),0,1) -> 1 | C104: =IF(AND('[1]Cockpit Retorno'!$E$67=Sim,Mestre!M104=Mestre!$M$97),0,1) -> 1 | D104: MOA_MOD_MOI | F104: Nacional | H104: MOI | I104: =VLOOKUP(K104,$N$74:$O$95,2) -> Serviços | J104: ATK | K104: MOA | L104: ATK | M104: ATK | N104: NA | O104: M.O. | P104: NA | Q104: NA | R104: NA | S104: NA | T104: NA | U104: NA | V104: NA | W104: NA | X104: Execução | Y104: NA | Z104: NA | AA104: 0 | AB104: NA | AC104: NA | AD104: NA | AF104: NA | AG104: 1 | AH104: 179538.84 | AI104: 0 | AJ104: 0 | AM104: =(((IF(L104=$L$101,1,IF(L104=$L$47,1,0))*(AH104*(1-AK104)))*AG104)*(1-AL104)) -> 179538.84 | AN104: =IF(K104=$K$50,AM104,IF(K104=$K$53,AM104,IF(K104=$K$54,AM104,IF(K104=$K$55,AM104,IF(K104=$K$56,AM104,IF(K104=$K$57,AM104,IF(K104=$K$58,AM104,IF(K104=$K$65,AM104,IF(K104=$K$66,AM104,IF(K104=$K$67,AM104,IF(K104=$K$68,AM104,IF(K104=$K$69,AM104,IF(K104=$K$51,AM104,(AM104*(1+AI104))))))))))))))) -> 179538.84 | AO104: 1.9 | AP104: =AM104*AO104 -> 341123.79 | AQ104: =AP104*Fator_Venda -> 295571.93 | AR104: =AO104*AN104 -> 341123.79 | AS104: =IFERROR(IF($AX$94=0,(CQ104/AN104),CQ104/AM104),0) -> 1.5861947 | AT104: =K104 -> MOA | AU104: =I104 -> Serviços | AW104: =IF(K104=$K$50,0,IF(K104=$K$53,0,IF(K104=$K$54,0,IF(K104=$K$55,0,IF(K104=$K$56,0,IF(K104=$K$57,0,IF(K104=$K$58,0,IF(K104=$K$65,0,IF(K104=$K$66,0,IF(K104=$K$67,0,IF(K104=$K$68,0,IF(K104=$K$69,0,IF(K104=$K$51,0,1))))))))))))*AM104*AI104) -> 0 | AX104: =IF(K104=$K$50,0,IF(K104=$K$53,0,IF(K104=$K$54,0,IF(K104=$K$55,0,IF(K104=$K$56,0,IF(K104=$K$57,0,IF(K104=$K$58,0,IF(K104=$K$65,0,IF(K104=$K$66,0,IF(K104=$K$67,0,IF(K104=$K$68,0,IF(K104=$K$69,0,IF(K104=$K$51,0,1))))))))))))*AM104*AJ104*$AX$94) -> 0 | AY104: =IF(K104=$K$53,0,IF(K104=$K$54,0,IF(K104=$K$55,0,IF(K104=$K$56,0,IF(K104=$K$58,0,IF(K104=$K$50,0,IF(K104=$K$65,0,IF(K104=$K$57,0,IF(K104=$K$51,0,AM104*$AY$102))))))))) -> 0 | AZ104: =IF(K104=$K$53,0,IF(K104=$K$54,0,IF(K104=$K$55,0,IF(K104=$K$56,0,IF(K104=$K$58,0,IF(K104=$K$50,0,IF(K104=$K$65,0,IF(K104=$K$57,0,IF(K104=$K$51,0,AM104*$AZ$102))))))))) -> 0 | BA104: =AZ104+AY104+AX104 -> 0 | BB104: =IF($BA$97=1,AQ104*$BB$102,IF(K104=$K$50,0,IF(K104=$K$53,0,IF(K104=$K$54,0,IF(K104=$K$55,0,IF(K104=$K$56,0,IF(K104=$K$57,0,IF(K104=$K$58,0,IF(K104=$K$65,0,IF(K104=$K$66,0,IF(K104=$K$67,0,IF(K104=$K$68,0,IF(K104=$K$69,0,IF(K104=$K$51,0,1)))))))))))*AQ104*$BB$102))) -> 0 | BC104: =AQ104*$BC$102 -> 1921.2176 | BD104: =$BD$102*AQ104 -> 8867.1579 | BE104: =IF($BE$95=I104,$BE$97,IF(I104=$BE$96,$BE$97,1))*($BE$102*AQ104)*$AZ$97 -> 0 | BF104: =IF('[1]Cockpit Retorno'!$C$65=Sim,Mestre!BA104,SUM(BB104:BE104)+(IF(K104=$K$56,AQ104*MOE_IRRF_LR,0))) -> 10788.375 | BG104: =IF(AA104>0,0,IF(Z104=$Z$82,AG104*1,(IF(Z104=$Z$81,AG104*1,0)))) -> 0 | BH104: =IF(AA104>0,0,IF(Z104=$Z$83,AG104*1,IF(Z104=$Z$81,AG104*1,0))) -> 0 | BI104: =IF(AA104>0,0,IF(Z104=$Z$84,AG104*1,IF(Z104=$Z$93,AG104*2,IF(Z104=$Z$100,AG104,IF(Z104=$Z$81,AG104*2,IF(Z104=$Z$80,AG104*1,IF(Z104=$Z$79,AG104*3,IF(Z104=$Z$78,AG104*2,0)))))))) -> 0 | BJ104: =IF(AA104>0,0,IF(Z104=$Z$85,AG104,IF(Z104=$Z$93,AG104,IF(Z104=$Z$100,AG104,IF(Z104=$Z$81,AG104*1,IF(Z104=$Z$80,AG104*2,IF(Z104=$Z$79,AG104*2,IF(Z104=$Z$78,AG104*2,0)))))))) -> 0 | BK104: =IF(AA104>0,0,IF(Z104=$Z$92,AG104,0)) -> 0 | BL104: =IF(AA104>0,0,IF(Z104=$Z$91,AG104,0)) -> 0 | BM104: =IF(AA104>0,0,IF(Z104=$Z$86,AG104,0)) -> 0 | BN104: =IF(AA104>0,0,IF(Z104=$Z$87,AG104,0)) -> 0 | BO104: =IF(AA104>0,0,IF(Z104=$Z$88,AG104,0)) -> 0 | BP104: =IF(AA104>0,0,IF(Z104=$Z$89,AG104,0)) -> 0 | BQ104: =IF(AA104>0,0,IF(Z104=$Z$90,AG104,0)) -> 0 | BR104: =IF(Z104=$Z$82,AA104*AG104,0) -> 0 | BS104: =IF(Z104=$Z$83,AA104*AG104,0) -> 0 | BT104: =IF(AA104<1,0,IF(Z104=$Z$84,AA104*AG104,IF(Z104=$Z$93,"ERRO",IF(Z104=$Z$100,"ERRO",0)))) -> 0 | BU104: =IF(AA104<1,0,IF(Z104=$Z$85,AA104*AG104,IF(Z104=$Z$93,"ERRO",IF(Z104=$Z$100,"ERRO",0)))) -> 0 | BV104: =IF(Z104=$Z$92,AA104*AG104,0) -> 0 | BW104: =IF(Z104=$Z$91,AA104*AG104,0) -> 0 | BX104: =IF(Z104=$Z$86,AA104*AG104,0) -> 0 | BY104: =IF(Z104=$Z$87,AA104*AG104,0) -> 0 | BZ104: =IF(Z104=$Z$88,AA104*AG104,0) -> 0 | CA104: =IF(Z104=$Z$89,AA104*AG104,0) -> 0 | CB104: =IF(Z104=$Z$90,AA104*AG104,0) -> 0 | CC104: =IFERROR(IF(L104=$L$49,AG104*AH104*(1+AI104)*(1-AK104)*(1-AL104),0),0) -> 0 | CD104: =IF(I104=$CD$97,1,IF(I104=$CD$100,2,IF(K104=$K$66,1,IF(K104=$K$69,1,3)))) -> 3 | CE104: =IF($CD104=1,1.07,IF($CD104=2,1.07,1.3)) -> 1.3 | CF104: =CG104*0.87 -> 1.74 | CG104: =IF($CD104=1,1.42,IF($CD104=2,1.47,2)) -> 2 | CH104: =CG104*1.09 -> 2.18 | CI104: =IF($CD104=1,1.7,IF($CD104=2,1.7,2.4)) -> 2.4 | CJ104: =CE104*$CJ$102 -> 1.274 | CK104: =CF104*$CK$102 -> 1.6182 | CL104: =CG104*$CL$102 -> 1.96 | CM104: =CH104*$CM$102 -> 2.1146 | CN104: =CI104*$CN$102 -> 2.304 | CO104: =CJ104*$CO$102 -> 1.22304 | CP104: =BF104-BA104 -> 10788.375 | CQ104: =AQ104-CP104 -> 284783.56 | CR104: =BC104+BD104 -> 10788.375
A105: =IF(AND('[1]Cockpit Retorno'!$E$67=Sim,Mestre!M105=Mestre!$M$98),0,1) -> 1 | B105: =IF(AND('[1]Cockpit Retorno'!$E$67=Sim,Mestre!L105=Mestre!$L$48),0,1) -> 0 | C105: =IF(AND('[1]Cockpit Retorno'!$E$67=Sim,Mestre!M105=Mestre!$M$97),0,1) -> 1 | D105: MOA_MOD_MOI | F105: Nacional | H105: MOI | I105: =VLOOKUP(K105,$N$74:$O$95,2) -> Serviços | J105: ATK | K105: MOI | L105: ATM | M105: ATK | N105: NA | O105: M.O. | P105: NA | Q105: NA | R105: NA | S105: NA | T105: NA | U105: NA | V105: NA | W105: NA | X105: Execução | Y105: NA | Z105: NA | AA105: 0 | AB105: NA | AC105: NA | AD105: NA | AF105: NA | AG105: 1 | AH105: 463129.33 | AI105: 0 | AJ105: 0 | AM105: =(((IF(L105=$L$101,1,IF(L105=$L$47,1,0))*(AH105*(1-AK105)))*AG105)*(1-AL105)) -> 463129.33 | AN105: =IF(K105=$K$50,AM105,IF(K105=$K$53,AM105,IF(K105=$K$54,AM105,IF(K105=$K$55,AM105,IF(K105=$K$56,AM105,IF(K105=$K$57,AM105,IF(K105=$K$58,AM105,IF(K105=$K$65,AM105,IF(K105=$K$66,AM105,IF(K105=$K$67,AM105,IF(K105=$K$68,AM105,IF(K105=$K$69,AM105,IF(K105=$K$51,AM105,(AM105*(1+AI105))))))))))))))) -> 463129.33 | AO105: 1.9 | AP105: =AM105*AO105 -> 879945.73 | AQ105: =AP105*Fator_Venda -> 762442.46 | AR105: =AO105*AN105 -> 879945.73 | AS105: =IFERROR(IF($AX$94=0,(CQ105/AN105),CQ105/AM105),0) -> 1.5861947 | AT105: =K105 -> MOI | AU105: =I105 -> Serviços | AW105: =IF(K105=$K$50,0,IF(K105=$K$53,0,IF(K105=$K$54,0,IF(K105=$K$55,0,IF(K105=$K$56,0,IF(K105=$K$57,0,IF(K105=$K$58,0,IF(K105=$K$65,0,IF(K105=$K$66,0,IF(K105=$K$67,0,IF(K105=$K$68,0,IF(K105=$K$69,0,IF(K105=$K$51,0,1))))))))))))*AM105*AI105) -> 0 | AX105: =IF(K105=$K$50,0,IF(K105=$K$53,0,IF(K105=$K$54,0,IF(K105=$K$55,0,IF(K105=$K$56,0,IF(K105=$K$57,0,IF(K105=$K$58,0,IF(K105=$K$65,0,IF(K105=$K$66,0,IF(K105=$K$67,0,IF(K105=$K$68,0,IF(K105=$K$69,0,IF(K105=$K$51,0,1))))))))))))*AM105*AJ105*$AX$94) -> 0 | AY105: =IF(K105=$K$53,0,IF(K105=$K$54,0,IF(K105=$K$55,0,IF(K105=$K$56,0,IF(K105=$K$58,0,IF(K105=$K$50,0,IF(K105=$K$65,0,IF(K105=$K$57,0,IF(K105=$K$51,0,AM105*$AY$102))))))))) -> 0 | AZ105: =IF(K105=$K$53,0,IF(K105=$K$54,0,IF(K105=$K$55,0,IF(K105=$K$56,0,IF(K105=$K$58,0,IF(K105=$K$50,0,IF(K105=$K$65,0,IF(K105=$K$57,0,IF(K105=$K$51,0,AM105*$AZ$102))))))))) -> 0 | BA105: =AZ105+AY105+AX105 -> 0 | BB105: =IF($BA$97=1,AQ105*$BB$102,IF(K105=$K$50,0,IF(K105=$K$53,0,IF(K105=$K$54,0,IF(K105=$K$55,0,IF(K105=$K$56,0,IF(K105=$K$57,0,IF(K105=$K$58,0,IF(K105=$K$65,0,IF(K105=$K$66,0,IF(K105=$K$67,0,IF(K105=$K$68,0,IF(K105=$K$69,0,IF(K105=$K$51,0,1)))))))))))*AQ105*$BB$102))) -> 0 | BC105: =AQ105*$BC$102 -> 4955.876 | BD105: =$BD$102*AQ105 -> 22873.274 | BE105: =IF($BE$95=I105,$BE$97,IF(I105=$BE$96,$BE$97,1))*($BE$102*AQ105)*$AZ$97 -> 0 | BF105: =IF('[1]Cockpit Retorno'!$C$65=Sim,Mestre!BA105,SUM(BB105:BE105)+(IF(K105=$K$56,AQ105*MOE_IRRF_LR,0))) -> 27829.15 | BG105: =IF(AA105>0,0,IF(Z105=$Z$82,AG105*1,(IF(Z105=$Z$81,AG105*1,0)))) -> 0 | BH105: =IF(AA105>0,0,IF(Z105=$Z$83,AG105*1,IF(Z105=$Z$81,AG105*1,0))) -> 0 | BI105: =IF(AA105>0,0,IF(Z105=$Z$84,AG105*1,IF(Z105=$Z$93,AG105*2,IF(Z105=$Z$100,AG105,IF(Z105=$Z$81,AG105*2,IF(Z105=$Z$80,AG105*1,IF(Z105=$Z$79,AG105*3,IF(Z105=$Z$78,AG105*2,0)))))))) -> 0 | BJ105: =IF(AA105>0,0,IF(Z105=$Z$85,AG105,IF(Z105=$Z$93,AG105,IF(Z105=$Z$100,AG105,IF(Z105=$Z$81,AG105*1,IF(Z105=$Z$80,AG105*2,IF(Z105=$Z$79,AG105*2,IF(Z105=$Z$78,AG105*2,0)))))))) -> 0 | BK105: =IF(AA105>0,0,IF(Z105=$Z$92,AG105,0)) -> 0 | BL105: =IF(AA105>0,0,IF(Z105=$Z$91,AG105,0)) -> 0 | BM105: =IF(AA105>0,0,IF(Z105=$Z$86,AG105,0)) -> 0 | BN105: =IF(AA105>0,0,IF(Z105=$Z$87,AG105,0)) -> 0 | BO105: =IF(AA105>0,0,IF(Z105=$Z$88,AG105,0)) -> 0 | BP105: =IF(AA105>0,0,IF(Z105=$Z$89,AG105,0)) -> 0 | BQ105: =IF(AA105>0,0,IF(Z105=$Z$90,AG105,0)) -> 0 | BR105: =IF(Z105=$Z$82,AA105*AG105,0) -> 0 | BS105: =IF(Z105=$Z$83,AA105*AG105,0) -> 0 | BT105: =IF(AA105<1,0,IF(Z105=$Z$84,AA105*AG105,IF(Z105=$Z$93,"ERRO",IF(Z105=$Z$100,"ERRO",0)))) -> 0 | BU105: =IF(AA105<1,0,IF(Z105=$Z$85,AA105*AG105,IF(Z105=$Z$93,"ERRO",IF(Z105=$Z$100,"ERRO",0)))) -> 0 | BV105: =IF(Z105=$Z$92,AA105*AG105,0) -> 0 | BW105: =IF(Z105=$Z$91,AA105*AG105,0) -> 0 | BX105: =IF(Z105=$Z$86,AA105*AG105,0) -> 0 | BY105: =IF(Z105=$Z$87,AA105*AG105,0) -> 0 | BZ105: =IF(Z105=$Z$88,AA105*AG105,0) -> 0 | CA105: =IF(Z105=$Z$89,AA105*AG105,0) -> 0 | CB105: =IF(Z105=$Z$90,AA105*AG105,0) -> 0 | CC105: =IFERROR(IF(L105=$L$49,AG105*AH105*(1+AI105)*(1-AK105)*(1-AL105),0),0) -> 0 | CD105: =IF(I105=$CD$97,1,IF(I105=$CD$100,2,IF(K105=$K$66,1,IF(K105=$K$69,1,3)))) -> 3 | CE105: =IF($CD105=1,1.07,IF($CD105=2,1.07,1.3)) -> 1.3 | CF105: =CG105*0.87 -> 1.74 | CG105: =IF($CD105=1,1.42,IF($CD105=2,1.47,2)) -> 2 | CH105: =CG105*1.09 -> 2.18 | CI105: =IF($CD105=1,1.7,IF($CD105=2,1.7,2.4)) -> 2.4 | CJ105: =CE105*$CJ$102 -> 1.274 | CK105: =CF105*$CK$102 -> 1.6182 | CL105: =CG105*$CL$102 -> 1.96 | CM105: =CH105*$CM$102 -> 2.1146 | CN105: =CI105*$CN$102 -> 2.304 | CO105: =CJ105*$CO$102 -> 1.22304 | CP105: =BF105-BA105 -> 27829.15 | CQ105: =AQ105-CP105 -> 734613.31 | CR105: =BC105+BD105 -> 27829.15
A106: =IF(AND('[1]Cockpit Retorno'!$E$67=Sim,Mestre!M106=Mestre!$M$98),0,1) -> 1 | B106: =IF(AND('[1]Cockpit Retorno'!$E$67=Sim,Mestre!L106=Mestre!$L$48),0,1) -> 0 | C106: =IF(AND('[1]Cockpit Retorno'!$E$67=Sim,Mestre!M106=Mestre!$M$97),0,1) -> 1 | D106: MOA_MOD_MOI | F106: Nacional | H106: MOD | I106: =VLOOKUP(K106,$N$74:$O$95,2) -> Serviços | J106: ATK | K106: MOD | L106: ATM | M106: ATK | N106: NA | O106: M.O. | P106: NA | Q106: NA | R106: NA | S106: NA | T106: NA | U106: NA | V106: NA | W106: NA | X106: Execução | Y106: NA | Z106: NA | AA106: 0 | AB106: NA | AC106: NA | AD106: NA | AF106: NA | AG106: 1 | AH106: 1675388 | AI106: 0 | AJ106: 0 | AM106: =(((IF(L106=$L$101,1,IF(L106=$L$47,1,0))*(AH106*(1-AK106)))*AG106)*(1-AL106)) -> 1675388 | AN106: =IF(K106=$K$50,AM106,IF(K106=$K$53,AM106,IF(K106=$K$54,AM106,IF(K106=$K$55,AM106,IF(K106=$K$56,AM106,IF(K106=$K$57,AM106,IF(K106=$K$58,AM106,IF(K106=$K$65,AM106,IF(K106=$K$66,AM106,IF(K106=$K$67,AM106,IF(K106=$K$68,AM106,IF(K106=$K$69,AM106,IF(K106=$K$51,AM106,(AM106*(1+AI106))))))))))))))) -> 1675388 | AO106: 1.9 | AP106: =AM106*AO106 -> 3183237.2 | AQ106: =AP106*Fator_Venda -> 2758164.6 | AR106: =AO106*AN106 -> 3183237.2 | AS106: =IFERROR(IF($AX$94=0,(CQ106/AN106),CQ106/AM106),0) -> 1.5861947 | AT106: =K106 -> MOD | AU106: =I106 -> Serviços | AW106: =IF(K106=$K$50,0,IF(K106=$K$53,0,IF(K106=$K$54,0,IF(K106=$K$55,0,IF(K106=$K$56,0,IF(K106=$K$57,0,IF(K106=$K$58,0,IF(K106=$K$65,0,IF(K106=$K$66,0,IF(K106=$K$67,0,IF(K106=$K$68,0,IF(K106=$K$69,0,IF(K106=$K$51,0,1))))))))))))*AM106*AI106) -> 0 | AX106: =IF(K106=$K$50,0,IF(K106=$K$53,0,IF(K106=$K$54,0,IF(K106=$K$55,0,IF(K106=$K$56,0,IF(K106=$K$57,0,IF(K106=$K$58,0,IF(K106=$K$65,0,IF(K106=$K$66,0,IF(K106=$K$67,0,IF(K106=$K$68,0,IF(K106=$K$69,0,IF(K106=$K$51,0,1))))))))))))*AM106*AJ106*$AX$94) -> 0 | AY106: =IF(K106=$K$53,0,IF(K106=$K$54,0,IF(K106=$K$55,0,IF(K106=$K$56,0,IF(K106=$K$58,0,IF(K106=$K$50,0,IF(K106=$K$65,0,IF(K106=$K$57,0,IF(K106=$K$51,0,AM106*$AY$102))))))))) -> 0 | AZ106: =IF(K106=$K$53,0,IF(K106=$K$54,0,IF(K106=$K$55,0,IF(K106=$K$56,0,IF(K106=$K$58,0,IF(K106=$K$50,0,IF(K106=$K$65,0,IF(K106=$K$57,0,IF(K106=$K$51,0,AM106*$AZ$102))))))))) -> 0 | BA106: =AZ106+AY106+AX106 -> 0 | BB106: =IF($BA$97=1,AQ106*$BB$102,IF(K106=$K$50,0,IF(K106=$K$53,0,IF(K106=$K$54,0,IF(K106=$K$55,0,IF(K106=$K$56,0,IF(K106=$K$57,0,IF(K106=$K$58,0,IF(K106=$K$65,0,IF(K106=$K$66,0,IF(K106=$K$67,0,IF(K106=$K$68,0,IF(K106=$K$69,0,IF(K106=$K$51,0,1)))))))))))*AQ106*$BB$102))) -> 0 | BC106: =AQ106*$BC$102 -> 17928.07 | BD106: =$BD$102*AQ106 -> 82744.938 | BE106: =IF($BE$95=I106,$BE$97,IF(I106=$BE$96,$BE$97,1))*($BE$102*AQ106)*$AZ$97 -> 0 | BF106: =IF('[1]Cockpit Retorno'!$C$65=Sim,Mestre!BA106,SUM(BB106:BE106)+(IF(K106=$K$56,AQ106*MOE_IRRF_LR,0))) -> 100673.01 | BG106: =IF(AA106>0,0,IF(Z106=$Z$82,AG106*1,(IF(Z106=$Z$81,AG106*1,0)))) -> 0 | BH106: =IF(AA106>0,0,IF(Z106=$Z$83,AG106*1,IF(Z106=$Z$81,AG106*1,0))) -> 0 | BI106: =IF(AA106>0,0,IF(Z106=$Z$84,AG106*1,IF(Z106=$Z$93,AG106*2,IF(Z106=$Z$100,AG106,IF(Z106=$Z$81,AG106*2,IF(Z106=$Z$80,AG106*1,IF(Z106=$Z$79,AG106*3,IF(Z106=$Z$78,AG106*2,0)))))))) -> 0 | BJ106: =IF(AA106>0,0,IF(Z106=$Z$85,AG106,IF(Z106=$Z$93,AG106,IF(Z106=$Z$100,AG106,IF(Z106=$Z$81,AG106*1,IF(Z106=$Z$80,AG106*2,IF(Z106=$Z$79,AG106*2,IF(Z106=$Z$78,AG106*2,0)))))))) -> 0 | BK106: =IF(AA106>0,0,IF(Z106=$Z$92,AG106,0)) -> 0 | BL106: =IF(AA106>0,0,IF(Z106=$Z$91,AG106,0)) -> 0 | BM106: =IF(AA106>0,0,IF(Z106=$Z$86,AG106,0)) -> 0 | BN106: =IF(AA106>0,0,IF(Z106=$Z$87,AG106,0)) -> 0 | BO106: =IF(AA106>0,0,IF(Z106=$Z$88,AG106,0)) -> 0 | BP106: =IF(AA106>0,0,IF(Z106=$Z$89,AG106,0)) -> 0 | BQ106: =IF(AA106>0,0,IF(Z106=$Z$90,AG106,0)) -> 0 | BR106: =IF(Z106=$Z$82,AA106*AG106,0) -> 0 | BS106: =IF(Z106=$Z$83,AA106*AG106,0) -> 0 | BT106: =IF(AA106<1,0,IF(Z106=$Z$84,AA106*AG106,IF(Z106=$Z$93,"ERRO",IF(Z106=$Z$100,"ERRO",0)))) -> 0 | BU106: =IF(AA106<1,0,IF(Z106=$Z$85,AA106*AG106,IF(Z106=$Z$93,"ERRO",IF(Z106=$Z$100,"ERRO",0)))) -> 0 | BV106: =IF(Z106=$Z$92,AA106*AG106,0) -> 0 | BW106: =IF(Z106=$Z$91,AA106*AG106,0) -> 0 | BX106: =IF(Z106=$Z$86,AA106*AG106,0) -> 0 | BY106: =IF(Z106=$Z$87,AA106*AG106,0) -> 0 | BZ106: =IF(Z106=$Z$88,AA106*AG106,0) -> 0 | CA106: =IF(Z106=$Z$89,AA106*AG106,0) -> 0 | CB106: =IF(Z106=$Z$90,AA106*AG106,0) -> 0 | CC106: =IFERROR(IF(L106=$L$49,AG106*AH106*(1+AI106)*(1-AK106)*(1-AL106),0),0) -> 0 | CD106: =IF(I106=$CD$97,1,IF(I106=$CD$100,2,IF(K106=$K$66,1,IF(K106=$K$69,1,3)))) -> 3 | CE106: =IF($CD106=1,1.07,IF($CD106=2,1.07,1.3)) -> 1.3 | CF106: =CG106*0.87 -> 1.74 | CG106: =IF($CD106=1,1.42,IF($CD106=2,1.47,2)) -> 2 | CH106: =CG106*1.09 -> 2.18 | CI106: =IF($CD106=1,1.7,IF($CD106=2,1.7,2.4)) -> 2.4 | CJ106: =CE106*$CJ$102-0.05 -> 1.224 | CK106: =CF106*$CK$102-0.05 -> 1.5682 | CL106: =CG106*$CL$102-0.05 -> 1.91 | CM106: =CH106*$CM$102-0.05 -> 2.0646 | CN106: =CI106*$CN$102-0.05 -> 2.254 | CO106: 1.3 | CP106: =BF106-BA106 -> 100673.01 | CQ106: =AQ106-CP106 -> 2657491.6 | CR106: =BC106+BD106 -> 100673.01
A107: =IF(AND('[1]Cockpit Retorno'!$E$67=Sim,Mestre!M107=Mestre!$M$98),0,1) -> 1 | B107: =IF(AND('[1]Cockpit Retorno'!$E$67=Sim,Mestre!L107=Mestre!$L$48),0,1) -> 0 | C107: =IF(AND('[1]Cockpit Retorno'!$E$67=Sim,Mestre!M107=Mestre!$M$97),0,1) -> 1 | D107: MOA_MOD_MOI | F107: Nacional | H107: MOA | I107: =VLOOKUP(K107,$N$74:$O$95,2) -> Serviços | J107: ATK | K107: MOA | L107: ATM | M107: ATK | N107: NA | O107: M.O. | P107: NA | Q107: NA | R107: NA | S107: NA | T107: NA | U107: NA | V107: NA | W107: NA | X107: Integração ATM + Cliente | Y107: NA | Z107: NA | AA107: 0 | AB107: NA | AC107: NA | AD107: NA | AF107: NA | AG107: 1 | AH107: 0 | AI107: 0 | AJ107: 0 | AM107: =(((IF(L107=$L$101,1,IF(L107=$L$47,1,0))*(AH107*(1-AK107)))*AG107)*(1-AL107)) -> 0 | AN107: =IF(K107=$K$50,AM107,IF(K107=$K$53,AM107,IF(K107=$K$54,AM107,IF(K107=$K$55,AM107,IF(K107=$K$56,AM107,IF(K107=$K$57,AM107,IF(K107=$K$58,AM107,IF(K107=$K$65,AM107,IF(K107=$K$66,AM107,IF(K107=$K$67,AM107,IF(K107=$K$68,AM107,IF(K107=$K$69,AM107,IF(K107=$K$51,AM107,(AM107*(1+AI107))))))))))))))) -> 0 | AO107: 1.9 | AP107: =AM107*AO107 -> 0 | AQ107: =AP107*Fator_Venda -> 0 | AR107: =AO107*AN107 -> 0 | AS107: =IFERROR(IF($AX$94=0,(CQ107/AN107),CQ107/AM107),0) -> 0 | AT107: =K107 -> MOA | AU107: =I107 -> Serviços | AW107: =IF(K107=$K$50,0,IF(K107=$K$53,0,IF(K107=$K$54,0,IF(K107=$K$55,0,IF(K107=$K$56,0,IF(K107=$K$57,0,IF(K107=$K$58,0,IF(K107=$K$65,0,IF(K107=$K$66,0,IF(K107=$K$67,0,IF(K107=$K$68,0,IF(K107=$K$69,0,IF(K107=$K$51,0,1))))))))))))*AM107*AI107) -> 0 | AX107: =IF(K107=$K$50,0,IF(K107=$K$53,0,IF(K107=$K$54,0,IF(K107=$K$55,0,IF(K107=$K$56,0,IF(K107=$K$57,0,IF(K107=$K$58,0,IF(K107=$K$65,0,IF(K107=$K$66,0,IF(K107=$K$67,0,IF(K107=$K$68,0,IF(K107=$K$69,0,IF(K107=$K$51,0,1))))))))))))*AM107*AJ107*$AX$94) -> 0 | AY107: =IF(K107=$K$53,0,IF(K107=$K$54,0,IF(K107=$K$55,0,IF(K107=$K$56,0,IF(K107=$K$58,0,IF(K107=$K$50,0,IF(K107=$K$65,0,IF(K107=$K$57,0,IF(K107=$K$51,0,AM107*$AY$102))))))))) -> 0 | AZ107: =IF(K107=$K$53,0,IF(K107=$K$54,0,IF(K107=$K$55,0,IF(K107=$K$56,0,IF(K107=$K$58,0,IF(K107=$K$50,0,IF(K107=$K$65,0,IF(K107=$K$57,0,IF(K107=$K$51,0,AM107*$AZ$102))))))))) -> 0 | BA107: =AZ107+AY107+AX107 -> 0 | BB107: =IF($BA$97=1,AQ107*$BB$102,IF(K107=$K$50,0,IF(K107=$K$53,0,IF(K107=$K$54,0,IF(K107=$K$55,0,IF(K107=$K$56,0,IF(K107=$K$57,0,IF(K107=$K$58,0,IF(K107=$K$65,0,IF(K107=$K$66,0,IF(K107=$K$67,0,IF(K107=$K$68,0,IF(K107=$K$69,0,IF(K107=$K$51,0,1)))))))))))*AQ107*$BB$102))) -> 0 | BC107: =AQ107*$BC$102 -> 0 | BD107: =$BD$102*AQ107 -> 0 | BE107: =IF($BE$95=I107,$BE$97,IF(I107=$BE$96,$BE$97,1))*($BE$102*AQ107)*$AZ$97 -> 0 | BF107: =IF('[1]Cockpit Retorno'!$C$65=Sim,Mestre!BA107,SUM(BB107:BE107)+(IF(K107=$K$56,AQ107*MOE_IRRF_LR,0))) -> 0 | BG107: =IF(AA107>0,0,IF(Z107=$Z$82,AG107*1,(IF(Z107=$Z$81,AG107*1,0)))) -> 0 | BH107: =IF(AA107>0,0,IF(Z107=$Z$83,AG107*1,IF(Z107=$Z$81,AG107*1,0))) -> 0 | BI107: =IF(AA107>0,0,IF(Z107=$Z$84,AG107*1,IF(Z107=$Z$93,AG107*2,IF(Z107=$Z$100,AG107,IF(Z107=$Z$81,AG107*2,IF(Z107=$Z$80,AG107*1,IF(Z107=$Z$79,AG107*3,IF(Z107=$Z$78,AG107*2,0)))))))) -> 0 | BJ107: =IF(AA107>0,0,IF(Z107=$Z$85,AG107,IF(Z107=$Z$93,AG107,IF(Z107=$Z$100,AG107,IF(Z107=$Z$81,AG107*1,IF(Z107=$Z$80,AG107*2,IF(Z107=$Z$79,AG107*2,IF(Z107=$Z$78,AG107*2,0)))))))) -> 0 | BK107: =IF(AA107>0,0,IF(Z107=$Z$92,AG107,0)) -> 0 | BL107: =IF(AA107>0,0,IF(Z107=$Z$91,AG107,0)) -> 0 | BM107: =IF(AA107>0,0,IF(Z107=$Z$86,AG107,0)) -> 0 | BN107: =IF(AA107>0,0,IF(Z107=$Z$87,AG107,0)) -> 0 | BO107: =IF(AA107>0,0,IF(Z107=$Z$88,AG107,0)) -> 0 | BP107: =IF(AA107>0,0,IF(Z107=$Z$89,AG107,0)) -> 0 | BQ107: =IF(AA107>0,0,IF(Z107=$Z$90,AG107,0)) -> 0 | BR107: =IF(Z107=$Z$82,AA107*AG107,0) -> 0 | BS107: =IF(Z107=$Z$83,AA107*AG107,0) -> 0 | BT107: =IF(AA107<1,0,IF(Z107=$Z$84,AA107*AG107,IF(Z107=$Z$93,"ERRO",IF(Z107=$Z$100,"ERRO",0)))) -> 0 | BU107: =IF(AA107<1,0,IF(Z107=$Z$85,AA107*AG107,IF(Z107=$Z$93,"ERRO",IF(Z107=$Z$100,"ERRO",0)))) -> 0 | BV107: =IF(Z107=$Z$92,AA107*AG107,0) -> 0 | BW107: =IF(Z107=$Z$91,AA107*AG107,0) -> 0 | BX107: =IF(Z107=$Z$86,AA107*AG107,0) -> 0 | BY107: =IF(Z107=$Z$87,AA107*AG107,0) -> 0 | BZ107: =IF(Z107=$Z$88,AA107*AG107,0) -> 0 | CA107: =IF(Z107=$Z$89,AA107*AG107,0) -> 0 | CB107: =IF(Z107=$Z$90,AA107*AG107,0) -> 0 | CC107: =IFERROR(IF(L107=$L$49,AG107*AH107*(1+AI107)*(1-AK107)*(1-AL107),0),0) -> 0 | CD107: =IF(I107=$CD$97,1,IF(I107=$CD$100,2,IF(K107=$K$66,1,IF(K107=$K$69,1,3)))) -> 3 | CE107: =IF($CD107=1,1.07,IF($CD107=2,1.07,1.3)) -> 1.3 | CF107: =CG107*0.87 -> 1.74 | CG107: =IF($CD107=1,1.42,IF($CD107=2,1.47,2)) -> 2 | CH107: =CG107*1.09 -> 2.18 | CI107: =IF($CD107=1,1.7,IF($CD107=2,1.7,2.4)) -> 2.4 | CJ107: =CE107*$CJ$102 -> 1.274 | CK107: =CF107*$CK$102 -> 1.6182 | CL107: =CG107*$CL$102 -> 1.96 | CM107: =CH107*$CM$102 -> 2.1146 | CN107: =CI107*$CN$102 -> 2.304 | CO107: =CJ107*$CO$102 -> 1.22304 | CP107: =BF107-BA107 -> 0 | CQ107: =AQ107-CP107 -> 0 | CR107: =BC107+BD107 -> 0
A108: =IF(AND('[1]Cockpit Retorno'!$E$67=Sim,Mestre!M108=Mestre!$M$98),0,1) -> 1 | B108: =IF(AND('[1]Cockpit Retorno'!$E$67=Sim,Mestre!L108=Mestre!$L$48),0,1) -> 0 | C108: =IF(AND('[1]Cockpit Retorno'!$E$67=Sim,Mestre!M108=Mestre!$M$97),0,1) -> 1 | D108: MOA_MOD_MOI | F108: Nacional | H108: MOI | I108: =VLOOKUP(K108,$N$74:$O$95,2) -> Serviços | J108: ATK | K108: MOI | L108: ATM | M108: ATK | N108: NA | O108: M.O. | P108: NA | Q108: NA | R108: NA | S108: NA | T108: NA | U108: NA | V108: NA | W108: NA | X108: Integração ATM + Cliente | Y108: NA | Z108: NA | AA108: 0 | AB108: NA | AC108: NA | AD108: NA | AF108: NA | AG108: 1 | AH108: 7875.3947 | AI108: 0 | AJ108: 0 | AM108: =(((IF(L108=$L$101,1,IF(L108=$L$47,1,0))*(AH108*(1-AK108)))*AG108)*(1-AL108)) -> 7875.3947 | AN108: =IF(K108=$K$50,AM108,IF(K108=$K$53,AM108,IF(K108=$K$54,AM108,IF(K108=$K$55,AM108,IF(K108=$K$56,AM108,IF(K108=$K$57,AM108,IF(K108=$K$58,AM108,IF(K108=$K$65,AM108,IF(K108=$K$66,AM108,IF(K108=$K$67,AM108,IF(K108=$K$68,AM108,IF(K108=$K$69,AM108,IF(K108=$K$51,AM108,(AM108*(1+AI108))))))))))))))) -> 7875.3947 | AO108: 1.9 | AP108: =AM108*AO108 -> 14963.25 | AQ108: =AP108*Fator_Venda -> 12965.137 | AR108: =AO108*AN108 -> 14963.25 | AS108: =IFERROR(IF($AX$94=0,(CQ108/AN108),CQ108/AM108),0) -> 1.5861947 | AT108: =K108 -> MOI | AU108: =I108 -> Serviços | AW108: =IF(K108=$K$50,0,IF(K108=$K$53,0,IF(K108=$K$54,0,IF(K108=$K$55,0,IF(K108=$K$56,0,IF(K108=$K$57,0,IF(K108=$K$58,0,IF(K108=$K$65,0,IF(K108=$K$66,0,IF(K108=$K$67,0,IF(K108=$K$68,0,IF(K108=$K$69,0,IF(K108=$K$51,0,1))))))))))))*AM108*AI108) -> 0 | AX108: =IF(K108=$K$50,0,IF(K108=$K$53,0,IF(K108=$K$54,0,IF(K108=$K$55,0,IF(K108=$K$56,0,IF(K108=$K$57,0,IF(K108=$K$58,0,IF(K108=$K$65,0,IF(K108=$K$66,0,IF(K108=$K$67,0,IF(K108=$K$68,0,IF(K108=$K$69,0,IF(K108=$K$51,0,1))))))))))))*AM108*AJ108*$AX$94) -> 0 | AY108: =IF(K108=$K$53,0,IF(K108=$K$54,0,IF(K108=$K$55,0,IF(K108=$K$56,0,IF(K108=$K$58,0,IF(K108=$K$50,0,IF(K108=$K$65,0,IF(K108=$K$57,0,IF(K108=$K$51,0,AM108*$AY$102))))))))) -> 0 | AZ108: =IF(K108=$K$53,0,IF(K108=$K$54,0,IF(K108=$K$55,0,IF(K108=$K$56,0,IF(K108=$K$58,0,IF(K108=$K$50,0,IF(K108=$K$65,0,IF(K108=$K$57,0,IF(K108=$K$51,0,AM108*$AZ$102))))))))) -> 0 | BA108: =AZ108+AY108+AX108 -> 0 | BB108: =IF($BA$97=1,AQ108*$BB$102,IF(K108=$K$50,0,IF(K108=$K$53,0,IF(K108=$K$54,0,IF(K108=$K$55,0,IF(K108=$K$56,0,IF(K108=$K$57,0,IF(K108=$K$58,0,IF(K108=$K$65,0,IF(K108=$K$66,0,IF(K108=$K$67,0,IF(K108=$K$68,0,IF(K108=$K$69,0,IF(K108=$K$51,0,1)))))))))))*AQ108*$BB$102))) -> 0 | BC108: =AQ108*$BC$102 -> 84.273391 | BD108: =$BD$102*AQ108 -> 388.95411 | BE108: =IF($BE$95=I108,$BE$97,IF(I108=$BE$96,$BE$97,1))*($BE$102*AQ108)*$AZ$97 -> 0 | BF108: =IF('[1]Cockpit Retorno'!$C$65=Sim,Mestre!BA108,SUM(BB108:BE108)+(IF(K108=$K$56,AQ108*MOE_IRRF_LR,0))) -> 473.2275 | BG108: =IF(AA108>0,0,IF(Z108=$Z$82,AG108*1,(IF(Z108=$Z$81,AG108*1,0)))) -> 0 | BH108: =IF(AA108>0,0,IF(Z108=$Z$83,AG108*1,IF(Z108=$Z$81,AG108*1,0))) -> 0 | BI108: =IF(AA108>0,0,IF(Z108=$Z$84,AG108*1,IF(Z108=$Z$93,AG108*2,IF(Z108=$Z$100,AG108,IF(Z108=$Z$81,AG108*2,IF(Z108=$Z$80,AG108*1,IF(Z108=$Z$79,AG108*3,IF(Z108=$Z$78,AG108*2,0)))))))) -> 0 | BJ108: =IF(AA108>0,0,IF(Z108=$Z$85,AG108,IF(Z108=$Z$93,AG108,IF(Z108=$Z$100,AG108,IF(Z108=$Z$81,AG108*1,IF(Z108=$Z$80,AG108*2,IF(Z108=$Z$79,AG108*2,IF(Z108=$Z$78,AG108*2,0)))))))) -> 0 | BK108: =IF(AA108>0,0,IF(Z108=$Z$92,AG108,0)) -> 0 | BL108: =IF(AA108>0,0,IF(Z108=$Z$91,AG108,0)) -> 0 | BM108: =IF(AA108>0,0,IF(Z108=$Z$86,AG108,0)) -> 0 | BN108: =IF(AA108>0,0,IF(Z108=$Z$87,AG108,0)) -> 0 | BO108: =IF(AA108>0,0,IF(Z108=$Z$88,AG108,0)) -> 0 | BP108: =IF(AA108>0,0,IF(Z108=$Z$89,AG108,0)) -> 0 | BQ108: =IF(AA108>0,0,IF(Z108=$Z$90,AG108,0)) -> 0 | BR108: =IF(Z108=$Z$82,AA108*AG108,0) -> 0 | BS108: =IF(Z108=$Z$83,AA108*AG108,0) -> 0 | BT108: =IF(AA108<1,0,IF(Z108=$Z$84,AA108*AG108,IF(Z108=$Z$93,"ERRO",IF(Z108=$Z$100,"ERRO",0)))) -> 0 | BU108: =IF(AA108<1,0,IF(Z108=$Z$85,AA108*AG108,IF(Z108=$Z$93,"ERRO",IF(Z108=$Z$100,"ERRO",0)))) -> 0 | BV108: =IF(Z108=$Z$92,AA108*AG108,0) -> 0 | BW108: =IF(Z108=$Z$91,AA108*AG108,0) -> 0 | BX108: =IF(Z108=$Z$86,AA108*AG108,0) -> 0 | BY108: =IF(Z108=$Z$87,AA108*AG108,0) -> 0 | BZ108: =IF(Z108=$Z$88,AA108*AG108,0) -> 0 | CA108: =IF(Z108=$Z$89,AA108*AG108,0) -> 0 | CB108: =IF(Z108=$Z$90,AA108*AG108,0) -> 0 | CC108: =IFERROR(IF(L108=$L$49,AG108*AH108*(1+AI108)*(1-AK108)*(1-AL108),0),0) -> 0 | CD108: =IF(I108=$CD$97,1,IF(I108=$CD$100,2,IF(K108=$K$66,1,IF(K108=$K$69,1,3)))) -> 3 | CE108: =IF($CD108=1,1.07,IF($CD108=2,1.07,1.3)) -> 1.3 | CF108: =CG108*0.87 -> 1.74 | CG108: =IF($CD108=1,1.42,IF($CD108=2,1.47,2)) -> 2 | CH108: =CG108*1.09 -> 2.18 | CI108: =IF($CD108=1,1.7,IF($CD108=2,1.7,2.4)) -> 2.4 | CJ108: =CE108*$CJ$102 -> 1.274 | CK108: =CF108*$CK$102 -> 1.6182 | CL108: =CG108*$CL$102 -> 1.96 | CM108: =CH108*$CM$102 -> 2.1146 | CN108: =CI108*$CN$102 -> 2.304 | CO108: =CJ108*$CO$102 -> 1.22304 | CP108: =BF108-BA108 -> 473.2275 | CQ108: =AQ108-CP108 -> 12491.91 | CR108: =BC108+BD108 -> 473.2275
A109: =IF(AND('[1]Cockpit Retorno'!$E$67=Sim,Mestre!M109=Mestre!$M$98),0,1) -> 1 | B109: =IF(AND('[1]Cockpit Retorno'!$E$67=Sim,Mestre!L109=Mestre!$L$48),0,1) -> 0 | C109: =IF(AND('[1]Cockpit Retorno'!$E$67=Sim,Mestre!M109=Mestre!$M$97),0,1) -> 1 | D109: MOA_MOD_MOI | F109: Nacional | H109: MOD | I109: =VLOOKUP(K109,$N$74:$O$95,2) -> Serviços | J109: ATK | K109: MOD | L109: ATM | M109: ATK | N109: NA | O109: M.O. | P109: NA | Q109: NA | R109: NA | S109: NA | T109: NA | U109: NA | V109: NA | W109: NA | X109: Integração ATM + Cliente | Y109: NA | Z109: NA | AA109: 0 | AB109: NA | AC109: NA | AD109: NA | AF109: NA | AG109: 1 | AH109: 92263.577 | AI109: 0 | AJ109: 0 | AM109: =(((IF(L109=$L$101,1,IF(L109=$L$47,1,0))*(AH109*(1-AK109)))*AG109)*(1-AL109)) -> 92263.577 | AN109: =IF(K109=$K$50,AM109,IF(K109=$K$53,AM109,IF(K109=$K$54,AM109,IF(K109=$K$55,AM109,IF(K109=$K$56,AM109,IF(K109=$K$57,AM109,IF(K109=$K$58,AM109,IF(K109=$K$65,AM109,IF(K109=$K$66,AM109,IF(K109=$K$67,AM109,IF(K109=$K$68,AM109,IF(K109=$K$69,AM109,IF(K109=$K$51,AM109,(AM109*(1+AI109))))))))))))))) -> 92263.577 | AO109: 1.9 | AP109: =AM109*AO109 -> 175300.8 | AQ109: =AP109*Fator_Venda -> 151892.06 | AR109: =AO109*AN109 -> 175300.8 | AS109: =IFERROR(IF($AX$94=0,(CQ109/AN109),CQ109/AM109),0) -> 1.5861947 | AT109: =K109 -> MOD | AU109: =I109 -> Serviços | AW109: =IF(K109=$K$50,0,IF(K109=$K$53,0,IF(K109=$K$54,0,IF(K109=$K$55,0,IF(K109=$K$56,0,IF(K109=$K$57,0,IF(K109=$K$58,0,IF(K109=$K$65,0,IF(K109=$K$66,0,IF(K109=$K$67,0,IF(K109=$K$68,0,IF(K109=$K$69,0,IF(K109=$K$51,0,1))))))))))))*AM109*AI109) -> 0 | AX109: =IF(K109=$K$50,0,IF(K109=$K$53,0,IF(K109=$K$54,0,IF(K109=$K$55,0,IF(K109=$K$56,0,IF(K109=$K$57,0,IF(K109=$K$58,0,IF(K109=$K$65,0,IF(K109=$K$66,0,IF(K109=$K$67,0,IF(K109=$K$68,0,IF(K109=$K$69,0,IF(K109=$K$51,0,1))))))))))))*AM109*AJ109*$AX$94) -> 0 | AY109: =IF(K109=$K$53,0,IF(K109=$K$54,0,IF(K109=$K$55,0,IF(K109=$K$56,0,IF(K109=$K$58,0,IF(K109=$K$50,0,IF(K109=$K$65,0,IF(K109=$K$57,0,IF(K109=$K$51,0,AM109*$AY$102))))))))) -> 0 | AZ109: =IF(K109=$K$53,0,IF(K109=$K$54,0,IF(K109=$K$55,0,IF(K109=$K$56,0,IF(K109=$K$58,0,IF(K109=$K$50,0,IF(K109=$K$65,0,IF(K109=$K$57,0,IF(K109=$K$51,0,AM109*$AZ$102))))))))) -> 0 | BA109: =AZ109+AY109+AX109 -> 0 | BB109: =IF($BA$97=1,AQ109*$BB$102,IF(K109=$K$50,0,IF(K109=$K$53,0,IF(K109=$K$54,0,IF(K109=$K$55,0,IF(K109=$K$56,0,IF(K109=$K$57,0,IF(K109=$K$58,0,IF(K109=$K$65,0,IF(K109=$K$66,0,IF(K109=$K$67,0,IF(K109=$K$68,0,IF(K109=$K$69,0,IF(K109=$K$51,0,1)))))))))))*AQ109*$BB$102))) -> 0 | BC109: =AQ109*$BC$102 -> 987.29839 | BD109: =$BD$102*AQ109 -> 4556.7618 | BE109: =IF($BE$95=I109,$BE$97,IF(I109=$BE$96,$BE$97,1))*($BE$102*AQ109)*$AZ$97 -> 0 | BF109: =IF('[1]Cockpit Retorno'!$C$65=Sim,Mestre!BA109,SUM(BB109:BE109)+(IF(K109=$K$56,AQ109*MOE_IRRF_LR,0))) -> 5544.0602 | BG109: =IF(AA109>0,0,IF(Z109=$Z$82,AG109*1,(IF(Z109=$Z$81,AG109*1,0)))) -> 0 | BH109: =IF(AA109>0,0,IF(Z109=$Z$83,AG109*1,IF(Z109=$Z$81,AG109*1,0))) -> 0 | BI109: =IF(AA109>0,0,IF(Z109=$Z$84,AG109*1,IF(Z109=$Z$93,AG109*2,IF(Z109=$Z$100,AG109,IF(Z109=$Z$81,AG109*2,IF(Z109=$Z$80,AG109*1,IF(Z109=$Z$79,AG109*3,IF(Z109=$Z$78,AG109*2,0)))))))) -> 0 | BJ109: =IF(AA109>0,0,IF(Z109=$Z$85,AG109,IF(Z109=$Z$93,AG109,IF(Z109=$Z$100,AG109,IF(Z109=$Z$81,AG109*1,IF(Z109=$Z$80,AG109*2,IF(Z109=$Z$79,AG109*2,IF(Z109=$Z$78,AG109*2,0)))))))) -> 0 | BK109: =IF(AA109>0,0,IF(Z109=$Z$92,AG109,0)) -> 0 | BL109: =IF(AA109>0,0,IF(Z109=$Z$91,AG109,0)) -> 0 | BM109: =IF(AA109>0,0,IF(Z109=$Z$86,AG109,0)) -> 0 | BN109: =IF(AA109>0,0,IF(Z109=$Z$87,AG109,0)) -> 0 | BO109: =IF(AA109>0,0,IF(Z109=$Z$88,AG109,0)) -> 0 | BP109: =IF(AA109>0,0,IF(Z109=$Z$89,AG109,0)) -> 0 | BQ109: =IF(AA109>0,0,IF(Z109=$Z$90,AG109,0)) -> 0 | BR109: =IF(Z109=$Z$82,AA109*AG109,0) -> 0 | BS109: =IF(Z109=$Z$83,AA109*AG109,0) -> 0 | BT109: =IF(AA109<1,0,IF(Z109=$Z$84,AA109*AG109,IF(Z109=$Z$93,"ERRO",IF(Z109=$Z$100,"ERRO",0)))) -> 0 | BU109: =IF(AA109<1,0,IF(Z109=$Z$85,AA109*AG109,IF(Z109=$Z$93,"ERRO",IF(Z109=$Z$100,"ERRO",0)))) -> 0 | BV109: =IF(Z109=$Z$92,AA109*AG109,0) -> 0 | BW109: =IF(Z109=$Z$91,AA109*AG109,0) -> 0 | BX109: =IF(Z109=$Z$86,AA109*AG109,0) -> 0 | BY109: =IF(Z109=$Z$87,AA109*AG109,0) -> 0 | BZ109: =IF(Z109=$Z$88,AA109*AG109,0) -> 0 | CA109: =IF(Z109=$Z$89,AA109*AG109,0) -> 0 | CB109: =IF(Z109=$Z$90,AA109*AG109,0) -> 0 | CC109: =IFERROR(IF(L109=$L$49,AG109*AH109*(1+AI109)*(1-AK109)*(1-AL109),0),0) -> 0 | CD109: =IF(I109=$CD$97,1,IF(I109=$CD$100,2,IF(K109=$K$66,1,IF(K109=$K$69,1,3)))) -> 3 | CE109: =IF($CD109=1,1.07,IF($CD109=2,1.07,1.3)) -> 1.3 | CF109: =CG109*0.87 -> 1.74 | CG109: =IF($CD109=1,1.42,IF($CD109=2,1.47,2)) -> 2 | CH109: =CG109*1.09 -> 2.18 | CI109: =IF($CD109=1,1.7,IF($CD109=2,1.7,2.4)) -> 2.4 | CJ109: =CE109*$CJ$102-0.05 -> 1.224 | CK109: =CF109*$CK$102-0.05 -> 1.5682 | CL109: =CG109*$CL$102-0.05 -> 1.91 | CM109: =CH109*$CM$102-0.05 -> 2.0646 | CN109: =CI109*$CN$102-0.05 -> 2.254 | CO109: 1.3 | CP109: =BF109-BA109 -> 5544.0602 | CQ109: =AQ109-CP109 -> 146348 | CR109: =BC109+BD109 -> 5544.0602
A110: =IF(AND('[1]Cockpit Retorno'!$E$67=Sim,Mestre!M110=Mestre!$M$98),0,1) -> 1 | B110: =IF(AND('[1]Cockpit Retorno'!$E$67=Sim,Mestre!L110=Mestre!$L$48),0,1) -> 0 | C110: =IF(AND('[1]Cockpit Retorno'!$E$67=Sim,Mestre!M110=Mestre!$M$97),0,1) -> 1 | D110: MOA_MOD_MOI | F110: Nacional | H110: MOA | I110: =VLOOKUP(K110,$N$74:$O$95,2) -> Serviços | J110: ATK | K110: MOA | L110: ATM | M110: ATK | N110: NA | O110: MOB | P110: NA | Q110: NA | R110: NA | S110: NA | T110: NA | U110: NA | V110: NA | W110: NA | X110: Mobilização | Y110: NA | Z110: NA | AA110: 0 | AB110: NA | AC110: NA | AD110: NA | AF110: NA | AG110: 1 | AH110: 0 | AI110: 0 | AJ110: 0 | AM110: =(((IF(L110=$L$101,1,IF(L110=$L$47,1,0))*(AH110*(1-AK110)))*AG110)*(1-AL110)) -> 0 | AN110: =IF(K110=$K$50,AM110,IF(K110=$K$53,AM110,IF(K110=$K$54,AM110,IF(K110=$K$55,AM110,IF(K110=$K$56,AM110,IF(K110=$K$57,AM110,IF(K110=$K$58,AM110,IF(K110=$K$65,AM110,IF(K110=$K$66,AM110,IF(K110=$K$67,AM110,IF(K110=$K$68,AM110,IF(K110=$K$69,AM110,IF(K110=$K$51,AM110,(AM110*(1+AI110))))))))))))))) -> 0 | AO110: 1.9 | AP110: =AM110*AO110 -> 0 | AQ110: =AP110*Fator_Venda -> 0 | AR110: =AO110*AN110 -> 0 | AS110: =IFERROR(IF($AX$94=0,(CQ110/AN110),CQ110/AM110),0) -> 0 | AT110: =K110 -> MOA | AU110: =I110 -> Serviços | AW110: =IF(K110=$K$50,0,IF(K110=$K$53,0,IF(K110=$K$54,0,IF(K110=$K$55,0,IF(K110=$K$56,0,IF(K110=$K$57,0,IF(K110=$K$58,0,IF(K110=$K$65,0,IF(K110=$K$66,0,IF(K110=$K$67,0,IF(K110=$K$68,0,IF(K110=$K$69,0,IF(K110=$K$51,0,1))))))))))))*AM110*AI110) -> 0 | AX110: =IF(K110=$K$50,0,IF(K110=$K$53,0,IF(K110=$K$54,0,IF(K110=$K$55,0,IF(K110=$K$56,0,IF(K110=$K$57,0,IF(K110=$K$58,0,IF(K110=$K$65,0,IF(K110=$K$66,0,IF(K110=$K$67,0,IF(K110=$K$68,0,IF(K110=$K$69,0,IF(K110=$K$51,0,1))))))))))))*AM110*AJ110*$AX$94) -> 0 | AY110: =IF(K110=$K$53,0,IF(K110=$K$54,0,IF(K110=$K$55,0,IF(K110=$K$56,0,IF(K110=$K$58,0,IF(K110=$K$50,0,IF(K110=$K$65,0,IF(K110=$K$57,0,IF(K110=$K$51,0,AM110*$AY$102))))))))) -> 0 | AZ110: =IF(K110=$K$53,0,IF(K110=$K$54,0,IF(K110=$K$55,0,IF(K110=$K$56,0,IF(K110=$K$58,0,IF(K110=$K$50,0,IF(K110=$K$65,0,IF(K110=$K$57,0,IF(K110=$K$51,0,AM110*$AZ$102))))))))) -> 0 | BA110: =AZ110+AY110+AX110 -> 0 | BB110: =IF($BA$97=1,AQ110*$BB$102,IF(K110=$K$50,0,IF(K110=$K$53,0,IF(K110=$K$54,0,IF(K110=$K$55,0,IF(K110=$K$56,0,IF(K110=$K$57,0,IF(K110=$K$58,0,IF(K110=$K$65,0,IF(K110=$K$66,0,IF(K110=$K$67,0,IF(K110=$K$68,0,IF(K110=$K$69,0,IF(K110=$K$51,0,1)))))))))))*AQ110*$BB$102))) -> 0 | BC110: =AQ110*$BC$102 -> 0 | BD110: =$BD$102*AQ110 -> 0 | BE110: =IF($BE$95=I110,$BE$97,IF(I110=$BE$96,$BE$97,1))*($BE$102*AQ110)*$AZ$97 -> 0 | BF110: =IF('[1]Cockpit Retorno'!$C$65=Sim,Mestre!BA110,SUM(BB110:BE110)+(IF(K110=$K$56,AQ110*MOE_IRRF_LR,0))) -> 0 | BG110: =IF(AA110>0,0,IF(Z110=$Z$82,AG110*1,(IF(Z110=$Z$81,AG110*1,0)))) -> 0 | BH110: =IF(AA110>0,0,IF(Z110=$Z$83,AG110*1,IF(Z110=$Z$81,AG110*1,0))) -> 0 | BI110: =IF(AA110>0,0,IF(Z110=$Z$84,AG110*1,IF(Z110=$Z$93,AG110*2,IF(Z110=$Z$100,AG110,IF(Z110=$Z$81,AG110*2,IF(Z110=$Z$80,AG110*1,IF(Z110=$Z$79,AG110*3,IF(Z110=$Z$78,AG110*2,0)))))))) -> 0 | BJ110: =IF(AA110>0,0,IF(Z110=$Z$85,AG110,IF(Z110=$Z$93,AG110,IF(Z110=$Z$100,AG110,IF(Z110=$Z$81,AG110*1,IF(Z110=$Z$80,AG110*2,IF(Z110=$Z$79,AG110*2,IF(Z110=$Z$78,AG110*2,0)))))))) -> 0 | BK110: =IF(AA110>0,0,IF(Z110=$Z$92,AG110,0)) -> 0 | BL110: =IF(AA110>0,0,IF(Z110=$Z$91,AG110,0)) -> 0 | BM110: =IF(AA110>0,0,IF(Z110=$Z$86,AG110,0)) -> 0 | BN110: =IF(AA110>0,0,IF(Z110=$Z$87,AG110,0)) -> 0 | BO110: =IF(AA110>0,0,IF(Z110=$Z$88,AG110,0)) -> 0 | BP110: =IF(AA110>0,0,IF(Z110=$Z$89,AG110,0)) -> 0 | BQ110: =IF(AA110>0,0,IF(Z110=$Z$90,AG110,0)) -> 0 | BR110: =IF(Z110=$Z$82,AA110*AG110,0) -> 0 | BS110: =IF(Z110=$Z$83,AA110*AG110,0) -> 0 | BT110: =IF(AA110<1,0,IF(Z110=$Z$84,AA110*AG110,IF(Z110=$Z$93,"ERRO",IF(Z110=$Z$100,"ERRO",0)))) -> 0 | BU110: =IF(AA110<1,0,IF(Z110=$Z$85,AA110*AG110,IF(Z110=$Z$93,"ERRO",IF(Z110=$Z$100,"ERRO",0)))) -> 0 | BV110: =IF(Z110=$Z$92,AA110*AG110,0) -> 0 | BW110: =IF(Z110=$Z$91,AA110*AG110,0) -> 0 | BX110: =IF(Z110=$Z$86,AA110*AG110,0) -> 0 | BY110: =IF(Z110=$Z$87,AA110*AG110,0) -> 0 | BZ110: =IF(Z110=$Z$88,AA110*AG110,0) -> 0 | CA110: =IF(Z110=$Z$89,AA110*AG110,0) -> 0 | CB110: =IF(Z110=$Z$90,AA110*AG110,0) -> 0 | CC110: =IFERROR(IF(L110=$L$49,AG110*AH110*(1+AI110)*(1-AK110)*(1-AL110),0),0) -> 0 | CD110: =IF(I110=$CD$97,1,IF(I110=$CD$100,2,IF(K110=$K$66,1,IF(K110=$K$69,1,3)))) -> 3 | CE110: =IF($CD110=1,1.07,IF($CD110=2,1.07,1.3)) -> 1.3 | CF110: =CG110*0.87 -> 1.74 | CG110: =IF($CD110=1,1.42,IF($CD110=2,1.47,2)) -> 2 | CH110: =CG110*1.09 -> 2.18 | CI110: =IF($CD110=1,1.7,IF($CD110=2,1.7,2.4)) -> 2.4 | CJ110: =CE110*$CJ$102 -> 1.274 | CK110: =CF110*$CK$102 -> 1.6182 | CL110: =CG110*$CL$102 -> 1.96 | CM110: =CH110*$CM$102 -> 2.1146 | CN110: =CI110*$CN$102 -> 2.304 | CO110: =CJ110*$CO$102 -> 1.22304 | CP110: =BF110-BA110 -> 0 | CQ110: =AQ110-CP110 -> 0 | CR110: =BC110+BD110 -> 0
A111: =IF(AND('[1]Cockpit Retorno'!$E$67=Sim,Mestre!M111=Mestre!$M$98),0,1) -> 1 | B111: =IF(AND('[1]Cockpit Retorno'!$E$67=Sim,Mestre!L111=Mestre!$L$48),0,1) -> 0 | C111: =IF(AND('[1]Cockpit Retorno'!$E$67=Sim,Mestre!M111=Mestre!$M$97),0,1) -> 1 | D111: MOA_MOD_MOI | F111: Nacional | H111: MOI | I111: =VLOOKUP(K111,$N$74:$O$95,2) -> Serviços | J111: ATK | K111: MOI | L111: ATM | M111: ATK | N111: NA | O111: MOB | P111: NA | Q111: NA | R111: NA | S111: NA | T111: NA | U111: NA | V111: NA | W111: NA | X111: Mobilização | Y111: NA | Z111: NA | AA111: 0 | AB111: NA | AC111: NA | AD111: NA | AF111: NA | AG111: 1 | AH111: 4185.0405 | AI111: 0 | AJ111: 0 | AM111: =(((IF(L111=$L$101,1,IF(L111=$L$47,1,0))*(AH111*(1-AK111)))*AG111)*(1-AL111)) -> 4185.0405 | AN111: =IF(K111=$K$50,AM111,IF(K111=$K$53,AM111,IF(K111=$K$54,AM111,IF(K111=$K$55,AM111,IF(K111=$K$56,AM111,IF(K111=$K$57,AM111,IF(K111=$K$58,AM111,IF(K111=$K$65,AM111,IF(K111=$K$66,AM111,IF(K111=$K$67,AM111,IF(K111=$K$68,AM111,IF(K111=$K$69,AM111,IF(K111=$K$51,AM111,(AM111*(1+AI111))))))))))))))) -> 4185.0405 | AO111: 1.9 | AP111: =AM111*AO111 -> 7951.5769 | AQ111: =AP111*Fator_Venda -> 6889.7656 | AR111: =AO111*AN111 -> 7951.5769 | AS111: =IFERROR(IF($AX$94=0,(CQ111/AN111),CQ111/AM111),0) -> 1.5861947 | AT111: =K111 -> MOI | AU111: =I111 -> Serviços | AW111: =IF(K111=$K$50,0,IF(K111=$K$53,0,IF(K111=$K$54,0,IF(K111=$K$55,0,IF(K111=$K$56,0,IF(K111=$K$57,0,IF(K111=$K$58,0,IF(K111=$K$65,0,IF(K111=$K$66,0,IF(K111=$K$67,0,IF(K111=$K$68,0,IF(K111=$K$69,0,IF(K111=$K$51,0,1))))))))))))*AM111*AI111) -> 0 | AX111: =IF(K111=$K$50,0,IF(K111=$K$53,0,IF(K111=$K$54,0,IF(K111=$K$55,0,IF(K111=$K$56,0,IF(K111=$K$57,0,IF(K111=$K$58,0,IF(K111=$K$65,0,IF(K111=$K$66,0,IF(K111=$K$67,0,IF(K111=$K$68,0,IF(K111=$K$69,0,IF(K111=$K$51,0,1))))))))))))*AM111*AJ111*$AX$94) -> 0 | AY111: =IF(K111=$K$53,0,IF(K111=$K$54,0,IF(K111=$K$55,0,IF(K111=$K$56,0,IF(K111=$K$58,0,IF(K111=$K$50,0,IF(K111=$K$65,0,IF(K111=$K$57,0,IF(K111=$K$51,0,AM111*$AY$102))))))))) -> 0 | AZ111: =IF(K111=$K$53,0,IF(K111=$K$54,0,IF(K111=$K$55,0,IF(K111=$K$56,0,IF(K111=$K$58,0,IF(K111=$K$50,0,IF(K111=$K$65,0,IF(K111=$K$57,0,IF(K111=$K$51,0,AM111*$AZ$102))))))))) -> 0 | BA111: =AZ111+AY111+AX111 -> 0 | BB111: =IF($BA$97=1,AQ111*$BB$102,IF(K111=$K$50,0,IF(K111=$K$53,0,IF(K111=$K$54,0,IF(K111=$K$55,0,IF(K111=$K$56,0,IF(K111=$K$57,0,IF(K111=$K$58,0,IF(K111=$K$65,0,IF(K111=$K$66,0,IF(K111=$K$67,0,IF(K111=$K$68,0,IF(K111=$K$69,0,IF(K111=$K$51,0,1)))))))))))*AQ111*$BB$102))) -> 0 | BC111: =AQ111*$BC$102 -> 44.783477 | BD111: =$BD$102*AQ111 -> 206.69297 | BE111: =IF($BE$95=I111,$BE$97,IF(I111=$BE$96,$BE$97,1))*($BE$102*AQ111)*$AZ$97 -> 0 | BF111: =IF('[1]Cockpit Retorno'!$C$65=Sim,Mestre!BA111,SUM(BB111:BE111)+(IF(K111=$K$56,AQ111*MOE_IRRF_LR,0))) -> 251.47645 | BG111: =IF(AA111>0,0,IF(Z111=$Z$82,AG111*1,(IF(Z111=$Z$81,AG111*1,0)))) -> 0 | BH111: =IF(AA111>0,0,IF(Z111=$Z$83,AG111*1,IF(Z111=$Z$81,AG111*1,0))) -> 0 | BI111: =IF(AA111>0,0,IF(Z111=$Z$84,AG111*1,IF(Z111=$Z$93,AG111*2,IF(Z111=$Z$100,AG111,IF(Z111=$Z$81,AG111*2,IF(Z111=$Z$80,AG111*1,IF(Z111=$Z$79,AG111*3,IF(Z111=$Z$78,AG111*2,0)))))))) -> 0 | BJ111: =IF(AA111>0,0,IF(Z111=$Z$85,AG111,IF(Z111=$Z$93,AG111,IF(Z111=$Z$100,AG111,IF(Z111=$Z$81,AG111*1,IF(Z111=$Z$80,AG111*2,IF(Z111=$Z$79,AG111*2,IF(Z111=$Z$78,AG111*2,0)))))))) -> 0 | BK111: =IF(AA111>0,0,IF(Z111=$Z$92,AG111,0)) -> 0 | BL111: =IF(AA111>0,0,IF(Z111=$Z$91,AG111,0)) -> 0 | BM111: =IF(AA111>0,0,IF(Z111=$Z$86,AG111,0)) -> 0 | BN111: =IF(AA111>0,0,IF(Z111=$Z$87,AG111,0)) -> 0 | BO111: =IF(AA111>0,0,IF(Z111=$Z$88,AG111,0)) -> 0 | BP111: =IF(AA111>0,0,IF(Z111=$Z$89,AG111,0)) -> 0 | BQ111: =IF(AA111>0,0,IF(Z111=$Z$90,AG111,0)) -> 0 | BR111: =IF(Z111=$Z$82,AA111*AG111,0) -> 0 | BS111: =IF(Z111=$Z$83,AA111*AG111,0) -> 0 | BT111: =IF(AA111<1,0,IF(Z111=$Z$84,AA111*AG111,IF(Z111=$Z$93,"ERRO",IF(Z111=$Z$100,"ERRO",0)))) -> 0 | BU111: =IF(AA111<1,0,IF(Z111=$Z$85,AA111*AG111,IF(Z111=$Z$93,"ERRO",IF(Z111=$Z$100,"ERRO",0)))) -> 0 | BV111: =IF(Z111=$Z$92,AA111*AG111,0) -> 0 | BW111: =IF(Z111=$Z$91,AA111*AG111,0) -> 0 | BX111: =IF(Z111=$Z$86,AA111*AG111,0) -> 0 | BY111: =IF(Z111=$Z$87,AA111*AG111,0) -> 0 | BZ111: =IF(Z111=$Z$88,AA111*AG111,0) -> 0 | CA111: =IF(Z111=$Z$89,AA111*AG111,0) -> 0 | CB111: =IF(Z111=$Z$90,AA111*AG111,0) -> 0 | CC111: =IFERROR(IF(L111=$L$49,AG111*AH111*(1+AI111)*(1-AK111)*(1-AL111),0),0) -> 0 | CD111: =IF(I111=$CD$97,1,IF(I111=$CD$100,2,IF(K111=$K$66,1,IF(K111=$K$69,1,3)))) -> 3 | CE111: =IF($CD111=1,1.07,IF($CD111=2,1.07,1.3)) -> 1.3 | CF111: =CG111*0.87 -> 1.74 | CG111: =IF($CD111=1,1.42,IF($CD111=2,1.47,2)) -> 2 | CH111: =CG111*1.09 -> 2.18 | CI111: =IF($CD111=1,1.7,IF($CD111=2,1.7,2.4)) -> 2.4 | CJ111: =CE111*$CJ$102 -> 1.274 | CK111: =CF111*$CK$102 -> 1.6182 | CL111: =CG111*$CL$102 -> 1.96 | CM111: =CH111*$CM$102 -> 2.1146 | CN111: =CI111*$CN$102 -> 2.304 | CO111: =CJ111*$CO$102 -> 1.22304 | CP111: =BF111-BA111 -> 251.47645 | CQ111: =AQ111-CP111 -> 6638.2892 | CR111: =BC111+BD111 -> 251.47645
A112: =IF(AND('[1]Cockpit Retorno'!$E$67=Sim,Mestre!M112=Mestre!$M$98),0,1) -> 1 | B112: =IF(AND('[1]Cockpit Retorno'!$E$67=Sim,Mestre!L112=Mestre!$L$48),0,1) -> 0 | C112: =IF(AND('[1]Cockpit Retorno'!$E$67=Sim,Mestre!M112=Mestre!$M$97),0,1) -> 1 | D112: MOA_MOD_MOI | F112: Nacional | H112: MOD | I112: =VLOOKUP(K112,$N$74:$O$95,2) -> Serviços | J112: ATK | K112: MOD | L112: ATM | M112: ATK | N112: NA | O112: MOB | P112: NA | Q112: NA | R112: NA | S112: NA | T112: NA | U112: NA | V112: NA | W112: NA | X112: Mobilização | Y112: NA | Z112: NA | AA112: 0 | AB112: NA | AC112: NA | AD112: NA | AF112: NA | AG112: 1 | AH112: 4854.5957 | AI112: 0 | AJ112: 0 | AM112: =(((IF(L112=$L$101,1,IF(L112=$L$47,1,0))*(AH112*(1-AK112)))*AG112)*(1-AL112)) -> 4854.5957 | AN112: =IF(K112=$K$50,AM112,IF(K112=$K$53,AM112,IF(K112=$K$54,AM112,IF(K112=$K$55,AM112,IF(K112=$K$56,AM112,IF(K112=$K$57,AM112,IF(K112=$K$58,AM112,IF(K112=$K$65,AM112,IF(K112=$K$66,AM112,IF(K112=$K$67,AM112,IF(K112=$K$68,AM112,IF(K112=$K$69,AM112,IF(K112=$K$51,AM112,(AM112*(1+AI112))))))))))))))) -> 4854.5957 | AO112: 1.9 | AP112: =AM112*AO112 -> 9223.7319 | AQ112: =AP112*Fator_Venda -> 7992.0437 | AR112: =AO112*AN112 -> 9223.7319 | AS112: =IFERROR(IF($AX$94=0,(CQ112/AN112),CQ112/AM112),0) -> 1.5861947 | AT112: =K112 -> MOD | AU112: =I112 -> Serviços | AW112: =IF(K112=$K$50,0,IF(K112=$K$53,0,IF(K112=$K$54,0,IF(K112=$K$55,0,IF(K112=$K$56,0,IF(K112=$K$57,0,IF(K112=$K$58,0,IF(K112=$K$65,0,IF(K112=$K$66,0,IF(K112=$K$67,0,IF(K112=$K$68,0,IF(K112=$K$69,0,IF(K112=$K$51,0,1))))))))))))*AM112*AI112) -> 0 | AX112: =IF(K112=$K$50,0,IF(K112=$K$53,0,IF(K112=$K$54,0,IF(K112=$K$55,0,IF(K112=$K$56,0,IF(K112=$K$57,0,IF(K112=$K$58,0,IF(K112=$K$65,0,IF(K112=$K$66,0,IF(K112=$K$67,0,IF(K112=$K$68,0,IF(K112=$K$69,0,IF(K112=$K$51,0,1))))))))))))*AM112*AJ112*$AX$94) -> 0 | AY112: =IF(K112=$K$53,0,IF(K112=$K$54,0,IF(K112=$K$55,0,IF(K112=$K$56,0,IF(K112=$K$58,0,IF(K112=$K$50,0,IF(K112=$K$65,0,IF(K112=$K$57,0,IF(K112=$K$51,0,AM112*$AY$102))))))))) -> 0 | AZ112: =IF(K112=$K$53,0,IF(K112=$K$54,0,IF(K112=$K$55,0,IF(K112=$K$56,0,IF(K112=$K$58,0,IF(K112=$K$50,0,IF(K112=$K$65,0,IF(K112=$K$57,0,IF(K112=$K$51,0,AM112*$AZ$102))))))))) -> 0 | BA112: =AZ112+AY112+AX112 -> 0 | BB112: =IF($BA$97=1,AQ112*$BB$102,IF(K112=$K$50,0,IF(K112=$K$53,0,IF(K112=$K$54,0,IF(K112=$K$55,0,IF(K112=$K$56,0,IF(K112=$K$57,0,IF(K112=$K$58,0,IF(K112=$K$65,0,IF(K112=$K$66,0,IF(K112=$K$67,0,IF(K112=$K$68,0,IF(K112=$K$69,0,IF(K112=$K$51,0,1)))))))))))*AQ112*$BB$102))) -> 0 | BC112: =AQ112*$BC$102 -> 51.948284 | BD112: =$BD$102*AQ112 -> 239.76131 | BE112: =IF($BE$95=I112,$BE$97,IF(I112=$BE$96,$BE$97,1))*($BE$102*AQ112)*$AZ$97 -> 0 | BF112: =IF('[1]Cockpit Retorno'!$C$65=Sim,Mestre!BA112,SUM(BB112:BE112)+(IF(K112=$K$56,AQ112*MOE_IRRF_LR,0))) -> 291.7096 | BG112: =IF(AA112>0,0,IF(Z112=$Z$82,AG112*1,(IF(Z112=$Z$81,AG112*1,0)))) -> 0 | BH112: =IF(AA112>0,0,IF(Z112=$Z$83,AG112*1,IF(Z112=$Z$81,AG112*1,0))) -> 0 | BI112: =IF(AA112>0,0,IF(Z112=$Z$84,AG112*1,IF(Z112=$Z$93,AG112*2,IF(Z112=$Z$100,AG112,IF(Z112=$Z$81,AG112*2,IF(Z112=$Z$80,AG112*1,IF(Z112=$Z$79,AG112*3,IF(Z112=$Z$78,AG112*2,0)))))))) -> 0 | BJ112: =IF(AA112>0,0,IF(Z112=$Z$85,AG112,IF(Z112=$Z$93,AG112,IF(Z112=$Z$100,AG112,IF(Z112=$Z$81,AG112*1,IF(Z112=$Z$80,AG112*2,IF(Z112=$Z$79,AG112*2,IF(Z112=$Z$78,AG112*2,0)))))))) -> 0 | BK112: =IF(AA112>0,0,IF(Z112=$Z$92,AG112,0)) -> 0 | BL112: =IF(AA112>0,0,IF(Z112=$Z$91,AG112,0)) -> 0 | BM112: =IF(AA112>0,0,IF(Z112=$Z$86,AG112,0)) -> 0 | BN112: =IF(AA112>0,0,IF(Z112=$Z$87,AG112,0)) -> 0 | BO112: =IF(AA112>0,0,IF(Z112=$Z$88,AG112,0)) -> 0 | BP112: =IF(AA112>0,0,IF(Z112=$Z$89,AG112,0)) -> 0 | BQ112: =IF(AA112>0,0,IF(Z112=$Z$90,AG112,0)) -> 0 | BR112: =IF(Z112=$Z$82,AA112*AG112,0) -> 0 | BS112: =IF(Z112=$Z$83,AA112*AG112,0) -> 0 | BT112: =IF(AA112<1,0,IF(Z112=$Z$84,AA112*AG112,IF(Z112=$Z$93,"ERRO",IF(Z112=$Z$100,"ERRO",0)))) -> 0 | BU112: =IF(AA112<1,0,IF(Z112=$Z$85,AA112*AG112,IF(Z112=$Z$93,"ERRO",IF(Z112=$Z$100,"ERRO",0)))) -> 0 | BV112: =IF(Z112=$Z$92,AA112*AG112,0) -> 0 | BW112: =IF(Z112=$Z$91,AA112*AG112,0) -> 0 | BX112: =IF(Z112=$Z$86,AA112*AG112,0) -> 0 | BY112: =IF(Z112=$Z$87,AA112*AG112,0) -> 0 | BZ112: =IF(Z112=$Z$88,AA112*AG112,0) -> 0 | CA112: =IF(Z112=$Z$89,AA112*AG112,0) -> 0 | CB112: =IF(Z112=$Z$90,AA112*AG112,0) -> 0 | CC112: =IFERROR(IF(L112=$L$49,AG112*AH112*(1+AI112)*(1-AK112)*(1-AL112),0),0) -> 0 | CD112: =IF(I112=$CD$97,1,IF(I112=$CD$100,2,IF(K112=$K$66,1,IF(K112=$K$69,1,3)))) -> 3 | CE112: =IF($CD112=1,1.07,IF($CD112=2,1.07,1.3)) -> 1.3 | CF112: =CG112*0.87 -> 1.74 | CG112: =IF($CD112=1,1.42,IF($CD112=2,1.47,2)) -> 2 | CH112: =CG112*1.09 -> 2.18 | CI112: =IF($CD112=1,1.7,IF($CD112=2,1.7,2.4)) -> 2.4 | CJ112: =CE112*$CJ$102-0.05 -> 1.224 | CK112: =CF112*$CK$102-0.05 -> 1.5682 | CL112: =CG112*$CL$102-0.05 -> 1.91 | CM112: =CH112*$CM$102-0.05 -> 2.0646 | CN112: =CI112*$CN$102-0.05 -> 2.254 | CO112: 1.3 | CP112: =BF112-BA112 -> 291.7096 | CQ112: =AQ112-CP112 -> 7700.3341 | CR112: =BC112+BD112 -> 291.7096
A113: =IF(AND('[1]Cockpit Retorno'!$E$67=Sim,Mestre!M113=Mestre!$M$98),0,1) -> 1 | B113: =IF(AND('[1]Cockpit Retorno'!$E$67=Sim,Mestre!L113=Mestre!$L$48),0,1) -> 0 | C113: =IF(AND('[1]Cockpit Retorno'!$E$67=Sim,Mestre!M113=Mestre!$M$97),0,1) -> 1 | D113: MOA_MOD_MOI | F113: Nacional | H113: MOD | I113: =VLOOKUP(K113,$N$74:$O$95,2) -> Serviços | J113: ATK | K113: MOD | L113: ATM | M113: ATK | N113: NA | O113: M.O. | P113: NA | Q113: NA | R113: NA | S113: NA | T113: NA | U113: NA | V113: NA | W113: NA | X113: Periculosidade | Y113: NA | Z113: NA | AA113: 0 | AB113: NA | AC113: NA | AD113: NA | AF113: NA | AG113: 1 | AH113: 30311.455 | AI113: 0 | AJ113: 0 | AM113: =(((IF(L113=$L$101,1,IF(L113=$L$47,1,0))*(AH113*(1-AK113)))*AG113)*(1-AL113)) -> 30311.455 | AN113: =IF(K113=$K$50,AM113,IF(K113=$K$53,AM113,IF(K113=$K$54,AM113,IF(K113=$K$55,AM113,IF(K113=$K$56,AM113,IF(K113=$K$57,AM113,IF(K113=$K$58,AM113,IF(K113=$K$65,AM113,IF(K113=$K$66,AM113,IF(K113=$K$67,AM113,IF(K113=$K$68,AM113,IF(K113=$K$69,AM113,IF(K113=$K$51,AM113,(AM113*(1+AI113))))))))))))))) -> 30311.455 | AO113: 1.9 | AP113: =AM113*AO113 -> 57591.765 | AQ113: =AP113*Fator_Venda -> 49901.267 | AR113: =AO113*AN113 -> 57591.765 | AS113: =IFERROR(IF($AX$94=0,(CQ113/AN113),CQ113/AM113),0) -> 1.5861947 | AT113: =K113 -> MOD | AU113: =I113 -> Serviços | AW113: =IF(K113=$K$50,0,IF(K113=$K$53,0,IF(K113=$K$54,0,IF(K113=$K$55,0,IF(K113=$K$56,0,IF(K113=$K$57,0,IF(K113=$K$58,0,IF(K113=$K$65,0,IF(K113=$K$66,0,IF(K113=$K$67,0,IF(K113=$K$68,0,IF(K113=$K$69,0,IF(K113=$K$51,0,1))))))))))))*AM113*AI113) -> 0 | AX113: =IF(K113=$K$50,0,IF(K113=$K$53,0,IF(K113=$K$54,0,IF(K113=$K$55,0,IF(K113=$K$56,0,IF(K113=$K$57,0,IF(K113=$K$58,0,IF(K113=$K$65,0,IF(K113=$K$66,0,IF(K113=$K$67,0,IF(K113=$K$68,0,IF(K113=$K$69,0,IF(K113=$K$51,0,1))))))))))))*AM113*AJ113*$AX$94) -> 0 | AY113: =IF(K113=$K$53,0,IF(K113=$K$54,0,IF(K113=$K$55,0,IF(K113=$K$56,0,IF(K113=$K$58,0,IF(K113=$K$50,0,IF(K113=$K$65,0,IF(K113=$K$57,0,IF(K113=$K$51,0,AM113*$AY$102))))))))) -> 0 | AZ113: =IF(K113=$K$53,0,IF(K113=$K$54,0,IF(K113=$K$55,0,IF(K113=$K$56,0,IF(K113=$K$58,0,IF(K113=$K$50,0,IF(K113=$K$65,0,IF(K113=$K$57,0,IF(K113=$K$51,0,AM113*$AZ$102))))))))) -> 0 | BA113: =AZ113+AY113+AX113 -> 0 | BB113: =IF($BA$97=1,AQ113*$BB$102,IF(K113=$K$50,0,IF(K113=$K$53,0,IF(K113=$K$54,0,IF(K113=$K$55,0,IF(K113=$K$56,0,IF(K113=$K$57,0,IF(K113=$K$58,0,IF(K113=$K$65,0,IF(K113=$K$66,0,IF(K113=$K$67,0,IF(K113=$K$68,0,IF(K113=$K$69,0,IF(K113=$K$51,0,1)))))))))))*AQ113*$BB$102))) -> 0 | BC113: =AQ113*$BC$102 -> 324.35824 | BD113: =$BD$102*AQ113 -> 1497.038 | BE113: =IF($BE$95=I113,$BE$97,IF(I113=$BE$96,$BE$97,1))*($BE$102*AQ113)*$AZ$97 -> 0 | BF113: =IF('[1]Cockpit Retorno'!$C$65=Sim,Mestre!BA113,SUM(BB113:BE113)+(IF(K113=$K$56,AQ113*MOE_IRRF_LR,0))) -> 1821.3962 | BG113: =IF(AA113>0,0,IF(Z113=$Z$82,AG113*1,(IF(Z113=$Z$81,AG113*1,0)))) -> 0 | BH113: =IF(AA113>0,0,IF(Z113=$Z$83,AG113*1,IF(Z113=$Z$81,AG113*1,0))) -> 0 | BI113: =IF(AA113>0,0,IF(Z113=$Z$84,AG113*1,IF(Z113=$Z$93,AG113*2,IF(Z113=$Z$100,AG113,IF(Z113=$Z$81,AG113*2,IF(Z113=$Z$80,AG113*1,IF(Z113=$Z$79,AG113*3,IF(Z113=$Z$78,AG113*2,0)))))))) -> 0 | BJ113: =IF(AA113>0,0,IF(Z113=$Z$85,AG113,IF(Z113=$Z$93,AG113,IF(Z113=$Z$100,AG113,IF(Z113=$Z$81,AG113*1,IF(Z113=$Z$80,AG113*2,IF(Z113=$Z$79,AG113*2,IF(Z113=$Z$78,AG113*2,0)))))))) -> 0 | BK113: =IF(AA113>0,0,IF(Z113=$Z$92,AG113,0)) -> 0 | BL113: =IF(AA113>0,0,IF(Z113=$Z$91,AG113,0)) -> 0 | BM113: =IF(AA113>0,0,IF(Z113=$Z$86,AG113,0)) -> 0 | BN113: =IF(AA113>0,0,IF(Z113=$Z$87,AG113,0)) -> 0 | BO113: =IF(AA113>0,0,IF(Z113=$Z$88,AG113,0)) -> 0 | BP113: =IF(AA113>0,0,IF(Z113=$Z$89,AG113,0)) -> 0 | BQ113: =IF(AA113>0,0,IF(Z113=$Z$90,AG113,0)) -> 0 | BR113: =IF(Z113=$Z$82,AA113*AG113,0) -> 0 | BS113: =IF(Z113=$Z$83,AA113*AG113,0) -> 0 | BT113: =IF(AA113<1,0,IF(Z113=$Z$84,AA113*AG113,IF(Z113=$Z$93,"ERRO",IF(Z113=$Z$100,"ERRO",0)))) -> 0 | BU113: =IF(AA113<1,0,IF(Z113=$Z$85,AA113*AG113,IF(Z113=$Z$93,"ERRO",IF(Z113=$Z$100,"ERRO",0)))) -> 0 | BV113: =IF(Z113=$Z$92,AA113*AG113,0) -> 0 | BW113: =IF(Z113=$Z$91,AA113*AG113,0) -> 0 | BX113: =IF(Z113=$Z$86,AA113*AG113,0) -> 0 | BY113: =IF(Z113=$Z$87,AA113*AG113,0) -> 0 | BZ113: =IF(Z113=$Z$88,AA113*AG113,0) -> 0 | CA113: =IF(Z113=$Z$89,AA113*AG113,0) -> 0 | CB113: =IF(Z113=$Z$90,AA113*AG113,0) -> 0 | CC113: =IFERROR(IF(L113=$L$49,AG113*AH113*(1+AI113)*(1-AK113)*(1-AL113),0),0) -> 0 | CD113: =IF(I113=$CD$97,1,IF(I113=$CD$100,2,IF(K113=$K$66,1,IF(K113=$K$69,1,3)))) -> 3 | CE113: =IF($CD113=1,1.07,IF($CD113=2,1.07,1.3)) -> 1.3 | CF113: =CG113*0.87 -> 1.74 | CG113: =IF($CD113=1,1.42,IF($CD113=2,1.47,2)) -> 2 | CH113: =CG113*1.09 -> 2.18 | CI113: =IF($CD113=1,1.7,IF($CD113=2,1.7,2.4)) -> 2.4 | CJ113: =CE113*$CJ$102-0.05 -> 1.224 | CK113: =CF113*$CK$102-0.05 -> 1.5682 | CL113: =CG113*$CL$102-0.05 -> 1.91 | CM113: =CH113*$CM$102-0.05 -> 2.0646 | CN113: =CI113*$CN$102-0.05 -> 2.254 | CO113: 1.3 | CP113: =BF113-BA113 -> 1821.3962 | CQ113: =AQ113-CP113 -> 48079.871 | CR113: =BC113+BD113 -> 1821.3962
A114: =IF(AND('[1]Cockpit Retorno'!$E$67=Sim,Mestre!M114=Mestre!$M$98),0,1) -> 1 | B114: =IF(AND('[1]Cockpit Retorno'!$E$67=Sim,Mestre!L114=Mestre!$L$48),0,1) -> 0 | C114: =IF(AND('[1]Cockpit Retorno'!$E$67=Sim,Mestre!M114=Mestre!$M$97),0,1) -> 1 | D114: MOA_MOD_MOI | F114: Nacional | H114: MOD | I114: =VLOOKUP(K114,$N$74:$O$95,2) -> Serviços | J114: ATK | K114: MOD | L114: ATM | M114: ATK | N114: NA | O114: M.O. | P114: NA | Q114: NA | R114: NA | S114: NA | T114: NA | U114: NA | V114: NA | W114: NA | X114: Turnover | Y114: NA | Z114: NA | AA114: 0 | AB114: NA | AC114: NA | AD114: NA | AF114: NA | AG114: 1 | AH114: 203503.14 | AI114: 0 | AJ114: 0 | AM114: =(((IF(L114=$L$101,1,IF(L114=$L$47,1,0))*(AH114*(1-AK114)))*AG114)*(1-AL114)) -> 203503.14 | AN114: =IF(K114=$K$50,AM114,IF(K114=$K$53,AM114,IF(K114=$K$54,AM114,IF(K114=$K$55,AM114,IF(K114=$K$56,AM114,IF(K114=$K$57,AM114,IF(K114=$K$58,AM114,IF(K114=$K$65,AM114,IF(K114=$K$66,AM114,IF(K114=$K$67,AM114,IF(K114=$K$68,AM114,IF(K114=$K$69,AM114,IF(K114=$K$51,AM114,(AM114*(1+AI114))))))))))))))) -> 203503.14 | AO114: 1.9 | AP114: =AM114*AO114 -> 386655.96 | AQ114: =AP114*Fator_Venda -> 335023.98 | AR114: =AO114*AN114 -> 386655.96 | AS114: =IFERROR(IF($AX$94=0,(CQ114/AN114),CQ114/AM114),0) -> 1.5861947 | AT114: =K114 -> MOD | AU114: =I114 -> Serviços | AW114: =IF(K114=$K$50,0,IF(K114=$K$53,0,IF(K114=$K$54,0,IF(K114=$K$55,0,IF(K114=$K$56,0,IF(K114=$K$57,0,IF(K114=$K$58,0,IF(K114=$K$65,0,IF(K114=$K$66,0,IF(K114=$K$67,0,IF(K114=$K$68,0,IF(K114=$K$69,0,IF(K114=$K$51,0,1))))))))))))*AM114*AI114) -> 0 | AX114: =IF(K114=$K$50,0,IF(K114=$K$53,0,IF(K114=$K$54,0,IF(K114=$K$55,0,IF(K114=$K$56,0,IF(K114=$K$57,0,IF(K114=$K$58,0,IF(K114=$K$65,0,IF(K114=$K$66,0,IF(K114=$K$67,0,IF(K114=$K$68,0,IF(K114=$K$69,0,IF(K114=$K$51,0,1))))))))))))*AM114*AJ114*$AX$94) -> 0 | AY114: =IF(K114=$K$53,0,IF(K114=$K$54,0,IF(K114=$K$55,0,IF(K114=$K$56,0,IF(K114=$K$58,0,IF(K114=$K$50,0,IF(K114=$K$65,0,IF(K114=$K$57,0,IF(K114=$K$51,0,AM114*$AY$102))))))))) -> 0 | AZ114: =IF(K114=$K$53,0,IF(K114=$K$54,0,IF(K114=$K$55,0,IF(K114=$K$56,0,IF(K114=$K$58,0,IF(K114=$K$50,0,IF(K114=$K$65,0,IF(K114=$K$57,0,IF(K114=$K$51,0,AM114*$AZ$102))))))))) -> 0 | BA114: =AZ114+AY114+AX114 -> 0 | BB114: =IF($BA$97=1,AQ114*$BB$102,IF(K114=$K$50,0,IF(K114=$K$53,0,IF(K114=$K$54,0,IF(K114=$K$55,0,IF(K114=$K$56,0,IF(K114=$K$57,0,IF(K114=$K$58,0,IF(K114=$K$65,0,IF(K114=$K$66,0,IF(K114=$K$67,0,IF(K114=$K$68,0,IF(K114=$K$69,0,IF(K114=$K$51,0,1)))))))))))*AQ114*$BB$102))) -> 0 | BC114: =AQ114*$BC$102 -> 2177.6559 | BD114: =$BD$102*AQ114 -> 10050.719 | BE114: =IF($BE$95=I114,$BE$97,IF(I114=$BE$96,$BE$97,1))*($BE$102*AQ114)*$AZ$97 -> 0 | BF114: =IF('[1]Cockpit Retorno'!$C$65=Sim,Mestre!BA114,SUM(BB114:BE114)+(IF(K114=$K$56,AQ114*MOE_IRRF_LR,0))) -> 12228.375 | BG114: =IF(AA114>0,0,IF(Z114=$Z$82,AG114*1,(IF(Z114=$Z$81,AG114*1,0)))) -> 0 | BH114: =IF(AA114>0,0,IF(Z114=$Z$83,AG114*1,IF(Z114=$Z$81,AG114*1,0))) -> 0 | BI114: =IF(AA114>0,0,IF(Z114=$Z$84,AG114*1,IF(Z114=$Z$93,AG114*2,IF(Z114=$Z$100,AG114,IF(Z114=$Z$81,AG114*2,IF(Z114=$Z$80,AG114*1,IF(Z114=$Z$79,AG114*3,IF(Z114=$Z$78,AG114*2,0)))))))) -> 0 | BJ114: =IF(AA114>0,0,IF(Z114=$Z$85,AG114,IF(Z114=$Z$93,AG114,IF(Z114=$Z$100,AG114,IF(Z114=$Z$81,AG114*1,IF(Z114=$Z$80,AG114*2,IF(Z114=$Z$79,AG114*2,IF(Z114=$Z$78,AG114*2,0)))))))) -> 0 | BK114: =IF(AA114>0,0,IF(Z114=$Z$92,AG114,0)) -> 0 | BL114: =IF(AA114>0,0,IF(Z114=$Z$91,AG114,0)) -> 0 | BM114: =IF(AA114>0,0,IF(Z114=$Z$86,AG114,0)) -> 0 | BN114: =IF(AA114>0,0,IF(Z114=$Z$87,AG114,0)) -> 0 | BO114: =IF(AA114>0,0,IF(Z114=$Z$88,AG114,0)) -> 0 | BP114: =IF(AA114>0,0,IF(Z114=$Z$89,AG114,0)) -> 0 | BQ114: =IF(AA114>0,0,IF(Z114=$Z$90,AG114,0)) -> 0 | BR114: =IF(Z114=$Z$82,AA114*AG114,0) -> 0 | BS114: =IF(Z114=$Z$83,AA114*AG114,0) -> 0 | BT114: =IF(AA114<1,0,IF(Z114=$Z$84,AA114*AG114,IF(Z114=$Z$93,"ERRO",IF(Z114=$Z$100,"ERRO",0)))) -> 0 | BU114: =IF(AA114<1,0,IF(Z114=$Z$85,AA114*AG114,IF(Z114=$Z$93,"ERRO",IF(Z114=$Z$100,"ERRO",0)))) -> 0 | BV114: =IF(Z114=$Z$92,AA114*AG114,0) -> 0 | BW114: =IF(Z114=$Z$91,AA114*AG114,0) -> 0 | BX114: =IF(Z114=$Z$86,AA114*AG114,0) -> 0 | BY114: =IF(Z114=$Z$87,AA114*AG114,0) -> 0 | BZ114: =IF(Z114=$Z$88,AA114*AG114,0) -> 0 | CA114: =IF(Z114=$Z$89,AA114*AG114,0) -> 0 | CB114: =IF(Z114=$Z$90,AA114*AG114,0) -> 0 | CC114: =IFERROR(IF(L114=$L$49,AG114*AH114*(1+AI114)*(1-AK114)*(1-AL114),0),0) -> 0 | CD114: =IF(I114=$CD$97,1,IF(I114=$CD$100,2,IF(K114=$K$66,1,IF(K114=$K$69,1,3)))) -> 3 | CE114: =IF($CD114=1,1.07,IF($CD114=2,1.07,1.3)) -> 1.3 | CF114: =CG114*0.87 -> 1.74 | CG114: =IF($CD114=1,1.42,IF($CD114=2,1.47,2)) -> 2 | CH114: =CG114*1.09 -> 2.18 | CI114: =IF($CD114=1,1.7,IF($CD114=2,1.7,2.4)) -> 2.4 | CJ114: =CE114*$CJ$102-0.05 -> 1.224 | CK114: =CF114*$CK$102-0.05 -> 1.5682 | CL114: =CG114*$CL$102-0.05 -> 1.91 | CM114: =CH114*$CM$102-0.05 -> 2.0646 | CN114: =CI114*$CN$102-0.05 -> 2.254 | CO114: 1.3 | CP114: =BF114-BA114 -> 12228.375 | CQ114: =AQ114-CP114 -> 322795.6 | CR114: =BC114+BD114 -> 12228.375
A115: =IF(AND('[1]Cockpit Retorno'!$E$67=Sim,Mestre!M115=Mestre!$M$98),0,1) -> 1 | B115: =IF(AND('[1]Cockpit Retorno'!$E$67=Sim,Mestre!L115=Mestre!$L$48),0,1) -> 0 | C115: =IF(AND('[1]Cockpit Retorno'!$E$67=Sim,Mestre!M115=Mestre!$M$97),0,1) -> 1 | D115: LOG_LOGM_TRS | F115: Nacional | H115: LOG MON | I115: =VLOOKUP(K115,$N$74:$O$95,2) -> Despesas | J115: ATK | K115: LOG_M | L115: ATM | M115: ATK | N115: NA | O115: M.O. | P115: NA | Q115: NA | R115: NA | S115: NA | T115: NA | U115: NA | V115: NA | W115: NA | X115: Logistica Campo | Y115: NA | Z115: NA | AA115: 0 | AB115: NA | AC115: NA | AD115: NA | AF115: NA | AG115: 1 | AH115: 1320907.2 | AI115: 0 | AJ115: 0 | AM115: =(((IF(L115=$L$101,1,IF(L115=$L$47,1,0))*(AH115*(1-AK115)))*AG115)*(1-AL115)) -> 1320907.2 | AN115: =IF(K115=$K$50,AM115,IF(K115=$K$53,AM115,IF(K115=$K$54,AM115,IF(K115=$K$55,AM115,IF(K115=$K$56,AM115,IF(K115=$K$57,AM115,IF(K115=$K$58,AM115,IF(K115=$K$65,AM115,IF(K115=$K$66,AM115,IF(K115=$K$67,AM115,IF(K115=$K$68,AM115,IF(K115=$K$69,AM115,IF(K115=$K$51,AM115,(AM115*(1+AI115))))))))))))))) -> 1320907.2 | AO115: 1.6 | AP115: =AM115*AO115 -> 2113451.6 | AQ115: =AP115*Fator_Venda -> 1831232.5 | AR115: =AO115*AN115 -> 2113451.6 | AS115: =IFERROR(IF($AX$94=0,(CQ115/AN115),CQ115/AM115),0) -> 1.3357429 | AT115: =K115 -> LOG_M | AU115: =I115 -> Despesas | AW115: =IF(K115=$K$50,0,IF(K115=$K$53,0,IF(K115=$K$54,0,IF(K115=$K$55,0,IF(K115=$K$56,0,IF(K115=$K$57,0,IF(K115=$K$58,0,IF(K115=$K$65,0,IF(K115=$K$66,0,IF(K115=$K$67,0,IF(K115=$K$68,0,IF(K115=$K$69,0,IF(K115=$K$51,0,1))))))))))))*AM115*AI115) -> 0 | AX115: =IF(K115=$K$50,0,IF(K115=$K$53,0,IF(K115=$K$54,0,IF(K115=$K$55,0,IF(K115=$K$56,0,IF(K115=$K$57,0,IF(K115=$K$58,0,IF(K115=$K$65,0,IF(K115=$K$66,0,IF(K115=$K$67,0,IF(K115=$K$68,0,IF(K115=$K$69,0,IF(K115=$K$51,0,1))))))))))))*AM115*AJ115*$AX$94) -> 0 | AY115: =IF(K115=$K$53,0,IF(K115=$K$54,0,IF(K115=$K$55,0,IF(K115=$K$56,0,IF(K115=$K$58,0,IF(K115=$K$50,0,IF(K115=$K$65,0,IF(K115=$K$57,0,IF(K115=$K$51,0,AM115*$AY$102))))))))) -> 0 | AZ115: =IF(K115=$K$53,0,IF(K115=$K$54,0,IF(K115=$K$55,0,IF(K115=$K$56,0,IF(K115=$K$58,0,IF(K115=$K$50,0,IF(K115=$K$65,0,IF(K115=$K$57,0,IF(K115=$K$51,0,AM115*$AZ$102))))))))) -> 0 | BA115: =AZ115+AY115+AX115 -> 0 | BB115: =IF($BA$97=1,AQ115*$BB$102,IF(K115=$K$50,0,IF(K115=$K$53,0,IF(K115=$K$54,0,IF(K115=$K$55,0,IF(K115=$K$56,0,IF(K115=$K$57,0,IF(K115=$K$58,0,IF(K115=$K$65,0,IF(K115=$K$66,0,IF(K115=$K$67,0,IF(K115=$K$68,0,IF(K115=$K$69,0,IF(K115=$K$51,0,1)))))))))))*AQ115*$BB$102))) -> 0 | BC115: =AQ115*$BC$102 -> 11903.011 | BD115: =$BD$102*AQ115 -> 54936.975 | BE115: =IF($BE$95=I115,$BE$97,IF(I115=$BE$96,$BE$97,1))*($BE$102*AQ115)*$AZ$97 -> 0 | BF115: =IF('[1]Cockpit Retorno'!$C$65=Sim,Mestre!BA115,SUM(BB115:BE115)+(IF(K115=$K$56,AQ115*MOE_IRRF_LR,0))) -> 66839.986 | BG115: =IF(AA115>0,0,IF(Z115=$Z$82,AG115*1,(IF(Z115=$Z$81,AG115*1,0)))) -> 0 | BH115: =IF(AA115>0,0,IF(Z115=$Z$83,AG115*1,IF(Z115=$Z$81,AG115*1,0))) -> 0 | BI115: =IF(AA115>0,0,IF(Z115=$Z$84,AG115*1,IF(Z115=$Z$93,AG115*2,IF(Z115=$Z$100,AG115,IF(Z115=$Z$81,AG115*2,IF(Z115=$Z$80,AG115*1,IF(Z115=$Z$79,AG115*3,IF(Z115=$Z$78,AG115*2,0)))))))) -> 0 | BJ115: =IF(AA115>0,0,IF(Z115=$Z$85,AG115,IF(Z115=$Z$93,AG115,IF(Z115=$Z$100,AG115,IF(Z115=$Z$81,AG115*1,IF(Z115=$Z$80,AG115*2,IF(Z115=$Z$79,AG115*2,IF(Z115=$Z$78,AG115*2,0)))))))) -> 0 | BK115: =IF(AA115>0,0,IF(Z115=$Z$92,AG115,0)) -> 0 | BL115: =IF(AA115>0,0,IF(Z115=$Z$91,AG115,0)) -> 0 | BM115: =IF(AA115>0,0,IF(Z115=$Z$86,AG115,0)) -> 0 | BN115: =IF(AA115>0,0,IF(Z115=$Z$87,AG115,0)) -> 0 | BO115: =IF(AA115>0,0,IF(Z115=$Z$88,AG115,0)) -> 0 | BP115: =IF(AA115>0,0,IF(Z115=$Z$89,AG115,0)) -> 0 | BQ115: =IF(AA115>0,0,IF(Z115=$Z$90,AG115,0)) -> 0 | BR115: =IF(Z115=$Z$82,AA115*AG115,0) -> 0 | BS115: =IF(Z115=$Z$83,AA115*AG115,0) -> 0 | BT115: =IF(AA115<1,0,IF(Z115=$Z$84,AA115*AG115,IF(Z115=$Z$93,"ERRO",IF(Z115=$Z$100,"ERRO",0)))) -> 0 | BU115: =IF(AA115<1,0,IF(Z115=$Z$85,AA115*AG115,IF(Z115=$Z$93,"ERRO",IF(Z115=$Z$100,"ERRO",0)))) -> 0 | BV115: =IF(Z115=$Z$92,AA115*AG115,0) -> 0 | BW115: =IF(Z115=$Z$91,AA115*AG115,0) -> 0 | BX115: =IF(Z115=$Z$86,AA115*AG115,0) -> 0 | BY115: =IF(Z115=$Z$87,AA115*AG115,0) -> 0 | BZ115: =IF(Z115=$Z$88,AA115*AG115,0) -> 0 | CA115: =IF(Z115=$Z$89,AA115*AG115,0) -> 0 | CB115: =IF(Z115=$Z$90,AA115*AG115,0) -> 0 | CC115: =IFERROR(IF(L115=$L$49,AG115*AH115*(1+AI115)*(1-AK115)*(1-AL115),0),0) -> 0 | CD115: =IF(I115=$CD$97,1,IF(I115=$CD$100,2,IF(K115=$K$66,1,IF(K115=$K$69,1,3)))) -> 2 | CE115: =IF($CD115=1,1.07,IF($CD115=2,1.07,1.3)) -> 1.07 | CF115: =CG115*0.87 -> 1.2789 | CG115: =IF($CD115=1,1.42,IF($CD115=2,1.47,2)) -> 1.47 | CH115: =CG115*1.09 -> 1.6023 | CI115: =IF($CD115=1,1.7,IF($CD115=2,1.7,2.4)) -> 1.7 | CJ115: =CE115*$CJ$102 -> 1.0486 | CK115: =CF115*$CK$102 -> 1.189377 | CL115: =CG115*$CL$102 -> 1.4406 | CM115: =CH115*$CM$102 -> 1.554231 | CN115: =CI115*$CN$102 -> 1.632 | CO115: 1.3 | CP115: =BF115-BA115 -> 66839.986 | CQ115: =AQ115-CP115 -> 1764392.5 | CR115: =BC115+BD115 -> 66839.986
A116: =IF(AND('[1]Cockpit Retorno'!$E$67=Sim,Mestre!M116=Mestre!$M$98),0,1) -> 1 | B116: =IF(AND('[1]Cockpit Retorno'!$E$67=Sim,Mestre!L116=Mestre!$L$48),0,1) -> 0 | C116: =IF(AND('[1]Cockpit Retorno'!$E$67=Sim,Mestre!M116=Mestre!$M$97),0,1) -> 1 | D116: LOG_LOGM_TRS | F116: Nacional | H116: LOG MON | I116: =VLOOKUP(K116,$N$74:$O$95,2) -> Despesas | J116: ATK | K116: LOG_M | L116: ATM | M116: ATK | N116: NA | O116: M.O. | P116: NA | Q116: NA | R116: NA | S116: NA | T116: NA | U116: NA | V116: NA | W116: NA | X116: Logistica Integração | Y116: NA | Z116: NA | AA116: 0 | AB116: NA | AC116: NA | AD116: NA | AF116: NA | AG116: 1 | AH116: 49684.939 | AI116: 0 | AJ116: 0 | AM116: =(((IF(L116=$L$101,1,IF(L116=$L$47,1,0))*(AH116*(1-AK116)))*AG116)*(1-AL116)) -> 49684.939 | AN116: =IF(K116=$K$50,AM116,IF(K116=$K$53,AM116,IF(K116=$K$54,AM116,IF(K116=$K$55,AM116,IF(K116=$K$56,AM116,IF(K116=$K$57,AM116,IF(K116=$K$58,AM116,IF(K116=$K$65,AM116,IF(K116=$K$66,AM116,IF(K116=$K$67,AM116,IF(K116=$K$68,AM116,IF(K116=$K$69,AM116,IF(K116=$K$51,AM116,(AM116*(1+AI116))))))))))))))) -> 49684.939 | AO116: 1.6 | AP116: =AM116*AO116 -> 79495.903 | AQ116: =AP116*Fator_Venda -> 68880.443 | AR116: =AO116*AN116 -> 79495.903 | AS116: =IFERROR(IF($AX$94=0,(CQ116/AN116),CQ116/AM116),0) -> 1.3357429 | AT116: =K116 -> LOG_M | AU116: =I116 -> Despesas | AW116: =IF(K116=$K$50,0,IF(K116=$K$53,0,IF(K116=$K$54,0,IF(K116=$K$55,0,IF(K116=$K$56,0,IF(K116=$K$57,0,IF(K116=$K$58,0,IF(K116=$K$65,0,IF(K116=$K$66,0,IF(K116=$K$67,0,IF(K116=$K$68,0,IF(K116=$K$69,0,IF(K116=$K$51,0,1))))))))))))*AM116*AI116) -> 0 | AX116: =IF(K116=$K$50,0,IF(K116=$K$53,0,IF(K116=$K$54,0,IF(K116=$K$55,0,IF(K116=$K$56,0,IF(K116=$K$57,0,IF(K116=$K$58,0,IF(K116=$K$65,0,IF(K116=$K$66,0,IF(K116=$K$67,0,IF(K116=$K$68,0,IF(K116=$K$69,0,IF(K116=$K$51,0,1))))))))))))*AM116*AJ116*$AX$94) -> 0 | AY116: =IF(K116=$K$53,0,IF(K116=$K$54,0,IF(K116=$K$55,0,IF(K116=$K$56,0,IF(K116=$K$58,0,IF(K116=$K$50,0,IF(K116=$K$65,0,IF(K116=$K$57,0,IF(K116=$K$51,0,AM116*$AY$102))))))))) -> 0 | AZ116: =IF(K116=$K$53,0,IF(K116=$K$54,0,IF(K116=$K$55,0,IF(K116=$K$56,0,IF(K116=$K$58,0,IF(K116=$K$50,0,IF(K116=$K$65,0,IF(K116=$K$57,0,IF(K116=$K$51,0,AM116*$AZ$102))))))))) -> 0 | BA116: =AZ116+AY116+AX116 -> 0 | BB116: =IF($BA$97=1,AQ116*$BB$102,IF(K116=$K$50,0,IF(K116=$K$53,0,IF(K116=$K$54,0,IF(K116=$K$55,0,IF(K116=$K$56,0,IF(K116=$K$57,0,IF(K116=$K$58,0,IF(K116=$K$65,0,IF(K116=$K$66,0,IF(K116=$K$67,0,IF(K116=$K$68,0,IF(K116=$K$69,0,IF(K116=$K$51,0,1)))))))))))*AQ116*$BB$102))) -> 0 | BC116: =AQ116*$BC$102 -> 447.72288 | BD116: =$BD$102*AQ116 -> 2066.4133 | BE116: =IF($BE$95=I116,$BE$97,IF(I116=$BE$96,$BE$97,1))*($BE$102*AQ116)*$AZ$97 -> 0 | BF116: =IF('[1]Cockpit Retorno'!$C$65=Sim,Mestre!BA116,SUM(BB116:BE116)+(IF(K116=$K$56,AQ116*MOE_IRRF_LR,0))) -> 2514.1362 | BG116: =IF(AA116>0,0,IF(Z116=$Z$82,AG116*1,(IF(Z116=$Z$81,AG116*1,0)))) -> 0 | BH116: =IF(AA116>0,0,IF(Z116=$Z$83,AG116*1,IF(Z116=$Z$81,AG116*1,0))) -> 0 | BI116: =IF(AA116>0,0,IF(Z116=$Z$84,AG116*1,IF(Z116=$Z$93,AG116*2,IF(Z116=$Z$100,AG116,IF(Z116=$Z$81,AG116*2,IF(Z116=$Z$80,AG116*1,IF(Z116=$Z$79,AG116*3,IF(Z116=$Z$78,AG116*2,0)))))))) -> 0 | BJ116: =IF(AA116>0,0,IF(Z116=$Z$85,AG116,IF(Z116=$Z$93,AG116,IF(Z116=$Z$100,AG116,IF(Z116=$Z$81,AG116*1,IF(Z116=$Z$80,AG116*2,IF(Z116=$Z$79,AG116*2,IF(Z116=$Z$78,AG116*2,0)))))))) -> 0 | BK116: =IF(AA116>0,0,IF(Z116=$Z$92,AG116,0)) -> 0 | BL116: =IF(AA116>0,0,IF(Z116=$Z$91,AG116,0)) -> 0 | BM116: =IF(AA116>0,0,IF(Z116=$Z$86,AG116,0)) -> 0 | BN116: =IF(AA116>0,0,IF(Z116=$Z$87,AG116,0)) -> 0 | BO116: =IF(AA116>0,0,IF(Z116=$Z$88,AG116,0)) -> 0 | BP116: =IF(AA116>0,0,IF(Z116=$Z$89,AG116,0)) -> 0 | BQ116: =IF(AA116>0,0,IF(Z116=$Z$90,AG116,0)) -> 0 | BR116: =IF(Z116=$Z$82,AA116*AG116,0) -> 0 | BS116: =IF(Z116=$Z$83,AA116*AG116,0) -> 0 | BT116: =IF(AA116<1,0,IF(Z116=$Z$84,AA116*AG116,IF(Z116=$Z$93,"ERRO",IF(Z116=$Z$100,"ERRO",0)))) -> 0 | BU116: =IF(AA116<1,0,IF(Z116=$Z$85,AA116*AG116,IF(Z116=$Z$93,"ERRO",IF(Z116=$Z$100,"ERRO",0)))) -> 0 | BV116: =IF(Z116=$Z$92,AA116*AG116,0) -> 0 | BW116: =IF(Z116=$Z$91,AA116*AG116,0) -> 0 | BX116: =IF(Z116=$Z$86,AA116*AG116,0) -> 0 | BY116: =IF(Z116=$Z$87,AA116*AG116,0) -> 0 | BZ116: =IF(Z116=$Z$88,AA116*AG116,0) -> 0 | CA116: =IF(Z116=$Z$89,AA116*AG116,0) -> 0 | CB116: =IF(Z116=$Z$90,AA116*AG116,0) -> 0 | CC116: =IFERROR(IF(L116=$L$49,AG116*AH116*(1+AI116)*(1-AK116)*(1-AL116),0),0) -> 0 | CD116: =IF(I116=$CD$97,1,IF(I116=$CD$100,2,IF(K116=$K$66,1,IF(K116=$K$69,1,3)))) -> 2 | CE116: =IF($CD116=1,1.07,IF($CD116=2,1.07,1.3)) -> 1.07 | CF116: =CG116*0.87 -> 1.2789 | CG116: =IF($CD116=1,1.42,IF($CD116=2,1.47,2)) -> 1.47 | CH116: =CG116*1.09 -> 1.6023 | CI116: =IF($CD116=1,1.7,IF($CD116=2,1.7,2.4)) -> 1.7 | CJ116: =CE116*$CJ$102 -> 1.0486 | CK116: =CF116*$CK$102 -> 1.189377 | CL116: =CG116*$CL$102 -> 1.4406 | CM116: =CH116*$CM$102 -> 1.554231 | CN116: =CI116*$CN$102 -> 1.632 | CO116: 1.3 | CP116: =BF116-BA116 -> 2514.1362 | CQ116: =AQ116-CP116 -> 66366.306 | CR116: =BC116+BD116 -> 2514.1362
A117: =IF(AND('[1]Cockpit Retorno'!$E$67=Sim,Mestre!M117=Mestre!$M$98),0,1) -> 1 | B117: =IF(AND('[1]Cockpit Retorno'!$E$67=Sim,Mestre!L117=Mestre!$L$48),0,1) -> 0 | C117: =IF(AND('[1]Cockpit Retorno'!$E$67=Sim,Mestre!M117=Mestre!$M$97),0,1) -> 1 | D117: LOG_LOGM_TRS | F117: Nacional | H117: LOG MON | I117: =VLOOKUP(K117,$N$74:$O$95,2) -> Despesas | J117: ATK | K117: LOG_M | L117: ATM | M117: ATK | N117: NA | O117: M.O. | P117: NA | Q117: NA | R117: NA | S117: NA | T117: NA | U117: NA | V117: NA | W117: NA | X117: Logistica Mobilização | Y117: NA | Z117: NA | AA117: 0 | AB117: NA | AC117: NA | AD117: NA | AF117: NA | AG117: 1 | AH117: 2782.932 | AI117: 0 | AJ117: 0 | AM117: =(((IF(L117=$L$101,1,IF(L117=$L$47,1,0))*(AH117*(1-AK117)))*AG117)*(1-AL117)) -> 2782.932 | AN117: =IF(K117=$K$50,AM117,IF(K117=$K$53,AM117,IF(K117=$K$54,AM117,IF(K117=$K$55,AM117,IF(K117=$K$56,AM117,IF(K117=$K$57,AM117,IF(K117=$K$58,AM117,IF(K117=$K$65,AM117,IF(K117=$K$66,AM117,IF(K117=$K$67,AM117,IF(K117=$K$68,AM117,IF(K117=$K$69,AM117,IF(K117=$K$51,AM117,(AM117*(1+AI117))))))))))))))) -> 2782.932 | AO117: 1.6 | AP117: =AM117*AO117 -> 4452.6911 | AQ117: =AP117*Fator_Venda -> 3858.1024 | AR117: =AO117*AN117 -> 4452.6911 | AS117: =IFERROR(IF($AX$94=0,(CQ117/AN117),CQ117/AM117),0) -> 1.3357429 | AT117: =K117 -> LOG_M | AU117: =I117 -> Despesas | AW117: =IF(K117=$K$50,0,IF(K117=$K$53,0,IF(K117=$K$54,0,IF(K117=$K$55,0,IF(K117=$K$56,0,IF(K117=$K$57,0,IF(K117=$K$58,0,IF(K117=$K$65,0,IF(K117=$K$66,0,IF(K117=$K$67,0,IF(K117=$K$68,0,IF(K117=$K$69,0,IF(K117=$K$51,0,1))))))))))))*AM117*AI117) -> 0 | AX117: =IF(K117=$K$50,0,IF(K117=$K$53,0,IF(K117=$K$54,0,IF(K117=$K$55,0,IF(K117=$K$56,0,IF(K117=$K$57,0,IF(K117=$K$58,0,IF(K117=$K$65,0,IF(K117=$K$66,0,IF(K117=$K$67,0,IF(K117=$K$68,0,IF(K117=$K$69,0,IF(K117=$K$51,0,1))))))))))))*AM117*AJ117*$AX$94) -> 0 | AY117: =IF(K117=$K$53,0,IF(K117=$K$54,0,IF(K117=$K$55,0,IF(K117=$K$56,0,IF(K117=$K$58,0,IF(K117=$K$50,0,IF(K117=$K$65,0,IF(K117=$K$57,0,IF(K117=$K$51,0,AM117*$AY$102))))))))) -> 0 | AZ117: =IF(K117=$K$53,0,IF(K117=$K$54,0,IF(K117=$K$55,0,IF(K117=$K$56,0,IF(K117=$K$58,0,IF(K117=$K$50,0,IF(K117=$K$65,0,IF(K117=$K$57,0,IF(K117=$K$51,0,AM117*$AZ$102))))))))) -> 0 | BA117: =AZ117+AY117+AX117 -> 0 | BB117: =IF($BA$97=1,AQ117*$BB$102,IF(K117=$K$50,0,IF(K117=$K$53,0,IF(K117=$K$54,0,IF(K117=$K$55,0,IF(K117=$K$56,0,IF(K117=$K$57,0,IF(K117=$K$58,0,IF(K117=$K$65,0,IF(K117=$K$66,0,IF(K117=$K$67,0,IF(K117=$K$68,0,IF(K117=$K$69,0,IF(K117=$K$51,0,1)))))))))))*AQ117*$BB$102))) -> 0 | BC117: =AQ117*$BC$102 -> 25.077666 | BD117: =$BD$102*AQ117 -> 115.74307 | BE117: =IF($BE$95=I117,$BE$97,IF(I117=$BE$96,$BE$97,1))*($BE$102*AQ117)*$AZ$97 -> 0 | BF117: =IF('[1]Cockpit Retorno'!$C$65=Sim,Mestre!BA117,SUM(BB117:BE117)+(IF(K117=$K$56,AQ117*MOE_IRRF_LR,0))) -> 140.82074 | BG117: =IF(AA117>0,0,IF(Z117=$Z$82,AG117*1,(IF(Z117=$Z$81,AG117*1,0)))) -> 0 | BH117: =IF(AA117>0,0,IF(Z117=$Z$83,AG117*1,IF(Z117=$Z$81,AG117*1,0))) -> 0 | BI117: =IF(AA117>0,0,IF(Z117=$Z$84,AG117*1,IF(Z117=$Z$93,AG117*2,IF(Z117=$Z$100,AG117,IF(Z117=$Z$81,AG117*2,IF(Z117=$Z$80,AG117*1,IF(Z117=$Z$79,AG117*3,IF(Z117=$Z$78,AG117*2,0)))))))) -> 0 | BJ117: =IF(AA117>0,0,IF(Z117=$Z$85,AG117,IF(Z117=$Z$93,AG117,IF(Z117=$Z$100,AG117,IF(Z117=$Z$81,AG117*1,IF(Z117=$Z$80,AG117*2,IF(Z117=$Z$79,AG117*2,IF(Z117=$Z$78,AG117*2,0)))))))) -> 0 | BK117: =IF(AA117>0,0,IF(Z117=$Z$92,AG117,0)) -> 0 | BL117: =IF(AA117>0,0,IF(Z117=$Z$91,AG117,0)) -> 0 | BM117: =IF(AA117>0,0,IF(Z117=$Z$86,AG117,0)) -> 0 | BN117: =IF(AA117>0,0,IF(Z117=$Z$87,AG117,0)) -> 0 | BO117: =IF(AA117>0,0,IF(Z117=$Z$88,AG117,0)) -> 0 | BP117: =IF(AA117>0,0,IF(Z117=$Z$89,AG117,0)) -> 0 | BQ117: =IF(AA117>0,0,IF(Z117=$Z$90,AG117,0)) -> 0 | BR117: =IF(Z117=$Z$82,AA117*AG117,0) -> 0 | BS117: =IF(Z117=$Z$83,AA117*AG117,0) -> 0 | BT117: =IF(AA117<1,0,IF(Z117=$Z$84,AA117*AG117,IF(Z117=$Z$93,"ERRO",IF(Z117=$Z$100,"ERRO",0)))) -> 0 | BU117: =IF(AA117<1,0,IF(Z117=$Z$85,AA117*AG117,IF(Z117=$Z$93,"ERRO",IF(Z117=$Z$100,"ERRO",0)))) -> 0 | BV117: =IF(Z117=$Z$92,AA117*AG117,0) -> 0 | BW117: =IF(Z117=$Z$91,AA117*AG117,0) -> 0 | BX117: =IF(Z117=$Z$86,AA117*AG117,0) -> 0 | BY117: =IF(Z117=$Z$87,AA117*AG117,0) -> 0 | BZ117: =IF(Z117=$Z$88,AA117*AG117,0) -> 0 | CA117: =IF(Z117=$Z$89,AA117*AG117,0) -> 0 | CB117: =IF(Z117=$Z$90,AA117*AG117,0) -> 0 | CC117: =IFERROR(IF(L117=$L$49,AG117*AH117*(1+AI117)*(1-AK117)*(1-AL117),0),0) -> 0 | CD117: =IF(I117=$CD$97,1,IF(I117=$CD$100,2,IF(K117=$K$66,1,IF(K117=$K$69,1,3)))) -> 2 | CE117: =IF($CD117=1,1.07,IF($CD117=2,1.07,1.3)) -> 1.07 | CF117: =CG117*0.87 -> 1.2789 | CG117: =IF($CD117=1,1.42,IF($CD117=2,1.47,2)) -> 1.47 | CH117: =CG117*1.09 -> 1.6023 | CI117: =IF($CD117=1,1.7,IF($CD117=2,1.7,2.4)) -> 1.7 | CJ117: =CE117*$CJ$102 -> 1.0486 | CK117: =CF117*$CK$102 -> 1.189377 | CL117: =CG117*$CL$102 -> 1.4406 | CM117: =CH117*$CM$102 -> 1.554231 | CN117: =CI117*$CN$102 -> 1.632 | CO117: 1.3 | CP117: =BF117-BA117 -> 140.82074 | CQ117: =AQ117-CP117 -> 3717.2817 | CR117: =BC117+BD117 -> 140.82074
A118: =IF(AND('[1]Cockpit Retorno'!$E$67=Sim,Mestre!M118=Mestre!$M$98),0,1) -> 1 | B118: =IF(AND('[1]Cockpit Retorno'!$E$67=Sim,Mestre!L118=Mestre!$L$48),0,1) -> 0 | C118: =IF(AND('[1]Cockpit Retorno'!$E$67=Sim,Mestre!M118=Mestre!$M$97),0,1) -> 1 | D118: MOB_SSMA | F118: Nacional | H118: MOB | I118: =VLOOKUP(K118,$N$74:$O$95,2) -> Despesas | J118: ATK | K118: MOB | L118: ATM | M118: ATK | N118: NA | O118: MOB | P118: NA | Q118: NA | R118: NA | S118: NA | T118: NA | U118: NA | V118: NA | W118: NA | X118: Mobilização | Y118: NA | Z118: NA | AA118: 0 | AB118: NA | AC118: NA | AD118: NA | AF118: NA | AG118: 1 | AH118: 726454.54 | AI118: 0 | AJ118: 0 | AM118: =(((IF(L118=$L$101,1,IF(L118=$L$47,1,0))*(AH118*(1-AK118)))*AG118)*(1-AL118)) -> 726454.54 | AN118: =IF(K118=$K$50,AM118,IF(K118=$K$53,AM118,IF(K118=$K$54,AM118,IF(K118=$K$55,AM118,IF(K118=$K$56,AM118,IF(K118=$K$57,AM118,IF(K118=$K$58,AM118,IF(K118=$K$65,AM118,IF(K118=$K$66,AM118,IF(K118=$K$67,AM118,IF(K118=$K$68,AM118,IF(K118=$K$69,AM118,IF(K118=$K$51,AM118,(AM118*(1+AI118))))))))))))))) -> 726454.54 | AO118: 1.6 | AP118: =AM118*AO118 -> 1162327.3 | AQ118: =AP118*Fator_Venda -> 1007116.3 | AR118: =AO118*AN118 -> 1162327.3 | AS118: =IFERROR(IF($AX$94=0,(CQ118/AN118),CQ118/AM118),0) -> 1.3357429 | AT118: =K118 -> MOB | AU118: =I118 -> Despesas | AW118: =IF(K118=$K$50,0,IF(K118=$K$53,0,IF(K118=$K$54,0,IF(K118=$K$55,0,IF(K118=$K$56,0,IF(K118=$K$57,0,IF(K118=$K$58,0,IF(K118=$K$65,0,IF(K118=$K$66,0,IF(K118=$K$67,0,IF(K118=$K$68,0,IF(K118=$K$69,0,IF(K118=$K$51,0,1))))))))))))*AM118*AI118) -> 0 | AX118: =IF(K118=$K$50,0,IF(K118=$K$53,0,IF(K118=$K$54,0,IF(K118=$K$55,0,IF(K118=$K$56,0,IF(K118=$K$57,0,IF(K118=$K$58,0,IF(K118=$K$65,0,IF(K118=$K$66,0,IF(K118=$K$67,0,IF(K118=$K$68,0,IF(K118=$K$69,0,IF(K118=$K$51,0,1))))))))))))*AM118*AJ118*$AX$94) -> 0 | AY118: =IF(K118=$K$53,0,IF(K118=$K$54,0,IF(K118=$K$55,0,IF(K118=$K$56,0,IF(K118=$K$58,0,IF(K118=$K$50,0,IF(K118=$K$65,0,IF(K118=$K$57,0,IF(K118=$K$51,0,AM118*$AY$102))))))))) -> 0 | AZ118: =IF(K118=$K$53,0,IF(K118=$K$54,0,IF(K118=$K$55,0,IF(K118=$K$56,0,IF(K118=$K$58,0,IF(K118=$K$50,0,IF(K118=$K$65,0,IF(K118=$K$57,0,IF(K118=$K$51,0,AM118*$AZ$102))))))))) -> 0 | BA118: =AZ118+AY118+AX118 -> 0 | BB118: =IF($BA$97=1,AQ118*$BB$102,IF(K118=$K$50,0,IF(K118=$K$53,0,IF(K118=$K$54,0,IF(K118=$K$55,0,IF(K118=$K$56,0,IF(K118=$K$57,0,IF(K118=$K$58,0,IF(K118=$K$65,0,IF(K118=$K$66,0,IF(K118=$K$67,0,IF(K118=$K$68,0,IF(K118=$K$69,0,IF(K118=$K$51,0,1)))))))))))*AQ118*$BB$102))) -> 0 | BC118: =AQ118*$BC$102 -> 6546.2557 | BD118: =$BD$102*AQ118 -> 30213.488 | BE118: =IF($BE$95=I118,$BE$97,IF(I118=$BE$96,$BE$97,1))*($BE$102*AQ118)*$AZ$97 -> 0 | BF118: =IF('[1]Cockpit Retorno'!$C$65=Sim,Mestre!BA118,SUM(BB118:BE118)+(IF(K118=$K$56,AQ118*MOE_IRRF_LR,0))) -> 36759.743 | BG118: =IF(AA118>0,0,IF(Z118=$Z$82,AG118*1,(IF(Z118=$Z$81,AG118*1,0)))) -> 0 | BH118: =IF(AA118>0,0,IF(Z118=$Z$83,AG118*1,IF(Z118=$Z$81,AG118*1,0))) -> 0 | BI118: =IF(AA118>0,0,IF(Z118=$Z$84,AG118*1,IF(Z118=$Z$93,AG118*2,IF(Z118=$Z$100,AG118,IF(Z118=$Z$81,AG118*2,IF(Z118=$Z$80,AG118*1,IF(Z118=$Z$79,AG118*3,IF(Z118=$Z$78,AG118*2,0)))))))) -> 0 | BJ118: =IF(AA118>0,0,IF(Z118=$Z$85,AG118,IF(Z118=$Z$93,AG118,IF(Z118=$Z$100,AG118,IF(Z118=$Z$81,AG118*1,IF(Z118=$Z$80,AG118*2,IF(Z118=$Z$79,AG118*2,IF(Z118=$Z$78,AG118*2,0)))))))) -> 0 | BK118: =IF(AA118>0,0,IF(Z118=$Z$92,AG118,0)) -> 0 | BL118: =IF(AA118>0,0,IF(Z118=$Z$91,AG118,0)) -> 0 | BM118: =IF(AA118>0,0,IF(Z118=$Z$86,AG118,0)) -> 0 | BN118: =IF(AA118>0,0,IF(Z118=$Z$87,AG118,0)) -> 0 | BO118: =IF(AA118>0,0,IF(Z118=$Z$88,AG118,0)) -> 0 | BP118: =IF(AA118>0,0,IF(Z118=$Z$89,AG118,0)) -> 0 | BQ118: =IF(AA118>0,0,IF(Z118=$Z$90,AG118,0)) -> 0 | BR118: =IF(Z118=$Z$82,AA118*AG118,0) -> 0 | BS118: =IF(Z118=$Z$83,AA118*AG118,0) -> 0 | BT118: =IF(AA118<1,0,IF(Z118=$Z$84,AA118*AG118,IF(Z118=$Z$93,"ERRO",IF(Z118=$Z$100,"ERRO",0)))) -> 0 | BU118: =IF(AA118<1,0,IF(Z118=$Z$85,AA118*AG118,IF(Z118=$Z$93,"ERRO",IF(Z118=$Z$100,"ERRO",0)))) -> 0 | BV118: =IF(Z118=$Z$92,AA118*AG118,0) -> 0 | BW118: =IF(Z118=$Z$91,AA118*AG118,0) -> 0 | BX118: =IF(Z118=$Z$86,AA118*AG118,0) -> 0 | BY118: =IF(Z118=$Z$87,AA118*AG118,0) -> 0 | BZ118: =IF(Z118=$Z$88,AA118*AG118,0) -> 0 | CA118: =IF(Z118=$Z$89,AA118*AG118,0) -> 0 | CB118: =IF(Z118=$Z$90,AA118*AG118,0) -> 0 | CC118: =IFERROR(IF(L118=$L$49,AG118*AH118*(1+AI118)*(1-AK118)*(1-AL118),0),0) -> 0 | CD118: =IF(I118=$CD$97,1,IF(I118=$CD$100,2,IF(K118=$K$66,1,IF(K118=$K$69,1,3)))) -> 2 | CE118: =IF($CD118=1,1.07,IF($CD118=2,1.07,1.3)) -> 1.07 | CF118: =CG118*0.87 -> 1.2789 | CG118: =IF($CD118=1,1.42,IF($CD118=2,1.47,2)) -> 1.47 | CH118: =CG118*1.09 -> 1.6023 | CI118: =IF($CD118=1,1.7,IF($CD118=2,1.7,2.4)) -> 1.7 | CJ118: =CE118*$CJ$102 -> 1.0486 | CK118: =CF118*$CK$102 -> 1.189377 | CL118: =CG118*$CL$102 -> 1.4406 | CM118: =CH118*$CM$102 -> 1.554231 | CN118: =CI118*$CN$102 -> 1.632 | CO118: =CJ118*$CO$102 -> 1.006656 | CP118: =BF118-BA118 -> 36759.743 | CQ118: =AQ118-CP118 -> 970356.52 | CR118: =BC118+BD118 -> 36759.743
A119: =IF(AND('[1]Cockpit Retorno'!$E$67=Sim,Mestre!M119=Mestre!$M$98),0,1) -> 1 | B119: =IF(AND('[1]Cockpit Retorno'!$E$67=Sim,Mestre!L119=Mestre!$L$48),0,1) -> 0 | C119: =IF(AND('[1]Cockpit Retorno'!$E$67=Sim,Mestre!M119=Mestre!$M$97),0,1) -> 1 | D119: MOB_SSMA | F119: Nacional | H119: SSMA | I119: =VLOOKUP(K119,$N$74:$O$95,2) -> Despesas | J119: ATK | K119: SSMA | L119: ATM | M119: ATK | N119: NA | O119: M.O. | P119: NA | Q119: NA | R119: NA | S119: NA | T119: NA | U119: NA | V119: NA | W119: NA | X119: SSMA | Y119: NA | Z119: NA | AA119: 0 | AB119: NA | AC119: NA | AD119: NA | AF119: NA | AG119: 1 | AH119: 193073.15 | AI119: 0 | AJ119: 0 | AM119: =(((IF(L119=$L$101,1,IF(L119=$L$47,1,0))*(AH119*(1-AK119)))*AG119)*(1-AL119)) -> 193073.15 | AN119: =IF(K119=$K$50,AM119,IF(K119=$K$53,AM119,IF(K119=$K$54,AM119,IF(K119=$K$55,AM119,IF(K119=$K$56,AM119,IF(K119=$K$57,AM119,IF(K119=$K$58,AM119,IF(K119=$K$65,AM119,IF(K119=$K$66,AM119,IF(K119=$K$67,AM119,IF(K119=$K$68,AM119,IF(K119=$K$69,AM119,IF(K119=$K$51,AM119,(AM119*(1+AI119))))))))))))))) -> 193073.15 | AO119: 1.6 | AP119: =AM119*AO119 -> 308917.04 | AQ119: =AP119*Fator_Venda -> 267665.9 | AR119: =AO119*AN119 -> 308917.04 | AS119: =IFERROR(IF($AX$94=0,(CQ119/AN119),CQ119/AM119),0) -> 1.4282429 | AT119: =K119 -> SSMA | AU119: =I119 -> Despesas | AW119: =IF(K119=$K$50,0,IF(K119=$K$53,0,IF(K119=$K$54,0,IF(K119=$K$55,0,IF(K119=$K$56,0,IF(K119=$K$57,0,IF(K119=$K$58,0,IF(K119=$K$65,0,IF(K119=$K$66,0,IF(K119=$K$67,0,IF(K119=$K$68,0,IF(K119=$K$69,0,IF(K119=$K$51,0,1))))))))))))*AM119*AI119) -> 0 | AX119: =IF(K119=$K$50,0,IF(K119=$K$53,0,IF(K119=$K$54,0,IF(K119=$K$55,0,IF(K119=$K$56,0,IF(K119=$K$57,0,IF(K119=$K$58,0,IF(K119=$K$65,0,IF(K119=$K$66,0,IF(K119=$K$67,0,IF(K119=$K$68,0,IF(K119=$K$69,0,IF(K119=$K$51,0,1))))))))))))*AM119*AJ119*$AX$94) -> 0 | AY119: =IF(K119=$K$53,0,IF(K119=$K$54,0,IF(K119=$K$55,0,IF(K119=$K$56,0,IF(K119=$K$58,0,IF(K119=$K$50,0,IF(K119=$K$65,0,IF(K119=$K$57,0,IF(K119=$K$51,0,AM119*$AY$102))))))))) -> 3185.707 | AZ119: =IF(K119=$K$53,0,IF(K119=$K$54,0,IF(K119=$K$55,0,IF(K119=$K$56,0,IF(K119=$K$58,0,IF(K119=$K$50,0,IF(K119=$K$65,0,IF(K119=$K$57,0,IF(K119=$K$51,0,AM119*$AZ$102))))))))) -> 14673.56 | BA119: =AZ119+AY119+AX119 -> 17859.267 | BB119: =IF($BA$97=1,AQ119*$BB$102,IF(K119=$K$50,0,IF(K119=$K$53,0,IF(K119=$K$54,0,IF(K119=$K$55,0,IF(K119=$K$56,0,IF(K119=$K$57,0,IF(K119=$K$58,0,IF(K119=$K$65,0,IF(K119=$K$66,0,IF(K119=$K$67,0,IF(K119=$K$68,0,IF(K119=$K$69,0,IF(K119=$K$51,0,1)))))))))))*AQ119*$BB$102))) -> 0 | BC119: =AQ119*$BC$102 -> 1739.8284 | BD119: =$BD$102*AQ119 -> 8029.9771 | BE119: =IF($BE$95=I119,$BE$97,IF(I119=$BE$96,$BE$97,1))*($BE$102*AQ119)*$AZ$97 -> 0 | BF119: =IF('[1]Cockpit Retorno'!$C$65=Sim,Mestre!BA119,SUM(BB119:BE119)+(IF(K119=$K$56,AQ119*MOE_IRRF_LR,0))) -> 9769.8055 | BG119: =IF(AA119>0,0,IF(Z119=$Z$82,AG119*1,(IF(Z119=$Z$81,AG119*1,0)))) -> 0 | BH119: =IF(AA119>0,0,IF(Z119=$Z$83,AG119*1,IF(Z119=$Z$81,AG119*1,0))) -> 0 | BI119: =IF(AA119>0,0,IF(Z119=$Z$84,AG119*1,IF(Z119=$Z$93,AG119*2,IF(Z119=$Z$100,AG119,IF(Z119=$Z$81,AG119*2,IF(Z119=$Z$80,AG119*1,IF(Z119=$Z$79,AG119*3,IF(Z119=$Z$78,AG119*2,0)))))))) -> 0 | BJ119: =IF(AA119>0,0,IF(Z119=$Z$85,AG119,IF(Z119=$Z$93,AG119,IF(Z119=$Z$100,AG119,IF(Z119=$Z$81,AG119*1,IF(Z119=$Z$80,AG119*2,IF(Z119=$Z$79,AG119*2,IF(Z119=$Z$78,AG119*2,0)))))))) -> 0 | BK119: =IF(AA119>0,0,IF(Z119=$Z$92,AG119,0)) -> 0 | BL119: =IF(AA119>0,0,IF(Z119=$Z$91,AG119,0)) -> 0 | BM119: =IF(AA119>0,0,IF(Z119=$Z$86,AG119,0)) -> 0 | BN119: =IF(AA119>0,0,IF(Z119=$Z$87,AG119,0)) -> 0 | BO119: =IF(AA119>0,0,IF(Z119=$Z$88,AG119,0)) -> 0 | BP119: =IF(AA119>0,0,IF(Z119=$Z$89,AG119,0)) -> 0 | BQ119: =IF(AA119>0,0,IF(Z119=$Z$90,AG119,0)) -> 0 | BR119: =IF(Z119=$Z$82,AA119*AG119,0) -> 0 | BS119: =IF(Z119=$Z$83,AA119*AG119,0) -> 0 | BT119: =IF(AA119<1,0,IF(Z119=$Z$84,AA119*AG119,IF(Z119=$Z$93,"ERRO",IF(Z119=$Z$100,"ERRO",0)))) -> 0 | BU119: =IF(AA119<1,0,IF(Z119=$Z$85,AA119*AG119,IF(Z119=$Z$93,"ERRO",IF(Z119=$Z$100,"ERRO",0)))) -> 0 | BV119: =IF(Z119=$Z$92,AA119*AG119,0) -> 0 | BW119: =IF(Z119=$Z$91,AA119*AG119,0) -> 0 | BX119: =IF(Z119=$Z$86,AA119*AG119,0) -> 0 | BY119: =IF(Z119=$Z$87,AA119*AG119,0) -> 0 | BZ119: =IF(Z119=$Z$88,AA119*AG119,0) -> 0 | CA119: =IF(Z119=$Z$89,AA119*AG119,0) -> 0 | CB119: =IF(Z119=$Z$90,AA119*AG119,0) -> 0 | CC119: =IFERROR(IF(L119=$L$49,AG119*AH119*(1+AI119)*(1-AK119)*(1-AL119),0),0) -> 0 | CD119: =IF(I119=$CD$97,1,IF(I119=$CD$100,2,IF(K119=$K$66,1,IF(K119=$K$69,1,3)))) -> 2 | CE119: =IF($CD119=1,1.07,IF($CD119=2,1.07,1.3)) -> 1.07 | CF119: =CG119*0.87 -> 1.2789 | CG119: =IF($CD119=1,1.42,IF($CD119=2,1.47,2)) -> 1.47 | CH119: =CG119*1.09 -> 1.6023 | CI119: =IF($CD119=1,1.7,IF($CD119=2,1.7,2.4)) -> 1.7 | CJ119: =CE119*$CJ$102 -> 1.0486 | CK119: =CF119*$CK$102 -> 1.189377 | CL119: =CG119*$CL$102 -> 1.4406 | CM119: =CH119*$CM$102 -> 1.554231 | CN119: =CI119*$CN$102 -> 1.632 | CO119: =CJ119*$CO$102 -> 1.006656 | CP119: =BF119-BA119 -> -8089.4611 | CQ119: =AQ119-CP119 -> 275755.37 | CR119: =BC119+BD119 -> 9769.8055
A120: =IF(AND('[1]Cockpit Retorno'!$E$67=Sim,Mestre!M120=Mestre!$M$98),0,1) -> 1 | B120: =IF(AND('[1]Cockpit Retorno'!$E$67=Sim,Mestre!L120=Mestre!$L$48),0,1) -> 0 | C120: =IF(AND('[1]Cockpit Retorno'!$E$67=Sim,Mestre!M120=Mestre!$M$97),0,1) -> 1 | D120: LOG_LOGM_TRS | F120: Nacional | H120: TRS | I120: =VLOOKUP(K120,$N$74:$O$95,2) -> Despesas | J120: ATK | K120: TRS | L120: ATM | M120: ATK | N120: NA | O120: M.O. | P120: NA | Q120: NA | R120: NA | S120: NA | T120: NA | U120: NA | V120: NA | W120: NA | X120: Transporte leitos/ eletrocalhas e Cabos | Y120: NA | Z120: NA | AA120: 0 | AB120: NA | AC120: NA | AD120: NA | AF120: NA | AG120: 6 | AH120: 6741.9355 | AI120: 0 | AJ120: 0.07 | AM120: =(((IF(L120=$L$101,1,IF(L120=$L$47,1,0))*(AH120*(1-AK120)))*AG120)*(1-AL120)) -> 40451.613 | AN120: =IF(K120=$K$50,AM120,IF(K120=$K$53,AM120,IF(K120=$K$54,AM120,IF(K120=$K$55,AM120,IF(K120=$K$56,AM120,IF(K120=$K$57,AM120,IF(K120=$K$58,AM120,IF(K120=$K$65,AM120,IF(K120=$K$66,AM120,IF(K120=$K$67,AM120,IF(K120=$K$68,AM120,IF(K120=$K$69,AM120,IF(K120=$K$51,AM120,(AM120*(1+AI120))))))))))))))) -> 40451.613 | AO120: 1.6 | AP120: =AM120*AO120 -> 64722.581 | AQ120: =AP120*Fator_Venda -> 56079.871 | AR120: =AO120*AN120 -> 64722.581 | AS120: =IFERROR(IF($AX$94=0,(CQ120/AN120),CQ120/AM120),0) -> 1.4282429 | AT120: =K120 -> TRS | AU120: =I120 -> Despesas | AW120: =IF(K120=$K$50,0,IF(K120=$K$53,0,IF(K120=$K$54,0,IF(K120=$K$55,0,IF(K120=$K$56,0,IF(K120=$K$57,0,IF(K120=$K$58,0,IF(K120=$K$65,0,IF(K120=$K$66,0,IF(K120=$K$67,0,IF(K120=$K$68,0,IF(K120=$K$69,0,IF(K120=$K$51,0,1))))))))))))*AM120*AI120) -> 0 | AX120: =IF(K120=$K$50,0,IF(K120=$K$53,0,IF(K120=$K$54,0,IF(K120=$K$55,0,IF(K120=$K$56,0,IF(K120=$K$57,0,IF(K120=$K$58,0,IF(K120=$K$65,0,IF(K120=$K$66,0,IF(K120=$K$67,0,IF(K120=$K$68,0,IF(K120=$K$69,0,IF(K120=$K$51,0,1))))))))))))*AM120*AJ120*$AX$94) -> 0 | AY120: =IF(K120=$K$53,0,IF(K120=$K$54,0,IF(K120=$K$55,0,IF(K120=$K$56,0,IF(K120=$K$58,0,IF(K120=$K$50,0,IF(K120=$K$65,0,IF(K120=$K$57,0,IF(K120=$K$51,0,AM120*$AY$102))))))))) -> 667.45161 | AZ120: =IF(K120=$K$53,0,IF(K120=$K$54,0,IF(K120=$K$55,0,IF(K120=$K$56,0,IF(K120=$K$58,0,IF(K120=$K$50,0,IF(K120=$K$65,0,IF(K120=$K$57,0,IF(K120=$K$51,0,AM120*$AZ$102))))))))) -> 3074.3226 | BA120: =AZ120+AY120+AX120 -> 3741.7742 | BB120: =IF($BA$97=1,AQ120*$BB$102,IF(K120=$K$50,0,IF(K120=$K$53,0,IF(K120=$K$54,0,IF(K120=$K$55,0,IF(K120=$K$56,0,IF(K120=$K$57,0,IF(K120=$K$58,0,IF(K120=$K$65,0,IF(K120=$K$66,0,IF(K120=$K$67,0,IF(K120=$K$68,0,IF(K120=$K$69,0,IF(K120=$K$51,0,1)))))))))))*AQ120*$BB$102))) -> 0 | BC120: =AQ120*$BC$102 -> 364.51916 | BD120: =$BD$102*AQ120 -> 1682.3961 | BE120: =IF($BE$95=I120,$BE$97,IF(I120=$BE$96,$BE$97,1))*($BE$102*AQ120)*$AZ$97 -> 0 | BF120: =IF('[1]Cockpit Retorno'!$C$65=Sim,Mestre!BA120,SUM(BB120:BE120)+(IF(K120=$K$56,AQ120*MOE_IRRF_LR,0))) -> 2046.9153 | BG120: =IF(AA120>0,0,IF(Z120=$Z$82,AG120*1,(IF(Z120=$Z$81,AG120*1,0)))) -> 0 | BH120: =IF(AA120>0,0,IF(Z120=$Z$83,AG120*1,IF(Z120=$Z$81,AG120*1,0))) -> 0 | BI120: =IF(AA120>0,0,IF(Z120=$Z$84,AG120*1,IF(Z120=$Z$93,AG120*2,IF(Z120=$Z$100,AG120,IF(Z120=$Z$81,AG120*2,IF(Z120=$Z$80,AG120*1,IF(Z120=$Z$79,AG120*3,IF(Z120=$Z$78,AG120*2,0)))))))) -> 0 | BJ120: =IF(AA120>0,0,IF(Z120=$Z$85,AG120,IF(Z120=$Z$93,AG120,IF(Z120=$Z$100,AG120,IF(Z120=$Z$81,AG120*1,IF(Z120=$Z$80,AG120*2,IF(Z120=$Z$79,AG120*2,IF(Z120=$Z$78,AG120*2,0)))))))) -> 0 | BK120: =IF(AA120>0,0,IF(Z120=$Z$92,AG120,0)) -> 0 | BL120: =IF(AA120>0,0,IF(Z120=$Z$91,AG120,0)) -> 0 | BM120: =IF(AA120>0,0,IF(Z120=$Z$86,AG120,0)) -> 0 | BN120: =IF(AA120>0,0,IF(Z120=$Z$87,AG120,0)) -> 0 | BO120: =IF(AA120>0,0,IF(Z120=$Z$88,AG120,0)) -> 0 | BP120: =IF(AA120>0,0,IF(Z120=$Z$89,AG120,0)) -> 0 | BQ120: =IF(AA120>0,0,IF(Z120=$Z$90,AG120,0)) -> 0 | BR120: =IF(Z120=$Z$82,AA120*AG120,0) -> 0 | BS120: =IF(Z120=$Z$83,AA120*AG120,0) -> 0 | BT120: =IF(AA120<1,0,IF(Z120=$Z$84,AA120*AG120,IF(Z120=$Z$93,"ERRO",IF(Z120=$Z$100,"ERRO",0)))) -> 0 | BU120: =IF(AA120<1,0,IF(Z120=$Z$85,AA120*AG120,IF(Z120=$Z$93,"ERRO",IF(Z120=$Z$100,"ERRO",0)))) -> 0 | BV120: =IF(Z120=$Z$92,AA120*AG120,0) -> 0 | BW120: =IF(Z120=$Z$91,AA120*AG120,0) -> 0 | BX120: =IF(Z120=$Z$86,AA120*AG120,0) -> 0 | BY120: =IF(Z120=$Z$87,AA120*AG120,0) -> 0 | BZ120: =IF(Z120=$Z$88,AA120*AG120,0) -> 0 | CA120: =IF(Z120=$Z$89,AA120*AG120,0) -> 0 | CB120: =IF(Z120=$Z$90,AA120*AG120,0) -> 0 | CC120: =IFERROR(IF(L120=$L$49,AG120*AH120*(1+AI120)*(1-AK120)*(1-AL120),0),0) -> 0 | CD120: =IF(I120=$CD$97,1,IF(I120=$CD$100,2,IF(K120=$K$66,1,IF(K120=$K$69,1,3)))) -> 2 | CE120: =IF($CD120=1,1.07,IF($CD120=2,1.07,1.3)) -> 1.07 | CF120: =CG120*0.87 -> 1.2789 | CG120: =IF($CD120=1,1.42,IF($CD120=2,1.47,2)) -> 1.47 | CH120: =CG120*1.09 -> 1.6023 | CI120: =IF($CD120=1,1.7,IF($CD120=2,1.7,2.4)) -> 1.7 | CJ120: =CE120*$CJ$102 -> 1.0486 | CK120: =CF120*$CK$102 -> 1.189377 | CL120: =CG120*$CL$102 -> 1.4406 | CM120: =CH120*$CM$102 -> 1.554231 | CN120: =CI120*$CN$102 -> 1.632 | CO120: =CJ120*$CO$102 -> 1.006656 | CP120: =BF120-BA120 -> -1694.8589 | CQ120: =AQ120-CP120 -> 57774.73 | CR120: =BC120+BD120 -> 2046.9153
A121: =IF(AND('[1]Cockpit Retorno'!$E$67=Sim,Mestre!M121=Mestre!$M$98),0,1) -> 1 | B121: =IF(AND('[1]Cockpit Retorno'!$E$67=Sim,Mestre!L121=Mestre!$L$48),0,1) -> 0 | C121: =IF(AND('[1]Cockpit Retorno'!$E$67=Sim,Mestre!M121=Mestre!$M$97),0,1) -> 1 | D121: LOG_LOGM_TRS | F121: Nacional | H121: TRS | I121: =VLOOKUP(K121,$N$74:$O$95,2) -> Despesas | J121: ATK | K121: TRS | L121: ATM | M121: ATK | N121: NA | O121: M.O. | P121: NA | Q121: NA | R121: NA | S121: NA | T121: NA | U121: NA | V121: NA | W121: NA | X121: Transporte leitos/ eletrocalhas e Cabos | Y121: NA | Z121: NA | AA121: 0 | AB121: NA | AC121: NA | AD121: NA | AF121: NA | AG121: 1 | AH121: 11526.744 | AI121: 0 | AJ121: 0.07 | AM121: =(((IF(L121=$L$101,1,IF(L121=$L$47,1,0))*(AH121*(1-AK121)))*AG121)*(1-AL121)) -> 11526.744 | AN121: =IF(K121=$K$50,AM121,IF(K121=$K$53,AM121,IF(K121=$K$54,AM121,IF(K121=$K$55,AM121,IF(K121=$K$56,AM121,IF(K121=$K$57,AM121,IF(K121=$K$58,AM121,IF(K121=$K$65,AM121,IF(K121=$K$66,AM121,IF(K121=$K$67,AM121,IF(K121=$K$68,AM121,IF(K121=$K$69,AM121,IF(K121=$K$51,AM121,(AM121*(1+AI121))))))))))))))) -> 11526.744 | AO121: 1.6 | AP121: =AM121*AO121 -> 18442.791 | AQ121: =AP121*Fator_Venda -> 15980.038 | AR121: =AO121*AN121 -> 18442.791 | AS121: =IFERROR(IF($AX$94=0,(CQ121/AN121),CQ121/AM121),0) -> 1.4282429 | AT121: =K121 -> TRS | AU121: =I121 -> Despesas | AW121: =IF(K121=$K$50,0,IF(K121=$K$53,0,IF(K121=$K$54,0,IF(K121=$K$55,0,IF(K121=$K$56,0,IF(K121=$K$57,0,IF(K121=$K$58,0,IF(K121=$K$65,0,IF(K121=$K$66,0,IF(K121=$K$67,0,IF(K121=$K$68,0,IF(K121=$K$69,0,IF(K121=$K$51,0,1))))))))))))*AM121*AI121) -> 0 | AX121: =IF(K121=$K$50,0,IF(K121=$K$53,0,IF(K121=$K$54,0,IF(K121=$K$55,0,IF(K121=$K$56,0,IF(K121=$K$57,0,IF(K121=$K$58,0,IF(K121=$K$65,0,IF(K121=$K$66,0,IF(K121=$K$67,0,IF(K121=$K$68,0,IF(K121=$K$69,0,IF(K121=$K$51,0,1))))))))))))*AM121*AJ121*$AX$94) -> 0 | AY121: =IF(K121=$K$53,0,IF(K121=$K$54,0,IF(K121=$K$55,0,IF(K121=$K$56,0,IF(K121=$K$58,0,IF(K121=$K$50,0,IF(K121=$K$65,0,IF(K121=$K$57,0,IF(K121=$K$51,0,AM121*$AY$102))))))))) -> 190.19128 | AZ121: =IF(K121=$K$53,0,IF(K121=$K$54,0,IF(K121=$K$55,0,IF(K121=$K$56,0,IF(K121=$K$58,0,IF(K121=$K$50,0,IF(K121=$K$65,0,IF(K121=$K$57,0,IF(K121=$K$51,0,AM121*$AZ$102))))))))) -> 876.03255 | BA121: =AZ121+AY121+AX121 -> 1066.2238 | BB121: =IF($BA$97=1,AQ121*$BB$102,IF(K121=$K$50,0,IF(K121=$K$53,0,IF(K121=$K$54,0,IF(K121=$K$55,0,IF(K121=$K$56,0,IF(K121=$K$57,0,IF(K121=$K$58,0,IF(K121=$K$65,0,IF(K121=$K$66,0,IF(K121=$K$67,0,IF(K121=$K$68,0,IF(K121=$K$69,0,IF(K121=$K$51,0,1)))))))))))*AQ121*$BB$102))) -> 0 | BC121: =AQ121*$BC$102 -> 103.87025 | BD121: =$BD$102*AQ121 -> 479.40115 | BE121: =IF($BE$95=I121,$BE$97,IF(I121=$BE$96,$BE$97,1))*($BE$102*AQ121)*$AZ$97 -> 0 | BF121: =IF('[1]Cockpit Retorno'!$C$65=Sim,Mestre!BA121,SUM(BB121:BE121)+(IF(K121=$K$56,AQ121*MOE_IRRF_LR,0))) -> 583.2714 | BG121: =IF(AA121>0,0,IF(Z121=$Z$82,AG121*1,(IF(Z121=$Z$81,AG121*1,0)))) -> 0 | BH121: =IF(AA121>0,0,IF(Z121=$Z$83,AG121*1,IF(Z121=$Z$81,AG121*1,0))) -> 0 | BI121: =IF(AA121>0,0,IF(Z121=$Z$84,AG121*1,IF(Z121=$Z$93,AG121*2,IF(Z121=$Z$100,AG121,IF(Z121=$Z$81,AG121*2,IF(Z121=$Z$80,AG121*1,IF(Z121=$Z$79,AG121*3,IF(Z121=$Z$78,AG121*2,0)))))))) -> 0 | BJ121: =IF(AA121>0,0,IF(Z121=$Z$85,AG121,IF(Z121=$Z$93,AG121,IF(Z121=$Z$100,AG121,IF(Z121=$Z$81,AG121*1,IF(Z121=$Z$80,AG121*2,IF(Z121=$Z$79,AG121*2,IF(Z121=$Z$78,AG121*2,0)))))))) -> 0 | BK121: =IF(AA121>0,0,IF(Z121=$Z$92,AG121,0)) -> 0 | BL121: =IF(AA121>0,0,IF(Z121=$Z$91,AG121,0)) -> 0 | BM121: =IF(AA121>0,0,IF(Z121=$Z$86,AG121,0)) -> 0 | BN121: =IF(AA121>0,0,IF(Z121=$Z$87,AG121,0)) -> 0 | BO121: =IF(AA121>0,0,IF(Z121=$Z$88,AG121,0)) -> 0 | BP121: =IF(AA121>0,0,IF(Z121=$Z$89,AG121,0)) -> 0 | BQ121: =IF(AA121>0,0,IF(Z121=$Z$90,AG121,0)) -> 0 | BR121: =IF(Z121=$Z$82,AA121*AG121,0) -> 0 | BS121: =IF(Z121=$Z$83,AA121*AG121,0) -> 0 | BT121: =IF(AA121<1,0,IF(Z121=$Z$84,AA121*AG121,IF(Z121=$Z$93,"ERRO",IF(Z121=$Z$100,"ERRO",0)))) -> 0 | BU121: =IF(AA121<1,0,IF(Z121=$Z$85,AA121*AG121,IF(Z121=$Z$93,"ERRO",IF(Z121=$Z$100,"ERRO",0)))) -> 0 | BV121: =IF(Z121=$Z$92,AA121*AG121,0) -> 0 | BW121: =IF(Z121=$Z$91,AA121*AG121,0) -> 0 | BX121: =IF(Z121=$Z$86,AA121*AG121,0) -> 0 | BY121: =IF(Z121=$Z$87,AA121*AG121,0) -> 0 | BZ121: =IF(Z121=$Z$88,AA121*AG121,0) -> 0 | CA121: =IF(Z121=$Z$89,AA121*AG121,0) -> 0 | CB121: =IF(Z121=$Z$90,AA121*AG121,0) -> 0 | CC121: =IFERROR(IF(L121=$L$49,AG121*AH121*(1+AI121)*(1-AK121)*(1-AL121),0),0) -> 0 | CD121: =IF(I121=$CD$97,1,IF(I121=$CD$100,2,IF(K121=$K$66,1,IF(K121=$K$69,1,3)))) -> 2 | CE121: =IF($CD121=1,1.07,IF($CD121=2,1.07,1.3)) -> 1.07 | CF121: =CG121*0.87 -> 1.2789 | CG121: =IF($CD121=1,1.42,IF($CD121=2,1.47,2)) -> 1.47 | CH121: =CG121*1.09 -> 1.6023 | CI121: =IF($CD121=1,1.7,IF($CD121=2,1.7,2.4)) -> 1.7 | CJ121: =CE121*$CJ$102 -> 1.0486 | CK121: =CF121*$CK$102 -> 1.189377 | CL121: =CG121*$CL$102 -> 1.4406 | CM121: =CH121*$CM$102 -> 1.554231 | CN121: =CI121*$CN$102 -> 1.632 | CO121: =CJ121*$CO$102 -> 1.006656 | CP121: =BF121-BA121 -> -482.95243 | CQ121: =AQ121-CP121 -> 16462.991 | CR121: =BC121+BD121 -> 583.2714
A122: =IF(AND('[1]Cockpit Retorno'!$E$67=Sim,Mestre!M122=Mestre!$M$98),0,1) -> 1 | B122: =IF(AND('[1]Cockpit Retorno'!$E$67=Sim,Mestre!L122=Mestre!$L$48),0,1) -> 0 | C122: =IF(AND('[1]Cockpit Retorno'!$E$67=Sim,Mestre!M122=Mestre!$M$97),0,1) -> 1 | D122: LOG_LOGM_TRS | F122: Nacional | H122: TRS | I122: =VLOOKUP(K122,$N$74:$O$95,2) -> Despesas | J122: ATK | K122: TRS | L122: ATM | M122: ATK | N122: NA | O122: M.O. | P122: NA | Q122: NA | R122: NA | S122: NA | T122: NA | U122: NA | V122: NA | W122: NA | X122: Transporte miscelaneas | Y122: NA | Z122: NA | AA122: 0 | AB122: NA | AC122: NA | AD122: NA | AF122: NA | AG122: 2 | AH122: 6741.9355 | AI122: 0 | AJ122: 0.07 | AM122: =(((IF(L122=$L$101,1,IF(L122=$L$47,1,0))*(AH122*(1-AK122)))*AG122)*(1-AL122)) -> 13483.871 | AN122: =IF(K122=$K$50,AM122,IF(K122=$K$53,AM122,IF(K122=$K$54,AM122,IF(K122=$K$55,AM122,IF(K122=$K$56,AM122,IF(K122=$K$57,AM122,IF(K122=$K$58,AM122,IF(K122=$K$65,AM122,IF(K122=$K$66,AM122,IF(K122=$K$67,AM122,IF(K122=$K$68,AM122,IF(K122=$K$69,AM122,IF(K122=$K$51,AM122,(AM122*(1+AI122))))))))))))))) -> 13483.871 | AO122: 1.6 | AP122: =AM122*AO122 -> 21574.194 | AQ122: =AP122*Fator_Venda -> 18693.29 | AR122: =AO122*AN122 -> 21574.194 | AS122: =IFERROR(IF($AX$94=0,(CQ122/AN122),CQ122/AM122),0) -> 1.4282429 | AT122: =K122 -> TRS | AU122: =I122 -> Despesas | AW122: =IF(K122=$K$50,0,IF(K122=$K$53,0,IF(K122=$K$54,0,IF(K122=$K$55,0,IF(K122=$K$56,0,IF(K122=$K$57,0,IF(K122=$K$58,0,IF(K122=$K$65,0,IF(K122=$K$66,0,IF(K122=$K$67,0,IF(K122=$K$68,0,IF(K122=$K$69,0,IF(K122=$K$51,0,1))))))))))))*AM122*AI122) -> 0 | AX122: =IF(K122=$K$50,0,IF(K122=$K$53,0,IF(K122=$K$54,0,IF(K122=$K$55,0,IF(K122=$K$56,0,IF(K122=$K$57,0,IF(K122=$K$58,0,IF(K122=$K$65,0,IF(K122=$K$66,0,IF(K122=$K$67,0,IF(K122=$K$68,0,IF(K122=$K$69,0,IF(K122=$K$51,0,1))))))))))))*AM122*AJ122*$AX$94) -> 0 | AY122: =IF(K122=$K$53,0,IF(K122=$K$54,0,IF(K122=$K$55,0,IF(K122=$K$56,0,IF(K122=$K$58,0,IF(K122=$K$50,0,IF(K122=$K$65,0,IF(K122=$K$57,0,IF(K122=$K$51,0,AM122*$AY$102))))))))) -> 222.48387 | AZ122: =IF(K122=$K$53,0,IF(K122=$K$54,0,IF(K122=$K$55,0,IF(K122=$K$56,0,IF(K122=$K$58,0,IF(K122=$K$50,0,IF(K122=$K$65,0,IF(K122=$K$57,0,IF(K122=$K$51,0,AM122*$AZ$102))))))))) -> 1024.7742 | BA122: =AZ122+AY122+AX122 -> 1247.2581 | BB122: =IF($BA$97=1,AQ122*$BB$102,IF(K122=$K$50,0,IF(K122=$K$53,0,IF(K122=$K$54,0,IF(K122=$K$55,0,IF(K122=$K$56,0,IF(K122=$K$57,0,IF(K122=$K$58,0,IF(K122=$K$65,0,IF(K122=$K$66,0,IF(K122=$K$67,0,IF(K122=$K$68,0,IF(K122=$K$69,0,IF(K122=$K$51,0,1)))))))))))*AQ122*$BB$102))) -> 0 | BC122: =AQ122*$BC$102 -> 121.50639 | BD122: =$BD$102*AQ122 -> 560.79871 | BE122: =IF($BE$95=I122,$BE$97,IF(I122=$BE$96,$BE$97,1))*($BE$102*AQ122)*$AZ$97 -> 0 | BF122: =IF('[1]Cockpit Retorno'!$C$65=Sim,Mestre!BA122,SUM(BB122:BE122)+(IF(K122=$K$56,AQ122*MOE_IRRF_LR,0))) -> 682.3051 | BG122: =IF(AA122>0,0,IF(Z122=$Z$82,AG122*1,(IF(Z122=$Z$81,AG122*1,0)))) -> 0 | BH122: =IF(AA122>0,0,IF(Z122=$Z$83,AG122*1,IF(Z122=$Z$81,AG122*1,0))) -> 0 | BI122: =IF(AA122>0,0,IF(Z122=$Z$84,AG122*1,IF(Z122=$Z$93,AG122*2,IF(Z122=$Z$100,AG122,IF(Z122=$Z$81,AG122*2,IF(Z122=$Z$80,AG122*1,IF(Z122=$Z$79,AG122*3,IF(Z122=$Z$78,AG122*2,0)))))))) -> 0 | BJ122: =IF(AA122>0,0,IF(Z122=$Z$85,AG122,IF(Z122=$Z$93,AG122,IF(Z122=$Z$100,AG122,IF(Z122=$Z$81,AG122*1,IF(Z122=$Z$80,AG122*2,IF(Z122=$Z$79,AG122*2,IF(Z122=$Z$78,AG122*2,0)))))))) -> 0 | BK122: =IF(AA122>0,0,IF(Z122=$Z$92,AG122,0)) -> 0 | BL122: =IF(AA122>0,0,IF(Z122=$Z$91,AG122,0)) -> 0 | BM122: =IF(AA122>0,0,IF(Z122=$Z$86,AG122,0)) -> 0 | BN122: =IF(AA122>0,0,IF(Z122=$Z$87,AG122,0)) -> 0 | BO122: =IF(AA122>0,0,IF(Z122=$Z$88,AG122,0)) -> 0 | BP122: =IF(AA122>0,0,IF(Z122=$Z$89,AG122,0)) -> 0 | BQ122: =IF(AA122>0,0,IF(Z122=$Z$90,AG122,0)) -> 0 | BR122: =IF(Z122=$Z$82,AA122*AG122,0) -> 0 | BS122: =IF(Z122=$Z$83,AA122*AG122,0) -> 0 | BT122: =IF(AA122<1,0,IF(Z122=$Z$84,AA122*AG122,IF(Z122=$Z$93,"ERRO",IF(Z122=$Z$100,"ERRO",0)))) -> 0 | BU122: =IF(AA122<1,0,IF(Z122=$Z$85,AA122*AG122,IF(Z122=$Z$93,"ERRO",IF(Z122=$Z$100,"ERRO",0)))) -> 0 | BV122: =IF(Z122=$Z$92,AA122*AG122,0) -> 0 | BW122: =IF(Z122=$Z$91,AA122*AG122,0) -> 0 | BX122: =IF(Z122=$Z$86,AA122*AG122,0) -> 0 | BY122: =IF(Z122=$Z$87,AA122*AG122,0) -> 0 | BZ122: =IF(Z122=$Z$88,AA122*AG122,0) -> 0 | CA122: =IF(Z122=$Z$89,AA122*AG122,0) -> 0 | CB122: =IF(Z122=$Z$90,AA122*AG122,0) -> 0 | CC122: =IFERROR(IF(L122=$L$49,AG122*AH122*(1+AI122)*(1-AK122)*(1-AL122),0),0) -> 0 | CD122: =IF(I122=$CD$97,1,IF(I122=$CD$100,2,IF(K122=$K$66,1,IF(K122=$K$69,1,3)))) -> 2 | CE122: =IF($CD122=1,1.07,IF($CD122=2,1.07,1.3)) -> 1.07 | CF122: =CG122*0.87 -> 1.2789 | CG122: =IF($CD122=1,1.42,IF($CD122=2,1.47,2)) -> 1.47 | CH122: =CG122*1.09 -> 1.6023 | CI122: =IF($CD122=1,1.7,IF($CD122=2,1.7,2.4)) -> 1.7 | CJ122: =CE122*$CJ$102 -> 1.0486 | CK122: =CF122*$CK$102 -> 1.189377 | CL122: =CG122*$CL$102 -> 1.4406 | CM122: =CH122*$CM$102 -> 1.554231 | CN122: =CI122*$CN$102 -> 1.632 | CO122: =CJ122*$CO$102 -> 1.006656 | CP122: =BF122-BA122 -> -564.95296 | CQ122: =AQ122-CP122 -> 19258.243 | CR122: =BC122+BD122 -> 682.3051
A123: =IF(AND('[1]Cockpit Retorno'!$E$67=Sim,Mestre!M123=Mestre!$M$98),0,1) -> 1 | B123: =IF(AND('[1]Cockpit Retorno'!$E$67=Sim,Mestre!L123=Mestre!$L$48),0,1) -> 0 | C123: =IF(AND('[1]Cockpit Retorno'!$E$67=Sim,Mestre!M123=Mestre!$M$97),0,1) -> 1 | D123: LOG_LOGM_TRS | F123: Nacional | H123: TRS | I123: =VLOOKUP(K123,$N$74:$O$95,2) -> Despesas | J123: ATK | K123: TRS | L123: ATM | M123: ATK | N123: NA | O123: M.O. | P123: NA | Q123: NA | R123: NA | S123: NA | T123: NA | U123: NA | V123: NA | W123: NA | X123: Transporte miscelaneas | Y123: NA | Z123: NA | AA123: 0 | AB123: NA | AC123: NA | AD123: NA | AF123: NA | AG123: 1 | AH123: 564.42324 | AI123: 0 | AJ123: 0.07 | AM123: =(((IF(L123=$L$101,1,IF(L123=$L$47,1,0))*(AH123*(1-AK123)))*AG123)*(1-AL123)) -> 564.42324 | AN123: =IF(K123=$K$50,AM123,IF(K123=$K$53,AM123,IF(K123=$K$54,AM123,IF(K123=$K$55,AM123,IF(K123=$K$56,AM123,IF(K123=$K$57,AM123,IF(K123=$K$58,AM123,IF(K123=$K$65,AM123,IF(K123=$K$66,AM123,IF(K123=$K$67,AM123,IF(K123=$K$68,AM123,IF(K123=$K$69,AM123,IF(K123=$K$51,AM123,(AM123*(1+AI123))))))))))))))) -> 564.42324 | AO123: 1.6 | AP123: =AM123*AO123 -> 903.07719 | AQ123: =AP123*Fator_Venda -> 782.48506 | AR123: =AO123*AN123 -> 903.07719 | AS123: =IFERROR(IF($AX$94=0,(CQ123/AN123),CQ123/AM123),0) -> 1.4282429 | AT123: =K123 -> TRS | AU123: =I123 -> Despesas | AW123: =IF(K123=$K$50,0,IF(K123=$K$53,0,IF(K123=$K$54,0,IF(K123=$K$55,0,IF(K123=$K$56,0,IF(K123=$K$57,0,IF(K123=$K$58,0,IF(K123=$K$65,0,IF(K123=$K$66,0,IF(K123=$K$67,0,IF(K123=$K$68,0,IF(K123=$K$69,0,IF(K123=$K$51,0,1))))))))))))*AM123*AI123) -> 0 | AX123: =IF(K123=$K$50,0,IF(K123=$K$53,0,IF(K123=$K$54,0,IF(K123=$K$55,0,IF(K123=$K$56,0,IF(K123=$K$57,0,IF(K123=$K$58,0,IF(K123=$K$65,0,IF(K123=$K$66,0,IF(K123=$K$67,0,IF(K123=$K$68,0,IF(K123=$K$69,0,IF(K123=$K$51,0,1))))))))))))*AM123*AJ123*$AX$94) -> 0 | AY123: =IF(K123=$K$53,0,IF(K123=$K$54,0,IF(K123=$K$55,0,IF(K123=$K$56,0,IF(K123=$K$58,0,IF(K123=$K$50,0,IF(K123=$K$65,0,IF(K123=$K$57,0,IF(K123=$K$51,0,AM123*$AY$102))))))))) -> 9.3129835 | AZ123: =IF(K123=$K$53,0,IF(K123=$K$54,0,IF(K123=$K$55,0,IF(K123=$K$56,0,IF(K123=$K$58,0,IF(K123=$K$50,0,IF(K123=$K$65,0,IF(K123=$K$57,0,IF(K123=$K$51,0,AM123*$AZ$102))))))))) -> 42.896166 | BA123: =AZ123+AY123+AX123 -> 52.20915 | BB123: =IF($BA$97=1,AQ123*$BB$102,IF(K123=$K$50,0,IF(K123=$K$53,0,IF(K123=$K$54,0,IF(K123=$K$55,0,IF(K123=$K$56,0,IF(K123=$K$57,0,IF(K123=$K$58,0,IF(K123=$K$65,0,IF(K123=$K$66,0,IF(K123=$K$67,0,IF(K123=$K$68,0,IF(K123=$K$69,0,IF(K123=$K$51,0,1)))))))))))*AQ123*$BB$102))) -> 0 | BC123: =AQ123*$BC$102 -> 5.0861529 | BD123: =$BD$102*AQ123 -> 23.474552 | BE123: =IF($BE$95=I123,$BE$97,IF(I123=$BE$96,$BE$97,1))*($BE$102*AQ123)*$AZ$97 -> 0 | BF123: =IF('[1]Cockpit Retorno'!$C$65=Sim,Mestre!BA123,SUM(BB123:BE123)+(IF(K123=$K$56,AQ123*MOE_IRRF_LR,0))) -> 28.560705 | BG123: =IF(AA123>0,0,IF(Z123=$Z$82,AG123*1,(IF(Z123=$Z$81,AG123*1,0)))) -> 0 | BH123: =IF(AA123>0,0,IF(Z123=$Z$83,AG123*1,IF(Z123=$Z$81,AG123*1,0))) -> 0 | BI123: =IF(AA123>0,0,IF(Z123=$Z$84,AG123*1,IF(Z123=$Z$93,AG123*2,IF(Z123=$Z$100,AG123,IF(Z123=$Z$81,AG123*2,IF(Z123=$Z$80,AG123*1,IF(Z123=$Z$79,AG123*3,IF(Z123=$Z$78,AG123*2,0)))))))) -> 0 | BJ123: =IF(AA123>0,0,IF(Z123=$Z$85,AG123,IF(Z123=$Z$93,AG123,IF(Z123=$Z$100,AG123,IF(Z123=$Z$81,AG123*1,IF(Z123=$Z$80,AG123*2,IF(Z123=$Z$79,AG123*2,IF(Z123=$Z$78,AG123*2,0)))))))) -> 0 | BK123: =IF(AA123>0,0,IF(Z123=$Z$92,AG123,0)) -> 0 | BL123: =IF(AA123>0,0,IF(Z123=$Z$91,AG123,0)) -> 0 | BM123: =IF(AA123>0,0,IF(Z123=$Z$86,AG123,0)) -> 0 | BN123: =IF(AA123>0,0,IF(Z123=$Z$87,AG123,0)) -> 0 | BO123: =IF(AA123>0,0,IF(Z123=$Z$88,AG123,0)) -> 0 | BP123: =IF(AA123>0,0,IF(Z123=$Z$89,AG123,0)) -> 0 | BQ123: =IF(AA123>0,0,IF(Z123=$Z$90,AG123,0)) -> 0 | BR123: =IF(Z123=$Z$82,AA123*AG123,0) -> 0 | BS123: =IF(Z123=$Z$83,AA123*AG123,0) -> 0 | BT123: =IF(AA123<1,0,IF(Z123=$Z$84,AA123*AG123,IF(Z123=$Z$93,"ERRO",IF(Z123=$Z$100,"ERRO",0)))) -> 0 | BU123: =IF(AA123<1,0,IF(Z123=$Z$85,AA123*AG123,IF(Z123=$Z$93,"ERRO",IF(Z123=$Z$100,"ERRO",0)))) -> 0 | BV123: =IF(Z123=$Z$92,AA123*AG123,0) -> 0 | BW123: =IF(Z123=$Z$91,AA123*AG123,0) -> 0 | BX123: =IF(Z123=$Z$86,AA123*AG123,0) -> 0 | BY123: =IF(Z123=$Z$87,AA123*AG123,0) -> 0 | BZ123: =IF(Z123=$Z$88,AA123*AG123,0) -> 0 | CA123: =IF(Z123=$Z$89,AA123*AG123,0) -> 0 | CB123: =IF(Z123=$Z$90,AA123*AG123,0) -> 0 | CC123: =IFERROR(IF(L123=$L$49,AG123*AH123*(1+AI123)*(1-AK123)*(1-AL123),0),0) -> 0 | CD123: =IF(I123=$CD$97,1,IF(I123=$CD$100,2,IF(K123=$K$66,1,IF(K123=$K$69,1,3)))) -> 2 | CE123: =IF($CD123=1,1.07,IF($CD123=2,1.07,1.3)) -> 1.07 | CF123: =CG123*0.87 -> 1.2789 | CG123: =IF($CD123=1,1.42,IF($CD123=2,1.47,2)) -> 1.47 | CH123: =CG123*1.09 -> 1.6023 | CI123: =IF($CD123=1,1.7,IF($CD123=2,1.7,2.4)) -> 1.7 | CJ123: =CE123*$CJ$102 -> 1.0486 | CK123: =CF123*$CK$102 -> 1.189377 | CL123: =CG123*$CL$102 -> 1.4406 | CM123: =CH123*$CM$102 -> 1.554231 | CN123: =CI123*$CN$102 -> 1.632 | CO123: =CJ123*$CO$102 -> 1.006656 | CP123: =BF123-BA123 -> -23.648445 | CQ123: =AQ123-CP123 -> 806.1335 | CR123: =BC123+BD123 -> 28.560705
A124: =IF(AND('[1]Cockpit Retorno'!$E$67=Sim,Mestre!M124=Mestre!$M$98),0,1) -> 1 | B124: =IF(AND('[1]Cockpit Retorno'!$E$67=Sim,Mestre!L124=Mestre!$L$48),0,1) -> 0 | C124: =IF(AND('[1]Cockpit Retorno'!$E$67=Sim,Mestre!M124=Mestre!$M$97),0,1) -> 1 | D124: MOE_MOC_SERV | F124: Nacional | H124: MOC | I124: =VLOOKUP(K124,$N$74:$O$95,2) -> Serviços | J124: ATK | K124: MOC | L124: ATM | M124: ATK | N124: NA | O124: COM | P124: NA | Q124: NA | R124: NA | S124: NA | T124: NA | U124: NA | V124: NA | W124: NA | X124: Comissionamento e Start Up - Instrumentação | Y124: NA | Z124: NA | AA124: 0 | AB124: NA | AC124: NA | AD124: NA | AF124: NA | AG124: =ROUNDUP('[1]Avulso HH'!M9,0) -> 617 | AH124: 155.78853 | AI124: 0 | AJ124: 0 | AM124: =(((IF(L124=$L$101,1,IF(L124=$L$47,1,0))*(AH124*(1-AK124)))*AG124)*(1-AL124)) -> 96121.521 | AN124: =IF(K124=$K$50,AM124,IF(K124=$K$53,AM124,IF(K124=$K$54,AM124,IF(K124=$K$55,AM124,IF(K124=$K$56,AM124,IF(K124=$K$57,AM124,IF(K124=$K$58,AM124,IF(K124=$K$65,AM124,IF(K124=$K$66,AM124,IF(K124=$K$67,AM124,IF(K124=$K$68,AM124,IF(K124=$K$69,AM124,IF(K124=$K$51,AM124,(AM124*(1+AI124))))))))))))))) -> 96121.521 | AO124: 1.9 | AP124: =AM124*AO124 -> 182630.89 | AQ124: =AP124*Fator_Venda -> 158243.33 | AR124: =AO124*AN124 -> 182630.89 | AS124: =IFERROR(IF($AX$94=0,(CQ124/AN124),CQ124/AM124),0) -> 1.5861947 | AT124: =K124 -> MOC | AU124: =I124 -> Serviços | AW124: =IF(K124=$K$50,0,IF(K124=$K$53,0,IF(K124=$K$54,0,IF(K124=$K$55,0,IF(K124=$K$56,0,IF(K124=$K$57,0,IF(K124=$K$58,0,IF(K124=$K$65,0,IF(K124=$K$66,0,IF(K124=$K$67,0,IF(K124=$K$68,0,IF(K124=$K$69,0,IF(K124=$K$51,0,1))))))))))))*AM124*AI124) -> 0 | AX124: =IF(K124=$K$50,0,IF(K124=$K$53,0,IF(K124=$K$54,0,IF(K124=$K$55,0,IF(K124=$K$56,0,IF(K124=$K$57,0,IF(K124=$K$58,0,IF(K124=$K$65,0,IF(K124=$K$66,0,IF(K124=$K$67,0,IF(K124=$K$68,0,IF(K124=$K$69,0,IF(K124=$K$51,0,1))))))))))))*AM124*AJ124*$AX$94) -> 0 | AY124: =IF(K124=$K$53,0,IF(K124=$K$54,0,IF(K124=$K$55,0,IF(K124=$K$56,0,IF(K124=$K$58,0,IF(K124=$K$50,0,IF(K124=$K$65,0,IF(K124=$K$57,0,IF(K124=$K$51,0,AM124*$AY$102))))))))) -> 0 | AZ124: =IF(K124=$K$53,0,IF(K124=$K$54,0,IF(K124=$K$55,0,IF(K124=$K$56,0,IF(K124=$K$58,0,IF(K124=$K$50,0,IF(K124=$K$65,0,IF(K124=$K$57,0,IF(K124=$K$51,0,AM124*$AZ$102))))))))) -> 0 | BA124: =AZ124+AY124+AX124 -> 0 | BB124: =IF($BA$97=1,AQ124*$BB$102,IF(K124=$K$50,0,IF(K124=$K$53,0,IF(K124=$K$54,0,IF(K124=$K$55,0,IF(K124=$K$56,0,IF(K124=$K$57,0,IF(K124=$K$58,0,IF(K124=$K$65,0,IF(K124=$K$66,0,IF(K124=$K$67,0,IF(K124=$K$68,0,IF(K124=$K$69,0,IF(K124=$K$51,0,1)))))))))))*AQ124*$BB$102))) -> 0 | BC124: =AQ124*$BC$102 -> 1028.5817 | BD124: =$BD$102*AQ124 -> 4747.3 | BE124: =IF($BE$95=I124,$BE$97,IF(I124=$BE$96,$BE$97,1))*($BE$102*AQ124)*$AZ$97 -> 0 | BF124: =IF('[1]Cockpit Retorno'!$C$65=Sim,Mestre!BA124,SUM(BB124:BE124)+(IF(K124=$K$56,AQ124*MOE_IRRF_LR,0))) -> 5775.8816 | BG124: =IF(AA124>0,0,IF(Z124=$Z$82,AG124*1,(IF(Z124=$Z$81,AG124*1,0)))) -> 0 | BH124: =IF(AA124>0,0,IF(Z124=$Z$83,AG124*1,IF(Z124=$Z$81,AG124*1,0))) -> 0 | BI124: =IF(AA124>0,0,IF(Z124=$Z$84,AG124*1,IF(Z124=$Z$93,AG124*2,IF(Z124=$Z$100,AG124,IF(Z124=$Z$81,AG124*2,IF(Z124=$Z$80,AG124*1,IF(Z124=$Z$79,AG124*3,IF(Z124=$Z$78,AG124*2,0)))))))) -> 0 | BJ124: =IF(AA124>0,0,IF(Z124=$Z$85,AG124,IF(Z124=$Z$93,AG124,IF(Z124=$Z$100,AG124,IF(Z124=$Z$81,AG124*1,IF(Z124=$Z$80,AG124*2,IF(Z124=$Z$79,AG124*2,IF(Z124=$Z$78,AG124*2,0)))))))) -> 0 | BK124: =IF(AA124>0,0,IF(Z124=$Z$92,AG124,0)) -> 0 | BL124: =IF(AA124>0,0,IF(Z124=$Z$91,AG124,0)) -> 0 | BM124: =IF(AA124>0,0,IF(Z124=$Z$86,AG124,0)) -> 0 | BN124: =IF(AA124>0,0,IF(Z124=$Z$87,AG124,0)) -> 0 | BO124: =IF(AA124>0,0,IF(Z124=$Z$88,AG124,0)) -> 0 | BP124: =IF(AA124>0,0,IF(Z124=$Z$89,AG124,0)) -> 0 | BQ124: =IF(AA124>0,0,IF(Z124=$Z$90,AG124,0)) -> 0 | BR124: =IF(Z124=$Z$82,AA124*AG124,0) -> 0 | BS124: =IF(Z124=$Z$83,AA124*AG124,0) -> 0 | BT124: =IF(AA124<1,0,IF(Z124=$Z$84,AA124*AG124,IF(Z124=$Z$93,"ERRO",IF(Z124=$Z$100,"ERRO",0)))) -> 0 | BU124: =IF(AA124<1,0,IF(Z124=$Z$85,AA124*AG124,IF(Z124=$Z$93,"ERRO",IF(Z124=$Z$100,"ERRO",0)))) -> 0 | BV124: =IF(Z124=$Z$92,AA124*AG124,0) -> 0 | BW124: =IF(Z124=$Z$91,AA124*AG124,0) -> 0 | BX124: =IF(Z124=$Z$86,AA124*AG124,0) -> 0 | BY124: =IF(Z124=$Z$87,AA124*AG124,0) -> 0 | BZ124: =IF(Z124=$Z$88,AA124*AG124,0) -> 0 | CA124: =IF(Z124=$Z$89,AA124*AG124,0) -> 0 | CB124: =IF(Z124=$Z$90,AA124*AG124,0) -> 0 | CC124: =IFERROR(IF(L124=$L$49,AG124*AH124*(1+AI124)*(1-AK124)*(1-AL124),0),0) -> 0 | CD124: =IF(I124=$CD$97,1,IF(I124=$CD$100,2,IF(K124=$K$66,1,IF(K124=$K$69,1,3)))) -> 3 | CE124: =IF($CD124=1,1.07,IF($CD124=2,1.07,1.3)) -> 1.3 | CF124: =CG124*0.87 -> 1.74 | CG124: =IF($CD124=1,1.42,IF($CD124=2,1.47,2)) -> 2 | CH124: =CG124*1.09 -> 2.18 | CI124: =IF($CD124=1,1.7,IF($CD124=2,1.7,2.4)) -> 2.4 | CJ124: =CE124*$CJ$102 -> 1.274 | CK124: =CF124*$CK$102 -> 1.6182 | CL124: =CG124*$CL$102 -> 1.96 | CM124: =CH124*$CM$102 -> 2.1146 | CN124: =CI124*$CN$102 -> 2.304 | CO124: =CJ124*$CO$102 -> 1.22304 | CP124: =BF124-BA124 -> 5775.8816 | CQ124: =AQ124-CP124 -> 152467.45 | CR124: =BC124+BD124 -> 5775.8816
A125: =IF(AND('[1]Cockpit Retorno'!$E$67=Sim,Mestre!M125=Mestre!$M$98),0,1) -> 1 | B125: =IF(AND('[1]Cockpit Retorno'!$E$67=Sim,Mestre!L125=Mestre!$L$48),0,1) -> 0 | C125: =IF(AND('[1]Cockpit Retorno'!$E$67=Sim,Mestre!M125=Mestre!$M$97),0,1) -> 1 | D125: LOG_LOGM_TRS | F125: Nacional | H125: LOG COM | I125: =VLOOKUP(K125,$N$74:$O$95,2) -> Despesas | J125: ATK | K125: LOG | L125: ATM | M125: ATK | N125: NA | O125: COM | P125: NA | Q125: NA | R125: NA | S125: NA | T125: NA | U125: NA | V125: NA | W125: NA | X125: Logistica Comissionamento e Start Up - Instrumentação | Y125: NA | Z125: NA | AA125: 0 | AB125: NA | AC125: NA | AD125: NA | AF125: NA | AG125: 1 | AH125: 24632.961 | AI125: 0 | AJ125: 0 | AM125: =(((IF(L125=$L$101,1,IF(L125=$L$47,1,0))*(AH125*(1-AK125)))*AG125)*(1-AL125)) -> 24632.961 | AN125: =IF(K125=$K$50,AM125,IF(K125=$K$53,AM125,IF(K125=$K$54,AM125,IF(K125=$K$55,AM125,IF(K125=$K$56,AM125,IF(K125=$K$57,AM125,IF(K125=$K$58,AM125,IF(K125=$K$65,AM125,IF(K125=$K$66,AM125,IF(K125=$K$67,AM125,IF(K125=$K$68,AM125,IF(K125=$K$69,AM125,IF(K125=$K$51,AM125,(AM125*(1+AI125))))))))))))))) -> 24632.961 | AO125: 1.6 | AP125: =AM125*AO125 -> 39412.738 | AQ125: =AP125*Fator_Venda -> 34149.77 | AR125: =AO125*AN125 -> 39412.738 | AS125: =IFERROR(IF($AX$94=0,(CQ125/AN125),CQ125/AM125),0) -> 1.3357429 | AT125: =K125 -> LOG | AU125: =I125 -> Despesas | AW125: =IF(K125=$K$50,0,IF(K125=$K$53,0,IF(K125=$K$54,0,IF(K125=$K$55,0,IF(K125=$K$56,0,IF(K125=$K$57,0,IF(K125=$K$58,0,IF(K125=$K$65,0,IF(K125=$K$66,0,IF(K125=$K$67,0,IF(K125=$K$68,0,IF(K125=$K$69,0,IF(K125=$K$51,0,1))))))))))))*AM125*AI125) -> 0 | AX125: =IF(K125=$K$50,0,IF(K125=$K$53,0,IF(K125=$K$54,0,IF(K125=$K$55,0,IF(K125=$K$56,0,IF(K125=$K$57,0,IF(K125=$K$58,0,IF(K125=$K$65,0,IF(K125=$K$66,0,IF(K125=$K$67,0,IF(K125=$K$68,0,IF(K125=$K$69,0,IF(K125=$K$51,0,1))))))))))))*AM125*AJ125*$AX$94) -> 0 | AY125: =IF(K125=$K$53,0,IF(K125=$K$54,0,IF(K125=$K$55,0,IF(K125=$K$56,0,IF(K125=$K$58,0,IF(K125=$K$50,0,IF(K125=$K$65,0,IF(K125=$K$57,0,IF(K125=$K$51,0,AM125*$AY$102))))))))) -> 0 | AZ125: =IF(K125=$K$53,0,IF(K125=$K$54,0,IF(K125=$K$55,0,IF(K125=$K$56,0,IF(K125=$K$58,0,IF(K125=$K$50,0,IF(K125=$K$65,0,IF(K125=$K$57,0,IF(K125=$K$51,0,AM125*$AZ$102))))))))) -> 0 | BA125: =AZ125+AY125+AX125 -> 0 | BB125: =IF($BA$97=1,AQ125*$BB$102,IF(K125=$K$50,0,IF(K125=$K$53,0,IF(K125=$K$54,0,IF(K125=$K$55,0,IF(K125=$K$56,0,IF(K125=$K$57,0,IF(K125=$K$58,0,IF(K125=$K$65,0,IF(K125=$K$66,0,IF(K125=$K$67,0,IF(K125=$K$68,0,IF(K125=$K$69,0,IF(K125=$K$51,0,1)))))))))))*AQ125*$BB$102))) -> 0 | BC125: =AQ125*$BC$102 -> 221.97351 | BD125: =$BD$102*AQ125 -> 1024.4931 | BE125: =IF($BE$95=I125,$BE$97,IF(I125=$BE$96,$BE$97,1))*($BE$102*AQ125)*$AZ$97 -> 0 | BF125: =IF('[1]Cockpit Retorno'!$C$65=Sim,Mestre!BA125,SUM(BB125:BE125)+(IF(K125=$K$56,AQ125*MOE_IRRF_LR,0))) -> 1246.4666 | BG125: =IF(AA125>0,0,IF(Z125=$Z$82,AG125*1,(IF(Z125=$Z$81,AG125*1,0)))) -> 0 | BH125: =IF(AA125>0,0,IF(Z125=$Z$83,AG125*1,IF(Z125=$Z$81,AG125*1,0))) -> 0 | BI125: =IF(AA125>0,0,IF(Z125=$Z$84,AG125*1,IF(Z125=$Z$93,AG125*2,IF(Z125=$Z$100,AG125,IF(Z125=$Z$81,AG125*2,IF(Z125=$Z$80,AG125*1,IF(Z125=$Z$79,AG125*3,IF(Z125=$Z$78,AG125*2,0)))))))) -> 0 | BJ125: =IF(AA125>0,0,IF(Z125=$Z$85,AG125,IF(Z125=$Z$93,AG125,IF(Z125=$Z$100,AG125,IF(Z125=$Z$81,AG125*1,IF(Z125=$Z$80,AG125*2,IF(Z125=$Z$79,AG125*2,IF(Z125=$Z$78,AG125*2,0)))))))) -> 0 | BK125: =IF(AA125>0,0,IF(Z125=$Z$92,AG125,0)) -> 0 | BL125: =IF(AA125>0,0,IF(Z125=$Z$91,AG125,0)) -> 0 | BM125: =IF(AA125>0,0,IF(Z125=$Z$86,AG125,0)) -> 0 | BN125: =IF(AA125>0,0,IF(Z125=$Z$87,AG125,0)) -> 0 | BO125: =IF(AA125>0,0,IF(Z125=$Z$88,AG125,0)) -> 0 | BP125: =IF(AA125>0,0,IF(Z125=$Z$89,AG125,0)) -> 0 | BQ125: =IF(AA125>0,0,IF(Z125=$Z$90,AG125,0)) -> 0 | BR125: =IF(Z125=$Z$82,AA125*AG125,0) -> 0 | BS125: =IF(Z125=$Z$83,AA125*AG125,0) -> 0 | BT125: =IF(AA125<1,0,IF(Z125=$Z$84,AA125*AG125,IF(Z125=$Z$93,"ERRO",IF(Z125=$Z$100,"ERRO",0)))) -> 0 | BU125: =IF(AA125<1,0,IF(Z125=$Z$85,AA125*AG125,IF(Z125=$Z$93,"ERRO",IF(Z125=$Z$100,"ERRO",0)))) -> 0 | BV125: =IF(Z125=$Z$92,AA125*AG125,0) -> 0 | BW125: =IF(Z125=$Z$91,AA125*AG125,0) -> 0 | BX125: =IF(Z125=$Z$86,AA125*AG125,0) -> 0 | BY125: =IF(Z125=$Z$87,AA125*AG125,0) -> 0 | BZ125: =IF(Z125=$Z$88,AA125*AG125,0) -> 0 | CA125: =IF(Z125=$Z$89,AA125*AG125,0) -> 0 | CB125: =IF(Z125=$Z$90,AA125*AG125,0) -> 0 | CC125: =IFERROR(IF(L125=$L$49,AG125*AH125*(1+AI125)*(1-AK125)*(1-AL125),0),0) -> 0 | CD125: =IF(I125=$CD$97,1,IF(I125=$CD$100,2,IF(K125=$K$66,1,IF(K125=$K$69,1,3)))) -> 2 | CE125: =IF($CD125=1,1.07,IF($CD125=2,1.07,1.3)) -> 1.07 | CF125: =CG125*0.87 -> 1.2789 | CG125: =IF($CD125=1,1.42,IF($CD125=2,1.47,2)) -> 1.47 | CH125: =CG125*1.09 -> 1.6023 | CI125: =IF($CD125=1,1.7,IF($CD125=2,1.7,2.4)) -> 1.7 | CJ125: =CE125*$CJ$102 -> 1.0486 | CK125: =CF125*$CK$102 -> 1.189377 | CL125: =CG125*$CL$102 -> 1.4406 | CM125: =CH125*$CM$102 -> 1.554231 | CN125: =CI125*$CN$102 -> 1.632 | CO125: 1.3 | CP125: =BF125-BA125 -> 1246.4666 | CQ125: =AQ125-CP125 -> 32903.304 | CR125: =BC125+BD125 -> 1246.4666
A126: =IF(AND('[1]Cockpit Retorno'!$E$67=Sim,Mestre!M126=Mestre!$M$98),0,1) -> 1 | B126: =IF(AND('[1]Cockpit Retorno'!$E$67=Sim,Mestre!L126=Mestre!$L$48),0,1) -> 0 | C126: =IF(AND('[1]Cockpit Retorno'!$E$67=Sim,Mestre!M126=Mestre!$M$97),0,1) -> 1 | D126: MOE_MOC_SERV | F126: Nacional | H126: MOC | I126: =VLOOKUP(K126,$N$74:$O$95,2) -> Serviços | J126: ATK | K126: MOC | L126: ATM | M126: ATK | N126: NA | O126: COM | P126: NA | Q126: NA | R126: NA | S126: NA | T126: NA | U126: NA | V126: NA | W126: NA | X126: Operação Assistida - Instrumentação | Y126: NA | Z126: NA | AA126: 0 | AB126: NA | AC126: NA | AD126: NA | AF126: NA | AG126: =ROUNDUP('[1]Avulso HH'!W9,0) -> 271 | AH126: 155.78853 | AI126: 0 | AJ126: 0 | AM126: =(((IF(L126=$L$101,1,IF(L126=$L$47,1,0))*(AH126*(1-AK126)))*AG126)*(1-AL126)) -> 42218.691 | AN126: =IF(K126=$K$50,AM126,IF(K126=$K$53,AM126,IF(K126=$K$54,AM126,IF(K126=$K$55,AM126,IF(K126=$K$56,AM126,IF(K126=$K$57,AM126,IF(K126=$K$58,AM126,IF(K126=$K$65,AM126,IF(K126=$K$66,AM126,IF(K126=$K$67,AM126,IF(K126=$K$68,AM126,IF(K126=$K$69,AM126,IF(K126=$K$51,AM126,(AM126*(1+AI126))))))))))))))) -> 42218.691 | AO126: 1.9 | AP126: =AM126*AO126 -> 80215.513 | AQ126: =AP126*Fator_Venda -> 69503.96 | AR126: =AO126*AN126 -> 80215.513 | AS126: =IFERROR(IF($AX$94=0,(CQ126/AN126),CQ126/AM126),0) -> 1.5861947 | AT126: =K126 -> MOC | AU126: =I126 -> Serviços | AW126: =IF(K126=$K$50,0,IF(K126=$K$53,0,IF(K126=$K$54,0,IF(K126=$K$55,0,IF(K126=$K$56,0,IF(K126=$K$57,0,IF(K126=$K$58,0,IF(K126=$K$65,0,IF(K126=$K$66,0,IF(K126=$K$67,0,IF(K126=$K$68,0,IF(K126=$K$69,0,IF(K126=$K$51,0,1))))))))))))*AM126*AI126) -> 0 | AX126: =IF(K126=$K$50,0,IF(K126=$K$53,0,IF(K126=$K$54,0,IF(K126=$K$55,0,IF(K126=$K$56,0,IF(K126=$K$57,0,IF(K126=$K$58,0,IF(K126=$K$65,0,IF(K126=$K$66,0,IF(K126=$K$67,0,IF(K126=$K$68,0,IF(K126=$K$69,0,IF(K126=$K$51,0,1))))))))))))*AM126*AJ126*$AX$94) -> 0 | AY126: =IF(K126=$K$53,0,IF(K126=$K$54,0,IF(K126=$K$55,0,IF(K126=$K$56,0,IF(K126=$K$58,0,IF(K126=$K$50,0,IF(K126=$K$65,0,IF(K126=$K$57,0,IF(K126=$K$51,0,AM126*$AY$102))))))))) -> 0 | AZ126: =IF(K126=$K$53,0,IF(K126=$K$54,0,IF(K126=$K$55,0,IF(K126=$K$56,0,IF(K126=$K$58,0,IF(K126=$K$50,0,IF(K126=$K$65,0,IF(K126=$K$57,0,IF(K126=$K$51,0,AM126*$AZ$102))))))))) -> 0 | BA126: =AZ126+AY126+AX126 -> 0 | BB126: =IF($BA$97=1,AQ126*$BB$102,IF(K126=$K$50,0,IF(K126=$K$53,0,IF(K126=$K$54,0,IF(K126=$K$55,0,IF(K126=$K$56,0,IF(K126=$K$57,0,IF(K126=$K$58,0,IF(K126=$K$65,0,IF(K126=$K$66,0,IF(K126=$K$67,0,IF(K126=$K$68,0,IF(K126=$K$69,0,IF(K126=$K$51,0,1)))))))))))*AQ126*$BB$102))) -> 0 | BC126: =AQ126*$BC$102 -> 451.77574 | BD126: =$BD$102*AQ126 -> 2085.1188 | BE126: =IF($BE$95=I126,$BE$97,IF(I126=$BE$96,$BE$97,1))*($BE$102*AQ126)*$AZ$97 -> 0 | BF126: =IF('[1]Cockpit Retorno'!$C$65=Sim,Mestre!BA126,SUM(BB126:BE126)+(IF(K126=$K$56,AQ126*MOE_IRRF_LR,0))) -> 2536.8945 | BG126: =IF(AA126>0,0,IF(Z126=$Z$82,AG126*1,(IF(Z126=$Z$81,AG126*1,0)))) -> 0 | BH126: =IF(AA126>0,0,IF(Z126=$Z$83,AG126*1,IF(Z126=$Z$81,AG126*1,0))) -> 0 | BI126: =IF(AA126>0,0,IF(Z126=$Z$84,AG126*1,IF(Z126=$Z$93,AG126*2,IF(Z126=$Z$100,AG126,IF(Z126=$Z$81,AG126*2,IF(Z126=$Z$80,AG126*1,IF(Z126=$Z$79,AG126*3,IF(Z126=$Z$78,AG126*2,0)))))))) -> 0 | BJ126: =IF(AA126>0,0,IF(Z126=$Z$85,AG126,IF(Z126=$Z$93,AG126,IF(Z126=$Z$100,AG126,IF(Z126=$Z$81,AG126*1,IF(Z126=$Z$80,AG126*2,IF(Z126=$Z$79,AG126*2,IF(Z126=$Z$78,AG126*2,0)))))))) -> 0 | BK126: =IF(AA126>0,0,IF(Z126=$Z$92,AG126,0)) -> 0 | BL126: =IF(AA126>0,0,IF(Z126=$Z$91,AG126,0)) -> 0 | BM126: =IF(AA126>0,0,IF(Z126=$Z$86,AG126,0)) -> 0 | BN126: =IF(AA126>0,0,IF(Z126=$Z$87,AG126,0)) -> 0 | BO126: =IF(AA126>0,0,IF(Z126=$Z$88,AG126,0)) -> 0 | BP126: =IF(AA126>0,0,IF(Z126=$Z$89,AG126,0)) -> 0 | BQ126: =IF(AA126>0,0,IF(Z126=$Z$90,AG126,0)) -> 0 | BR126: =IF(Z126=$Z$82,AA126*AG126,0) -> 0 | BS126: =IF(Z126=$Z$83,AA126*AG126,0) -> 0 | BT126: =IF(AA126<1,0,IF(Z126=$Z$84,AA126*AG126,IF(Z126=$Z$93,"ERRO",IF(Z126=$Z$100,"ERRO",0)))) -> 0 | BU126: =IF(AA126<1,0,IF(Z126=$Z$85,AA126*AG126,IF(Z126=$Z$93,"ERRO",IF(Z126=$Z$100,"ERRO",0)))) -> 0 | BV126: =IF(Z126=$Z$92,AA126*AG126,0) -> 0 | BW126: =IF(Z126=$Z$91,AA126*AG126,0) -> 0 | BX126: =IF(Z126=$Z$86,AA126*AG126,0) -> 0 | BY126: =IF(Z126=$Z$87,AA126*AG126,0) -> 0 | BZ126: =IF(Z126=$Z$88,AA126*AG126,0) -> 0 | CA126: =IF(Z126=$Z$89,AA126*AG126,0) -> 0 | CB126: =IF(Z126=$Z$90,AA126*AG126,0) -> 0 | CC126: =IFERROR(IF(L126=$L$49,AG126*AH126*(1+AI126)*(1-AK126)*(1-AL126),0),0) -> 0 | CD126: =IF(I126=$CD$97,1,IF(I126=$CD$100,2,IF(K126=$K$66,1,IF(K126=$K$69,1,3)))) -> 3 | CE126: =IF($CD126=1,1.07,IF($CD126=2,1.07,1.3)) -> 1.3 | CF126: =CG126*0.87 -> 1.74 | CG126: =IF($CD126=1,1.42,IF($CD126=2,1.47,2)) -> 2 | CH126: =CG126*1.09 -> 2.18 | CI126: =IF($CD126=1,1.7,IF($CD126=2,1.7,2.4)) -> 2.4 | CJ126: =CE126*$CJ$102 -> 1.274 | CK126: =CF126*$CK$102 -> 1.6182 | CL126: =CG126*$CL$102 -> 1.96 | CM126: =CH126*$CM$102 -> 2.1146 | CN126: =CI126*$CN$102 -> 2.304 | CO126: =CJ126*$CO$102 -> 1.22304 | CP126: =BF126-BA126 -> 2536.8945 | CQ126: =AQ126-CP126 -> 66967.065 | CR126: =BC126+BD126 -> 2536.8945
A127: =IF(AND('[1]Cockpit Retorno'!$E$67=Sim,Mestre!M127=Mestre!$M$98),0,1) -> 1 | B127: =IF(AND('[1]Cockpit Retorno'!$E$67=Sim,Mestre!L127=Mestre!$L$48),0,1) -> 0 | C127: =IF(AND('[1]Cockpit Retorno'!$E$67=Sim,Mestre!M127=Mestre!$M$97),0,1) -> 1 | D127: LOG_LOGM_TRS | F127: Nacional | H127: LOG COM | I127: =VLOOKUP(K127,$N$74:$O$95,2) -> Despesas | J127: ATK | K127: LOG | L127: ATM | M127: ATK | N127: NA | O127: COM | P127: NA | Q127: NA | R127: NA | S127: NA | T127: NA | U127: NA | V127: NA | W127: NA | X127: Logistica Operação Assistida - Instrumentação | Y127: NA | Z127: NA | AA127: 0 | AB127: NA | AC127: NA | AD127: NA | AF127: NA | AG127: 1 | AH127: 8403.2264 | AI127: 0 | AJ127: 0 | AM127: =(((IF(L127=$L$101,1,IF(L127=$L$47,1,0))*(AH127*(1-AK127)))*AG127)*(1-AL127)) -> 8403.2264 | AN127: =IF(K127=$K$50,AM127,IF(K127=$K$53,AM127,IF(K127=$K$54,AM127,IF(K127=$K$55,AM127,IF(K127=$K$56,AM127,IF(K127=$K$57,AM127,IF(K127=$K$58,AM127,IF(K127=$K$65,AM127,IF(K127=$K$66,AM127,IF(K127=$K$67,AM127,IF(K127=$K$68,AM127,IF(K127=$K$69,AM127,IF(K127=$K$51,AM127,(AM127*(1+AI127))))))))))))))) -> 8403.2264 | AO127: 1.6 | AP127: =AM127*AO127 -> 13445.162 | AQ127: =AP127*Fator_Venda -> 11649.767 | AR127: =AO127*AN127 -> 13445.162 | AS127: =IFERROR(IF($AX$94=0,(CQ127/AN127),CQ127/AM127),0) -> 1.3357429 | AT127: =K127 -> LOG | AU127: =I127 -> Despesas | AW127: =IF(K127=$K$50,0,IF(K127=$K$53,0,IF(K127=$K$54,0,IF(K127=$K$55,0,IF(K127=$K$56,0,IF(K127=$K$57,0,IF(K127=$K$58,0,IF(K127=$K$65,0,IF(K127=$K$66,0,IF(K127=$K$67,0,IF(K127=$K$68,0,IF(K127=$K$69,0,IF(K127=$K$51,0,1))))))))))))*AM127*AI127) -> 0 | AX127: =IF(K127=$K$50,0,IF(K127=$K$53,0,IF(K127=$K$54,0,IF(K127=$K$55,0,IF(K127=$K$56,0,IF(K127=$K$57,0,IF(K127=$K$58,0,IF(K127=$K$65,0,IF(K127=$K$66,0,IF(K127=$K$67,0,IF(K127=$K$68,0,IF(K127=$K$69,0,IF(K127=$K$51,0,1))))))))))))*AM127*AJ127*$AX$94) -> 0 | AY127: =IF(K127=$K$53,0,IF(K127=$K$54,0,IF(K127=$K$55,0,IF(K127=$K$56,0,IF(K127=$K$58,0,IF(K127=$K$50,0,IF(K127=$K$65,0,IF(K127=$K$57,0,IF(K127=$K$51,0,AM127*$AY$102))))))))) -> 0 | AZ127: =IF(K127=$K$53,0,IF(K127=$K$54,0,IF(K127=$K$55,0,IF(K127=$K$56,0,IF(K127=$K$58,0,IF(K127=$K$50,0,IF(K127=$K$65,0,IF(K127=$K$57,0,IF(K127=$K$51,0,AM127*$AZ$102))))))))) -> 0 | BA127: =AZ127+AY127+AX127 -> 0 | BB127: =IF($BA$97=1,AQ127*$BB$102,IF(K127=$K$50,0,IF(K127=$K$53,0,IF(K127=$K$54,0,IF(K127=$K$55,0,IF(K127=$K$56,0,IF(K127=$K$57,0,IF(K127=$K$58,0,IF(K127=$K$65,0,IF(K127=$K$66,0,IF(K127=$K$67,0,IF(K127=$K$68,0,IF(K127=$K$69,0,IF(K127=$K$51,0,1)))))))))))*AQ127*$BB$102))) -> 0 | BC127: =AQ127*$BC$102 -> 75.723484 | BD127: =$BD$102*AQ127 -> 349.493 | BE127: =IF($BE$95=I127,$BE$97,IF(I127=$BE$96,$BE$97,1))*($BE$102*AQ127)*$AZ$97 -> 0 | BF127: =IF('[1]Cockpit Retorno'!$C$65=Sim,Mestre!BA127,SUM(BB127:BE127)+(IF(K127=$K$56,AQ127*MOE_IRRF_LR,0))) -> 425.21649 | BG127: =IF(AA127>0,0,IF(Z127=$Z$82,AG127*1,(IF(Z127=$Z$81,AG127*1,0)))) -> 0 | BH127: =IF(AA127>0,0,IF(Z127=$Z$83,AG127*1,IF(Z127=$Z$81,AG127*1,0))) -> 0 | BI127: =IF(AA127>0,0,IF(Z127=$Z$84,AG127*1,IF(Z127=$Z$93,AG127*2,IF(Z127=$Z$100,AG127,IF(Z127=$Z$81,AG127*2,IF(Z127=$Z$80,AG127*1,IF(Z127=$Z$79,AG127*3,IF(Z127=$Z$78,AG127*2,0)))))))) -> 0 | BJ127: =IF(AA127>0,0,IF(Z127=$Z$85,AG127,IF(Z127=$Z$93,AG127,IF(Z127=$Z$100,AG127,IF(Z127=$Z$81,AG127*1,IF(Z127=$Z$80,AG127*2,IF(Z127=$Z$79,AG127*2,IF(Z127=$Z$78,AG127*2,0)))))))) -> 0 | BK127: =IF(AA127>0,0,IF(Z127=$Z$92,AG127,0)) -> 0 | BL127: =IF(AA127>0,0,IF(Z127=$Z$91,AG127,0)) -> 0 | BM127: =IF(AA127>0,0,IF(Z127=$Z$86,AG127,0)) -> 0 | BN127: =IF(AA127>0,0,IF(Z127=$Z$87,AG127,0)) -> 0 | BO127: =IF(AA127>0,0,IF(Z127=$Z$88,AG127,0)) -> 0 | BP127: =IF(AA127>0,0,IF(Z127=$Z$89,AG127,0)) -> 0 | BQ127: =IF(AA127>0,0,IF(Z127=$Z$90,AG127,0)) -> 0 | BR127: =IF(Z127=$Z$82,AA127*AG127,0) -> 0 | BS127: =IF(Z127=$Z$83,AA127*AG127,0) -> 0 | BT127: =IF(AA127<1,0,IF(Z127=$Z$84,AA127*AG127,IF(Z127=$Z$93,"ERRO",IF(Z127=$Z$100,"ERRO",0)))) -> 0 | BU127: =IF(AA127<1,0,IF(Z127=$Z$85,AA127*AG127,IF(Z127=$Z$93,"ERRO",IF(Z127=$Z$100,"ERRO",0)))) -> 0 | BV127: =IF(Z127=$Z$92,AA127*AG127,0) -> 0 | BW127: =IF(Z127=$Z$91,AA127*AG127,0) -> 0 | BX127: =IF(Z127=$Z$86,AA127*AG127,0) -> 0 | BY127: =IF(Z127=$Z$87,AA127*AG127,0) -> 0 | BZ127: =IF(Z127=$Z$88,AA127*AG127,0) -> 0 | CA127: =IF(Z127=$Z$89,AA127*AG127,0) -> 0 | CB127: =IF(Z127=$Z$90,AA127*AG127,0) -> 0 | CC127: =IFERROR(IF(L127=$L$49,AG127*AH127*(1+AI127)*(1-AK127)*(1-AL127),0),0) -> 0 | CD127: =IF(I127=$CD$97,1,IF(I127=$CD$100,2,IF(K127=$K$66,1,IF(K127=$K$69,1,3)))) -> 2 | CE127: =IF($CD127=1,1.07,IF($CD127=2,1.07,1.3)) -> 1.07 | CF127: =CG127*0.87 -> 1.2789 | CG127: =IF($CD127=1,1.42,IF($CD127=2,1.47,2)) -> 1.47 | CH127: =CG127*1.09 -> 1.6023 | CI127: =IF($CD127=1,1.7,IF($CD127=2,1.7,2.4)) -> 1.7 | CJ127: =CE127*$CJ$102 -> 1.0486 | CK127: =CF127*$CK$102 -> 1.189377 | CL127: =CG127*$CL$102 -> 1.4406 | CM127: =CH127*$CM$102 -> 1.554231 | CN127: =CI127*$CN$102 -> 1.632 | CO127: 1.3 | CP127: =BF127-BA127 -> 425.21649 | CQ127: =AQ127-CP127 -> 11224.55 | CR127: =BC127+BD127 -> 425.21649
A128: =IF(AND('[1]Cockpit Retorno'!$E$67=Sim,Mestre!M128=Mestre!$M$98),0,1) -> 1 | B128: =IF(AND('[1]Cockpit Retorno'!$E$67=Sim,Mestre!L128=Mestre!$L$48),0,1) -> 0 | C128: =IF(AND('[1]Cockpit Retorno'!$E$67=Sim,Mestre!M128=Mestre!$M$97),0,1) -> 1 | D128: MOE_MOC_SERV | F128: Nacional | H128: MOD | I128: =VLOOKUP(K128,$N$74:$O$95,2) -> Serviços | J128: ATK | K128: MOC | L128: ATM | M128: ATK | N128: NA | O128: COM | P128: NA | Q128: NA | R128: NA | S128: NA | T128: NA | U128: NA | V128: NA | W128: NA | X128: Comissionamento e Start Up - Elétrica | Y128: NA | Z128: NA | AA128: 0 | AB128: NA | AC128: NA | AD128: NA | AF128: NA | AG128: ='[1]Avulso HH'!C253 -> 810 | AH128: 30.486725 | AI128: 0 | AJ128: 0 | AM128: =(((IF(L128=$L$101,1,IF(L128=$L$47,1,0))*(AH128*(1-AK128)))*AG128)*(1-AL128)) -> 24694.247 | AN128: =IF(K128=$K$50,AM128,IF(K128=$K$53,AM128,IF(K128=$K$54,AM128,IF(K128=$K$55,AM128,IF(K128=$K$56,AM128,IF(K128=$K$57,AM128,IF(K128=$K$58,AM128,IF(K128=$K$65,AM128,IF(K128=$K$66,AM128,IF(K128=$K$67,AM128,IF(K128=$K$68,AM128,IF(K128=$K$69,AM128,IF(K128=$K$51,AM128,(AM128*(1+AI128))))))))))))))) -> 24694.247 | AO128: 1.9 | AP128: =AM128*AO128 -> 46919.07 | AQ128: =AP128*Fator_Venda -> 40653.747 | AR128: =AO128*AN128 -> 46919.07 | AS128: =IFERROR(IF($AX$94=0,(CQ128/AN128),CQ128/AM128),0) -> 1.5861947 | AT128: =K128 -> MOC | AU128: =I128 -> Serviços | AW128: =IF(K128=$K$50,0,IF(K128=$K$53,0,IF(K128=$K$54,0,IF(K128=$K$55,0,IF(K128=$K$56,0,IF(K128=$K$57,0,IF(K128=$K$58,0,IF(K128=$K$65,0,IF(K128=$K$66,0,IF(K128=$K$67,0,IF(K128=$K$68,0,IF(K128=$K$69,0,IF(K128=$K$51,0,1))))))))))))*AM128*AI128) -> 0 | AX128: =IF(K128=$K$50,0,IF(K128=$K$53,0,IF(K128=$K$54,0,IF(K128=$K$55,0,IF(K128=$K$56,0,IF(K128=$K$57,0,IF(K128=$K$58,0,IF(K128=$K$65,0,IF(K128=$K$66,0,IF(K128=$K$67,0,IF(K128=$K$68,0,IF(K128=$K$69,0,IF(K128=$K$51,0,1))))))))))))*AM128*AJ128*$AX$94) -> 0 | AY128: =IF(K128=$K$53,0,IF(K128=$K$54,0,IF(K128=$K$55,0,IF(K128=$K$56,0,IF(K128=$K$58,0,IF(K128=$K$50,0,IF(K128=$K$65,0,IF(K128=$K$57,0,IF(K128=$K$51,0,AM128*$AY$102))))))))) -> 0 | AZ128: =IF(K128=$K$53,0,IF(K128=$K$54,0,IF(K128=$K$55,0,IF(K128=$K$56,0,IF(K128=$K$58,0,IF(K128=$K$50,0,IF(K128=$K$65,0,IF(K128=$K$57,0,IF(K128=$K$51,0,AM128*$AZ$102))))))))) -> 0 | BA128: =AZ128+AY128+AX128 -> 0 | BB128: =IF($BA$97=1,AQ128*$BB$102,IF(K128=$K$50,0,IF(K128=$K$53,0,IF(K128=$K$54,0,IF(K128=$K$55,0,IF(K128=$K$56,0,IF(K128=$K$57,0,IF(K128=$K$58,0,IF(K128=$K$65,0,IF(K128=$K$66,0,IF(K128=$K$67,0,IF(K128=$K$68,0,IF(K128=$K$69,0,IF(K128=$K$51,0,1)))))))))))*AQ128*$BB$102))) -> 0 | BC128: =AQ128*$BC$102 -> 264.24935 | BD128: =$BD$102*AQ128 -> 1219.6124 | BE128: =IF($BE$95=I128,$BE$97,IF(I128=$BE$96,$BE$97,1))*($BE$102*AQ128)*$AZ$97 -> 0 | BF128: =IF('[1]Cockpit Retorno'!$C$65=Sim,Mestre!BA128,SUM(BB128:BE128)+(IF(K128=$K$56,AQ128*MOE_IRRF_LR,0))) -> 1483.8617 | BG128: =IF(AA128>0,0,IF(Z128=$Z$82,AG128*1,(IF(Z128=$Z$81,AG128*1,0)))) -> 0 | BH128: =IF(AA128>0,0,IF(Z128=$Z$83,AG128*1,IF(Z128=$Z$81,AG128*1,0))) -> 0 | BI128: =IF(AA128>0,0,IF(Z128=$Z$84,AG128*1,IF(Z128=$Z$93,AG128*2,IF(Z128=$Z$100,AG128,IF(Z128=$Z$81,AG128*2,IF(Z128=$Z$80,AG128*1,IF(Z128=$Z$79,AG128*3,IF(Z128=$Z$78,AG128*2,0)))))))) -> 0 | BJ128: =IF(AA128>0,0,IF(Z128=$Z$85,AG128,IF(Z128=$Z$93,AG128,IF(Z128=$Z$100,AG128,IF(Z128=$Z$81,AG128*1,IF(Z128=$Z$80,AG128*2,IF(Z128=$Z$79,AG128*2,IF(Z128=$Z$78,AG128*2,0)))))))) -> 0 | BK128: =IF(AA128>0,0,IF(Z128=$Z$92,AG128,0)) -> 0 | BL128: =IF(AA128>0,0,IF(Z128=$Z$91,AG128,0)) -> 0 | BM128: =IF(AA128>0,0,IF(Z128=$Z$86,AG128,0)) -> 0 | BN128: =IF(AA128>0,0,IF(Z128=$Z$87,AG128,0)) -> 0 | BO128: =IF(AA128>0,0,IF(Z128=$Z$88,AG128,0)) -> 0 | BP128: =IF(AA128>0,0,IF(Z128=$Z$89,AG128,0)) -> 0 | BQ128: =IF(AA128>0,0,IF(Z128=$Z$90,AG128,0)) -> 0 | BR128: =IF(Z128=$Z$82,AA128*AG128,0) -> 0 | BS128: =IF(Z128=$Z$83,AA128*AG128,0) -> 0 | BT128: =IF(AA128<1,0,IF(Z128=$Z$84,AA128*AG128,IF(Z128=$Z$93,"ERRO",IF(Z128=$Z$100,"ERRO",0)))) -> 0 | BU128: =IF(AA128<1,0,IF(Z128=$Z$85,AA128*AG128,IF(Z128=$Z$93,"ERRO",IF(Z128=$Z$100,"ERRO",0)))) -> 0 | BV128: =IF(Z128=$Z$92,AA128*AG128,0) -> 0 | BW128: =IF(Z128=$Z$91,AA128*AG128,0) -> 0 | BX128: =IF(Z128=$Z$86,AA128*AG128,0) -> 0 | BY128: =IF(Z128=$Z$87,AA128*AG128,0) -> 0 | BZ128: =IF(Z128=$Z$88,AA128*AG128,0) -> 0 | CA128: =IF(Z128=$Z$89,AA128*AG128,0) -> 0 | CB128: =IF(Z128=$Z$90,AA128*AG128,0) -> 0 | CC128: =IFERROR(IF(L128=$L$49,AG128*AH128*(1+AI128)*(1-AK128)*(1-AL128),0),0) -> 0 | CD128: =IF(I128=$CD$97,1,IF(I128=$CD$100,2,IF(K128=$K$66,1,IF(K128=$K$69,1,3)))) -> 3 | CE128: =IF($CD128=1,1.07,IF($CD128=2,1.07,1.3)) -> 1.3 | CF128: =CG128*0.87 -> 1.74 | CG128: =IF($CD128=1,1.42,IF($CD128=2,1.47,2)) -> 2 | CH128: =CG128*1.09 -> 2.18 | CI128: =IF($CD128=1,1.7,IF($CD128=2,1.7,2.4)) -> 2.4 | CJ128: =CE128*$CJ$102 -> 1.274 | CK128: =CF128*$CK$102 -> 1.6182 | CL128: =CG128*$CL$102 -> 1.96 | CM128: =CH128*$CM$102 -> 2.1146 | CN128: =CI128*$CN$102 -> 2.304 | CO128: =CJ128*$CO$102 -> 1.22304 | CP128: =BF128-BA128 -> 1483.8617 | CQ128: =AQ128-CP128 -> 39169.885 | CR128: =BC128+BD128 -> 1483.8617
A129: =IF(AND('[1]Cockpit Retorno'!$E$67=Sim,Mestre!M129=Mestre!$M$98),0,1) -> 1 | B129: =IF(AND('[1]Cockpit Retorno'!$E$67=Sim,Mestre!L129=Mestre!$L$48),0,1) -> 0 | C129: =IF(AND('[1]Cockpit Retorno'!$E$67=Sim,Mestre!M129=Mestre!$M$97),0,1) -> 1 | D129: LOG_LOGM_TRS | F129: Nacional | H129: LOG MON | I129: =VLOOKUP(K129,$N$74:$O$95,2) -> Despesas | J129: ATK | K129: LOG | L129: ATM | M129: ATK | N129: NA | O129: COM | P129: NA | Q129: NA | R129: NA | S129: NA | T129: NA | U129: NA | V129: NA | W129: NA | X129: Logistica Comissionamento e Start Up - Inst - Elétrica | Y129: NA | Z129: NA | AA129: 0 | AB129: NA | AC129: NA | AD129: NA | AF129: NA | AG129: 1 | AH129: 16793.01 | AI129: 0 | AJ129: 0 | AM129: =(((IF(L129=$L$101,1,IF(L129=$L$47,1,0))*(AH129*(1-AK129)))*AG129)*(1-AL129)) -> 16793.01 | AN129: =IF(K129=$K$50,AM129,IF(K129=$K$53,AM129,IF(K129=$K$54,AM129,IF(K129=$K$55,AM129,IF(K129=$K$56,AM129,IF(K129=$K$57,AM129,IF(K129=$K$58,AM129,IF(K129=$K$65,AM129,IF(K129=$K$66,AM129,IF(K129=$K$67,AM129,IF(K129=$K$68,AM129,IF(K129=$K$69,AM129,IF(K129=$K$51,AM129,(AM129*(1+AI129))))))))))))))) -> 16793.01 | AO129: 1.6 | AP129: =AM129*AO129 -> 26868.816 | AQ129: =AP129*Fator_Venda -> 23280.897 | AR129: =AO129*AN129 -> 26868.816 | AS129: =IFERROR(IF($AX$94=0,(CQ129/AN129),CQ129/AM129),0) -> 1.3357429 | AT129: =K129 -> LOG | AU129: =I129 -> Despesas | AW129: =IF(K129=$K$50,0,IF(K129=$K$53,0,IF(K129=$K$54,0,IF(K129=$K$55,0,IF(K129=$K$56,0,IF(K129=$K$57,0,IF(K129=$K$58,0,IF(K129=$K$65,0,IF(K129=$K$66,0,IF(K129=$K$67,0,IF(K129=$K$68,0,IF(K129=$K$69,0,IF(K129=$K$51,0,1))))))))))))*AM129*AI129) -> 0 | AX129: =IF(K129=$K$50,0,IF(K129=$K$53,0,IF(K129=$K$54,0,IF(K129=$K$55,0,IF(K129=$K$56,0,IF(K129=$K$57,0,IF(K129=$K$58,0,IF(K129=$K$65,0,IF(K129=$K$66,0,IF(K129=$K$67,0,IF(K129=$K$68,0,IF(K129=$K$69,0,IF(K129=$K$51,0,1))))))))))))*AM129*AJ129*$AX$94) -> 0 | AY129: =IF(K129=$K$53,0,IF(K129=$K$54,0,IF(K129=$K$55,0,IF(K129=$K$56,0,IF(K129=$K$58,0,IF(K129=$K$50,0,IF(K129=$K$65,0,IF(K129=$K$57,0,IF(K129=$K$51,0,AM129*$AY$102))))))))) -> 0 | AZ129: =IF(K129=$K$53,0,IF(K129=$K$54,0,IF(K129=$K$55,0,IF(K129=$K$56,0,IF(K129=$K$58,0,IF(K129=$K$50,0,IF(K129=$K$65,0,IF(K129=$K$57,0,IF(K129=$K$51,0,AM129*$AZ$102))))))))) -> 0 | BA129: =AZ129+AY129+AX129 -> 0 | BB129: =IF($BA$97=1,AQ129*$BB$102,IF(K129=$K$50,0,IF(K129=$K$53,0,IF(K129=$K$54,0,IF(K129=$K$55,0,IF(K129=$K$56,0,IF(K129=$K$57,0,IF(K129=$K$58,0,IF(K129=$K$65,0,IF(K129=$K$66,0,IF(K129=$K$67,0,IF(K129=$K$68,0,IF(K129=$K$69,0,IF(K129=$K$51,0,1)))))))))))*AQ129*$BB$102))) -> 0 | BC129: =AQ129*$BC$102 -> 151.32583 | BD129: =$BD$102*AQ129 -> 698.42691 | BE129: =IF($BE$95=I129,$BE$97,IF(I129=$BE$96,$BE$97,1))*($BE$102*AQ129)*$AZ$97 -> 0 | BF129: =IF('[1]Cockpit Retorno'!$C$65=Sim,Mestre!BA129,SUM(BB129:BE129)+(IF(K129=$K$56,AQ129*MOE_IRRF_LR,0))) -> 849.75275 | BG129: =IF(AA129>0,0,IF(Z129=$Z$82,AG129*1,(IF(Z129=$Z$81,AG129*1,0)))) -> 0 | BH129: =IF(AA129>0,0,IF(Z129=$Z$83,AG129*1,IF(Z129=$Z$81,AG129*1,0))) -> 0 | BI129: =IF(AA129>0,0,IF(Z129=$Z$84,AG129*1,IF(Z129=$Z$93,AG129*2,IF(Z129=$Z$100,AG129,IF(Z129=$Z$81,AG129*2,IF(Z129=$Z$80,AG129*1,IF(Z129=$Z$79,AG129*3,IF(Z129=$Z$78,AG129*2,0)))))))) -> 0 | BJ129: =IF(AA129>0,0,IF(Z129=$Z$85,AG129,IF(Z129=$Z$93,AG129,IF(Z129=$Z$100,AG129,IF(Z129=$Z$81,AG129*1,IF(Z129=$Z$80,AG129*2,IF(Z129=$Z$79,AG129*2,IF(Z129=$Z$78,AG129*2,0)))))))) -> 0 | BK129: =IF(AA129>0,0,IF(Z129=$Z$92,AG129,0)) -> 0 | BL129: =IF(AA129>0,0,IF(Z129=$Z$91,AG129,0)) -> 0 | BM129: =IF(AA129>0,0,IF(Z129=$Z$86,AG129,0)) -> 0 | BN129: =IF(AA129>0,0,IF(Z129=$Z$87,AG129,0)) -> 0 | BO129: =IF(AA129>0,0,IF(Z129=$Z$88,AG129,0)) -> 0 | BP129: =IF(AA129>0,0,IF(Z129=$Z$89,AG129,0)) -> 0 | BQ129: =IF(AA129>0,0,IF(Z129=$Z$90,AG129,0)) -> 0 | BR129: =IF(Z129=$Z$82,AA129*AG129,0) -> 0 | BS129: =IF(Z129=$Z$83,AA129*AG129,0) -> 0 | BT129: =IF(AA129<1,0,IF(Z129=$Z$84,AA129*AG129,IF(Z129=$Z$93,"ERRO",IF(Z129=$Z$100,"ERRO",0)))) -> 0 | BU129: =IF(AA129<1,0,IF(Z129=$Z$85,AA129*AG129,IF(Z129=$Z$93,"ERRO",IF(Z129=$Z$100,"ERRO",0)))) -> 0 | BV129: =IF(Z129=$Z$92,AA129*AG129,0) -> 0 | BW129: =IF(Z129=$Z$91,AA129*AG129,0) -> 0 | BX129: =IF(Z129=$Z$86,AA129*AG129,0) -> 0 | BY129: =IF(Z129=$Z$87,AA129*AG129,0) -> 0 | BZ129: =IF(Z129=$Z$88,AA129*AG129,0) -> 0 | CA129: =IF(Z129=$Z$89,AA129*AG129,0) -> 0 | CB129: =IF(Z129=$Z$90,AA129*AG129,0) -> 0 | CC129: =IFERROR(IF(L129=$L$49,AG129*AH129*(1+AI129)*(1-AK129)*(1-AL129),0),0) -> 0 | CD129: =IF(I129=$CD$97,1,IF(I129=$CD$100,2,IF(K129=$K$66,1,IF(K129=$K$69,1,3)))) -> 2 | CE129: =IF($CD129=1,1.07,IF($CD129=2,1.07,1.3)) -> 1.07 | CF129: =CG129*0.87 -> 1.2789 | CG129: =IF($CD129=1,1.42,IF($CD129=2,1.47,2)) -> 1.47 | CH129: =CG129*1.09 -> 1.6023 | CI129: =IF($CD129=1,1.7,IF($CD129=2,1.7,2.4)) -> 1.7 | CJ129: =CE129*$CJ$102 -> 1.0486 | CK129: =CF129*$CK$102 -> 1.189377 | CL129: =CG129*$CL$102 -> 1.4406 | CM129: =CH129*$CM$102 -> 1.554231 | CN129: =CI129*$CN$102 -> 1.632 | CO129: 1.3 | CP129: =BF129-BA129 -> 849.75275 | CQ129: =AQ129-CP129 -> 22431.144 | CR129: =BC129+BD129 -> 849.75275
A130: =IF(AND('[1]Cockpit Retorno'!$E$67=Sim,Mestre!M130=Mestre!$M$98),0,1) -> 1 | B130: =IF(AND('[1]Cockpit Retorno'!$E$67=Sim,Mestre!L130=Mestre!$L$48),0,1) -> 0 | C130: =IF(AND('[1]Cockpit Retorno'!$E$67=Sim,Mestre!M130=Mestre!$M$97),0,1) -> 1 | D130: MOE_MOC_SERV | F130: Nacional | H130: MOD | I130: =VLOOKUP(K130,$N$74:$O$95,2) -> Serviços | J130: ATK | K130: MOC | L130: ATM | M130: ATK | N130: NA | O130: COM | P130: NA | Q130: NA | R130: NA | S130: NA | T130: NA | U130: NA | V130: NA | W130: NA | X130: Operação Assistida - Elétrica | Y130: NA | Z130: NA | AA130: 0 | AB130: NA | AC130: NA | AD130: NA | AF130: NA | AG130: ='[1]Avulso HH'!M253 -> 270 | AH130: 30.486725 | AI130: 0 | AJ130: 0 | AM130: =(((IF(L130=$L$101,1,IF(L130=$L$47,1,0))*(AH130*(1-AK130)))*AG130)*(1-AL130)) -> 8231.4157 | AN130: =IF(K130=$K$50,AM130,IF(K130=$K$53,AM130,IF(K130=$K$54,AM130,IF(K130=$K$55,AM130,IF(K130=$K$56,AM130,IF(K130=$K$57,AM130,IF(K130=$K$58,AM130,IF(K130=$K$65,AM130,IF(K130=$K$66,AM130,IF(K130=$K$67,AM130,IF(K130=$K$68,AM130,IF(K130=$K$69,AM130,IF(K130=$K$51,AM130,(AM130*(1+AI130))))))))))))))) -> 8231.4157 | AO130: 1.9 | AP130: =AM130*AO130 -> 15639.69 | AQ130: =AP130*Fator_Venda -> 13551.249 | AR130: =AO130*AN130 -> 15639.69 | AS130: =IFERROR(IF($AX$94=0,(CQ130/AN130),CQ130/AM130),0) -> 1.5861947 | AT130: =K130 -> MOC | AU130: =I130 -> Serviços | AW130: =IF(K130=$K$50,0,IF(K130=$K$53,0,IF(K130=$K$54,0,IF(K130=$K$55,0,IF(K130=$K$56,0,IF(K130=$K$57,0,IF(K130=$K$58,0,IF(K130=$K$65,0,IF(K130=$K$66,0,IF(K130=$K$67,0,IF(K130=$K$68,0,IF(K130=$K$69,0,IF(K130=$K$51,0,1))))))))))))*AM130*AI130) -> 0 | AX130: =IF(K130=$K$50,0,IF(K130=$K$53,0,IF(K130=$K$54,0,IF(K130=$K$55,0,IF(K130=$K$56,0,IF(K130=$K$57,0,IF(K130=$K$58,0,IF(K130=$K$65,0,IF(K130=$K$66,0,IF(K130=$K$67,0,IF(K130=$K$68,0,IF(K130=$K$69,0,IF(K130=$K$51,0,1))))))))))))*AM130*AJ130*$AX$94) -> 0 | AY130: =IF(K130=$K$53,0,IF(K130=$K$54,0,IF(K130=$K$55,0,IF(K130=$K$56,0,IF(K130=$K$58,0,IF(K130=$K$50,0,IF(K130=$K$65,0,IF(K130=$K$57,0,IF(K130=$K$51,0,AM130*$AY$102))))))))) -> 0 | AZ130: =IF(K130=$K$53,0,IF(K130=$K$54,0,IF(K130=$K$55,0,IF(K130=$K$56,0,IF(K130=$K$58,0,IF(K130=$K$50,0,IF(K130=$K$65,0,IF(K130=$K$57,0,IF(K130=$K$51,0,AM130*$AZ$102))))))))) -> 0 | BA130: =AZ130+AY130+AX130 -> 0 | BB130: =IF($BA$97=1,AQ130*$BB$102,IF(K130=$K$50,0,IF(K130=$K$53,0,IF(K130=$K$54,0,IF(K130=$K$55,0,IF(K130=$K$56,0,IF(K130=$K$57,0,IF(K130=$K$58,0,IF(K130=$K$65,0,IF(K130=$K$66,0,IF(K130=$K$67,0,IF(K130=$K$68,0,IF(K130=$K$69,0,IF(K130=$K$51,0,1)))))))))))*AQ130*$BB$102))) -> 0 | BC130: =AQ130*$BC$102 -> 88.083117 | BD130: =$BD$102*AQ130 -> 406.53747 | BE130: =IF($BE$95=I130,$BE$97,IF(I130=$BE$96,$BE$97,1))*($BE$102*AQ130)*$AZ$97 -> 0 | BF130: =IF('[1]Cockpit Retorno'!$C$65=Sim,Mestre!BA130,SUM(BB130:BE130)+(IF(K130=$K$56,AQ130*MOE_IRRF_LR,0))) -> 494.62058 | BG130: =IF(AA130>0,0,IF(Z130=$Z$82,AG130*1,(IF(Z130=$Z$81,AG130*1,0)))) -> 0 | BH130: =IF(AA130>0,0,IF(Z130=$Z$83,AG130*1,IF(Z130=$Z$81,AG130*1,0))) -> 0 | BI130: =IF(AA130>0,0,IF(Z130=$Z$84,AG130*1,IF(Z130=$Z$93,AG130*2,IF(Z130=$Z$100,AG130,IF(Z130=$Z$81,AG130*2,IF(Z130=$Z$80,AG130*1,IF(Z130=$Z$79,AG130*3,IF(Z130=$Z$78,AG130*2,0)))))))) -> 0 | BJ130: =IF(AA130>0,0,IF(Z130=$Z$85,AG130,IF(Z130=$Z$93,AG130,IF(Z130=$Z$100,AG130,IF(Z130=$Z$81,AG130*1,IF(Z130=$Z$80,AG130*2,IF(Z130=$Z$79,AG130*2,IF(Z130=$Z$78,AG130*2,0)))))))) -> 0 | BK130: =IF(AA130>0,0,IF(Z130=$Z$92,AG130,0)) -> 0 | BL130: =IF(AA130>0,0,IF(Z130=$Z$91,AG130,0)) -> 0 | BM130: =IF(AA130>0,0,IF(Z130=$Z$86,AG130,0)) -> 0 | BN130: =IF(AA130>0,0,IF(Z130=$Z$87,AG130,0)) -> 0 | BO130: =IF(AA130>0,0,IF(Z130=$Z$88,AG130,0)) -> 0 | BP130: =IF(AA130>0,0,IF(Z130=$Z$89,AG130,0)) -> 0 | BQ130: =IF(AA130>0,0,IF(Z130=$Z$90,AG130,0)) -> 0 | BR130: =IF(Z130=$Z$82,AA130*AG130,0) -> 0 | BS130: =IF(Z130=$Z$83,AA130*AG130,0) -> 0 | BT130: =IF(AA130<1,0,IF(Z130=$Z$84,AA130*AG130,IF(Z130=$Z$93,"ERRO",IF(Z130=$Z$100,"ERRO",0)))) -> 0 | BU130: =IF(AA130<1,0,IF(Z130=$Z$85,AA130*AG130,IF(Z130=$Z$93,"ERRO",IF(Z130=$Z$100,"ERRO",0)))) -> 0 | BV130: =IF(Z130=$Z$92,AA130*AG130,0) -> 0 | BW130: =IF(Z130=$Z$91,AA130*AG130,0) -> 0 | BX130: =IF(Z130=$Z$86,AA130*AG130,0) -> 0 | BY130: =IF(Z130=$Z$87,AA130*AG130,0) -> 0 | BZ130: =IF(Z130=$Z$88,AA130*AG130,0) -> 0 | CA130: =IF(Z130=$Z$89,AA130*AG130,0) -> 0 | CB130: =IF(Z130=$Z$90,AA130*AG130,0) -> 0 | CC130: =IFERROR(IF(L130=$L$49,AG130*AH130*(1+AI130)*(1-AK130)*(1-AL130),0),0) -> 0 | CD130: =IF(I130=$CD$97,1,IF(I130=$CD$100,2,IF(K130=$K$66,1,IF(K130=$K$69,1,3)))) -> 3 | CE130: =IF($CD130=1,1.07,IF($CD130=2,1.07,1.3)) -> 1.3 | CF130: =CG130*0.87 -> 1.74 | CG130: =IF($CD130=1,1.42,IF($CD130=2,1.47,2)) -> 2 | CH130: =CG130*1.09 -> 2.18 | CI130: =IF($CD130=1,1.7,IF($CD130=2,1.7,2.4)) -> 2.4 | CJ130: =CE130*$CJ$102 -> 1.274 | CK130: =CF130*$CK$102 -> 1.6182 | CL130: =CG130*$CL$102 -> 1.96 | CM130: =CH130*$CM$102 -> 2.1146 | CN130: =CI130*$CN$102 -> 2.304 | CO130: =CJ130*$CO$102 -> 1.22304 | CP130: =BF130-BA130 -> 494.62058 | CQ130: =AQ130-CP130 -> 13056.628 | CR130: =BC130+BD130 -> 494.62058
A131: =IF(AND('[1]Cockpit Retorno'!$E$67=Sim,Mestre!M131=Mestre!$M$98),0,1) -> 1 | B131: =IF(AND('[1]Cockpit Retorno'!$E$67=Sim,Mestre!L131=Mestre!$L$48),0,1) -> 0 | C131: =IF(AND('[1]Cockpit Retorno'!$E$67=Sim,Mestre!M131=Mestre!$M$97),0,1) -> 1 | D131: LOG_LOGM_TRS | F131: Nacional | H131: LOG MON | I131: =VLOOKUP(K131,$N$74:$O$95,2) -> Despesas | J131: ATK | K131: LOG | L131: ATM | M131: ATK | N131: NA | O131: COM | P131: NA | Q131: NA | R131: NA | S131: NA | T131: NA | U131: NA | V131: NA | W131: NA | X131: Logistica Operação Assistida - Elétrica | Y131: NA | Z131: NA | AA131: 0 | AB131: NA | AC131: NA | AD131: NA | AF131: NA | AG131: 1 | AH131: 5746.47 | AI131: 0 | AJ131: 0 | AM131: =(((IF(L131=$L$101,1,IF(L131=$L$47,1,0))*(AH131*(1-AK131)))*AG131)*(1-AL131)) -> 5746.47 | AN131: =IF(K131=$K$50,AM131,IF(K131=$K$53,AM131,IF(K131=$K$54,AM131,IF(K131=$K$55,AM131,IF(K131=$K$56,AM131,IF(K131=$K$57,AM131,IF(K131=$K$58,AM131,IF(K131=$K$65,AM131,IF(K131=$K$66,AM131,IF(K131=$K$67,AM131,IF(K131=$K$68,AM131,IF(K131=$K$69,AM131,IF(K131=$K$51,AM131,(AM131*(1+AI131))))))))))))))) -> 5746.47 | AO131: 1.6 | AP131: =AM131*AO131 -> 9194.352 | AQ131: =AP131*Fator_Venda -> 7966.5871 | AR131: =AO131*AN131 -> 9194.352 | AS131: =IFERROR(IF($AX$94=0,(CQ131/AN131),CQ131/AM131),0) -> 1.3357429 | AT131: =K131 -> LOG | AU131: =I131 -> Despesas | AW131: =IF(K131=$K$50,0,IF(K131=$K$53,0,IF(K131=$K$54,0,IF(K131=$K$55,0,IF(K131=$K$56,0,IF(K131=$K$57,0,IF(K131=$K$58,0,IF(K131=$K$65,0,IF(K131=$K$66,0,IF(K131=$K$67,0,IF(K131=$K$68,0,IF(K131=$K$69,0,IF(K131=$K$51,0,1))))))))))))*AM131*AI131) -> 0 | AX131: =IF(K131=$K$50,0,IF(K131=$K$53,0,IF(K131=$K$54,0,IF(K131=$K$55,0,IF(K131=$K$56,0,IF(K131=$K$57,0,IF(K131=$K$58,0,IF(K131=$K$65,0,IF(K131=$K$66,0,IF(K131=$K$67,0,IF(K131=$K$68,0,IF(K131=$K$69,0,IF(K131=$K$51,0,1))))))))))))*AM131*AJ131*$AX$94) -> 0 | AY131: =IF(K131=$K$53,0,IF(K131=$K$54,0,IF(K131=$K$55,0,IF(K131=$K$56,0,IF(K131=$K$58,0,IF(K131=$K$50,0,IF(K131=$K$65,0,IF(K131=$K$57,0,IF(K131=$K$51,0,AM131*$AY$102))))))))) -> 0 | AZ131: =IF(K131=$K$53,0,IF(K131=$K$54,0,IF(K131=$K$55,0,IF(K131=$K$56,0,IF(K131=$K$58,0,IF(K131=$K$50,0,IF(K131=$K$65,0,IF(K131=$K$57,0,IF(K131=$K$51,0,AM131*$AZ$102))))))))) -> 0 | BA131: =AZ131+AY131+AX131 -> 0 | BB131: =IF($BA$97=1,AQ131*$BB$102,IF(K131=$K$50,0,IF(K131=$K$53,0,IF(K131=$K$54,0,IF(K131=$K$55,0,IF(K131=$K$56,0,IF(K131=$K$57,0,IF(K131=$K$58,0,IF(K131=$K$65,0,IF(K131=$K$66,0,IF(K131=$K$67,0,IF(K131=$K$68,0,IF(K131=$K$69,0,IF(K131=$K$51,0,1)))))))))))*AQ131*$BB$102))) -> 0 | BC131: =AQ131*$BC$102 -> 51.782816 | BD131: =$BD$102*AQ131 -> 238.99761 | BE131: =IF($BE$95=I131,$BE$97,IF(I131=$BE$96,$BE$97,1))*($BE$102*AQ131)*$AZ$97 -> 0 | BF131: =IF('[1]Cockpit Retorno'!$C$65=Sim,Mestre!BA131,SUM(BB131:BE131)+(IF(K131=$K$56,AQ131*MOE_IRRF_LR,0))) -> 290.78043 | BG131: =IF(AA131>0,0,IF(Z131=$Z$82,AG131*1,(IF(Z131=$Z$81,AG131*1,0)))) -> 0 | BH131: =IF(AA131>0,0,IF(Z131=$Z$83,AG131*1,IF(Z131=$Z$81,AG131*1,0))) -> 0 | BI131: =IF(AA131>0,0,IF(Z131=$Z$84,AG131*1,IF(Z131=$Z$93,AG131*2,IF(Z131=$Z$100,AG131,IF(Z131=$Z$81,AG131*2,IF(Z131=$Z$80,AG131*1,IF(Z131=$Z$79,AG131*3,IF(Z131=$Z$78,AG131*2,0)))))))) -> 0 | BJ131: =IF(AA131>0,0,IF(Z131=$Z$85,AG131,IF(Z131=$Z$93,AG131,IF(Z131=$Z$100,AG131,IF(Z131=$Z$81,AG131*1,IF(Z131=$Z$80,AG131*2,IF(Z131=$Z$79,AG131*2,IF(Z131=$Z$78,AG131*2,0)))))))) -> 0 | BK131: =IF(AA131>0,0,IF(Z131=$Z$92,AG131,0)) -> 0 | BL131: =IF(AA131>0,0,IF(Z131=$Z$91,AG131,0)) -> 0 | BM131: =IF(AA131>0,0,IF(Z131=$Z$86,AG131,0)) -> 0 | BN131: =IF(AA131>0,0,IF(Z131=$Z$87,AG131,0)) -> 0 | BO131: =IF(AA131>0,0,IF(Z131=$Z$88,AG131,0)) -> 0 | BP131: =IF(AA131>0,0,IF(Z131=$Z$89,AG131,0)) -> 0 | BQ131: =IF(AA131>0,0,IF(Z131=$Z$90,AG131,0)) -> 0 | BR131: =IF(Z131=$Z$82,AA131*AG131,0) -> 0 | BS131: =IF(Z131=$Z$83,AA131*AG131,0) -> 0 | BT131: =IF(AA131<1,0,IF(Z131=$Z$84,AA131*AG131,IF(Z131=$Z$93,"ERRO",IF(Z131=$Z$100,"ERRO",0)))) -> 0 | BU131: =IF(AA131<1,0,IF(Z131=$Z$85,AA131*AG131,IF(Z131=$Z$93,"ERRO",IF(Z131=$Z$100,"ERRO",0)))) -> 0 | BV131: =IF(Z131=$Z$92,AA131*AG131,0) -> 0 | BW131: =IF(Z131=$Z$91,AA131*AG131,0) -> 0 | BX131: =IF(Z131=$Z$86,AA131*AG131,0) -> 0 | BY131: =IF(Z131=$Z$87,AA131*AG131,0) -> 0 | BZ131: =IF(Z131=$Z$88,AA131*AG131,0) -> 0 | CA131: =IF(Z131=$Z$89,AA131*AG131,0) -> 0 | CB131: =IF(Z131=$Z$90,AA131*AG131,0) -> 0 | CC131: =IFERROR(IF(L131=$L$49,AG131*AH131*(1+AI131)*(1-AK131)*(1-AL131),0),0) -> 0 | CD131: =IF(I131=$CD$97,1,IF(I131=$CD$100,2,IF(K131=$K$66,1,IF(K131=$K$69,1,3)))) -> 2 | CE131: =IF($CD131=1,1.07,IF($CD131=2,1.07,1.3)) -> 1.07 | CF131: =CG131*0.87 -> 1.2789 | CG131: =IF($CD131=1,1.42,IF($CD131=2,1.47,2)) -> 1.47 | CH131: =CG131*1.09 -> 1.6023 | CI131: =IF($CD131=1,1.7,IF($CD131=2,1.7,2.4)) -> 1.7 | CJ131: =CE131*$CJ$102 -> 1.0486 | CK131: =CF131*$CK$102 -> 1.189377 | CL131: =CG131*$CL$102 -> 1.4406 | CM131: =CH131*$CM$102 -> 1.554231 | CN131: =CI131*$CN$102 -> 1.632 | CO131: 1.3 | CP131: =BF131-BA131 -> 290.78043 | CQ131: =AQ131-CP131 -> 7675.8067 | CR131: =BC131+BD131 -> 290.78043
A132: =IF(AND('[1]Cockpit Retorno'!$E$67=Sim,Mestre!M132=Mestre!$M$98),0,1) -> 1 | B132: =IF(AND('[1]Cockpit Retorno'!$E$67=Sim,Mestre!L132=Mestre!$L$48),0,1) -> 0 | C132: =IF(AND('[1]Cockpit Retorno'!$E$67=Sim,Mestre!M132=Mestre!$M$97),0,1) -> 1 | D132: MOE_MOC_SERV | F132: Nacional | H132: MOE | I132: =VLOOKUP(K132,$N$74:$O$95,2) -> Serviços | J132: ATK | K132: MOE | L132: ATM | M132: ATK | N132: NA | O132: ENG | P132: NA | Q132: NA | R132: NA | S132: NA | T132: NA | U132: NA | V132: NA | W132: NA | X132: Serviços de engenharia | Y132: NA | Z132: NA | AA132: 0 | AB132: NA | AC132: NA | AD132: NA | AF132: NA | AG132: =ROUNDUP([1]PHEA!F27,0) -> 181 | AH132: 78.681074 | AI132: 0 | AJ132: 0 | AM132: =(((IF(L132=$L$101,1,IF(L132=$L$47,1,0))*(AH132*(1-AK132)))*AG132)*(1-AL132)) -> 14241.274 | AN132: =IF(K132=$K$50,AM132,IF(K132=$K$53,AM132,IF(K132=$K$54,AM132,IF(K132=$K$55,AM132,IF(K132=$K$56,AM132,IF(K132=$K$57,AM132,IF(K132=$K$58,AM132,IF(K132=$K$65,AM132,IF(K132=$K$66,AM132,IF(K132=$K$67,AM132,IF(K132=$K$68,AM132,IF(K132=$K$69,AM132,IF(K132=$K$51,AM132,(AM132*(1+AI132))))))))))))))) -> 14241.274 | AO132: 1.9 | AP132: =AM132*AO132 -> 27058.422 | AQ132: =AP132*Fator_Venda -> 23445.184 | AR132: =AO132*AN132 -> 27058.422 | AS132: =IFERROR(IF($AX$94=0,(CQ132/AN132),CQ132/AM132),0) -> 1.5615005 | AT132: =K132 -> MOE | AU132: =I132 -> Serviços | AW132: =IF(K132=$K$50,0,IF(K132=$K$53,0,IF(K132=$K$54,0,IF(K132=$K$55,0,IF(K132=$K$56,0,IF(K132=$K$57,0,IF(K132=$K$58,0,IF(K132=$K$65,0,IF(K132=$K$66,0,IF(K132=$K$67,0,IF(K132=$K$68,0,IF(K132=$K$69,0,IF(K132=$K$51,0,1))))))))))))*AM132*AI132) -> 0 | AX132: =IF(K132=$K$50,0,IF(K132=$K$53,0,IF(K132=$K$54,0,IF(K132=$K$55,0,IF(K132=$K$56,0,IF(K132=$K$57,0,IF(K132=$K$58,0,IF(K132=$K$65,0,IF(K132=$K$66,0,IF(K132=$K$67,0,IF(K132=$K$68,0,IF(K132=$K$69,0,IF(K132=$K$51,0,1))))))))))))*AM132*AJ132*$AX$94) -> 0 | AY132: =IF(K132=$K$53,0,IF(K132=$K$54,0,IF(K132=$K$55,0,IF(K132=$K$56,0,IF(K132=$K$58,0,IF(K132=$K$50,0,IF(K132=$K$65,0,IF(K132=$K$57,0,IF(K132=$K$51,0,AM132*$AY$102))))))))) -> 0 | AZ132: =IF(K132=$K$53,0,IF(K132=$K$54,0,IF(K132=$K$55,0,IF(K132=$K$56,0,IF(K132=$K$58,0,IF(K132=$K$50,0,IF(K132=$K$65,0,IF(K132=$K$57,0,IF(K132=$K$51,0,AM132*$AZ$102))))))))) -> 0 | BA132: =AZ132+AY132+AX132 -> 0 | BB132: =IF($BA$97=1,AQ132*$BB$102,IF(K132=$K$50,0,IF(K132=$K$53,0,IF(K132=$K$54,0,IF(K132=$K$55,0,IF(K132=$K$56,0,IF(K132=$K$57,0,IF(K132=$K$58,0,IF(K132=$K$65,0,IF(K132=$K$66,0,IF(K132=$K$67,0,IF(K132=$K$68,0,IF(K132=$K$69,0,IF(K132=$K$51,0,1)))))))))))*AQ132*$BB$102))) -> 0 | BC132: =AQ132*$BC$102 -> 152.39369 | BD132: =$BD$102*AQ132 -> 703.35551 | BE132: =IF($BE$95=I132,$BE$97,IF(I132=$BE$96,$BE$97,1))*($BE$102*AQ132)*$AZ$97 -> 0 | BF132: =IF('[1]Cockpit Retorno'!$C$65=Sim,Mestre!BA132,SUM(BB132:BE132)+(IF(K132=$K$56,AQ132*MOE_IRRF_LR,0))) -> 1207.427 | BG132: =IF(AA132>0,0,IF(Z132=$Z$82,AG132*1,(IF(Z132=$Z$81,AG132*1,0)))) -> 0 | BH132: =IF(AA132>0,0,IF(Z132=$Z$83,AG132*1,IF(Z132=$Z$81,AG132*1,0))) -> 0 | BI132: =IF(AA132>0,0,IF(Z132=$Z$84,AG132*1,IF(Z132=$Z$93,AG132*2,IF(Z132=$Z$100,AG132,IF(Z132=$Z$81,AG132*2,IF(Z132=$Z$80,AG132*1,IF(Z132=$Z$79,AG132*3,IF(Z132=$Z$78,AG132*2,0)))))))) -> 0 | BJ132: =IF(AA132>0,0,IF(Z132=$Z$85,AG132,IF(Z132=$Z$93,AG132,IF(Z132=$Z$100,AG132,IF(Z132=$Z$81,AG132*1,IF(Z132=$Z$80,AG132*2,IF(Z132=$Z$79,AG132*2,IF(Z132=$Z$78,AG132*2,0)))))))) -> 0 | BK132: =IF(AA132>0,0,IF(Z132=$Z$92,AG132,0)) -> 0 | BL132: =IF(AA132>0,0,IF(Z132=$Z$91,AG132,0)) -> 0 | BM132: =IF(AA132>0,0,IF(Z132=$Z$86,AG132,0)) -> 0 | BN132: =IF(AA132>0,0,IF(Z132=$Z$87,AG132,0)) -> 0 | BO132: =IF(AA132>0,0,IF(Z132=$Z$88,AG132,0)) -> 0 | BP132: =IF(AA132>0,0,IF(Z132=$Z$89,AG132,0)) -> 0 | BQ132: =IF(AA132>0,0,IF(Z132=$Z$90,AG132,0)) -> 0 | BR132: =IF(Z132=$Z$82,AA132*AG132,0) -> 0 | BS132: =IF(Z132=$Z$83,AA132*AG132,0) -> 0 | BT132: =IF(AA132<1,0,IF(Z132=$Z$84,AA132*AG132,IF(Z132=$Z$93,"ERRO",IF(Z132=$Z$100,"ERRO",0)))) -> 0 | BU132: =IF(AA132<1,0,IF(Z132=$Z$85,AA132*AG132,IF(Z132=$Z$93,"ERRO",IF(Z132=$Z$100,"ERRO",0)))) -> 0 | BV132: =IF(Z132=$Z$92,AA132*AG132,0) -> 0 | BW132: =IF(Z132=$Z$91,AA132*AG132,0) -> 0 | BX132: =IF(Z132=$Z$86,AA132*AG132,0) -> 0 | BY132: =IF(Z132=$Z$87,AA132*AG132,0) -> 0 | BZ132: =IF(Z132=$Z$88,AA132*AG132,0) -> 0 | CA132: =IF(Z132=$Z$89,AA132*AG132,0) -> 0 | CB132: =IF(Z132=$Z$90,AA132*AG132,0) -> 0 | CC132: =IFERROR(IF(L132=$L$49,AG132*AH132*(1+AI132)*(1-AK132)*(1-AL132),0),0) -> 0 | CD132: =IF(I132=$CD$97,1,IF(I132=$CD$100,2,IF(K132=$K$66,1,IF(K132=$K$69,1,3)))) -> 3 | CE132: =IF($CD132=1,1.07,IF($CD132=2,1.07,1.3)) -> 1.3 | CF132: =CG132*0.87 -> 1.74 | CG132: =IF($CD132=1,1.42,IF($CD132=2,1.47,2)) -> 2 | CH132: =CG132*1.09 -> 2.18 | CI132: =IF($CD132=1,1.7,IF($CD132=2,1.7,2.4)) -> 2.4 | CJ132: =CE132*$CJ$102 -> 1.274 | CK132: =CF132*$CK$102 -> 1.6182 | CL132: =CG132*$CL$102 -> 1.96 | CM132: =CH132*$CM$102 -> 2.1146 | CN132: =CI132*$CN$102 -> 2.304 | CO132: 1.3 | CP132: =BF132-BA132 -> 1207.427 | CQ132: =AQ132-CP132 -> 22237.757 | CR132: =BC132+BD132 -> 855.74921
A133: =IF(AND('[1]Cockpit Retorno'!$E$67=Sim,Mestre!M133=Mestre!$M$98),0,1) -> 1 | B133: =IF(AND('[1]Cockpit Retorno'!$E$67=Sim,Mestre!L133=Mestre!$L$48),0,1) -> 0 | C133: =IF(AND('[1]Cockpit Retorno'!$E$67=Sim,Mestre!M133=Mestre!$M$97),0,1) -> 1 | D133: MOA_MOD_MOI | F133: Nacional | H133: MOD | I133: =VLOOKUP(K133,$N$74:$O$95,2) -> Serviços | J133: ATK | K133: MOD | L133: ATM | M133: ATK | N133: NA | O133: M.O. | P133: NA | Q133: NA | R133: NA | S133: NA | T133: NA | U133: NA | V133: NA | W133: NA | X133: Fusões Fibras Óticas | Y133: NA | Z133: NA | AA133: 0 | AB133: NA | AC133: NA | AD133: NA | AF133: NA | AG133: =ROUNDUP('[1]Avulso HH'!AG9,0)+30 -> 120 | AH133: 44.279955 | AI133: 0 | AJ133: 0 | AM133: =(((IF(L133=$L$101,1,IF(L133=$L$47,1,0))*(AH133*(1-AK133)))*AG133)*(1-AL133)) -> 5313.5946 | AN133: =IF(K133=$K$50,AM133,IF(K133=$K$53,AM133,IF(K133=$K$54,AM133,IF(K133=$K$55,AM133,IF(K133=$K$56,AM133,IF(K133=$K$57,AM133,IF(K133=$K$58,AM133,IF(K133=$K$65,AM133,IF(K133=$K$66,AM133,IF(K133=$K$67,AM133,IF(K133=$K$68,AM133,IF(K133=$K$69,AM133,IF(K133=$K$51,AM133,(AM133*(1+AI133))))))))))))))) -> 5313.5946 | AO133: 1.9 | AP133: =AM133*AO133 -> 10095.83 | AQ133: =AP133*Fator_Venda -> 8747.6864 | AR133: =AO133*AN133 -> 10095.83 | AS133: =IFERROR(IF($AX$94=0,(CQ133/AN133),CQ133/AM133),0) -> 1.5861947 | AT133: =K133 -> MOD | AU133: =I133 -> Serviços | AW133: =IF(K133=$K$50,0,IF(K133=$K$53,0,IF(K133=$K$54,0,IF(K133=$K$55,0,IF(K133=$K$56,0,IF(K133=$K$57,0,IF(K133=$K$58,0,IF(K133=$K$65,0,IF(K133=$K$66,0,IF(K133=$K$67,0,IF(K133=$K$68,0,IF(K133=$K$69,0,IF(K133=$K$51,0,1))))))))))))*AM133*AI133) -> 0 | AX133: =IF(K133=$K$50,0,IF(K133=$K$53,0,IF(K133=$K$54,0,IF(K133=$K$55,0,IF(K133=$K$56,0,IF(K133=$K$57,0,IF(K133=$K$58,0,IF(K133=$K$65,0,IF(K133=$K$66,0,IF(K133=$K$67,0,IF(K133=$K$68,0,IF(K133=$K$69,0,IF(K133=$K$51,0,1))))))))))))*AM133*AJ133*$AX$94) -> 0 | AY133: =IF(K133=$K$53,0,IF(K133=$K$54,0,IF(K133=$K$55,0,IF(K133=$K$56,0,IF(K133=$K$58,0,IF(K133=$K$50,0,IF(K133=$K$65,0,IF(K133=$K$57,0,IF(K133=$K$51,0,AM133*$AY$102))))))))) -> 0 | AZ133: =IF(K133=$K$53,0,IF(K133=$K$54,0,IF(K133=$K$55,0,IF(K133=$K$56,0,IF(K133=$K$58,0,IF(K133=$K$50,0,IF(K133=$K$65,0,IF(K133=$K$57,0,IF(K133=$K$51,0,AM133*$AZ$102))))))))) -> 0 | BA133: =AZ133+AY133+AX133 -> 0 | BB133: =IF($BA$97=1,AQ133*$BB$102,IF(K133=$K$50,0,IF(K133=$K$53,0,IF(K133=$K$54,0,IF(K133=$K$55,0,IF(K133=$K$56,0,IF(K133=$K$57,0,IF(K133=$K$58,0,IF(K133=$K$65,0,IF(K133=$K$66,0,IF(K133=$K$67,0,IF(K133=$K$68,0,IF(K133=$K$69,0,IF(K133=$K$51,0,1)))))))))))*AQ133*$BB$102))) -> 0 | BC133: =AQ133*$BC$102 -> 56.859961 | BD133: =$BD$102*AQ133 -> 262.43059 | BE133: =IF($BE$95=I133,$BE$97,IF(I133=$BE$96,$BE$97,1))*($BE$102*AQ133)*$AZ$97 -> 0 | BF133: =IF('[1]Cockpit Retorno'!$C$65=Sim,Mestre!BA133,SUM(BB133:BE133)+(IF(K133=$K$56,AQ133*MOE_IRRF_LR,0))) -> 319.29055 | BG133: =IF(AA133>0,0,IF(Z133=$Z$82,AG133*1,(IF(Z133=$Z$81,AG133*1,0)))) -> 0 | BH133: =IF(AA133>0,0,IF(Z133=$Z$83,AG133*1,IF(Z133=$Z$81,AG133*1,0))) -> 0 | BI133: =IF(AA133>0,0,IF(Z133=$Z$84,AG133*1,IF(Z133=$Z$93,AG133*2,IF(Z133=$Z$100,AG133,IF(Z133=$Z$81,AG133*2,IF(Z133=$Z$80,AG133*1,IF(Z133=$Z$79,AG133*3,IF(Z133=$Z$78,AG133*2,0)))))))) -> 0 | BJ133: =IF(AA133>0,0,IF(Z133=$Z$85,AG133,IF(Z133=$Z$93,AG133,IF(Z133=$Z$100,AG133,IF(Z133=$Z$81,AG133*1,IF(Z133=$Z$80,AG133*2,IF(Z133=$Z$79,AG133*2,IF(Z133=$Z$78,AG133*2,0)))))))) -> 0 | BK133: =IF(AA133>0,0,IF(Z133=$Z$92,AG133,0)) -> 0 | BL133: =IF(AA133>0,0,IF(Z133=$Z$91,AG133,0)) -> 0 | BM133: =IF(AA133>0,0,IF(Z133=$Z$86,AG133,0)) -> 0 | BN133: =IF(AA133>0,0,IF(Z133=$Z$87,AG133,0)) -> 0 | BO133: =IF(AA133>0,0,IF(Z133=$Z$88,AG133,0)) -> 0 | BP133: =IF(AA133>0,0,IF(Z133=$Z$89,AG133,0)) -> 0 | BQ133: =IF(AA133>0,0,IF(Z133=$Z$90,AG133,0)) -> 0 | BR133: =IF(Z133=$Z$82,AA133*AG133,0) -> 0 | BS133: =IF(Z133=$Z$83,AA133*AG133,0) -> 0 | BT133: =IF(AA133<1,0,IF(Z133=$Z$84,AA133*AG133,IF(Z133=$Z$93,"ERRO",IF(Z133=$Z$100,"ERRO",0)))) -> 0 | BU133: =IF(AA133<1,0,IF(Z133=$Z$85,AA133*AG133,IF(Z133=$Z$93,"ERRO",IF(Z133=$Z$100,"ERRO",0)))) -> 0 | BV133: =IF(Z133=$Z$92,AA133*AG133,0) -> 0 | BW133: =IF(Z133=$Z$91,AA133*AG133,0) -> 0 | BX133: =IF(Z133=$Z$86,AA133*AG133,0) -> 0 | BY133: =IF(Z133=$Z$87,AA133*AG133,0) -> 0 | BZ133: =IF(Z133=$Z$88,AA133*AG133,0) -> 0 | CA133: =IF(Z133=$Z$89,AA133*AG133,0) -> 0 | CB133: =IF(Z133=$Z$90,AA133*AG133,0) -> 0 | CC133: =IFERROR(IF(L133=$L$49,AG133*AH133*(1+AI133)*(1-AK133)*(1-AL133),0),0) -> 0 | CD133: =IF(I133=$CD$97,1,IF(I133=$CD$100,2,IF(K133=$K$66,1,IF(K133=$K$69,1,3)))) -> 3 | CE133: =IF($CD133=1,1.07,IF($CD133=2,1.07,1.3)) -> 1.3 | CF133: =CG133*0.87 -> 1.74 | CG133: =IF($CD133=1,1.42,IF($CD133=2,1.47,2)) -> 2 | CH133: =CG133*1.09 -> 2.18 | CI133: =IF($CD133=1,1.7,IF($CD133=2,1.7,2.4)) -> 2.4 | CJ133: =CE133*$CJ$102-0.05 -> 1.224 | CK133: =CF133*$CK$102-0.05 -> 1.5682 | CL133: =CG133*$CL$102-0.05 -> 1.91 | CM133: =CH133*$CM$102-0.05 -> 2.0646 | CN133: =CI133*$CN$102-0.05 -> 2.254 | CO133: 1.3 | CP133: =BF133-BA133 -> 319.29055 | CQ133: =AQ133-CP133 -> 8428.3958 | CR133: =BC133+BD133 -> 319.29055
A134: =IF(AND('[1]Cockpit Retorno'!$E$67=Sim,Mestre!M134=Mestre!$M$98),0,1) -> 1 | B134: =IF(AND('[1]Cockpit Retorno'!$E$67=Sim,Mestre!L134=Mestre!$L$48),0,1) -> 0 | C134: =IF(AND('[1]Cockpit Retorno'!$E$67=Sim,Mestre!M134=Mestre!$M$97),0,1) -> 1 | D134: LOG_LOGM_TRS | F134: Nacional | H134: LOG MON | I134: =VLOOKUP(K134,$N$74:$O$95,2) -> Despesas | J134: ATK | K134: LOG | L134: ATM | M134: ATK | N134: NA | O134: M.O. | P134: NA | Q134: NA | R134: NA | S134: NA | T134: NA | U134: NA | V134: NA | W134: NA | X134: Logistica Fusões Fibras Óticas | Y134: NA | Z134: NA | AA134: 0 | AB134: NA | AC134: NA | AD134: NA | AF134: NA | AG134: 1 | AH134: 3320.1 | AI134: 0 | AJ134: 0 | AM134: =(((IF(L134=$L$101,1,IF(L134=$L$47,1,0))*(AH134*(1-AK134)))*AG134)*(1-AL134)) -> 3320.1 | AN134: =IF(K134=$K$50,AM134,IF(K134=$K$53,AM134,IF(K134=$K$54,AM134,IF(K134=$K$55,AM134,IF(K134=$K$56,AM134,IF(K134=$K$57,AM134,IF(K134=$K$58,AM134,IF(K134=$K$65,AM134,IF(K134=$K$66,AM134,IF(K134=$K$67,AM134,IF(K134=$K$68,AM134,IF(K134=$K$69,AM134,IF(K134=$K$51,AM134,(AM134*(1+AI134))))))))))))))) -> 3320.1 | AO134: 1.6 | AP134: =AM134*AO134 -> 5312.16 | AQ134: =AP134*Fator_Venda -> 4602.8024 | AR134: =AO134*AN134 -> 5312.16 | AS134: =IFERROR(IF($AX$94=0,(CQ134/AN134),CQ134/AM134),0) -> 1.3357429 | AT134: =K134 -> LOG | AU134: =I134 -> Despesas | AW134: =IF(K134=$K$50,0,IF(K134=$K$53,0,IF(K134=$K$54,0,IF(K134=$K$55,0,IF(K134=$K$56,0,IF(K134=$K$57,0,IF(K134=$K$58,0,IF(K134=$K$65,0,IF(K134=$K$66,0,IF(K134=$K$67,0,IF(K134=$K$68,0,IF(K134=$K$69,0,IF(K134=$K$51,0,1))))))))))))*AM134*AI134) -> 0 | AX134: =IF(K134=$K$50,0,IF(K134=$K$53,0,IF(K134=$K$54,0,IF(K134=$K$55,0,IF(K134=$K$56,0,IF(K134=$K$57,0,IF(K134=$K$58,0,IF(K134=$K$65,0,IF(K134=$K$66,0,IF(K134=$K$67,0,IF(K134=$K$68,0,IF(K134=$K$69,0,IF(K134=$K$51,0,1))))))))))))*AM134*AJ134*$AX$94) -> 0 | AY134: =IF(K134=$K$53,0,IF(K134=$K$54,0,IF(K134=$K$55,0,IF(K134=$K$56,0,IF(K134=$K$58,0,IF(K134=$K$50,0,IF(K134=$K$65,0,IF(K134=$K$57,0,IF(K134=$K$51,0,AM134*$AY$102))))))))) -> 0 | AZ134: =IF(K134=$K$53,0,IF(K134=$K$54,0,IF(K134=$K$55,0,IF(K134=$K$56,0,IF(K134=$K$58,0,IF(K134=$K$50,0,IF(K134=$K$65,0,IF(K134=$K$57,0,IF(K134=$K$51,0,AM134*$AZ$102))))))))) -> 0 | BA134: =AZ134+AY134+AX134 -> 0 | BB134: =IF($BA$97=1,AQ134*$BB$102,IF(K134=$K$50,0,IF(K134=$K$53,0,IF(K134=$K$54,0,IF(K134=$K$55,0,IF(K134=$K$56,0,IF(K134=$K$57,0,IF(K134=$K$58,0,IF(K134=$K$65,0,IF(K134=$K$66,0,IF(K134=$K$67,0,IF(K134=$K$68,0,IF(K134=$K$69,0,IF(K134=$K$51,0,1)))))))))))*AQ134*$BB$102))) -> 0 | BC134: =AQ134*$BC$102 -> 29.918216 | BD134: =$BD$102*AQ134 -> 138.08407 | BE134: =IF($BE$95=I134,$BE$97,IF(I134=$BE$96,$BE$97,1))*($BE$102*AQ134)*$AZ$97 -> 0 | BF134: =IF('[1]Cockpit Retorno'!$C$65=Sim,Mestre!BA134,SUM(BB134:BE134)+(IF(K134=$K$56,AQ134*MOE_IRRF_LR,0))) -> 168.00229 | BG134: =IF(AA134>0,0,IF(Z134=$Z$82,AG134*1,(IF(Z134=$Z$81,AG134*1,0)))) -> 0 | BH134: =IF(AA134>0,0,IF(Z134=$Z$83,AG134*1,IF(Z134=$Z$81,AG134*1,0))) -> 0 | BI134: =IF(AA134>0,0,IF(Z134=$Z$84,AG134*1,IF(Z134=$Z$93,AG134*2,IF(Z134=$Z$100,AG134,IF(Z134=$Z$81,AG134*2,IF(Z134=$Z$80,AG134*1,IF(Z134=$Z$79,AG134*3,IF(Z134=$Z$78,AG134*2,0)))))))) -> 0 | BJ134: =IF(AA134>0,0,IF(Z134=$Z$85,AG134,IF(Z134=$Z$93,AG134,IF(Z134=$Z$100,AG134,IF(Z134=$Z$81,AG134*1,IF(Z134=$Z$80,AG134*2,IF(Z134=$Z$79,AG134*2,IF(Z134=$Z$78,AG134*2,0)))))))) -> 0 | BK134: =IF(AA134>0,0,IF(Z134=$Z$92,AG134,0)) -> 0 | BL134: =IF(AA134>0,0,IF(Z134=$Z$91,AG134,0)) -> 0 | BM134: =IF(AA134>0,0,IF(Z134=$Z$86,AG134,0)) -> 0 | BN134: =IF(AA134>0,0,IF(Z134=$Z$87,AG134,0)) -> 0 | BO134: =IF(AA134>0,0,IF(Z134=$Z$88,AG134,0)) -> 0 | BP134: =IF(AA134>0,0,IF(Z134=$Z$89,AG134,0)) -> 0 | BQ134: =IF(AA134>0,0,IF(Z134=$Z$90,AG134,0)) -> 0 | BR134: =IF(Z134=$Z$82,AA134*AG134,0) -> 0 | BS134: =IF(Z134=$Z$83,AA134*AG134,0) -> 0 | BT134: =IF(AA134<1,0,IF(Z134=$Z$84,AA134*AG134,IF(Z134=$Z$93,"ERRO",IF(Z134=$Z$100,"ERRO",0)))) -> 0 | BU134: =IF(AA134<1,0,IF(Z134=$Z$85,AA134*AG134,IF(Z134=$Z$93,"ERRO",IF(Z134=$Z$100,"ERRO",0)))) -> 0 | BV134: =IF(Z134=$Z$92,AA134*AG134,0) -> 0 | BW134: =IF(Z134=$Z$91,AA134*AG134,0) -> 0 | BX134: =IF(Z134=$Z$86,AA134*AG134,0) -> 0 | BY134: =IF(Z134=$Z$87,AA134*AG134,0) -> 0 | BZ134: =IF(Z134=$Z$88,AA134*AG134,0) -> 0 | CA134: =IF(Z134=$Z$89,AA134*AG134,0) -> 0 | CB134: =IF(Z134=$Z$90,AA134*AG134,0) -> 0 | CC134: =IFERROR(IF(L134=$L$49,AG134*AH134*(1+AI134)*(1-AK134)*(1-AL134),0),0) -> 0 | CD134: =IF(I134=$CD$97,1,IF(I134=$CD$100,2,IF(K134=$K$66,1,IF(K134=$K$69,1,3)))) -> 2 | CE134: =IF($CD134=1,1.07,IF($CD134=2,1.07,1.3)) -> 1.07 | CF134: =CG134*0.87 -> 1.2789 | CG134: =IF($CD134=1,1.42,IF($CD134=2,1.47,2)) -> 1.47 | CH134: =CG134*1.09 -> 1.6023 | CI134: =IF($CD134=1,1.7,IF($CD134=2,1.7,2.4)) -> 1.7 | CJ134: =CE134*$CJ$102 -> 1.0486 | CK134: =CF134*$CK$102 -> 1.189377 | CL134: =CG134*$CL$102 -> 1.4406 | CM134: =CH134*$CM$102 -> 1.554231 | CN134: =CI134*$CN$102 -> 1.632 | CO134: 1.3 | CP134: =BF134-BA134 -> 168.00229 | CQ134: =AQ134-CP134 -> 4434.8001 | CR134: =BC134+BD134 -> 168.00229
A135: =IF(AND('[1]Cockpit Retorno'!$E$67=Sim,Mestre!M135=Mestre!$M$98),0,1) -> 1 | B135: =IF(AND('[1]Cockpit Retorno'!$E$67=Sim,Mestre!L135=Mestre!$L$48),0,1) -> 0 | C135: =IF(AND('[1]Cockpit Retorno'!$E$67=Sim,Mestre!M135=Mestre!$M$97),0,1) -> 1 | D135: LOG_LOGM_TRS | F135: Nacional | H135: LOG COM | I135: =VLOOKUP(K135,$N$74:$O$95,2) -> Despesas | J135: ATK | K135: LOG | L135: ATM | M135: ATK | N135: NA | O135: M.O. | P135: NA | Q135: NA | R135: NA | S135: NA | T135: NA | U135: NA | V135: NA | W135: NA | X135: Viagens alta gestão | Y135: NA | Z135: NA | AA135: 0 | AB135: NA | AC135: NA | AD135: NA | AF135: NA | AG135: 1 | AH135: 40401.568 | AI135: 0 | AJ135: 0 | AM135: =(((IF(L135=$L$101,1,IF(L135=$L$47,1,0))*(AH135*(1-AK135)))*AG135)*(1-AL135)) -> 40401.568 | AN135: =IF(K135=$K$50,AM135,IF(K135=$K$53,AM135,IF(K135=$K$54,AM135,IF(K135=$K$55,AM135,IF(K135=$K$56,AM135,IF(K135=$K$57,AM135,IF(K135=$K$58,AM135,IF(K135=$K$65,AM135,IF(K135=$K$66,AM135,IF(K135=$K$67,AM135,IF(K135=$K$68,AM135,IF(K135=$K$69,AM135,IF(K135=$K$51,AM135,(AM135*(1+AI135))))))))))))))) -> 40401.568 | AO135: 1.6 | AP135: =AM135*AO135 -> 64642.509 | AQ135: =AP135*Fator_Venda -> 56010.492 | AR135: =AO135*AN135 -> 64642.509 | AS135: =IFERROR(IF($AX$94=0,(CQ135/AN135),CQ135/AM135),0) -> 1.3357429 | AT135: =K135 -> LOG | AU135: =I135 -> Despesas | AW135: =IF(K135=$K$50,0,IF(K135=$K$53,0,IF(K135=$K$54,0,IF(K135=$K$55,0,IF(K135=$K$56,0,IF(K135=$K$57,0,IF(K135=$K$58,0,IF(K135=$K$65,0,IF(K135=$K$66,0,IF(K135=$K$67,0,IF(K135=$K$68,0,IF(K135=$K$69,0,IF(K135=$K$51,0,1))))))))))))*AM135*AI135) -> 0 | AX135: =IF(K135=$K$50,0,IF(K135=$K$53,0,IF(K135=$K$54,0,IF(K135=$K$55,0,IF(K135=$K$56,0,IF(K135=$K$57,0,IF(K135=$K$58,0,IF(K135=$K$65,0,IF(K135=$K$66,0,IF(K135=$K$67,0,IF(K135=$K$68,0,IF(K135=$K$69,0,IF(K135=$K$51,0,1))))))))))))*AM135*AJ135*$AX$94) -> 0 | AY135: =IF(K135=$K$53,0,IF(K135=$K$54,0,IF(K135=$K$55,0,IF(K135=$K$56,0,IF(K135=$K$58,0,IF(K135=$K$50,0,IF(K135=$K$65,0,IF(K135=$K$57,0,IF(K135=$K$51,0,AM135*$AY$102))))))))) -> 0 | AZ135: =IF(K135=$K$53,0,IF(K135=$K$54,0,IF(K135=$K$55,0,IF(K135=$K$56,0,IF(K135=$K$58,0,IF(K135=$K$50,0,IF(K135=$K$65,0,IF(K135=$K$57,0,IF(K135=$K$51,0,AM135*$AZ$102))))))))) -> 0 | BA135: =AZ135+AY135+AX135 -> 0 | BB135: =IF($BA$97=1,AQ135*$BB$102,IF(K135=$K$50,0,IF(K135=$K$53,0,IF(K135=$K$54,0,IF(K135=$K$55,0,IF(K135=$K$56,0,IF(K135=$K$57,0,IF(K135=$K$58,0,IF(K135=$K$65,0,IF(K135=$K$66,0,IF(K135=$K$67,0,IF(K135=$K$68,0,IF(K135=$K$69,0,IF(K135=$K$51,0,1)))))))))))*AQ135*$BB$102))) -> 0 | BC135: =AQ135*$BC$102 -> 364.0682 | BD135: =$BD$102*AQ135 -> 1680.3148 | BE135: =IF($BE$95=I135,$BE$97,IF(I135=$BE$96,$BE$97,1))*($BE$102*AQ135)*$AZ$97 -> 0 | BF135: =IF('[1]Cockpit Retorno'!$C$65=Sim,Mestre!BA135,SUM(BB135:BE135)+(IF(K135=$K$56,AQ135*MOE_IRRF_LR,0))) -> 2044.383 | BG135: =IF(AA135>0,0,IF(Z135=$Z$82,AG135*1,(IF(Z135=$Z$81,AG135*1,0)))) -> 0 | BH135: =IF(AA135>0,0,IF(Z135=$Z$83,AG135*1,IF(Z135=$Z$81,AG135*1,0))) -> 0 | BI135: =IF(AA135>0,0,IF(Z135=$Z$84,AG135*1,IF(Z135=$Z$93,AG135*2,IF(Z135=$Z$100,AG135,IF(Z135=$Z$81,AG135*2,IF(Z135=$Z$80,AG135*1,IF(Z135=$Z$79,AG135*3,IF(Z135=$Z$78,AG135*2,0)))))))) -> 0 | BJ135: =IF(AA135>0,0,IF(Z135=$Z$85,AG135,IF(Z135=$Z$93,AG135,IF(Z135=$Z$100,AG135,IF(Z135=$Z$81,AG135*1,IF(Z135=$Z$80,AG135*2,IF(Z135=$Z$79,AG135*2,IF(Z135=$Z$78,AG135*2,0)))))))) -> 0 | BK135: =IF(AA135>0,0,IF(Z135=$Z$92,AG135,0)) -> 0 | BL135: =IF(AA135>0,0,IF(Z135=$Z$91,AG135,0)) -> 0 | BM135: =IF(AA135>0,0,IF(Z135=$Z$86,AG135,0)) -> 0 | BN135: =IF(AA135>0,0,IF(Z135=$Z$87,AG135,0)) -> 0 | BO135: =IF(AA135>0,0,IF(Z135=$Z$88,AG135,0)) -> 0 | BP135: =IF(AA135>0,0,IF(Z135=$Z$89,AG135,0)) -> 0 | BQ135: =IF(AA135>0,0,IF(Z135=$Z$90,AG135,0)) -> 0 | BR135: =IF(Z135=$Z$82,AA135*AG135,0) -> 0 | BS135: =IF(Z135=$Z$83,AA135*AG135,0) -> 0 | BT135: =IF(AA135<1,0,IF(Z135=$Z$84,AA135*AG135,IF(Z135=$Z$93,"ERRO",IF(Z135=$Z$100,"ERRO",0)))) -> 0 | BU135: =IF(AA135<1,0,IF(Z135=$Z$85,AA135*AG135,IF(Z135=$Z$93,"ERRO",IF(Z135=$Z$100,"ERRO",0)))) -> 0 | BV135: =IF(Z135=$Z$92,AA135*AG135,0) -> 0 | BW135: =IF(Z135=$Z$91,AA135*AG135,0) -> 0 | BX135: =IF(Z135=$Z$86,AA135*AG135,0) -> 0 | BY135: =IF(Z135=$Z$87,AA135*AG135,0) -> 0 | BZ135: =IF(Z135=$Z$88,AA135*AG135,0) -> 0 | CA135: =IF(Z135=$Z$89,AA135*AG135,0) -> 0 | CB135: =IF(Z135=$Z$90,AA135*AG135,0) -> 0 | CC135: =IFERROR(IF(L135=$L$49,AG135*AH135*(1+AI135)*(1-AK135)*(1-AL135),0),0) -> 0 | CD135: =IF(I135=$CD$97,1,IF(I135=$CD$100,2,IF(K135=$K$66,1,IF(K135=$K$69,1,3)))) -> 2 | CE135: =IF($CD135=1,1.07,IF($CD135=2,1.07,1.3)) -> 1.07 | CF135: =CG135*0.87 -> 1.2789 | CG135: =IF($CD135=1,1.42,IF($CD135=2,1.47,2)) -> 1.47 | CH135: =CG135*1.09 -> 1.6023 | CI135: =IF($CD135=1,1.7,IF($CD135=2,1.7,2.4)) -> 1.7 | CJ135: =CE135*$CJ$102 -> 1.0486 | CK135: =CF135*$CK$102 -> 1.189377 | CL135: =CG135*$CL$102 -> 1.4406 | CM135: =CH135*$CM$102 -> 1.554231 | CN135: =CI135*$CN$102 -> 1.632 | CO135: 1.3 | CP135: =BF135-BA135 -> 2044.383 | CQ135: =AQ135-CP135 -> 53966.109 | CR135: =BC135+BD135 -> 2044.383
A136: =IF(AND('[1]Cockpit Retorno'!$E$67=Sim,Mestre!M136=Mestre!$M$98),0,1) -> 1 | B136: =IF(AND('[1]Cockpit Retorno'!$E$67=Sim,Mestre!L136=Mestre!$L$48),0,1) -> 0 | C136: =IF(AND('[1]Cockpit Retorno'!$E$67=Sim,Mestre!M136=Mestre!$M$97),0,1) -> 1 | D136: CFTV_REDE_TI | F136: Nacional | H136: CFTV | I136: =VLOOKUP(K136,$N$74:$O$95,2) -> Mercadorias | J136: ATM | K136: CFTV | L136: ATM | M136: ATK | N136: NA | O136: NA | P136: NA | Q136: NA | R136: NA | S136: NA | T136: NA | U136: NA | V136: NA | W136: NA | Y136: NA | Z136: NA | AA136: 0 | AB136: NA | AC136: NA | AD136: NA | AF136: NA | AH136: 0 | AM136: =(((IF(L136=$L$101,1,IF(L136=$L$47,1,0))*(AH136*(1-AK136)))*AG136)*(1-AL136)) -> 0 | AN136: =IF(K136=$K$50,AM136,IF(K136=$K$53,AM136,IF(K136=$K$54,AM136,IF(K136=$K$55,AM136,IF(K136=$K$56,AM136,IF(K136=$K$57,AM136,IF(K136=$K$58,AM136,IF(K136=$K$65,AM136,IF(K136=$K$66,AM136,IF(K136=$K$67,AM136,IF(K136=$K$68,AM136,IF(K136=$K$69,AM136,IF(K136=$K$51,AM136,(AM136*(1+AI136))))))))))))))) -> 0 | AO136: 1.4 | AP136: =AM136*AO136 -> 0 | AQ136: =AP136*Fator_Venda -> 0 | AR136: =AO136*AN136 -> 0 | AS136: =IFERROR(IF($AX$94=0,(CQ136/AN136),CQ136/AM136),0) -> 0 | AT136: =K136 -> CFTV | AU136: =I136 -> Mercadorias | AW136: =IF(K136=$K$50,0,IF(K136=$K$53,0,IF(K136=$K$54,0,IF(K136=$K$55,0,IF(K136=$K$56,0,IF(K136=$K$57,0,IF(K136=$K$58,0,IF(K136=$K$65,0,IF(K136=$K$66,0,IF(K136=$K$67,0,IF(K136=$K$68,0,IF(K136=$K$69,0,IF(K136=$K$51,0,1))))))))))))*AM136*AI136) -> 0 | AX136: =IF(K136=$K$50,0,IF(K136=$K$53,0,IF(K136=$K$54,0,IF(K136=$K$55,0,IF(K136=$K$56,0,IF(K136=$K$57,0,IF(K136=$K$58,0,IF(K136=$K$65,0,IF(K136=$K$66,0,IF(K136=$K$67,0,IF(K136=$K$68,0,IF(K136=$K$69,0,IF(K136=$K$51,0,1))))))))))))*AM136*AJ136*$AX$94) -> 0 | AY136: =IF(K136=$K$53,0,IF(K136=$K$54,0,IF(K136=$K$55,0,IF(K136=$K$56,0,IF(K136=$K$58,0,IF(K136=$K$50,0,IF(K136=$K$65,0,IF(K136=$K$57,0,IF(K136=$K$51,0,AM136*$AY$102))))))))) -> 0 | AZ136: =IF(K136=$K$53,0,IF(K136=$K$54,0,IF(K136=$K$55,0,IF(K136=$K$56,0,IF(K136=$K$58,0,IF(K136=$K$50,0,IF(K136=$K$65,0,IF(K136=$K$57,0,IF(K136=$K$51,0,AM136*$AZ$102))))))))) -> 0 | BA136: =AZ136+AY136+AX136 -> 0 | BB136: =IF($BA$97=1,AQ136*$BB$102,IF(K136=$K$50,0,IF(K136=$K$53,0,IF(K136=$K$54,0,IF(K136=$K$55,0,IF(K136=$K$56,0,IF(K136=$K$57,0,IF(K136=$K$58,0,IF(K136=$K$65,0,IF(K136=$K$66,0,IF(K136=$K$67,0,IF(K136=$K$68,0,IF(K136=$K$69,0,IF(K136=$K$51,0,1)))))))))))*AQ136*$BB$102))) -> 0 | BC136: =AQ136*$BC$102 -> 0 | BD136: =$BD$102*AQ136 -> 0 | BE136: =IF($BE$95=I136,$BE$97,IF(I136=$BE$96,$BE$97,1))*($BE$102*AQ136)*$AZ$97 -> 0 | BF136: =IF('[1]Cockpit Retorno'!$C$65=Sim,Mestre!BA136,SUM(BB136:BE136)+(IF(K136=$K$56,AQ136*MOE_IRRF_LR,0))) -> 0 | BG136: =IF(AA136>0,0,IF(Z136=$Z$82,AG136*1,(IF(Z136=$Z$81,AG136*1,0)))) -> 0 | BH136: =IF(AA136>0,0,IF(Z136=$Z$83,AG136*1,IF(Z136=$Z$81,AG136*1,0))) -> 0 | BI136: =IF(AA136>0,0,IF(Z136=$Z$84,AG136*1,IF(Z136=$Z$93,AG136*2,IF(Z136=$Z$100,AG136,IF(Z136=$Z$81,AG136*2,IF(Z136=$Z$80,AG136*1,IF(Z136=$Z$79,AG136*3,IF(Z136=$Z$78,AG136*2,0)))))))) -> 0 | BJ136: =IF(AA136>0,0,IF(Z136=$Z$85,AG136,IF(Z136=$Z$93,AG136,IF(Z136=$Z$100,AG136,IF(Z136=$Z$81,AG136*1,IF(Z136=$Z$80,AG136*2,IF(Z136=$Z$79,AG136*2,IF(Z136=$Z$78,AG136*2,0)))))))) -> 0 | BK136: =IF(AA136>0,0,IF(Z136=$Z$92,AG136,0)) -> 0 | BL136: =IF(AA136>0,0,IF(Z136=$Z$91,AG136,0)) -> 0 | BM136: =IF(AA136>0,0,IF(Z136=$Z$86,AG136,0)) -> 0 | BN136: =IF(AA136>0,0,IF(Z136=$Z$87,AG136,0)) -> 0 | BO136: =IF(AA136>0,0,IF(Z136=$Z$88,AG136,0)) -> 0 | BP136: =IF(AA136>0,0,IF(Z136=$Z$89,AG136,0)) -> 0 | BQ136: =IF(AA136>0,0,IF(Z136=$Z$90,AG136,0)) -> 0 | BR136: =IF(Z136=$Z$82,AA136*AG136,0) -> 0 | BS136: =IF(Z136=$Z$83,AA136*AG136,0) -> 0 | BT136: =IF(AA136<1,0,IF(Z136=$Z$84,AA136*AG136,IF(Z136=$Z$93,"ERRO",IF(Z136=$Z$100,"ERRO",0)))) -> 0 | BU136: =IF(AA136<1,0,IF(Z136=$Z$85,AA136*AG136,IF(Z136=$Z$93,"ERRO",IF(Z136=$Z$100,"ERRO",0)))) -> 0 | BV136: =IF(Z136=$Z$92,AA136*AG136,0) -> 0 | BW136: =IF(Z136=$Z$91,AA136*AG136,0) -> 0 | BX136: =IF(Z136=$Z$86,AA136*AG136,0) -> 0 | BY136: =IF(Z136=$Z$87,AA136*AG136,0) -> 0 | BZ136: =IF(Z136=$Z$88,AA136*AG136,0) -> 0 | CA136: =IF(Z136=$Z$89,AA136*AG136,0) -> 0 | CB136: =IF(Z136=$Z$90,AA136*AG136,0) -> 0 | CC136: =IFERROR(IF(L136=$L$49,AG136*AH136*(1+AI136)*(1-AK136)*(1-AL136),0),0) -> 0 | CD136: =IF(I136=$CD$97,1,IF(I136=$CD$100,2,IF(K136=$K$66,1,IF(K136=$K$69,1,3)))) -> 1 | CE136: =IF($CD136=1,1.07,IF($CD136=2,1.07,1.3)) -> 1.07 | CF136: =CG136*0.87 -> 1.2354 | CG136: =IF($CD136=1,1.42,IF($CD136=2,1.47,2)) -> 1.42 | CH136: =CG136*1.09 -> 1.5478 | CI136: =IF($CD136=1,1.7,IF($CD136=2,1.7,2.4)) -> 1.7 | CJ136: =CE136*$CJ$102 -> 1.0486 | CK136: =CF136*$CK$102 -> 1.148922 | CL136: =CG136*$CL$102 -> 1.3916 | CM136: =CH136*$CM$102 -> 1.501366 | CN136: =CI136*$CN$102 -> 1.632 | CO136: =CJ136*$CO$102 -> 1.006656 | CP136: =BF136-BA136 -> 0 | CQ136: =AQ136-CP136 -> 0 | CR136: =BC136+BD136 -> 0
...
